Workbook

Sheet PARÂMETROS
A1: PARÂMETROS — ÚNICA FONTE DE VERDADE
A3: REGIME DE TRABALHO
A4: Horas trabalhadas/dia (H) | B4: 8
A5: Dias trabalhados/semana (D) | B5: 6
A6: Preço Diesel (R$/L) | B6: 6.99
A8: BDI POR CATEGORIA
A9: BDI Diesel / Combustível (= BDI Material) | B9: 0.04
A10: BDI Mão de Obra (TER) | B10: 0.290573
A11: BDI Equipamentos | B11: 0.290573
A12: BDI Indiretos | B12: 0.25205
A14: ITENS EAP — QUANTITATIVOS, PRODUTIVIDADES E COMPOSIÇÃO
A15: Item ID | B15: Descrição | C15: Un. | D15: Quantitativo | E15: P (un/h) | F15: P.U.Diesel (R$/un) | G15: P.U.MO (R$/un) | H15: nEq médio | I15: Duração calc. (sem.)
A16: eap-1_0 | B16: Desmatamento e limpeza de area vegetada | C16: m2 | D16: 2400000 | E16: 714.2857 | F16: 0.2942 | G16: 0.5794 | H16: 1 | I16: =IF(AND(E16>0,H16>0),CEILING(D16/(E16*PARÂMETROS!$B$4*PARÂMETROS!$B$5*AVERAGE(PARÂMETROS!$B$40:$B$91)*H16),1),"N/D")
A17: eap-1_1 | B17: Esc/carg/transp 1aCat DMT<=2000m | C17: m3 | D17: 107463.11 | E17: 223.8815 | F17: 4.7099 | G17: 2.9484 | H17: 1 | I17: =IF(AND(E17>0,H17>0),CEILING(D17/(E17*PARÂMETROS!$B$4*PARÂMETROS!$B$5*AVERAGE(PARÂMETROS!$B$40:$B$91)*H17),1),"N/D")
A18: eap-1_2 | B18: Esc/carg/transp 1aCat DMT<=3000m | C18: m3 | D18: 336915.09 | E18: 226.7957 | F18: 5.1763 | G18: 3.2848 | H18: 1 | I18: =IF(AND(E18>0,H18>0),CEILING(D18/(E18*PARÂMETROS!$B$4*PARÂMETROS!$B$5*AVERAGE(PARÂMETROS!$B$40:$B$91)*H18),1),"N/D")
A19: eap-1_3 | B19: Esc/carg/transp 2aCat DMT<=2000m | C19: m3 | D19: 105311.33 | E19: 156.7133 | F19: 6.2476 | G19: 3.8464 | H19: 1 | I19: =IF(AND(E19>0,H19>0),CEILING(D19/(E19*PARÂMETROS!$B$4*PARÂMETROS!$B$5*AVERAGE(PARÂMETROS!$B$40:$B$91)*H19),1),"N/D")
A20: eap-1_4 | B20: Esc/carg/transp 2aCat DMT<=3000m | C20: m3 | D20: 585945.77 | E20: 156.4746 | F20: 6.6284 | G20: 4.0173 | H20: 1 | I20: =IF(AND(E20>0,H20>0),CEILING(D20/(E20*PARÂMETROS!$B$4*PARÂMETROS!$B$5*AVERAGE(PARÂMETROS!$B$40:$B$91)*H20),1),"N/D")
A21: eap-1_5 | B21: Esc/carg/transp 3aCat DMT<=2000m | C21: m3 | D21: 304634.46 | E21: 144.2398 | F21: 9.6856 | G21: 5.1859 | H21: 1 | I21: =IF(AND(E21>0,H21>0),CEILING(D21/(E21*PARÂMETROS!$B$4*PARÂMETROS!$B$5*AVERAGE(PARÂMETROS!$B$40:$B$91)*H21),1),"N/D")
A22: eap-1_6 | B22: Esc/carg/transp 3aCat DMT<=3000m | C22: m3 | D22: 676519.04 | E22: 143.9367 | F22: 11.7945 | G22: 6.4299 | H22: 1 | I22: =IF(AND(E22>0,H22>0),CEILING(D22/(E22*PARÂMETROS!$B$4*PARÂMETROS!$B$5*AVERAGE(PARÂMETROS!$B$40:$B$91)*H22),1),"N/D")
A23: eap-1_7 | B23: Compactacao aterros 100% Proctor Normal | C23: m3 | D23: 1135635.3 | E23: 189.0899 | F23: 6.1967 | G23: 2.935 | H23: 1 | I23: =IF(AND(E23>0,H23>0),CEILING(D23/(E23*PARÂMETROS!$B$4*PARÂMETROS!$B$5*AVERAGE(PARÂMETROS!$B$40:$B$91)*H23),1),"N/D")
A24: eap-1_8 | B24: Compactacao aterros 100% Proctor Intermediario | C24: m3 | D24: 29411 | E24: 102.1215 | F24: 8.1022 | G24: 3.8375 | H24: 1 | I24: =IF(AND(E24>0,H24>0),CEILING(D24/(E24*PARÂMETROS!$B$4*PARÂMETROS!$B$5*AVERAGE(PARÂMETROS!$B$40:$B$91)*H24),1),"N/D")
A25: eap-1_9 | B25: Construcao corpo aterro material 3a categoria | C25: m3 | D25: 981153.5 | E25: 235.0682 | F25: 4.0706 | G25: 1.8024 | H25: 1 | I25: =IF(AND(E25>0,H25>0),CEILING(D25/(E25*PARÂMETROS!$B$4*PARÂMETROS!$B$5*AVERAGE(PARÂMETROS!$B$40:$B$91)*H25),1),"N/D")
A26: eap-1_10 | B26: Compactacao camada final aterro sobre rocha | C26: m3 | D26: 24721.17 | E26: 85.8374 | F26: 5.6619 | G26: 8.7753 | H26: 1 | I26: =IF(AND(E26>0,H26>0),CEILING(D26/(E26*PARÂMETROS!$B$4*PARÂMETROS!$B$5*AVERAGE(PARÂMETROS!$B$40:$B$91)*H26),1),"N/D")
A29: INDIRETOS — CUSTO FIXO MENSAL E PERMANÊNCIA
A30: Categoria | B30: Custo Fixo Mensal (R$) | C30: Permanência (meses)
A31: ADM | B31: 1059228.6 | C31: 12.93
A32: TOP | B32: 66415.96 | C32: 12.93
A33: LAB | B33: 10794.14 | C33: 12.93
A34: QSMS | B34: 58451.48 | C34: 12.93
A35: MOB | B35: 311892.34 | C35: 13
A38: PRATICABILIDADE SEMANAL (p_j) — VALORES REAIS
A39: Semana ISO | B39: Fator [0,1]
A40: 2026-W24 | B40: 1
A41: 2026-W25 | B41: 1
A42: 2026-W26 | B42: 1
A43: 2026-W27 | B43: 1
A44: 2026-W28 | B44: 1
A45: 2026-W29 | B45: 1
A46: 2026-W30 | B46: 1
A47: 2026-W31 | B47: 1
A48: 2026-W32 | B48: 1
A49: 2026-W33 | B49: 1
A50: 2026-W34 | B50: 1
A51: 2026-W35 | B51: 1
... A91: 2027-W22 | B91: 1
A93: ALOCAÇÃO SEMANAL — NÚMERO DE EQUIPES E_{j,i}
A94: Item ID | B94: Desc. | C94: Qt. total | D94: 2026-W2 | E94: 2026-W2 | F94: 2026-W2 | G94: 2026-W2 | H94: 2026-W2 | I94: 2026-W2 | J94: 2026-W3 | K94: 2026-W3 | L94: 2026-W3 | M94: 2026-W3 | N94: 2026-W3 | O94: 2026-W3 | P94: 2026-W3 | Q94: 2026-W3 | R94: 2026-W3 | S94: 2026-W3 | T94: 2026-W4 | U94: 2026-W4 | V94: 2026-W4 | W94: 2026-W4 | X94: 2026-W4 | Y94: 2026-W4 | Z94: 2026-W4 | AA94: 2026-W4 | AB94: 2026-W4 | AC94: 2026-W4 | AD94: 2026-W5 | AE94: 2026-W5 | AF94: 2026-W5 | AG94: 2026-W5 | AH94: 2027-W0 | AI94: 2027-W0 | AJ94: 2027-W0 | AK94: 2027-W0 | AL94: 2027-W0 | AM94: 2027-W0 | AN94: 2027-W0 | AO94: 2027-W0 | AP94: 2027-W0 | AQ94: 2027-W1 | AR94: 2027-W1 | AS94: 2027-W1 | AT94: 2027-W1 | AU94: 2027-W1 | AV94: 2027-W1 | AW94: 2027-W1 | AX94: 2027-W1 | AY94: 2027-W1 | AZ94: 2027-W1 | BA94: 2027-W2 | BB94: 2027-W2 | BC94: 2027-W2
A95: eap-1_0 | B95: Desmatamento e limpeza de | C95: =PARÂMETROS!D16 | D95: 5 | E95: 5 | F95: 5 | G95: 5 | H95: 5 | I95: 5 | J95: 5 | K95: 5 | L95: 5 | M95: 5 | N95: 5 | O95: 5 | P95: 5 | Q95: 5 | R95: 5 | S95: 5 | T95: 5 | U95: 5 | V95: 5 | W95: 5 | X95: 5 | Y95: 5 | Z95: 5 | AA95: 5 | AB95: 5
A96: eap-1_1 | B96: Esc/carg/transp 1aCat DMT | C96: =PARÂMETROS!D17 | D96: 1 | E96: 1 | F96: 1 | G96: 1 | H96: 1 | I96: 1 | J96: 1 | K96: 1 | L96: 1 | M96: 1 | N96: 1 | O96: 1 | P96: 1 | Q96: 1 | R96: 1 | S96: 1 | T96: 1 | U96: 1 | V96: 1 | W96: 1 | X96: 1 | Y96: 1 | Z96: 1 | AA96: 1 | AB96: 1 | AC96: 1 | AD96: 1 | AE96: 1 | AF96: 1 | AG96: 1 | AH96: 1 | AI96: 1 | AJ96: 1 | AK96: 1 | AL96: 1 | AM96: 1 | AN96: 1 | AO96: 1 | AP96: 1 | AQ96: 1 | AR96: 1 | AS96: 1 | AT96: 1 | AU96: 1 | AV96: 1
A97: eap-1_2 | B97: Esc/carg/transp 1aCat DMT | C97: =PARÂMETROS!D18 | D97: 1 | E97: 1 | F97: 1 | G97: 1 | H97: 1 | I97: 1 | J97: 1 | K97: 1 | L97: 1 | M97: 1 | N97: 1 | O97: 1 | P97: 1 | Q97: 1 | R97: 1 | S97: 1 | T97: 1 | U97: 1 | V97: 1 | W97: 1 | X97: 1 | Y97: 1 | Z97: 1 | AA97: 1 | AB97: 1 | AC97: 1 | AD97: 1 | AE97: 1 | AF97: 1 | AG97: 1 | AH97: 1 | AI97: 1 | AJ97: 1 | AK97: 1 | AL97: 1 | AM97: 1 | AN97: 1 | AO97: 1 | AP97: 1 | AQ97: 1 | AR97: 1 | AS97: 1 | AT97: 1 | AU97: 1 | AV97: 1
A98: eap-1_3 | B98: Esc/carg/transp 2aCat DMT | C98: =PARÂMETROS!D19 | D98: 2 | E98: 2 | F98: 2 | G98: 2 | H98: 2 | I98: 2 | J98: 2 | K98: 2 | L98: 2 | M98: 2 | N98: 2 | O98: 2 | P98: 2 | Q98: 2 | R98: 2 | S98: 2 | T98: 2 | U98: 2 | V98: 2 | W98: 2 | X98: 2 | Y98: 2 | Z98: 2 | AA98: 2 | AB98: 2 | AC98: 2 | AD98: 2 | AE98: 2 | AF98: 2 | AG98: 2 | AH98: 2 | AI98: 2 | AJ98: 2 | AK98: 2 | AL98: 2 | AM98: 2 | AN98: 2 | AO98: 2 | AP98: 2 | AQ98: 2 | AR98: 2 | AS98: 2 | AT98: 2 | AU98: 2 | AV98: 2 | AW98: 2 | AX98: 2 | AY98: 2 | AZ98: 2 | BA98: 2 | BB98: 2
A99: eap-1_4 | B99: Esc/carg/transp 2aCat DMT | C99: =PARÂMETROS!D20 | D99: 2 | E99: 2 | F99: 2 | G99: 2 | H99: 2 | I99: 2 | J99: 2 | K99: 2 | L99: 2 | M99: 2 | N99: 2 | O99: 2 | P99: 2 | Q99: 2 | R99: 2 | S99: 2 | T99: 2 | U99: 2 | V99: 2 | W99: 2 | X99: 2 | Y99: 2 | Z99: 2 | AA99: 2 | AB99: 2 | AC99: 2 | AD99: 2 | AE99: 2 | AF99: 2 | AG99: 2 | AH99: 2 | AI99: 2 | AJ99: 2 | AK99: 2 | AL99: 2 | AM99: 2 | AN99: 2 | AO99: 2 | AP99: 2 | AQ99: 2 | AR99: 2 | AS99: 2 | AT99: 2 | AU99: 2 | AV99: 2 | AW99: 2 | AX99: 2 | AY99: 2 | AZ99: 2 | BA99: 2 | BB99: 2
A100: eap-1_5 | B100: Esc/carg/transp 3aCat DMT | C100: =PARÂMETROS!D21 | D100: 4 | E100: 4 | F100: 4 | G100: 4 | H100: 4 | I100: 4 | J100: 4 | K100: 4 | L100: 4 | M100: 4 | N100: 4 | O100: 4 | P100: 4 | Q100: 4 | R100: 4 | S100: 4 | T100: 4 | U100: 4 | V100: 4 | W100: 4 | X100: 4 | Y100: 4 | Z100: 4 | AA100: 4 | AB100: 4 | AC100: 4 | AD100: 4 | AE100: 4 | AF100: 4 | AG100: 4 | AH100: 4 | AI100: 4 | AJ100: 4 | AK100: 4 | AL100: 4 | AM100: 4 | AN100: 4 | AO100: 4 | AP100: 4 | AQ100: 4 | AR100: 4 | AS100: 4 | AT100: 4 | AU100: 4 | AV100: 4 | AW100: 4 | AX100: 4 | AY100: 4 | AZ100: 4
A101: eap-1_6 | B101: Esc/carg/transp 3aCat DMT | C101: =PARÂMETROS!D22 | D101: 4 | E101: 4 | F101: 4 | G101: 4 | H101: 4 | I101: 4 | J101: 4 | K101: 4 | L101: 4 | M101: 4 | N101: 4 | O101: 4 | P101: 4 | Q101: 4 | R101: 4 | S101: 4 | T101: 4 | U101: 4 | V101: 4 | W101: 4 | X101: 4 | Y101: 4 | Z101: 4 | AA101: 4 | AB101: 4 | AC101: 4 | AD101: 4 | AE101: 4 | AF101: 4 | AG101: 4 | AH101: 4 | AI101: 4 | AJ101: 4 | AK101: 4 | AL101: 4 | AM101: 4 | AN101: 4 | AO101: 4 | AP101: 4 | AQ101: 4 | AR101: 4 | AS101: 4 | AT101: 4 | AU101: 4 | AV101: 4 | AW101: 4 | AX101: 4 | AY101: 4 | AZ101: 4
A102: eap-1_7 | B102: Compactacao aterros 100% | C102: =PARÂMETROS!D23 | D102: 3 | E102: 3 | F102: 3 | G102: 3 | H102: 3 | I102: 3 | J102: 3 | K102: 3 | L102: 3 | M102: 3 | N102: 3 | O102: 3 | P102: 3 | Q102: 3 | R102: 3 | S102: 3 | T102: 3 | U102: 3 | V102: 3 | W102: 3 | X102: 3 | Y102: 3 | Z102: 3 | AA102: 3 | AB102: 3 | AC102: 3 | AD102: 3 | AE102: 3 | AF102: 3 | AG102: 3 | AH102: 3 | AI102: 3 | AJ102: 3 | AK102: 3 | AL102: 3 | AM102: 3 | AN102: 3 | AO102: 3 | AP102: 3 | AQ102: 3 | AR102: 3 | AS102: 3 | AT102: 3 | AU102: 3 | AV102: 3 | AW102: 3 | AX102: 3 | AY102: 3 | AZ102: 3 | BA102: 3 | BB102: 3
A103: eap-1_8 | B103: Compactacao aterros 100% | C103: =PARÂMETROS!D24 | D103: 2 | E103: 2 | F103: 2
A104: eap-1_9 | B104: Construcao corpo aterro m | C104: =PARÂMETROS!D25 | D104: 2 | E104: 2 | F104: 2 | G104: 2 | H104: 2 | I104: 2 | J104: 2 | K104: 2 | L104: 2 | M104: 2 | N104: 2 | O104: 2 | P104: 2 | Q104: 2 | R104: 2 | S104: 2 | T104: 2 | U104: 2 | V104: 2 | W104: 2 | X104: 2 | Y104: 2 | Z104: 2 | AA104: 2 | AB104: 2 | AC104: 2 | AD104: 2 | AE104: 2 | AF104: 2 | AG104: 2 | AH104: 2 | AI104: 2 | AJ104: 2 | AK104: 2 | AL104: 2 | AM104: 2 | AN104: 2 | AO104: 2 | AP104: 2 | AQ104: 2 | AR104: 2 | AS104: 2 | AT104: 2 | AU104: 2 | AV104: 2 | AW104: 2 | AX104: 2 | AY104: 2 | AZ104: 2 | BA104: 2 | BB104: 2 | BC104: 2
A105: eap-1_10 | B105: Compactacao camada final | C105: =PARÂMETROS!D26 | D105: 1 | E105: 1 | F105: 1 | G105: 1 | H105: 1 | I105: 1

Sheet RECURSOS
A1: RECURSOS — TAXAS E COMPOSIÇÃO DAS EQUIPES
A3: MÃO DE OBRA — TAXAS MENSAIS
A4: ID Função | B4: Descrição | C4: Custo Mensal Unitário (R$)
A5: P0040 | B5: Operador de Escavadeira | C5: 10300
A6: P0048 | B6: Operador de Trator de Esteiras | C6: 10300
A7: P0062 | B7: Operador de motosserra | C7: 7307.65
A8: P0001 | B8: Ajudante | C8: 4209.32
A9: P0079 | B9: SINALEIRO | C9: 6341.17
A10: P0065 | B10: Encarregado de Frente | C10: 7500
A11: P0072 | B11: Apontador | C11: 6341.17
A12: P0032 | B12: Motorista de Caminhão Basculante | C12: 6341.17
A13: P0043 | B13: Operador de Motoniveladora | C13: 10300
A14: P0049 | B14: Operador de Trator de Pneu | C14: 6341.17
A15: P0033 | B15: Motorista de Caminhão Pipa | C15: 6341.17
A16: P0046 | B16: Operador de Rolo Compactador | C16: 6341.17
A17: P0029 | B17: Gredista | C17: 6341.17
A20: EQUIPAMENTOS — TAXAS MENSAIS
A21: ID Equip. | B21: Descrição | C21: Aluguel Mensal (R$) | D21: Comb. Mensal (R$) (por unidade)
A22: EQ-E0016 | B22: Escavadeira Hidráulica 22t | C22: 35639.3 | D22: 0
A23: EQ-E0035 | B23: Trator de esteiras 20T | C23: 21683.2 | D23: 22957.71
A24: EQ-E0028 | B24: Motoniveladora 120HP | C24: 36664.32 | D24: 11478.86
A25: EQ-E0034 | B25: Trator de pneus com grade | C25: 7744 | D25: 10203.43
A26: EQ-E0037 | B26: Trator de esteiras 40T | C26: 20421.63 | D26: 30610.29
A29: COMPOSIÇÃO DAS EQUIPES — nº PESSOAS / UNIDADES POR ITEM
A30: Item ID | B30: Descrição | C30: P0040 | D30: P0048 | E30: P0062 | F30: P0001 | G30: P0079 | H30: P0065 | I30: P0072 | J30: P0032 | K30: P0043 | L30: P0049 | M30: P0033 | N30: P0046 | O30: P0029 | P30: EQ-E0016 | Q30: EQ-E0035 | R30: EQ-E0028 | S30: EQ-E0034 | T30: EQ-E0037
A31: eap-1_0 | B31: Desmatamento e limpeza de | C31: 1 | D31: 6 | E31: 6 | F31: 6 | G31: 6 | H31: 1 | I31: 1 | P31: 1 | Q31: 6
A32: eap-1_1 | B32: Esc/carg/transp 1aCat DMT | C32: 1 | F32: 1 | H32: 1 | J32: 7 | P32: 1
A33: eap-1_2 | B33: Esc/carg/transp 1aCat DMT | C33: 1 | F33: 1 | H33: 1 | J33: 7 | P33: 1
A34: eap-1_3 | B34: Esc/carg/transp 2aCat DMT | C34: 2 | F34: 2 | H34: 1 | J34: 11 | P34: 2
A35: eap-1_4 | B35: Esc/carg/transp 2aCat DMT | C35: 2 | F35: 2 | H35: 1 | J35: 11 | P35: 2
A36: eap-1_5 | B36: Esc/carg/transp 3aCat DMT | C36: 4 | F36: 4 | J36: 25 | P36: 4
A37: eap-1_6 | B37: Esc/carg/transp 3aCat DMT | C37: 4 | F37: 4 | J37: 25 | P37: 4
A38: eap-1_7 | B38: Compactacao aterros 100% | F38: 6 | H38: 2 | K38: 3 | L38: 3 | M38: 3 | N38: 6 | O38: 3 | R38: 3 | S38: 3
A39: eap-1_8 | B39: Compactacao aterros 100% | F39: 6 | H39: 2 | K39: 3 | L39: 3 | M39: 3 | N39: 6 | O39: 3 | R39: 3 | S39: 3
A40: eap-1_9 | B40: Construcao corpo aterro m | D40: 2 | F40: 4 | H40: 1 | N40: 4 | O40: 2 | T40: 2
A41: eap-1_10 | B41: Compactacao camada final | D41: 1 | F41: 2 | M41: 1 | N41: 3 | Q41: 1

Sheet CUSTOS DIR.
A1: CUSTOS DIRETOS — EQUIPES POR ITEM (FÓRMULAS SOBRE RECURSOS)
A2: Item ID | B2: Desc. | C2: MO Mensal (R$) | D2: EQ Mensal (R$) | E2: Comb. Mensal (R$) | F2: Total Fixo/Mês (R$) | G2: Permanência (sem.) | H2: Permanência (mes.) | I2: Custo Total (R$)
A3: eap-1_0 | B3: Desmatamento e limpeza | C3: =RECURSOS!C31*RECURSOS!$C$5+RECURSOS!D31*RECURSOS!$C$6+RECURSOS!E31*RECURSOS!$C$7+RECURSOS!F31*RECURSOS!$C$8+RECURSOS!G31*RECURSOS!$C$9+RECURSOS!H31*RECURSOS!$C$10+RECURSOS!I31*RECURSOS!$C$11+RECURSOS!J31*RECURSOS!$C$12+RECURSOS!K31*RECURSOS!$C$13+RECURSOS!L31*RECURSOS!$C$14+RECURSOS!M31*RECURSOS!$C$15+RECURSOS!N31*RECURSOS!$C$16+RECURSOS!O31*RECURSOS!$C$17 | D3: =RECURSOS!P31*RECURSOS!$C$22+RECURSOS!Q31*RECURSOS!$C$23+RECURSOS!R31*RECURSOS!$C$24+RECURSOS!S31*RECURSOS!$C$25+RECURSOS!T31*RECURSOS!$C$26 | E3: =RECURSOS!P31*RECURSOS!$D$22+RECURSOS!Q31*RECURSOS!$D$23+RECURSOS!R31*RECURSOS!$D$24+RECURSOS!S31*RECURSOS!$D$25+RECURSOS!T31*RECURSOS!$D$26 | F3: =C3+D3+E3 | G3: =PARÂMETROS!I16 | H3: =G3/4.348 | I3: =F3*H3
A4: eap-1_1 | B4: Esc/carg/transp 1aCat | C4: =RECURSOS!C32*RECURSOS!$C$5+RECURSOS!D32*RECURSOS!$C$6+RECURSOS!E32*RECURSOS!$C$7+RECURSOS!F32*RECURSOS!$C$8+RECURSOS!G32*RECURSOS!$C$9+RECURSOS!H32*RECURSOS!$C$10+RECURSOS!I32*RECURSOS!$C$11+RECURSOS!J32*RECURSOS!$C$12+RECURSOS!K32*RECURSOS!$C$13+RECURSOS!L32*RECURSOS!$C$14+RECURSOS!M32*RECURSOS!$C$15+RECURSOS!N32*RECURSOS!$C$16+RECURSOS!O32*RECURSOS!$C$17 | D4: =RECURSOS!P32*RECURSOS!$C$22+RECURSOS!Q32*RECURSOS!$C$23+RECURSOS!R32*RECURSOS!$C$24+RECURSOS!S32*RECURSOS!$C$25+RECURSOS!T32*RECURSOS!$C$26 | E4: =RECURSOS!P32*RECURSOS!$D$22+RECURSOS!Q32*RECURSOS!$D$23+RECURSOS!R32*RECURSOS!$D$24+RECURSOS!S32*RECURSOS!$D$25+RECURSOS!T32*RECURSOS!$D$26 | F4: =C4+D4+E4 | G4: =PARÂMETROS!I17 | H4: =G4/4.348 | I4: =F4*H4
A5: eap-1_2 | B5: Esc/carg/transp 1aCat | C5: =RECURSOS!C33*RECURSOS!$C$5+RECURSOS!D33*RECURSOS!$C$6+RECURSOS!E33*RECURSOS!$C$7+RECURSOS!F33*RECURSOS!$C$8+RECURSOS!G33*RECURSOS!$C$9+RECURSOS!H33*RECURSOS!$C$10+RECURSOS!I33*RECURSOS!$C$11+RECURSOS!J33*RECURSOS!$C$12+RECURSOS!K33*RECURSOS!$C$13+RECURSOS!L33*RECURSOS!$C$14+RECURSOS!M33*RECURSOS!$C$15+RECURSOS!N33*RECURSOS!$C$16+RECURSOS!O33*RECURSOS!$C$17 | D5: =RECURSOS!P33*RECURSOS!$C$22+RECURSOS!Q33*RECURSOS!$C$23+RECURSOS!R33*RECURSOS!$C$24+RECURSOS!S33*RECURSOS!$C$25+RECURSOS!T33*RECURSOS!$C$26 | E5: =RECURSOS!P33*RECURSOS!$D$22+RECURSOS!Q33*RECURSOS!$D$23+RECURSOS!R33*RECURSOS!$D$24+RECURSOS!S33*RECURSOS!$D$25+RECURSOS!T33*RECURSOS!$D$26 | F5: =C5+D5+E5 | G5: =PARÂMETROS!I18 | H5: =G5/4.348 | I5: =F5*H5
A6: eap-1_3 | B6: Esc/carg/transp 2aCat | C6: =RECURSOS!C34*RECURSOS!$C$5+RECURSOS!D34*RECURSOS!$C$6+RECURSOS!E34*RECURSOS!$C$7+RECURSOS!F34*RECURSOS!$C$8+RECURSOS!G34*RECURSOS!$C$9+RECURSOS!H34*RECURSOS!$C$10+RECURSOS!I34*RECURSOS!$C$11+RECURSOS!J34*RECURSOS!$C$12+RECURSOS!K34*RECURSOS!$C$13+RECURSOS!L34*RECURSOS!$C$14+RECURSOS!M34*RECURSOS!$C$15+RECURSOS!N34*RECURSOS!$C$16+RECURSOS!O34*RECURSOS!$C$17 | D6: =RECURSOS!P34*RECURSOS!$C$22+RECURSOS!Q34*RECURSOS!$C$23+RECURSOS!R34*RECURSOS!$C$24+RECURSOS!S34*RECURSOS!$C$25+RECURSOS!T34*RECURSOS!$C$26 | E6: =RECURSOS!P34*RECURSOS!$D$22+RECURSOS!Q34*RECURSOS!$D$23+RECURSOS!R34*RECURSOS!$D$24+RECURSOS!S34*RECURSOS!$D$25+RECURSOS!T34*RECURSOS!$D$26 | F6: =C6+D6+E6 | G6: =PARÂMETROS!I19 | H6: =G6/4.348 | I6: =F6*H6
A7: eap-1_4 | B7: Esc/carg/transp 2aCat | C7: =RECURSOS!C35*RECURSOS!$C$5+RECURSOS!D35*RECURSOS!$C$6+RECURSOS!E35*RECURSOS!$C$7+RECURSOS!F35*RECURSOS!$C$8+RECURSOS!G35*RECURSOS!$C$9+RECURSOS!H35*RECURSOS!$C$10+RECURSOS!I35*RECURSOS!$C$11+RECURSOS!J35*RECURSOS!$C$12+RECURSOS!K35*RECURSOS!$C$13+RECURSOS!L35*RECURSOS!$C$14+RECURSOS!M35*RECURSOS!$C$15+RECURSOS!N35*RECURSOS!$C$16+RECURSOS!O35*RECURSOS!$C$17 | D7: =RECURSOS!P35*RECURSOS!$C$22+RECURSOS!Q35*RECURSOS!$C$23+RECURSOS!R35*RECURSOS!$C$24+RECURSOS!S35*RECURSOS!$C$25+RECURSOS!T35*RECURSOS!$C$26 | E7: =RECURSOS!P35*RECURSOS!$D$22+RECURSOS!Q35*RECURSOS!$D$23+RECURSOS!R35*RECURSOS!$D$24+RECURSOS!S35*RECURSOS!$D$25+RECURSOS!T35*RECURSOS!$D$26 | F7: =C7+D7+E7 | G7: =PARÂMETROS!I20 | H7: =G7/4.348 | I7: =F7*H7
A8: eap-1_5 | B8: Esc/carg/transp 3aCat | C8: =RECURSOS!C36*RECURSOS!$C$5+RECURSOS!D36*RECURSOS!$C$6+RECURSOS!E36*RECURSOS!$C$7+RECURSOS!F36*RECURSOS!$C$8+RECURSOS!G36*RECURSOS!$C$9+RECURSOS!H36*RECURSOS!$C$10+RECURSOS!I36*RECURSOS!$C$11+RECURSOS!J36*RECURSOS!$C$12+RECURSOS!K36*RECURSOS!$C$13+RECURSOS!L36*RECURSOS!$C$14+RECURSOS!M36*RECURSOS!$C$15+RECURSOS!N36*RECURSOS!$C$16+RECURSOS!O36*RECURSOS!$C$17 | D8: =RECURSOS!P36*RECURSOS!$C$22+RECURSOS!Q36*RECURSOS!$C$23+RECURSOS!R36*RECURSOS!$C$24+RECURSOS!S36*RECURSOS!$C$25+RECURSOS!T36*RECURSOS!$C$26 | E8: =RECURSOS!P36*RECURSOS!$D$22+RECURSOS!Q36*RECURSOS!$D$23+RECURSOS!R36*RECURSOS!$D$24+RECURSOS!S36*RECURSOS!$D$25+RECURSOS!T36*RECURSOS!$D$26 | F8: =C8+D8+E8 | G8: =PARÂMETROS!I21 | H8: =G8/4.348 | I8: =F8*H8
A9: eap-1_6 | B9: Esc/carg/transp 3aCat | C9: =RECURSOS!C37*RECURSOS!$C$5+RECURSOS!D37*RECURSOS!$C$6+RECURSOS!E37*RECURSOS!$C$7+RECURSOS!F37*RECURSOS!$C$8+RECURSOS!G37*RECURSOS!$C$9+RECURSOS!H37*RECURSOS!$C$10+RECURSOS!I37*RECURSOS!$C$11+RECURSOS!J37*RECURSOS!$C$12+RECURSOS!K37*RECURSOS!$C$13+RECURSOS!L37*RECURSOS!$C$14+RECURSOS!M37*RECURSOS!$C$15+RECURSOS!N37*RECURSOS!$C$16+RECURSOS!O37*RECURSOS!$C$17 | D9: =RECURSOS!P37*RECURSOS!$C$22+RECURSOS!Q37*RECURSOS!$C$23+RECURSOS!R37*RECURSOS!$C$24+RECURSOS!S37*RECURSOS!$C$25+RECURSOS!T37*RECURSOS!$C$26 | E9: =RECURSOS!P37*RECURSOS!$D$22+RECURSOS!Q37*RECURSOS!$D$23+RECURSOS!R37*RECURSOS!$D$24+RECURSOS!S37*RECURSOS!$D$25+RECURSOS!T37*RECURSOS!$D$26 | F9: =C9+D9+E9 | G9: =PARÂMETROS!I22 | H9: =G9/4.348 | I9: =F9*H9
A10: eap-1_7 | B10: Compactacao aterros 10 | C10: =RECURSOS!C38*RECURSOS!$C$5+RECURSOS!D38*RECURSOS!$C$6+RECURSOS!E38*RECURSOS!$C$7+RECURSOS!F38*RECURSOS!$C$8+RECURSOS!G38*RECURSOS!$C$9+RECURSOS!H38*RECURSOS!$C$10+RECURSOS!I38*RECURSOS!$C$11+RECURSOS!J38*RECURSOS!$C$12+RECURSOS!K38*RECURSOS!$C$13+RECURSOS!L38*RECURSOS!$C$14+RECURSOS!M38*RECURSOS!$C$15+RECURSOS!N38*RECURSOS!$C$16+RECURSOS!O38*RECURSOS!$C$17 | D10: =RECURSOS!P38*RECURSOS!$C$22+RECURSOS!Q38*RECURSOS!$C$23+RECURSOS!R38*RECURSOS!$C$24+RECURSOS!S38*RECURSOS!$C$25+RECURSOS!T38*RECURSOS!$C$26 | E10: =RECURSOS!P38*RECURSOS!$D$22+RECURSOS!Q38*RECURSOS!$D$23+RECURSOS!R38*RECURSOS!$D$24+RECURSOS!S38*RECURSOS!$D$25+RECURSOS!T38*RECURSOS!$D$26 | F10: =C10+D10+E10 | G10: =PARÂMETROS!I23 | H10: =G10/4.348 | I10: =F10*H10
A11: eap-1_8 | B11: Compactacao aterros 10 | C11: =RECURSOS!C39*RECURSOS!$C$5+RECURSOS!D39*RECURSOS!$C$6+RECURSOS!E39*RECURSOS!$C$7+RECURSOS!F39*RECURSOS!$C$8+RECURSOS!G39*RECURSOS!$C$9+RECURSOS!H39*RECURSOS!$C$10+RECURSOS!I39*RECURSOS!$C$11+RECURSOS!J39*RECURSOS!$C$12+RECURSOS!K39*RECURSOS!$C$13+RECURSOS!L39*RECURSOS!$C$14+RECURSOS!M39*RECURSOS!$C$15+RECURSOS!N39*RECURSOS!$C$16+RECURSOS!O39*RECURSOS!$C$17 | D11: =RECURSOS!P39*RECURSOS!$C$22+RECURSOS!Q39*RECURSOS!$C$23+RECURSOS!R39*RECURSOS!$C$24+RECURSOS!S39*RECURSOS!$C$25+RECURSOS!T39*RECURSOS!$C$26 | E11: =RECURSOS!P39*RECURSOS!$D$22+RECURSOS!Q39*RECURSOS!$D$23+RECURSOS!R39*RECURSOS!$D$24+RECURSOS!S39*RECURSOS!$D$25+RECURSOS!T39*RECURSOS!$D$26 | F11: =C11+D11+E11 | G11: =PARÂMETROS!I24 | H11: =G11/4.348 | I11: =F11*H11
A12: eap-1_9 | B12: Construcao corpo aterr | C12: =RECURSOS!C40*RECURSOS!$C$5+RECURSOS!D40*RECURSOS!$C$6+RECURSOS!E40*RECURSOS!$C$7+RECURSOS!F40*RECURSOS!$C$8+RECURSOS!G40*RECURSOS!$C$9+RECURSOS!H40*RECURSOS!$C$10+RECURSOS!I40*RECURSOS!$C$11+RECURSOS!J40*RECURSOS!$C$12+RECURSOS!K40*RECURSOS!$C$13+RECURSOS!L40*RECURSOS!$C$14+RECURSOS!M40*RECURSOS!$C$15+RECURSOS!N40*RECURSOS!$C$16+RECURSOS!O40*RECURSOS!$C$17 | D12: =RECURSOS!P40*RECURSOS!$C$22+RECURSOS!Q40*RECURSOS!$C$23+RECURSOS!R40*RECURSOS!$C$24+RECURSOS!S40*RECURSOS!$C$25+RECURSOS!T40*RECURSOS!$C$26 | E12: =RECURSOS!P40*RECURSOS!$D$22+RECURSOS!Q40*RECURSOS!$D$23+RECURSOS!R40*RECURSOS!$D$24+RECURSOS!S40*RECURSOS!$D$25+RECURSOS!T40*RECURSOS!$D$26 | F12: =C12+D12+E12 | G12: =PARÂMETROS!I25 | H12: =G12/4.348 | I12: =F12*H12
A13: eap-1_10 | B13: Compactacao camada fin | C13: =RECURSOS!C41*RECURSOS!$C$5+RECURSOS!D41*RECURSOS!$C$6+RECURSOS!E41*RECURSOS!$C$7+RECURSOS!F41*RECURSOS!$C$8+RECURSOS!G41*RECURSOS!$C$9+RECURSOS!H41*RECURSOS!$C$10+RECURSOS!I41*RECURSOS!$C$11+RECURSOS!J41*RECURSOS!$C$12+RECURSOS!K41*RECURSOS!$C$13+RECURSOS!L41*RECURSOS!$C$14+RECURSOS!M41*RECURSOS!$C$15+RECURSOS!N41*RECURSOS!$C$16+RECURSOS!O41*RECURSOS!$C$17 | D13: =RECURSOS!P41*RECURSOS!$C$22+RECURSOS!Q41*RECURSOS!$C$23+RECURSOS!R41*RECURSOS!$C$24+RECURSOS!S41*RECURSOS!$C$25+RECURSOS!T41*RECURSOS!$C$26 | E13: =RECURSOS!P41*RECURSOS!$D$22+RECURSOS!Q41*RECURSOS!$D$23+RECURSOS!R41*RECURSOS!$D$24+RECURSOS!S41*RECURSOS!$D$25+RECURSOS!T41*RECURSOS!$D$26 | F13: =C13+D13+E13 | G13: =PARÂMETROS!I26 | H13: =G13/4.348 | I13: =F13*H13
A14: TOTAL | C14: =SUM(C3:C13) | D14: =SUM(D3:D13) | E14: =SUM(E3:E13) | F14: =SUM(F3:F13) | I14: =SUM(I3:I13)

Sheet ORÇAMENTO
A1: ORÇAMENTO — PREÇOS UNITÁRIOS E SUBTOTAIS (FÓRMULAS)
A2: Item ID | B2: Descrição | C2: Un. | D2: Quantitativo | E2: P.U. Diesel | F2: P.U. MO | G2: P.U. s/BDI | H2: P.U. c/BDI | I2: Subtotal s/BDI | J2: Subtotal c/BDI | K2: Δ Cronograma
A3: =PARÂMETROS!A16 | B3: =PARÂMETROS!B16 | C3: =PARÂMETROS!C16 | D3: =PARÂMETROS!D16 | E3: =PARÂMETROS!F16 | F3: =PARÂMETROS!G16 | G3: =E3+F3 | H3: =E3*(1+PARÂMETROS!$B$9)+F3*(1+PARÂMETROS!$B$10) | I3: =D3*G3 | J3: =D3*H3 | K3: (ver CRONOGRAMA)
A4: =PARÂMETROS!A17 | B4: =PARÂMETROS!B17 | C4: =PARÂMETROS!C17 | D4: =PARÂMETROS!D17 | E4: =PARÂMETROS!F17 | F4: =PARÂMETROS!G17 | G4: =E4+F4 | H4: =E4*(1+PARÂMETROS!$B$9)+F4*(1+PARÂMETROS!$B$10) | I4: =D4*G4 | J4: =D4*H4 | K4: (ver CRONOGRAMA)
A5: =PARÂMETROS!A18 | B5: =PARÂMETROS!B18 | C5: =PARÂMETROS!C18 | D5: =PARÂMETROS!D18 | E5: =PARÂMETROS!F18 | F5: =PARÂMETROS!G18 | G5: =E5+F5 | H5: =E5*(1+PARÂMETROS!$B$9)+F5*(1+PARÂMETROS!$B$10) | I5: =D5*G5 | J5: =D5*H5 | K5: (ver CRONOGRAMA)
A6: =PARÂMETROS!A19 | B6: =PARÂMETROS!B19 | C6: =PARÂMETROS!C19 | D6: =PARÂMETROS!D19 | E6: =PARÂMETROS!F19 | F6: =PARÂMETROS!G19 | G6: =E6+F6 | H6: =E6*(1+PARÂMETROS!$B$9)+F6*(1+PARÂMETROS!$B$10) | I6: =D6*G6 | J6: =D6*H6 | K6: (ver CRONOGRAMA)
A7: =PARÂMETROS!A20 | B7: =PARÂMETROS!B20 | C7: =PARÂMETROS!C20 | D7: =PARÂMETROS!D20 | E7: =PARÂMETROS!F20 | F7: =PARÂMETROS!G20 | G7: =E7+F7 | H7: =E7*(1+PARÂMETROS!$B$9)+F7*(1+PARÂMETROS!$B$10) | I7: =D7*G7 | J7: =D7*H7 | K7: (ver CRONOGRAMA)
A8: =PARÂMETROS!A21 | B8: =PARÂMETROS!B21 | C8: =PARÂMETROS!C21 | D8: =PARÂMETROS!D21 | E8: =PARÂMETROS!F21 | F8: =PARÂMETROS!G21 | G8: =E8+F8 | H8: =E8*(1+PARÂMETROS!$B$9)+F8*(1+PARÂMETROS!$B$10) | I8: =D8*G8 | J8: =D8*H8 | K8: (ver CRONOGRAMA)
A9: =PARÂMETROS!A22 | B9: =PARÂMETROS!B22 | C9: =PARÂMETROS!C22 | D9: =PARÂMETROS!D22 | E9: =PARÂMETROS!F22 | F9: =PARÂMETROS!G22 | G9: =E9+F9 | H9: =E9*(1+PARÂMETROS!$B$9)+F9*(1+PARÂMETROS!$B$10) | I9: =D9*G9 | J9: =D9*H9 | K9: (ver CRONOGRAMA)
A10: =PARÂMETROS!A23 | B10: =PARÂMETROS!B23 | C10: =PARÂMETROS!C23 | D10: =PARÂMETROS!D23 | E10: =PARÂMETROS!F23 | F10: =PARÂMETROS!G23 | G10: =E10+F10 | H10: =E10*(1+PARÂMETROS!$B$9)+F10*(1+PARÂMETROS!$B$10) | I10: =D10*G10 | J10: =D10*H10 | K10: (ver CRONOGRAMA)
A11: =PARÂMETROS!A24 | B11: =PARÂMETROS!B24 | C11: =PARÂMETROS!C24 | D11: =PARÂMETROS!D24 | E11: =PARÂMETROS!F24 | F11: =PARÂMETROS!G24 | G11: =E11+F11 | H11: =E11*(1+PARÂMETROS!$B$9)+F11*(1+PARÂMETROS!$B$10) | I11: =D11*G11 | J11: =D11*H11 | K11: (ver CRONOGRAMA)
A12: =PARÂMETROS!A25 | B12: =PARÂMETROS!B25 | C12: =PARÂMETROS!C25 | D12: =PARÂMETROS!D25 | E12: =PARÂMETROS!F25 | F12: =PARÂMETROS!G25 | G12: =E12+F12 | H12: =E12*(1+PARÂMETROS!$B$9)+F12*(1+PARÂMETROS!$B$10) | I12: =D12*G12 | J12: =D12*H12 | K12: (ver CRONOGRAMA)
A13: =PARÂMETROS!A26 | B13: =PARÂMETROS!B26 | C13: =PARÂMETROS!C26 | D13: =PARÂMETROS!D26 | E13: =PARÂMETROS!F26 | F13: =PARÂMETROS!G26 | G13: =E13+F13 | H13: =E13*(1+PARÂMETROS!$B$9)+F13*(1+PARÂMETROS!$B$10) | I13: =D13*G13 | J13: =D13*H13 | K13: (ver CRONOGRAMA)
A14: TOTAL | I14: =SUM(I3:I13) | J14: =SUM(J3:J13)

Sheet CRONOGRAMA
A1: CRONOGRAMA — PRODUÇÃO E COMPLETUDE (E×P×H×D×p_j)
A2: Item ID | B2: Descrição | C2: Qtd. planif. | D2: Qtd. prog. total | E2: Δ fech. (%) | F2: Métrica | G2: 2026-W2 | H2: 2026-W2 | I2: 2026-W2 | J2: 2026-W2 | K2: 2026-W2 | L2: 2026-W2 | M2: 2026-W3 | N2: 2026-W3 | O2: 2026-W3 | P2: 2026-W3 | Q2: 2026-W3 | R2: 2026-W3 | S2: 2026-W3 | T2: 2026-W3 | U2: 2026-W3 | V2: 2026-W3 | W2: 2026-W4 | X2: 2026-W4 | Y2: 2026-W4 | Z2: 2026-W4 | AA2: 2026-W4 | AB2: 2026-W4 | AC2: 2026-W4 | AD2: 2026-W4 | AE2: 2026-W4 | AF2: 2026-W4 | AG2: 2026-W5 | AH2: 2026-W5 | AI2: 2026-W5 | AJ2: 2026-W5 | AK2: 2027-W0 | AL2: 2027-W0 | AM2: 2027-W0 | AN2: 2027-W0 | AO2: 2027-W0 | AP2: 2027-W0 | AQ2: 2027-W0 | AR2: 2027-W0 | AS2: 2027-W0 | AT2: 2027-W1 | AU2: 2027-W1 | AV2: 2027-W1 | AW2: 2027-W1 | AX2: 2027-W1 | AY2: 2027-W1 | AZ2: 2027-W1 | BA2: 2027-W1 | BB2: 2027-W1 | BC2: 2027-W1 | BD2: 2027-W2 | BE2: 2027-W2 | BF2: 2027-W2
A3: Praticabilidade (p_j) | G3: =PARÂMETROS!$B$40 | H3: =PARÂMETROS!$B$41 | I3: =PARÂMETROS!$B$42 | J3: =PARÂMETROS!$B$43 | K3: =PARÂMETROS!$B$44 | L3: =PARÂMETROS!$B$45 | M3: =PARÂMETROS!$B$46 | N3: =PARÂMETROS!$B$47 | O3: =PARÂMETROS!$B$48 | P3: =PARÂMETROS!$B$49 | Q3: =PARÂMETROS!$B$50 | R3: =PARÂMETROS!$B$51 | S3: =PARÂMETROS!$B$52 | T3: =PARÂMETROS!$B$53 | U3: =PARÂMETROS!$B$54 | V3: =PARÂMETROS!$B$55 | W3: =PARÂMETROS!$B$56 | X3: =PARÂMETROS!$B$57 | Y3: =PARÂMETROS!$B$58 | Z3: =PARÂMETROS!$B$59 | AA3: =PARÂMETROS!$B$60 | AB3: =PARÂMETROS!$B$61 | AC3: =PARÂMETROS!$B$62 | AD3: =PARÂMETROS!$B$63 | AE3: =PARÂMETROS!$B$64 | AF3: =PARÂMETROS!$B$65 | AG3: =PARÂMETROS!$B$66 | AH3: =PARÂMETROS!$B$67 | AI3: =PARÂMETROS!$B$68 | AJ3: =PARÂMETROS!$B$69 | AK3: =PARÂMETROS!$B$70 | AL3: =PARÂMETROS!$B$71 | AM3: =PARÂMETROS!$B$72 | AN3: =PARÂMETROS!$B$73 | AO3: =PARÂMETROS!$B$74 | AP3: =PARÂMETROS!$B$75 | AQ3: =PARÂMETROS!$B$76 | AR3: =PARÂMETROS!$B$77 | AS3: =PARÂMETROS!$B$78 | AT3: =PARÂMETROS!$B$79 | AU3: =PARÂMETROS!$B$80 | AV3: =PARÂMETROS!$B$81 | AW3: =PARÂMETROS!$B$82 | AX3: =PARÂMETROS!$B$83 | AY3: =PARÂMETROS!$B$84 | AZ3: =PARÂMETROS!$B$85 | BA3: =PARÂMETROS!$B$86 | BB3: =PARÂMETROS!$B$87 | BC3: =PARÂMETROS!$B$88 | BD3: =PARÂMETROS!$B$89 | BE3: =PARÂMETROS!$B$90 | BF3: =PARÂMETROS!$B$91
A4: eap-1_0 | B4: Desmatamento e limpeza de | C4: =PARÂMETROS!D16 | D4: =SUM(G4:BF4) | E4: =IF(C4>0,(D4-C4)/C4,0) | F4: Produção semanal | G4: =IFERROR(PARÂMETROS!D95*PARÂMETROS!E16*PARÂMETROS!$B$4*PARÂMETROS!$B$5*PARÂMETROS!$B$40,0) | H4: =IFERROR(PARÂMETROS!E95*PARÂMETROS!E16*PARÂMETROS!$B$4*PARÂMETROS!$B$5*PARÂMETROS!$B$41,0) | I4: =IFERROR(PARÂMETROS!F95*PARÂMETROS!E16*PARÂMETROS!$B$4*PARÂMETROS!$B$5*PARÂMETROS!$B$42,0) | J4: =IFERROR(PARÂMETROS!G95*PARÂMETROS!E16*PARÂMETROS!$B$4*PARÂMETROS!$B$5*PARÂMETROS!$B$43,0) | K4: =IFERROR(PARÂMETROS!H95*PARÂMETROS!E16*PARÂMETROS!$B$4*PARÂMETROS!$B$5*PARÂMETROS!$B$44,0) | L4: =IFERROR(PARÂMETROS!I95*PARÂMETROS!E16*PARÂMETROS!$B$4*PARÂMETROS!$B$5*PARÂMETROS!$B$45,0) | M4: =IFERROR(PARÂMETROS!J95*PARÂMETROS!E16*PARÂMETROS!$B$4*PARÂMETROS!$B$5*PARÂMETROS!$B$46,0) | N4: =IFERROR(PARÂMETROS!K95*PARÂMETROS!E16*PARÂMETROS!$B$4*PARÂMETROS!$B$5*PARÂMETROS!$B$47,0) | O4: =IFERROR(PARÂMETROS!L95*PARÂMETROS!E16*PARÂMETROS!$B$4*PARÂMETROS!$B$5*PARÂMETROS!$B$48,0) | P4: =IFERROR(PARÂMETROS!M95*PARÂMETROS!E16*PARÂMETROS!$B$4*PARÂMETROS!$B$5*PARÂMETROS!$B$49,0) | Q4: =IFERROR(PARÂMETROS!N95*PARÂMETROS!E16*PARÂMETROS!$B$4*PARÂMETROS!$B$5*PARÂMETROS!$B$50,0) | R4: =IFERROR(PARÂMETROS!O95*PARÂMETROS!E16*PARÂMETROS!$B$4*PARÂMETROS!$B$5*PARÂMETROS!$B$51,0) | S4: =IFERROR(PARÂMETROS!P95*PARÂMETROS!E16*PARÂMETROS!$B$4*PARÂMETROS!$B$5*PARÂMETROS!$B$52,0) | T4: =IFERROR(PARÂMETROS!Q95*PARÂMETROS!E16*PARÂMETROS!$B$4*PARÂMETROS!$B$5*PARÂMETROS!$B$53,0) | U4: =IFERROR(PARÂMETROS!R95*PARÂMETROS!E16*PARÂMETROS!$B$4*PARÂMETROS!$B$5*PARÂMETROS!$B$54,0) | V4: =IFERROR(PARÂMETROS!S95*PARÂMETROS!E16*PARÂMETROS!$B$4*PARÂMETROS!$B$5*PARÂMETROS!$B$55,0) | W4: =IFERROR(PARÂMETROS!T95*PARÂMETROS!E16*PARÂMETROS!$B$4*PARÂMETROS!$B$5*PARÂMETROS!$B$56,0) | X4: =IFERROR(PARÂMETROS!U95*PARÂMETROS!E16*PARÂMETROS!$B$4*PARÂMETROS!$B$5*PARÂMETROS!$B$57,0) | Y4: =IFERROR(PARÂMETROS!V95*PARÂMETROS!E16*PARÂMETROS!$B$4*PARÂMETROS!$B$5*PARÂMETROS!$B$58,0) | Z4: =IFERROR(PARÂMETROS!W95*PARÂMETROS!E16*PARÂMETROS!$B$4*PARÂMETROS!$B$5*PARÂMETROS!$B$59,0) | AA4: =IFERROR(PARÂMETROS!X95*PARÂMETROS!E16*PARÂMETROS!$B$4*PARÂMETROS!$B$5*PARÂMETROS!$B$60,0) | AB4: =IFERROR(PARÂMETROS!Y95*PARÂMETROS!E16*PARÂMETROS!$B$4*PARÂMETROS!$B$5*PARÂMETROS!$B$61,0) | AC4: =IFERROR(PARÂMETROS!Z95*PARÂMETROS!E16*PARÂMETROS!$B$4*PARÂMETROS!$B$5*PARÂMETROS!$B$62,0) | AD4: =IFERROR(PARÂMETROS!AA95*PARÂMETROS!E16*PARÂMETROS!$B$4*PARÂMETROS!$B$5*PARÂMETROS!$B$63,0) | AE4: =IFERROR(PARÂMETROS!AB95*PARÂMETROS!E16*PARÂMETROS!$B$4*PARÂMETROS!$B$5*PARÂMETROS!$B$64,0) | AF4: =IFERROR(PARÂMETROS!AC95*PARÂMETROS!E16*PARÂMETROS!$B$4*PARÂMETROS!$B$5*PARÂMETROS!$B$65,0) | AG4: =IFERROR(PARÂMETROS!AD95*PARÂMETROS!E16*PARÂMETROS!$B$4*PARÂMETROS!$B$5*PARÂMETROS!$B$66,0) | AH4: =IFERROR(PARÂMETROS!AE95*PARÂMETROS!E16*PARÂMETROS!$B$4*PARÂMETROS!$B$5*PARÂMETROS!$B$67,0) | AI4: =IFERROR(PARÂMETROS!AF95*PARÂMETROS!E16*PARÂMETROS!$B$4*PARÂMETROS!$B$5*PARÂMETROS!$B$68,0) | AJ4: =IFERROR(PARÂMETROS!AG95*PARÂMETROS!E16*PARÂMETROS!$B$4*PARÂMETROS!$B$5*PARÂMETROS!$B$69,0) | AK4: =IFERROR(PARÂMETROS!AH95*PARÂMETROS!E16*PARÂMETROS!$B$4*PARÂMETROS!$B$5*PARÂMETROS!$B$70,0) | AL4: =IFERROR(PARÂMETROS!AI95*PARÂMETROS!E16*PARÂMETROS!$B$4*PARÂMETROS!$B$5*PARÂMETROS!$B$71,0) | AM4: =IFERROR(PARÂMETROS!AJ95*PARÂMETROS!E16*PARÂMETROS!$B$4*PARÂMETROS!$B$5*PARÂMETROS!$B$72,0) | AN4: =IFERROR(PARÂMETROS!AK95*PARÂMETROS!E16*PARÂMETROS!$B$4*PARÂMETROS!$B$5*PARÂMETROS!$B$73,0) | AO4: =IFERROR(PARÂMETROS!AL95*PARÂMETROS!E16*PARÂMETROS!$B$4*PARÂMETROS!$B$5*PARÂMETROS!$B$74,0) | AP4: =IFERROR(PARÂMETROS!AM95*PARÂMETROS!E16*PARÂMETROS!$B$4*PARÂMETROS!$B$5*PARÂMETROS!$B$75,0) | AQ4: =IFERROR(PARÂMETROS!AN95*PARÂMETROS!E16*PARÂMETROS!$B$4*PARÂMETROS!$B$5*PARÂMETROS!$B$76,0) | AR4: =IFERROR(PARÂMETROS!AO95*PARÂMETROS!E16*PARÂMETROS!$B$4*PARÂMETROS!$B$5*PARÂMETROS!$B$77,0) | AS4: =IFERROR(PARÂMETROS!AP95*PARÂMETROS!E16*PARÂMETROS!$B$4*PARÂMETROS!$B$5*PARÂMETROS!$B$78,0) | AT4: =IFERROR(PARÂMETROS!AQ95*PARÂMETROS!E16*PARÂMETROS!$B$4*PARÂMETROS!$B$5*PARÂMETROS!$B$79,0) | AU4: =IFERROR(PARÂMETROS!AR95*PARÂMETROS!E16*PARÂMETROS!$B$4*PARÂMETROS!$B$5*PARÂMETROS!$B$80,0) | AV4: =IFERROR(PARÂMETROS!AS95*PARÂMETROS!E16*PARÂMETROS!$B$4*PARÂMETROS!$B$5*PARÂMETROS!$B$81,0) | AW4: =IFERROR(PARÂMETROS!AT95*PARÂMETROS!E16*PARÂMETROS!$B$4*PARÂMETROS!$B$5*PARÂMETROS!$B$82,0) | AX4: =IFERROR(PARÂMETROS!AU95*PARÂMETROS!E16*PARÂMETROS!$B$4*PARÂMETROS!$B$5*PARÂMETROS!$B$83,0) | AY4: =IFERROR(PARÂMETROS!AV95*PARÂMETROS!E16*PARÂMETROS!$B$4*PARÂMETROS!$B$5*PARÂMETROS!$B$84,0) | AZ4: =IFERROR(PARÂMETROS!AW95*PARÂMETROS!E16*PARÂMETROS!$B$4*PARÂMETROS!$B$5*PARÂMETROS!$B$85,0) | BA4: =IFERROR(PARÂMETROS!AX95*PARÂMETROS!E16*PARÂMETROS!$B$4*PARÂMETROS!$B$5*PARÂMETROS!$B$86,0) | BB4: =IFERROR(PARÂMETROS!AY95*PARÂMETROS!E16*PARÂMETROS!$B$4*PARÂMETROS!$B$5*PARÂMETROS!$B$87,0) | BC4: =IFERROR(PARÂMETROS!AZ95*PARÂMETROS!E16*PARÂMETROS!$B$4*PARÂMETROS!$B$5*PARÂMETROS!$B$88,0) | BD4: =IFERROR(PARÂMETROS!BA95*PARÂMETROS!E16*PARÂMETROS!$B$4*PARÂMETROS!$B$5*PARÂMETROS!$B$89,0) | BE4: =IFERROR(PARÂMETROS!BB95*PARÂMETROS!E16*PARÂMETROS!$B$4*PARÂMETROS!$B$5*PARÂMETROS!$B$90,0) | BF4: =IFERROR(PARÂMETROS!BC95*PARÂMETROS!E16*PARÂMETROS!$B$4*PARÂMETROS!$B$5*PARÂMETROS!$B$91,0)
F5: Acumulado | G5: =G4 | H5: =G5+H4 | I5: =H5+I4 | J5: =I5+J4 | K5: =J5+K4 | L5: =K5+L4 | M5: =L5+M4 | N5: =M5+N4 | O5: =N5+O4 | ... BF5: =BE5+BF4
F6: % Completude | G6: =IF(PARÂMETROS!D16>0,G5/PARÂMETROS!D16,0) | H6: =IF(PARÂMETROS!D16>0,H5/PARÂMETROS!D16,0) | I6: =IF(PARÂMETROS!D16>0,I5/PARÂMETROS!D16,0) | J6: =IF(PARÂMETROS!D16>0,J5/PARÂMETROS!D16,0) | K6: =IF(PARÂMETROS!D16>0,K5/PARÂMETROS!D16,0) | L6: =IF(PARÂMETROS!D16>0,L5/PARÂMETROS!D16,0) | M6: =IF(PARÂMETROS!D16>0,M5/PARÂMETROS!D16,0) | N6: =IF(PARÂMETROS!D16>0,N5/PARÂMETROS!D16,0) | O6: =IF(PARÂMETROS!D16>0,O5/PARÂMETROS!D16,0) | P6: =IF(PARÂMETROS!D16>0,P5/PARÂMETROS!D16,0) | Q6: =IF(PARÂMETROS!D16>0,Q5/PARÂMETROS!D16,0) | R6: =IF(PARÂMETROS!D16>0,R5/PARÂMETROS!D16,0) | S6: =IF(PARÂMETROS!D16>0,S5/PARÂMETROS!D16,0) | T6: =IF(PARÂMETROS!D16>0,T5/PARÂMETROS!D16,0) | U6: =IF(PARÂMETROS!D16>0,U5/PARÂMETROS!D16,0) | V6: =IF(PARÂMETROS!D16>0,V5/PARÂMETROS!D16,0) | W6: =IF(PARÂMETROS!D16>0,W5/PARÂMETROS!D16,0) | X6: =IF(PARÂMETROS!D16>0,X5/PARÂMETROS!D16,0) | Y6: =IF(PARÂMETROS!D16>0,Y5/PARÂMETROS!D16,0) | Z6: =IF(PARÂMETROS!D16>0,Z5/PARÂMETROS!D16,0) | AA6: =IF(PARÂMETROS!D16>0,AA5/PARÂMETROS!D16,0) | AB6: =IF(PARÂMETROS!D16>0,AB5/PARÂMETROS!D16,0) | AC6: =IF(PARÂMETROS!D16>0,AC5/PARÂMETROS!D16,0) | AD6: =IF(PARÂMETROS!D16>0,AD5/PARÂMETROS!D16,0) | AE6: =IF(PARÂMETROS!D16>0,AE5/PARÂMETROS!D16,0) | AF6: =IF(PARÂMETROS!D16>0,AF5/PARÂMETROS!D16,0) | AG6: =IF(PARÂMETROS!D16>0,AG5/PARÂMETROS!D16,0) | AH6: =IF(PARÂMETROS!D16>0,AH5/PARÂMETROS!D16,0) | AI6: =IF(PARÂMETROS!D16>0,AI5/PARÂMETROS!D16,0) | AJ6: =IF(PARÂMETROS!D16>0,AJ5/PARÂMETROS!D16,0) | AK6: =IF(PARÂMETROS!D16>0,AK5/PARÂMETROS!D16,0) | AL6: =IF(PARÂMETROS!D16>0,AL5/PARÂMETROS!D16,0) | AM6: =IF(PARÂMETROS!D16>0,AM5/PARÂMETROS!D16,0) | AN6: =IF(PARÂMETROS!D16>0,AN5/PARÂMETROS!D16,0) | AO6: =IF(PARÂMETROS!D16>0,AO5/PARÂMETROS!D16,0) | AP6: =IF(PARÂMETROS!D16>0,AP5/PARÂMETROS!D16,0) | AQ6: =IF(PARÂMETROS!D16>0,AQ5/PARÂMETROS!D16,0) | AR6: =IF(PARÂMETROS!D16>0,AR5/PARÂMETROS!D16,0) | AS6: =IF(PARÂMETROS!D16>0,AS5/PARÂMETROS!D16,0) | AT6: =IF(PARÂMETROS!D16>0,AT5/PARÂMETROS!D16,0) | AU6: =IF(PARÂMETROS!D16>0,AU5/PARÂMETROS!D16,0) | AV6: =IF(PARÂMETROS!D16>0,AV5/PARÂMETROS!D16,0) | AW6: =IF(PARÂMETROS!D16>0,AW5/PARÂMETROS!D16,0) | AX6: =IF(PARÂMETROS!D16>0,AX5/PARÂMETROS!D16,0) | AY6: =IF(PARÂMETROS!D16>0,AY5/PARÂMETROS!D16,0) | AZ6: =IF(PARÂMETROS!D16>0,AZ5/PARÂMETROS!D16,0) | BA6: =IF(PARÂMETROS!D16>0,BA5/PARÂMETROS!D16,0) | BB6: =IF(PARÂMETROS!D16>0,BB5/PARÂMETROS!D16,0) | BC6: =IF(PARÂMETROS!D16>0,BC5/PARÂMETROS!D16,0) | BD6: =IF(PARÂMETROS!D16>0,BD5/PARÂMETROS!D16,0) | BE6: =IF(PARÂMETROS!D16>0,BE5/PARÂMETROS!D16,0) | BF6: =IF(PARÂMETROS!D16>0,BF5/PARÂMETROS!D16,0)
A7: eap-1_1 | B7: Esc/carg/transp 1aCat DMT | C7: =PARÂMETROS!D17 | D7: =SUM(G7:BF7) | E7: =IF(C7>0,(D7-C7)/C7,0) | F7: Produção semanal | G7: =IFERROR(PARÂMETROS!D96*PARÂMETROS!E17*PARÂMETROS!$B$4*PARÂMETROS!$B$5*PARÂMETROS!$B$40,0) | H7: =IFERROR(PARÂMETROS!E96*PARÂMETROS!E17*PARÂMETROS!$B$4*PARÂMETROS!$B$5*PARÂMETROS!$B$41,0) | I7: =IFERROR(PARÂMETROS!F96*PARÂMETROS!E17*PARÂMETROS!$B$4*PARÂMETROS!$B$5*PARÂMETROS!$B$42,0) | J7: =IFERROR(PARÂMETROS!G96*PARÂMETROS!E17*PARÂMETROS!$B$4*PARÂMETROS!$B$5*PARÂMETROS!$B$43,0) | K7: =IFERROR(PARÂMETROS!H96*PARÂMETROS!E17*PARÂMETROS!$B$4*PARÂMETROS!$B$5*PARÂMETROS!$B$44,0) | L7: =IFERROR(PARÂMETROS!I96*PARÂMETROS!E17*PARÂMETROS!$B$4*PARÂMETROS!$B$5*PARÂMETROS!$B$45,0) | M7: =IFERROR(PARÂMETROS!J96*PARÂMETROS!E17*PARÂMETROS!$B$4*PARÂMETROS!$B$5*PARÂMETROS!$B$46,0) | N7: =IFERROR(PARÂMETROS!K96*PARÂMETROS!E17*PARÂMETROS!$B$4*PARÂMETROS!$B$5*PARÂMETROS!$B$47,0) | O7: =IFERROR(PARÂMETROS!L96*PARÂMETROS!E17*PARÂMETROS!$B$4*PARÂMETROS!$B$5*PARÂMETROS!$B$48,0) | P7: =IFERROR(PARÂMETROS!M96*PARÂMETROS!E17*PARÂMETROS!$B$4*PARÂMETROS!$B$5*PARÂMETROS!$B$49,0) | Q7: =IFERROR(PARÂMETROS!N96*PARÂMETROS!E17*PARÂMETROS!$B$4*PARÂMETROS!$B$5*PARÂMETROS!$B$50,0) | R7: =IFERROR(PARÂMETROS!O96*PARÂMETROS!E17*PARÂMETROS!$B$4*PARÂMETROS!$B$5*PARÂMETROS!$B$51,0) | S7: =IFERROR(PARÂMETROS!P96*PARÂMETROS!E17*PARÂMETROS!$B$4*PARÂMETROS!$B$5*PARÂMETROS!$B$52,0) | T7: =IFERROR(PARÂMETROS!Q96*PARÂMETROS!E17*PARÂMETROS!$B$4*PARÂMETROS!$B$5*PARÂMETROS!$B$53,0) | U7: =IFERROR(PARÂMETROS!R96*PARÂMETROS!E17*PARÂMETROS!$B$4*PARÂMETROS!$B$5*PARÂMETROS!$B$54,0) | V7: =IFERROR(PARÂMETROS!S96*PARÂMETROS!E17*PARÂMETROS!$B$4*PARÂMETROS!$B$5*PARÂMETROS!$B$55,0) | W7: =IFERROR(PARÂMETROS!T96*PARÂMETROS!E17*PARÂMETROS!$B$4*PARÂMETROS!$B$5*PARÂMETROS!$B$56,0) | X7: =IFERROR(PARÂMETROS!U96*PARÂMETROS!E17*PARÂMETROS!$B$4*PARÂMETROS!$B$5*PARÂMETROS!$B$57,0) | Y7: =IFERROR(PARÂMETROS!V96*PARÂMETROS!E17*PARÂMETROS!$B$4*PARÂMETROS!$B$5*PARÂMETROS!$B$58,0) | Z7: =IFERROR(PARÂMETROS!W96*PARÂMETROS!E17*PARÂMETROS!$B$4*PARÂMETROS!$B$5*PARÂMETROS!$B$59,0) | AA7: =IFERROR(PARÂMETROS!X96*PARÂMETROS!E17*PARÂMETROS!$B$4*PARÂMETROS!$B$5*PARÂMETROS!$B$60,0) | AB7: =IFERROR(PARÂMETROS!Y96*PARÂMETROS!E17*PARÂMETROS!$B$4*PARÂMETROS!$B$5*PARÂMETROS!$B$61,0) | AC7: =IFERROR(PARÂMETROS!Z96*PARÂMETROS!E17*PARÂMETROS!$B$4*PARÂMETROS!$B$5*PARÂMETROS!$B$62,0) | AD7: =IFERROR(PARÂMETROS!AA96*PARÂMETROS!E17*PARÂMETROS!$B$4*PARÂMETROS!$B$5*PARÂMETROS!$B$63,0) | AE7: =IFERROR(PARÂMETROS!AB96*PARÂMETROS!E17*PARÂMETROS!$B$4*PARÂMETROS!$B$5*PARÂMETROS!$B$64,0) | AF7: =IFERROR(PARÂMETROS!AC96*PARÂMETROS!E17*PARÂMETROS!$B$4*PARÂMETROS!$B$5*PARÂMETROS!$B$65,0) | AG7: =IFERROR(PARÂMETROS!AD96*PARÂMETROS!E17*PARÂMETROS!$B$4*PARÂMETROS!$B$5*PARÂMETROS!$B$66,0) | AH7: =IFERROR(PARÂMETROS!AE96*PARÂMETROS!E17*PARÂMETROS!$B$4*PARÂMETROS!$B$5*PARÂMETROS!$B$67,0) | AI7: =IFERROR(PARÂMETROS!AF96*PARÂMETROS!E17*PARÂMETROS!$B$4*PARÂMETROS!$B$5*PARÂMETROS!$B$68,0) | AJ7: =IFERROR(PARÂMETROS!AG96*PARÂMETROS!E17*PARÂMETROS!$B$4*PARÂMETROS!$B$5*PARÂMETROS!$B$69,0) | AK7: =IFERROR(PARÂMETROS!AH96*PARÂMETROS!E17*PARÂMETROS!$B$4*PARÂMETROS!$B$5*PARÂMETROS!$B$70,0) | AL7: =IFERROR(PARÂMETROS!AI96*PARÂMETROS!E17*PARÂMETROS!$B$4*PARÂMETROS!$B$5*PARÂMETROS!$B$71,0) | AM7: =IFERROR(PARÂMETROS!AJ96*PARÂMETROS!E17*PARÂMETROS!$B$4*PARÂMETROS!$B$5*PARÂMETROS!$B$72,0) | AN7: =IFERROR(PARÂMETROS!AK96*PARÂMETROS!E17*PARÂMETROS!$B$4*PARÂMETROS!$B$5*PARÂMETROS!$B$73,0) | AO7: =IFERROR(PARÂMETROS!AL96*PARÂMETROS!E17*PARÂMETROS!$B$4*PARÂMETROS!$B$5*PARÂMETROS!$B$74,0) | AP7: =IFERROR(PARÂMETROS!AM96*PARÂMETROS!E17*PARÂMETROS!$B$4*PARÂMETROS!$B$5*PARÂMETROS!$B$75,0) | AQ7: =IFERROR(PARÂMETROS!AN96*PARÂMETROS!E17*PARÂMETROS!$B$4*PARÂMETROS!$B$5*PARÂMETROS!$B$76,0) | AR7: =IFERROR(PARÂMETROS!AO96*PARÂMETROS!E17*PARÂMETROS!$B$4*PARÂMETROS!$B$5*PARÂMETROS!$B$77,0) | AS7: =IFERROR(PARÂMETROS!AP96*PARÂMETROS!E17*PARÂMETROS!$B$4*PARÂMETROS!$B$5*PARÂMETROS!$B$78,0) | AT7: =IFERROR(PARÂMETROS!AQ96*PARÂMETROS!E17*PARÂMETROS!$B$4*PARÂMETROS!$B$5*PARÂMETROS!$B$79,0) | AU7: =IFERROR(PARÂMETROS!AR96*PARÂMETROS!E17*PARÂMETROS!$B$4*PARÂMETROS!$B$5*PARÂMETROS!$B$80,0) | AV7: =IFERROR(PARÂMETROS!AS96*PARÂMETROS!E17*PARÂMETROS!$B$4*PARÂMETROS!$B$5*PARÂMETROS!$B$81,0) | AW7: =IFERROR(PARÂMETROS!AT96*PARÂMETROS!E17*PARÂMETROS!$B$4*PARÂMETROS!$B$5*PARÂMETROS!$B$82,0) | AX7: =IFERROR(PARÂMETROS!AU96*PARÂMETROS!E17*PARÂMETROS!$B$4*PARÂMETROS!$B$5*PARÂMETROS!$B$83,0) | AY7: =IFERROR(PARÂMETROS!AV96*PARÂMETROS!E17*PARÂMETROS!$B$4*PARÂMETROS!$B$5*PARÂMETROS!$B$84,0) | AZ7: =IFERROR(PARÂMETROS!AW96*PARÂMETROS!E17*PARÂMETROS!$B$4*PARÂMETROS!$B$5*PARÂMETROS!$B$85,0) | BA7: =IFERROR(PARÂMETROS!AX96*PARÂMETROS!E17*PARÂMETROS!$B$4*PARÂMETROS!$B$5*PARÂMETROS!$B$86,0) | BB7: =IFERROR(PARÂMETROS!AY96*PARÂMETROS!E17*PARÂMETROS!$B$4*PARÂMETROS!$B$5*PARÂMETROS!$B$87,0) | BC7: =IFERROR(PARÂMETROS!AZ96*PARÂMETROS!E17*PARÂMETROS!$B$4*PARÂMETROS!$B$5*PARÂMETROS!$B$88,0) | BD7: =IFERROR(PARÂMETROS!BA96*PARÂMETROS!E17*PARÂMETROS!$B$4*PARÂMETROS!$B$5*PARÂMETROS!$B$89,0) | BE7: =IFERROR(PARÂMETROS!BB96*PARÂMETROS!E17*PARÂMETROS!$B$4*PARÂMETROS!$B$5*PARÂMETROS!$B$90,0) | BF7: =IFERROR(PARÂMETROS!BC96*PARÂMETROS!E17*PARÂMETROS!$B$4*PARÂMETROS!$B$5*PARÂMETROS!$B$91,0)
F8: Acumulado | G8: =G7 | H8: =G8+H7 | I8: =H8+I7 | J8: =I8+J7 | K8: =J8+K7 | L8: =K8+L7 | M8: =L8+M7 | N8: =M8+N7 | O8: =N8+O7 | ... BF8: =BE8+BF7
F9: % Completude | G9: =IF(PARÂMETROS!D17>0,G8/PARÂMETROS!D17,0) | H9: =IF(PARÂMETROS!D17>0,H8/PARÂMETROS!D17,0) | I9: =IF(PARÂMETROS!D17>0,I8/PARÂMETROS!D17,0) | J9: =IF(PARÂMETROS!D17>0,J8/PARÂMETROS!D17,0) | K9: =IF(PARÂMETROS!D17>0,K8/PARÂMETROS!D17,0) | L9: =IF(PARÂMETROS!D17>0,L8/PARÂMETROS!D17,0) | M9: =IF(PARÂMETROS!D17>0,M8/PARÂMETROS!D17,0) | N9: =IF(PARÂMETROS!D17>0,N8/PARÂMETROS!D17,0) | O9: =IF(PARÂMETROS!D17>0,O8/PARÂMETROS!D17,0) | P9: =IF(PARÂMETROS!D17>0,P8/PARÂMETROS!D17,0) | Q9: =IF(PARÂMETROS!D17>0,Q8/PARÂMETROS!D17,0) | R9: =IF(PARÂMETROS!D17>0,R8/PARÂMETROS!D17,0) | S9: =IF(PARÂMETROS!D17>0,S8/PARÂMETROS!D17,0) | T9: =IF(PARÂMETROS!D17>0,T8/PARÂMETROS!D17,0) | U9: =IF(PARÂMETROS!D17>0,U8/PARÂMETROS!D17,0) | V9: =IF(PARÂMETROS!D17>0,V8/PARÂMETROS!D17,0) | W9: =IF(PARÂMETROS!D17>0,W8/PARÂMETROS!D17,0) | X9: =IF(PARÂMETROS!D17>0,X8/PARÂMETROS!D17,0) | Y9: =IF(PARÂMETROS!D17>0,Y8/PARÂMETROS!D17,0) | Z9: =IF(PARÂMETROS!D17>0,Z8/PARÂMETROS!D17,0) | AA9: =IF(PARÂMETROS!D17>0,AA8/PARÂMETROS!D17,0) | AB9: =IF(PARÂMETROS!D17>0,AB8/PARÂMETROS!D17,0) | AC9: =IF(PARÂMETROS!D17>0,AC8/PARÂMETROS!D17,0) | AD9: =IF(PARÂMETROS!D17>0,AD8/PARÂMETROS!D17,0) | AE9: =IF(PARÂMETROS!D17>0,AE8/PARÂMETROS!D17,0) | AF9: =IF(PARÂMETROS!D17>0,AF8/PARÂMETROS!D17,0) | AG9: =IF(PARÂMETROS!D17>0,AG8/PARÂMETROS!D17,0) | AH9: =IF(PARÂMETROS!D17>0,AH8/PARÂMETROS!D17,0) | AI9: =IF(PARÂMETROS!D17>0,AI8/PARÂMETROS!D17,0) | AJ9: =IF(PARÂMETROS!D17>0,AJ8/PARÂMETROS!D17,0) | AK9: =IF(PARÂMETROS!D17>0,AK8/PARÂMETROS!D17,0) | AL9: =IF(PARÂMETROS!D17>0,AL8/PARÂMETROS!D17,0) | AM9: =IF(PARÂMETROS!D17>0,AM8/PARÂMETROS!D17,0) | AN9: =IF(PARÂMETROS!D17>0,AN8/PARÂMETROS!D17,0) | AO9: =IF(PARÂMETROS!D17>0,AO8/PARÂMETROS!D17,0) | AP9: =IF(PARÂMETROS!D17>0,AP8/PARÂMETROS!D17,0) | AQ9: =IF(PARÂMETROS!D17>0,AQ8/PARÂMETROS!D17,0) | AR9: =IF(PARÂMETROS!D17>0,AR8/PARÂMETROS!D17,0) | AS9: =IF(PARÂMETROS!D17>0,AS8/PARÂMETROS!D17,0) | AT9: =IF(PARÂMETROS!D17>0,AT8/PARÂMETROS!D17,0) | AU9: =IF(PARÂMETROS!D17>0,AU8/PARÂMETROS!D17,0) | AV9: =IF(PARÂMETROS!D17>0,AV8/PARÂMETROS!D17,0) | AW9: =IF(PARÂMETROS!D17>0,AW8/PARÂMETROS!D17,0) | AX9: =IF(PARÂMETROS!D17>0,AX8/PARÂMETROS!D17,0) | AY9: =IF(PARÂMETROS!D17>0,AY8/PARÂMETROS!D17,0) | AZ9: =IF(PARÂMETROS!D17>0,AZ8/PARÂMETROS!D17,0) | BA9: =IF(PARÂMETROS!D17>0,BA8/PARÂMETROS!D17,0) | BB9: =IF(PARÂMETROS!D17>0,BB8/PARÂMETROS!D17,0) | BC9: =IF(PARÂMETROS!D17>0,BC8/PARÂMETROS!D17,0) | BD9: =IF(PARÂMETROS!D17>0,BD8/PARÂMETROS!D17,0) | BE9: =IF(PARÂMETROS!D17>0,BE8/PARÂMETROS!D17,0) | BF9: =IF(PARÂMETROS!D17>0,BF8/PARÂMETROS!D17,0)
A10: eap-1_2 | B10: Esc/carg/transp 1aCat DMT | C10: =PARÂMETROS!D18 | D10: =SUM(G10:BF10) | E10: =IF(C10>0,(D10-C10)/C10,0) | F10: Produção semanal | G10: =IFERROR(PARÂMETROS!D97*PARÂMETROS!E18*PARÂMETROS!$B$4*PARÂMETROS!$B$5*PARÂMETROS!$B$40,0) | H10: =IFERROR(PARÂMETROS!E97*PARÂMETROS!E18*PARÂMETROS!$B$4*PARÂMETROS!$B$5*PARÂMETROS!$B$41,0) | I10: =IFERROR(PARÂMETROS!F97*PARÂMETROS!E18*PARÂMETROS!$B$4*PARÂMETROS!$B$5*PARÂMETROS!$B$42,0) | J10: =IFERROR(PARÂMETROS!G97*PARÂMETROS!E18*PARÂMETROS!$B$4*PARÂMETROS!$B$5*PARÂMETROS!$B$43,0) | K10: =IFERROR(PARÂMETROS!H97*PARÂMETROS!E18*PARÂMETROS!$B$4*PARÂMETROS!$B$5*PARÂMETROS!$B$44,0) | L10: =IFERROR(PARÂMETROS!I97*PARÂMETROS!E18*PARÂMETROS!$B$4*PARÂMETROS!$B$5*PARÂMETROS!$B$45,0) | M10: =IFERROR(PARÂMETROS!J97*PARÂMETROS!E18*PARÂMETROS!$B$4*PARÂMETROS!$B$5*PARÂMETROS!$B$46,0) | N10: =IFERROR(PARÂMETROS!K97*PARÂMETROS!E18*PARÂMETROS!$B$4*PARÂMETROS!$B$5*PARÂMETROS!$B$47,0) | O10: =IFERROR(PARÂMETROS!L97*PARÂMETROS!E18*PARÂMETROS!$B$4*PARÂMETROS!$B$5*PARÂMETROS!$B$48,0) | P10: =IFERROR(PARÂMETROS!M97*PARÂMETROS!E18*PARÂMETROS!$B$4*PARÂMETROS!$B$5*PARÂMETROS!$B$49,0) | Q10: =IFERROR(PARÂMETROS!N97*PARÂMETROS!E18*PARÂMETROS!$B$4*PARÂMETROS!$B$5*PARÂMETROS!$B$50,0) | R10: =IFERROR(PARÂMETROS!O97*PARÂMETROS!E18*PARÂMETROS!$B$4*PARÂMETROS!$B$5*PARÂMETROS!$B$51,0) | S10: =IFERROR(PARÂMETROS!P97*PARÂMETROS!E18*PARÂMETROS!$B$4*PARÂMETROS!$B$5*PARÂMETROS!$B$52,0) | T10: =IFERROR(PARÂMETROS!Q97*PARÂMETROS!E18*PARÂMETROS!$B$4*PARÂMETROS!$B$5*PARÂMETROS!$B$53,0) | U10: =IFERROR(PARÂMETROS!R97*PARÂMETROS!E18*PARÂMETROS!$B$4*PARÂMETROS!$B$5*PARÂMETROS!$B$54,0) | V10: =IFERROR(PARÂMETROS!S97*PARÂMETROS!E18*PARÂMETROS!$B$4*PARÂMETROS!$B$5*PARÂMETROS!$B$55,0) | W10: =IFERROR(PARÂMETROS!T97*PARÂMETROS!E18*PARÂMETROS!$B$4*PARÂMETROS!$B$5*PARÂMETROS!$B$56,0) | X10: =IFERROR(PARÂMETROS!U97*PARÂMETROS!E18*PARÂMETROS!$B$4*PARÂMETROS!$B$5*PARÂMETROS!$B$57,0) | Y10: =IFERROR(PARÂMETROS!V97*PARÂMETROS!E18*PARÂMETROS!$B$4*PARÂMETROS!$B$5*PARÂMETROS!$B$58,0) | Z10: =IFERROR(PARÂMETROS!W97*PARÂMETROS!E18*PARÂMETROS!$B$4*PARÂMETROS!$B$5*PARÂMETROS!$B$59,0) | AA10: =IFERROR(PARÂMETROS!X97*PARÂMETROS!E18*PARÂMETROS!$B$4*PARÂMETROS!$B$5*PARÂMETROS!$B$60,0) | AB10: =IFERROR(PARÂMETROS!Y97*PARÂMETROS!E18*PARÂMETROS!$B$4*PARÂMETROS!$B$5*PARÂMETROS!$B$61,0) | AC10: =IFERROR(PARÂMETROS!Z97*PARÂMETROS!E18*PARÂMETROS!$B$4*PARÂMETROS!$B$5*PARÂMETROS!$B$62,0) | AD10: =IFERROR(PARÂMETROS!AA97*PARÂMETROS!E18*PARÂMETROS!$B$4*PARÂMETROS!$B$5*PARÂMETROS!$B$63,0) | AE10: =IFERROR(PARÂMETROS!AB97*PARÂMETROS!E18*PARÂMETROS!$B$4*PARÂMETROS!$B$5*PARÂMETROS!$B$64,0) | AF10: =IFERROR(PARÂMETROS!AC97*PARÂMETROS!E18*PARÂMETROS!$B$4*PARÂMETROS!$B$5*PARÂMETROS!$B$65,0) | AG10: =IFERROR(PARÂMETROS!AD97*PARÂMETROS!E18*PARÂMETROS!$B$4*PARÂMETROS!$B$5*PARÂMETROS!$B$66,0) | AH10: =IFERROR(PARÂMETROS!AE97*PARÂMETROS!E18*PARÂMETROS!$B$4*PARÂMETROS!$B$5*PARÂMETROS!$B$67,0) | AI10: =IFERROR(PARÂMETROS!AF97*PARÂMETROS!E18*PARÂMETROS!$B$4*PARÂMETROS!$B$5*PARÂMETROS!$B$68,0) | AJ10: =IFERROR(PARÂMETROS!AG97*PARÂMETROS!E18*PARÂMETROS!$B$4*PARÂMETROS!$B$5*PARÂMETROS!$B$69,0) | AK10: =IFERROR(PARÂMETROS!AH97*PARÂMETROS!E18*PARÂMETROS!$B$4*PARÂMETROS!$B$5*PARÂMETROS!$B$70,0) | AL10: =IFERROR(PARÂMETROS!AI97*PARÂMETROS!E18*PARÂMETROS!$B$4*PARÂMETROS!$B$5*PARÂMETROS!$B$71,0) | AM10: =IFERROR(PARÂMETROS!AJ97*PARÂMETROS!E18*PARÂMETROS!$B$4*PARÂMETROS!$B$5*PARÂMETROS!$B$72,0) | AN10: =IFERROR(PARÂMETROS!AK97*PARÂMETROS!E18*PARÂMETROS!$B$4*PARÂMETROS!$B$5*PARÂMETROS!$B$73,0) | AO10: =IFERROR(PARÂMETROS!AL97*PARÂMETROS!E18*PARÂMETROS!$B$4*PARÂMETROS!$B$5*PARÂMETROS!$B$74,0) | AP10: =IFERROR(PARÂMETROS!AM97*PARÂMETROS!E18*PARÂMETROS!$B$4*PARÂMETROS!$B$5*PARÂMETROS!$B$75,0) | AQ10: =IFERROR(PARÂMETROS!AN97*PARÂMETROS!E18*PARÂMETROS!$B$4*PARÂMETROS!$B$5*PARÂMETROS!$B$76,0) | AR10: =IFERROR(PARÂMETROS!AO97*PARÂMETROS!E18*PARÂMETROS!$B$4*PARÂMETROS!$B$5*PARÂMETROS!$B$77,0) | AS10: =IFERROR(PARÂMETROS!AP97*PARÂMETROS!E18*PARÂMETROS!$B$4*PARÂMETROS!$B$5*PARÂMETROS!$B$78,0) | AT10: =IFERROR(PARÂMETROS!AQ97*PARÂMETROS!E18*PARÂMETROS!$B$4*PARÂMETROS!$B$5*PARÂMETROS!$B$79,0) | AU10: =IFERROR(PARÂMETROS!AR97*PARÂMETROS!E18*PARÂMETROS!$B$4*PARÂMETROS!$B$5*PARÂMETROS!$B$80,0) | AV10: =IFERROR(PARÂMETROS!AS97*PARÂMETROS!E18*PARÂMETROS!$B$4*PARÂMETROS!$B$5*PARÂMETROS!$B$81,0) | AW10: =IFERROR(PARÂMETROS!AT97*PARÂMETROS!E18*PARÂMETROS!$B$4*PARÂMETROS!$B$5*PARÂMETROS!$B$82,0) | AX10: =IFERROR(PARÂMETROS!AU97*PARÂMETROS!E18*PARÂMETROS!$B$4*PARÂMETROS!$B$5*PARÂMETROS!$B$83,0) | AY10: =IFERROR(PARÂMETROS!AV97*PARÂMETROS!E18*PARÂMETROS!$B$4*PARÂMETROS!$B$5*PARÂMETROS!$B$84,0) | AZ10: =IFERROR(PARÂMETROS!AW97*PARÂMETROS!E18*PARÂMETROS!$B$4*PARÂMETROS!$B$5*PARÂMETROS!$B$85,0) | BA10: =IFERROR(PARÂMETROS!AX97*PARÂMETROS!E18*PARÂMETROS!$B$4*PARÂMETROS!$B$5*PARÂMETROS!$B$86,0) | BB10: =IFERROR(PARÂMETROS!AY97*PARÂMETROS!E18*PARÂMETROS!$B$4*PARÂMETROS!$B$5*PARÂMETROS!$B$87,0) | BC10: =IFERROR(PARÂMETROS!AZ97*PARÂMETROS!E18*PARÂMETROS!$B$4*PARÂMETROS!$B$5*PARÂMETROS!$B$88,0) | BD10: =IFERROR(PARÂMETROS!BA97*PARÂMETROS!E18*PARÂMETROS!$B$4*PARÂMETROS!$B$5*PARÂMETROS!$B$89,0) | BE10: =IFERROR(PARÂMETROS!BB97*PARÂMETROS!E18*PARÂMETROS!$B$4*PARÂMETROS!$B$5*PARÂMETROS!$B$90,0) | BF10: =IFERROR(PARÂMETROS!BC97*PARÂMETROS!E18*PARÂMETROS!$B$4*PARÂMETROS!$B$5*PARÂMETROS!$B$91,0)
F11: Acumulado | G11: =G10 | H11: =G11+H10 | I11: =H11+I10 | J11: =I11+J10 | K11: =J11+K10 | L11: =K11+L10 | M11: =L11+M10 | N11: =M11+N10 | O11: =N11+O10 | ... BF11: =BE11+BF10
F12: % Completude | G12: =IF(PARÂMETROS!D18>0,G11/PARÂMETROS!D18,0) | H12: =IF(PARÂMETROS!D18>0,H11/PARÂMETROS!D18,0) | I12: =IF(PARÂMETROS!D18>0,I11/PARÂMETROS!D18,0) | J12: =IF(PARÂMETROS!D18>0,J11/PARÂMETROS!D18,0) | K12: =IF(PARÂMETROS!D18>0,K11/PARÂMETROS!D18,0) | L12: =IF(PARÂMETROS!D18>0,L11/PARÂMETROS!D18,0) | M12: =IF(PARÂMETROS!D18>0,M11/PARÂMETROS!D18,0) | N12: =IF(PARÂMETROS!D18>0,N11/PARÂMETROS!D18,0) | O12: =IF(PARÂMETROS!D18>0,O11/PARÂMETROS!D18,0) | P12: =IF(PARÂMETROS!D18>0,P11/PARÂMETROS!D18,0) | Q12: =IF(PARÂMETROS!D18>0,Q11/PARÂMETROS!D18,0) | R12: =IF(PARÂMETROS!D18>0,R11/PARÂMETROS!D18,0) | S12: =IF(PARÂMETROS!D18>0,S11/PARÂMETROS!D18,0) | T12: =IF(PARÂMETROS!D18>0,T11/PARÂMETROS!D18,0) | U12: =IF(PARÂMETROS!D18>0,U11/PARÂMETROS!D18,0) | V12: =IF(PARÂMETROS!D18>0,V11/PARÂMETROS!D18,0) | W12: =IF(PARÂMETROS!D18>0,W11/PARÂMETROS!D18,0) | X12: =IF(PARÂMETROS!D18>0,X11/PARÂMETROS!D18,0) | Y12: =IF(PARÂMETROS!D18>0,Y11/PARÂMETROS!D18,0) | Z12: =IF(PARÂMETROS!D18>0,Z11/PARÂMETROS!D18,0) | AA12: =IF(PARÂMETROS!D18>0,AA11/PARÂMETROS!D18,0) | AB12: =IF(PARÂMETROS!D18>0,AB11/PARÂMETROS!D18,0) | AC12: =IF(PARÂMETROS!D18>0,AC11/PARÂMETROS!D18,0) | AD12: =IF(PARÂMETROS!D18>0,AD11/PARÂMETROS!D18,0) | AE12: =IF(PARÂMETROS!D18>0,AE11/PARÂMETROS!D18,0) | AF12: =IF(PARÂMETROS!D18>0,AF11/PARÂMETROS!D18,0) | AG12: =IF(PARÂMETROS!D18>0,AG11/PARÂMETROS!D18,0) | AH12: =IF(PARÂMETROS!D18>0,AH11/PARÂMETROS!D18,0) | AI12: =IF(PARÂMETROS!D18>0,AI11/PARÂMETROS!D18,0) | AJ12: =IF(PARÂMETROS!D18>0,AJ11/PARÂMETROS!D18,0) | AK12: =IF(PARÂMETROS!D18>0,AK11/PARÂMETROS!D18,0) | AL12: =IF(PARÂMETROS!D18>0,AL11/PARÂMETROS!D18,0) | AM12: =IF(PARÂMETROS!D18>0,AM11/PARÂMETROS!D18,0) | AN12: =IF(PARÂMETROS!D18>0,AN11/PARÂMETROS!D18,0) | AO12: =IF(PARÂMETROS!D18>0,AO11/PARÂMETROS!D18,0) | AP12: =IF(PARÂMETROS!D18>0,AP11/PARÂMETROS!D18,0) | AQ12: =IF(PARÂMETROS!D18>0,AQ11/PARÂMETROS!D18,0) | AR12: =IF(PARÂMETROS!D18>0,AR11/PARÂMETROS!D18,0) | AS12: =IF(PARÂMETROS!D18>0,AS11/PARÂMETROS!D18,0) | AT12: =IF(PARÂMETROS!D18>0,AT11/PARÂMETROS!D18,0) | AU12: =IF(PARÂMETROS!D18>0,AU11/PARÂMETROS!D18,0) | AV12: =IF(PARÂMETROS!D18>0,AV11/PARÂMETROS!D18,0) | AW12: =IF(PARÂMETROS!D18>0,AW11/PARÂMETROS!D18,0) | AX12: =IF(PARÂMETROS!D18>0,AX11/PARÂMETROS!D18,0) | AY12: =IF(PARÂMETROS!D18>0,AY11/PARÂMETROS!D18,0) | AZ12: =IF(PARÂMETROS!D18>0,AZ11/PARÂMETROS!D18,0) | BA12: =IF(PARÂMETROS!D18>0,BA11/PARÂMETROS!D18,0) | BB12: =IF(PARÂMETROS!D18>0,BB11/PARÂMETROS!D18,0) | BC12: =IF(PARÂMETROS!D18>0,BC11/PARÂMETROS!D18,0) | BD12: =IF(PARÂMETROS!D18>0,BD11/PARÂMETROS!D18,0) | BE12: =IF(PARÂMETROS!D18>0,BE11/PARÂMETROS!D18,0) | BF12: =IF(PARÂMETROS!D18>0,BF11/PARÂMETROS!D18,0)
A13: eap-1_3 | B13: Esc/carg/transp 2aCat DMT | C13: =PARÂMETROS!D19 | D13: =SUM(G13:BF13) | E13: =IF(C13>0,(D13-C13)/C13,0) | F13: Produção semanal | G13: =IFERROR(PARÂMETROS!D98*PARÂMETROS!E19*PARÂMETROS!$B$4*PARÂMETROS!$B$5*PARÂMETROS!$B$40,0) | H13: =IFERROR(PARÂMETROS!E98*PARÂMETROS!E19*PARÂMETROS!$B$4*PARÂMETROS!$B$5*PARÂMETROS!$B$41,0) | I13: =IFERROR(PARÂMETROS!F98*PARÂMETROS!E19*PARÂMETROS!$B$4*PARÂMETROS!$B$5*PARÂMETROS!$B$42,0) | J13: =IFERROR(PARÂMETROS!G98*PARÂMETROS!E19*PARÂMETROS!$B$4*PARÂMETROS!$B$5*PARÂMETROS!$B$43,0) | K13: =IFERROR(PARÂMETROS!H98*PARÂMETROS!E19*PARÂMETROS!$B$4*PARÂMETROS!$B$5*PARÂMETROS!$B$44,0) | L13: =IFERROR(PARÂMETROS!I98*PARÂMETROS!E19*PARÂMETROS!$B$4*PARÂMETROS!$B$5*PARÂMETROS!$B$45,0) | M13: =IFERROR(PARÂMETROS!J98*PARÂMETROS!E19*PARÂMETROS!$B$4*PARÂMETROS!$B$5*PARÂMETROS!$B$46,0) | N13: =IFERROR(PARÂMETROS!K98*PARÂMETROS!E19*PARÂMETROS!$B$4*PARÂMETROS!$B$5*PARÂMETROS!$B$47,0) | O13: =IFERROR(PARÂMETROS!L98*PARÂMETROS!E19*PARÂMETROS!$B$4*PARÂMETROS!$B$5*PARÂMETROS!$B$48,0) | P13: =IFERROR(PARÂMETROS!M98*PARÂMETROS!E19*PARÂMETROS!$B$4*PARÂMETROS!$B$5*PARÂMETROS!$B$49,0) | Q13: =IFERROR(PARÂMETROS!N98*PARÂMETROS!E19*PARÂMETROS!$B$4*PARÂMETROS!$B$5*PARÂMETROS!$B$50,0) | R13: =IFERROR(PARÂMETROS!O98*PARÂMETROS!E19*PARÂMETROS!$B$4*PARÂMETROS!$B$5*PARÂMETROS!$B$51,0) | S13: =IFERROR(PARÂMETROS!P98*PARÂMETROS!E19*PARÂMETROS!$B$4*PARÂMETROS!$B$5*PARÂMETROS!$B$52,0) | T13: =IFERROR(PARÂMETROS!Q98*PARÂMETROS!E19*PARÂMETROS!$B$4*PARÂMETROS!$B$5*PARÂMETROS!$B$53,0) | U13: =IFERROR(PARÂMETROS!R98*PARÂMETROS!E19*PARÂMETROS!$B$4*PARÂMETROS!$B$5*PARÂMETROS!$B$54,0) | V13: =IFERROR(PARÂMETROS!S98*PARÂMETROS!E19*PARÂMETROS!$B$4*PARÂMETROS!$B$5*PARÂMETROS!$B$55,0) | W13: =IFERROR(PARÂMETROS!T98*PARÂMETROS!E19*PARÂMETROS!$B$4*PARÂMETROS!$B$5*PARÂMETROS!$B$56,0) | X13: =IFERROR(PARÂMETROS!U98*PARÂMETROS!E19*PARÂMETROS!$B$4*PARÂMETROS!$B$5*PARÂMETROS!$B$57,0) | Y13: =IFERROR(PARÂMETROS!V98*PARÂMETROS!E19*PARÂMETROS!$B$4*PARÂMETROS!$B$5*PARÂMETROS!$B$58,0) | Z13: =IFERROR(PARÂMETROS!W98*PARÂMETROS!E19*PARÂMETROS!$B$4*PARÂMETROS!$B$5*PARÂMETROS!$B$59,0) | AA13: =IFERROR(PARÂMETROS!X98*PARÂMETROS!E19*PARÂMETROS!$B$4*PARÂMETROS!$B$5*PARÂMETROS!$B$60,0) | AB13: =IFERROR(PARÂMETROS!Y98*PARÂMETROS!E19*PARÂMETROS!$B$4*PARÂMETROS!$B$5*PARÂMETROS!$B$61,0) | AC13: =IFERROR(PARÂMETROS!Z98*PARÂMETROS!E19*PARÂMETROS!$B$4*PARÂMETROS!$B$5*PARÂMETROS!$B$62,0) | AD13: =IFERROR(PARÂMETROS!AA98*PARÂMETROS!E19*PARÂMETROS!$B$4*PARÂMETROS!$B$5*PARÂMETROS!$B$63,0) | AE13: =IFERROR(PARÂMETROS!AB98*PARÂMETROS!E19*PARÂMETROS!$B$4*PARÂMETROS!$B$5*PARÂMETROS!$B$64,0) | AF13: =IFERROR(PARÂMETROS!AC98*PARÂMETROS!E19*PARÂMETROS!$B$4*PARÂMETROS!$B$5*PARÂMETROS!$B$65,0) | AG13: =IFERROR(PARÂMETROS!AD98*PARÂMETROS!E19*PARÂMETROS!$B$4*PARÂMETROS!$B$5*PARÂMETROS!$B$66,0) | AH13: =IFERROR(PARÂMETROS!AE98*PARÂMETROS!E19*PARÂMETROS!$B$4*PARÂMETROS!$B$5*PARÂMETROS!$B$67,0) | AI13: =IFERROR(PARÂMETROS!AF98*PARÂMETROS!E19*PARÂMETROS!$B$4*PARÂMETROS!$B$5*PARÂMETROS!$B$68,0) | AJ13: =IFERROR(PARÂMETROS!AG98*PARÂMETROS!E19*PARÂMETROS!$B$4*PARÂMETROS!$B$5*PARÂMETROS!$B$69,0) | AK13: =IFERROR(PARÂMETROS!AH98*PARÂMETROS!E19*PARÂMETROS!$B$4*PARÂMETROS!$B$5*PARÂMETROS!$B$70,0) | AL13: =IFERROR(PARÂMETROS!AI98*PARÂMETROS!E19*PARÂMETROS!$B$4*PARÂMETROS!$B$5*PARÂMETROS!$B$71,0) | AM13: =IFERROR(PARÂMETROS!AJ98*PARÂMETROS!E19*PARÂMETROS!$B$4*PARÂMETROS!$B$5*PARÂMETROS!$B$72,0) | AN13: =IFERROR(PARÂMETROS!AK98*PARÂMETROS!E19*PARÂMETROS!$B$4*PARÂMETROS!$B$5*PARÂMETROS!$B$73,0) | AO13: =IFERROR(PARÂMETROS!AL98*PARÂMETROS!E19*PARÂMETROS!$B$4*PARÂMETROS!$B$5*PARÂMETROS!$B$74,0) | AP13: =IFERROR(PARÂMETROS!AM98*PARÂMETROS!E19*PARÂMETROS!$B$4*PARÂMETROS!$B$5*PARÂMETROS!$B$75,0) | AQ13: =IFERROR(PARÂMETROS!AN98*PARÂMETROS!E19*PARÂMETROS!$B$4*PARÂMETROS!$B$5*PARÂMETROS!$B$76,0) | AR13: =IFERROR(PARÂMETROS!AO98*PARÂMETROS!E19*PARÂMETROS!$B$4*PARÂMETROS!$B$5*PARÂMETROS!$B$77,0) | AS13: =IFERROR(PARÂMETROS!AP98*PARÂMETROS!E19*PARÂMETROS!$B$4*PARÂMETROS!$B$5*PARÂMETROS!$B$78,0) | AT13: =IFERROR(PARÂMETROS!AQ98*PARÂMETROS!E19*PARÂMETROS!$B$4*PARÂMETROS!$B$5*PARÂMETROS!$B$79,0) | AU13: =IFERROR(PARÂMETROS!AR98*PARÂMETROS!E19*PARÂMETROS!$B$4*PARÂMETROS!$B$5*PARÂMETROS!$B$80,0) | AV13: =IFERROR(PARÂMETROS!AS98*PARÂMETROS!E19*PARÂMETROS!$B$4*PARÂMETROS!$B$5*PARÂMETROS!$B$81,0) | AW13: =IFERROR(PARÂMETROS!AT98*PARÂMETROS!E19*PARÂMETROS!$B$4*PARÂMETROS!$B$5*PARÂMETROS!$B$82,0) | AX13: =IFERROR(PARÂMETROS!AU98*PARÂMETROS!E19*PARÂMETROS!$B$4*PARÂMETROS!$B$5*PARÂMETROS!$B$83,0) | AY13: =IFERROR(PARÂMETROS!AV98*PARÂMETROS!E19*PARÂMETROS!$B$4*PARÂMETROS!$B$5*PARÂMETROS!$B$84,0) | AZ13: =IFERROR(PARÂMETROS!AW98*PARÂMETROS!E19*PARÂMETROS!$B$4*PARÂMETROS!$B$5*PARÂMETROS!$B$85,0) | BA13: =IFERROR(PARÂMETROS!AX98*PARÂMETROS!E19*PARÂMETROS!$B$4*PARÂMETROS!$B$5*PARÂMETROS!$B$86,0) | BB13: =IFERROR(PARÂMETROS!AY98*PARÂMETROS!E19*PARÂMETROS!$B$4*PARÂMETROS!$B$5*PARÂMETROS!$B$87,0) | BC13: =IFERROR(PARÂMETROS!AZ98*PARÂMETROS!E19*PARÂMETROS!$B$4*PARÂMETROS!$B$5*PARÂMETROS!$B$88,0) | BD13: =IFERROR(PARÂMETROS!BA98*PARÂMETROS!E19*PARÂMETROS!$B$4*PARÂMETROS!$B$5*PARÂMETROS!$B$89,0) | BE13: =IFERROR(PARÂMETROS!BB98*PARÂMETROS!E19*PARÂMETROS!$B$4*PARÂMETROS!$B$5*PARÂMETROS!$B$90,0) | BF13: =IFERROR(PARÂMETROS!BC98*PARÂMETROS!E19*PARÂMETROS!$B$4*PARÂMETROS!$B$5*PARÂMETROS!$B$91,0)
F14: Acumulado | G14: =G13 | H14: =G14+H13 | I14: =H14+I13 | J14: =I14+J13 | K14: =J14+K13 | L14: =K14+L13 | M14: =L14+M13 | N14: =M14+N13 | O14: =N14+O13 | ... BF14: =BE14+BF13
F15: % Completude | G15: =IF(PARÂMETROS!D19>0,G14/PARÂMETROS!D19,0) | H15: =IF(PARÂMETROS!D19>0,H14/PARÂMETROS!D19,0) | I15: =IF(PARÂMETROS!D19>0,I14/PARÂMETROS!D19,0) | J15: =IF(PARÂMETROS!D19>0,J14/PARÂMETROS!D19,0) | K15: =IF(PARÂMETROS!D19>0,K14/PARÂMETROS!D19,0) | L15: =IF(PARÂMETROS!D19>0,L14/PARÂMETROS!D19,0) | M15: =IF(PARÂMETROS!D19>0,M14/PARÂMETROS!D19,0) | N15: =IF(PARÂMETROS!D19>0,N14/PARÂMETROS!D19,0) | O15: =IF(PARÂMETROS!D19>0,O14/PARÂMETROS!D19,0) | P15: =IF(PARÂMETROS!D19>0,P14/PARÂMETROS!D19,0) | Q15: =IF(PARÂMETROS!D19>0,Q14/PARÂMETROS!D19,0) | R15: =IF(PARÂMETROS!D19>0,R14/PARÂMETROS!D19,0) | S15: =IF(PARÂMETROS!D19>0,S14/PARÂMETROS!D19,0) | T15: =IF(PARÂMETROS!D19>0,T14/PARÂMETROS!D19,0) | U15: =IF(PARÂMETROS!D19>0,U14/PARÂMETROS!D19,0) | V15: =IF(PARÂMETROS!D19>0,V14/PARÂMETROS!D19,0) | W15: =IF(PARÂMETROS!D19>0,W14/PARÂMETROS!D19,0) | X15: =IF(PARÂMETROS!D19>0,X14/PARÂMETROS!D19,0) | Y15: =IF(PARÂMETROS!D19>0,Y14/PARÂMETROS!D19,0) | Z15: =IF(PARÂMETROS!D19>0,Z14/PARÂMETROS!D19,0) | AA15: =IF(PARÂMETROS!D19>0,AA14/PARÂMETROS!D19,0) | AB15: =IF(PARÂMETROS!D19>0,AB14/PARÂMETROS!D19,0) | AC15: =IF(PARÂMETROS!D19>0,AC14/PARÂMETROS!D19,0) | AD15: =IF(PARÂMETROS!D19>0,AD14/PARÂMETROS!D19,0) | AE15: =IF(PARÂMETROS!D19>0,AE14/PARÂMETROS!D19,0) | AF15: =IF(PARÂMETROS!D19>0,AF14/PARÂMETROS!D19,0) | AG15: =IF(PARÂMETROS!D19>0,AG14/PARÂMETROS!D19,0) | AH15: =IF(PARÂMETROS!D19>0,AH14/PARÂMETROS!D19,0) | AI15: =IF(PARÂMETROS!D19>0,AI14/PARÂMETROS!D19,0) | AJ15: =IF(PARÂMETROS!D19>0,AJ14/PARÂMETROS!D19,0) | AK15: =IF(PARÂMETROS!D19>0,AK14/PARÂMETROS!D19,0) | AL15: =IF(PARÂMETROS!D19>0,AL14/PARÂMETROS!D19,0) | AM15: =IF(PARÂMETROS!D19>0,AM14/PARÂMETROS!D19,0) | AN15: =IF(PARÂMETROS!D19>0,AN14/PARÂMETROS!D19,0) | AO15: =IF(PARÂMETROS!D19>0,AO14/PARÂMETROS!D19,0) | AP15: =IF(PARÂMETROS!D19>0,AP14/PARÂMETROS!D19,0) | AQ15: =IF(PARÂMETROS!D19>0,AQ14/PARÂMETROS!D19,0) | AR15: =IF(PARÂMETROS!D19>0,AR14/PARÂMETROS!D19,0) | AS15: =IF(PARÂMETROS!D19>0,AS14/PARÂMETROS!D19,0) | AT15: =IF(PARÂMETROS!D19>0,AT14/PARÂMETROS!D19,0) | AU15: =IF(PARÂMETROS!D19>0,AU14/PARÂMETROS!D19,0) | AV15: =IF(PARÂMETROS!D19>0,AV14/PARÂMETROS!D19,0) | AW15: =IF(PARÂMETROS!D19>0,AW14/PARÂMETROS!D19,0) | AX15: =IF(PARÂMETROS!D19>0,AX14/PARÂMETROS!D19,0) | AY15: =IF(PARÂMETROS!D19>0,AY14/PARÂMETROS!D19,0) | AZ15: =IF(PARÂMETROS!D19>0,AZ14/PARÂMETROS!D19,0) | BA15: =IF(PARÂMETROS!D19>0,BA14/PARÂMETROS!D19,0) | BB15: =IF(PARÂMETROS!D19>0,BB14/PARÂMETROS!D19,0) | BC15: =IF(PARÂMETROS!D19>0,BC14/PARÂMETROS!D19,0) | BD15: =IF(PARÂMETROS!D19>0,BD14/PARÂMETROS!D19,0) | BE15: =IF(PARÂMETROS!D19>0,BE14/PARÂMETROS!D19,0) | BF15: =IF(PARÂMETROS!D19>0,BF14/PARÂMETROS!D19,0)
A16: eap-1_4 | B16: Esc/carg/transp 2aCat DMT | C16: =PARÂMETROS!D20 | D16: =SUM(G16:BF16) | E16: =IF(C16>0,(D16-C16)/C16,0) | F16: Produção semanal | G16: =IFERROR(PARÂMETROS!D99*PARÂMETROS!E20*PARÂMETROS!$B$4*PARÂMETROS!$B$5*PARÂMETROS!$B$40,0) | H16: =IFERROR(PARÂMETROS!E99*PARÂMETROS!E20*PARÂMETROS!$B$4*PARÂMETROS!$B$5*PARÂMETROS!$B$41,0) | I16: =IFERROR(PARÂMETROS!F99*PARÂMETROS!E20*PARÂMETROS!$B$4*PARÂMETROS!$B$5*PARÂMETROS!$B$42,0) | J16: =IFERROR(PARÂMETROS!G99*PARÂMETROS!E20*PARÂMETROS!$B$4*PARÂMETROS!$B$5*PARÂMETROS!$B$43,0) | K16: =IFERROR(PARÂMETROS!H99*PARÂMETROS!E20*PARÂMETROS!$B$4*PARÂMETROS!$B$5*PARÂMETROS!$B$44,0) | L16: =IFERROR(PARÂMETROS!I99*PARÂMETROS!E20*PARÂMETROS!$B$4*PARÂMETROS!$B$5*PARÂMETROS!$B$45,0) | M16: =IFERROR(PARÂMETROS!J99*PARÂMETROS!E20*PARÂMETROS!$B$4*PARÂMETROS!$B$5*PARÂMETROS!$B$46,0) | N16: =IFERROR(PARÂMETROS!K99*PARÂMETROS!E20*PARÂMETROS!$B$4*PARÂMETROS!$B$5*PARÂMETROS!$B$47,0) | O16: =IFERROR(PARÂMETROS!L99*PARÂMETROS!E20*PARÂMETROS!$B$4*PARÂMETROS!$B$5*PARÂMETROS!$B$48,0) | P16: =IFERROR(PARÂMETROS!M99*PARÂMETROS!E20*PARÂMETROS!$B$4*PARÂMETROS!$B$5*PARÂMETROS!$B$49,0) | Q16: =IFERROR(PARÂMETROS!N99*PARÂMETROS!E20*PARÂMETROS!$B$4*PARÂMETROS!$B$5*PARÂMETROS!$B$50,0) | R16: =IFERROR(PARÂMETROS!O99*PARÂMETROS!E20*PARÂMETROS!$B$4*PARÂMETROS!$B$5*PARÂMETROS!$B$51,0) | S16: =IFERROR(PARÂMETROS!P99*PARÂMETROS!E20*PARÂMETROS!$B$4*PARÂMETROS!$B$5*PARÂMETROS!$B$52,0) | T16: =IFERROR(PARÂMETROS!Q99*PARÂMETROS!E20*PARÂMETROS!$B$4*PARÂMETROS!$B$5*PARÂMETROS!$B$53,0) | U16: =IFERROR(PARÂMETROS!R99*PARÂMETROS!E20*PARÂMETROS!$B$4*PARÂMETROS!$B$5*PARÂMETROS!$B$54,0) | V16: =IFERROR(PARÂMETROS!S99*PARÂMETROS!E20*PARÂMETROS!$B$4*PARÂMETROS!$B$5*PARÂMETROS!$B$55,0) | W16: =IFERROR(PARÂMETROS!T99*PARÂMETROS!E20*PARÂMETROS!$B$4*PARÂMETROS!$B$5*PARÂMETROS!$B$56,0) | X16: =IFERROR(PARÂMETROS!U99*PARÂMETROS!E20*PARÂMETROS!$B$4*PARÂMETROS!$B$5*PARÂMETROS!$B$57,0) | Y16: =IFERROR(PARÂMETROS!V99*PARÂMETROS!E20*PARÂMETROS!$B$4*PARÂMETROS!$B$5*PARÂMETROS!$B$58,0) | Z16: =IFERROR(PARÂMETROS!W99*PARÂMETROS!E20*PARÂMETROS!$B$4*PARÂMETROS!$B$5*PARÂMETROS!$B$59,0) | AA16: =IFERROR(PARÂMETROS!X99*PARÂMETROS!E20*PARÂMETROS!$B$4*PARÂMETROS!$B$5*PARÂMETROS!$B$60,0) | AB16: =IFERROR(PARÂMETROS!Y99*PARÂMETROS!E20*PARÂMETROS!$B$4*PARÂMETROS!$B$5*PARÂMETROS!$B$61,0) | AC16: =IFERROR(PARÂMETROS!Z99*PARÂMETROS!E20*PARÂMETROS!$B$4*PARÂMETROS!$B$5*PARÂMETROS!$B$62,0) | AD16: =IFERROR(PARÂMETROS!AA99*PARÂMETROS!E20*PARÂMETROS!$B$4*PARÂMETROS!$B$5*PARÂMETROS!$B$63,0) | AE16: =IFERROR(PARÂMETROS!AB99*PARÂMETROS!E20*PARÂMETROS!$B$4*PARÂMETROS!$B$5*PARÂMETROS!$B$64,0) | AF16: =IFERROR(PARÂMETROS!AC99*PARÂMETROS!E20*PARÂMETROS!$B$4*PARÂMETROS!$B$5*PARÂMETROS!$B$65,0) | AG16: =IFERROR(PARÂMETROS!AD99*PARÂMETROS!E20*PARÂMETROS!$B$4*PARÂMETROS!$B$5*PARÂMETROS!$B$66,0) | AH16: =IFERROR(PARÂMETROS!AE99*PARÂMETROS!E20*PARÂMETROS!$B$4*PARÂMETROS!$B$5*PARÂMETROS!$B$67,0) | AI16: =IFERROR(PARÂMETROS!AF99*PARÂMETROS!E20*PARÂMETROS!$B$4*PARÂMETROS!$B$5*PARÂMETROS!$B$68,0) | AJ16: =IFERROR(PARÂMETROS!AG99*PARÂMETROS!E20*PARÂMETROS!$B$4*PARÂMETROS!$B$5*PARÂMETROS!$B$69,0) | AK16: =IFERROR(PARÂMETROS!AH99*PARÂMETROS!E20*PARÂMETROS!$B$4*PARÂMETROS!$B$5*PARÂMETROS!$B$70,0) | AL16: =IFERROR(PARÂMETROS!AI99*PARÂMETROS!E20*PARÂMETROS!$B$4*PARÂMETROS!$B$5*PARÂMETROS!$B$71,0) | AM16: =IFERROR(PARÂMETROS!AJ99*PARÂMETROS!E20*PARÂMETROS!$B$4*PARÂMETROS!$B$5*PARÂMETROS!$B$72,0) | AN16: =IFERROR(PARÂMETROS!AK99*PARÂMETROS!E20*PARÂMETROS!$B$4*PARÂMETROS!$B$5*PARÂMETROS!$B$73,0) | AO16: =IFERROR(PARÂMETROS!AL99*PARÂMETROS!E20*PARÂMETROS!$B$4*PARÂMETROS!$B$5*PARÂMETROS!$B$74,0) | AP16: =IFERROR(PARÂMETROS!AM99*PARÂMETROS!E20*PARÂMETROS!$B$4*PARÂMETROS!$B$5*PARÂMETROS!$B$75,0) | AQ16: =IFERROR(PARÂMETROS!AN99*PARÂMETROS!E20*PARÂMETROS!$B$4*PARÂMETROS!$B$5*PARÂMETROS!$B$76,0) | AR16: =IFERROR(PARÂMETROS!AO99*PARÂMETROS!E20*PARÂMETROS!$B$4*PARÂMETROS!$B$5*PARÂMETROS!$B$77,0) | AS16: =IFERROR(PARÂMETROS!AP99*PARÂMETROS!E20*PARÂMETROS!$B$4*PARÂMETROS!$B$5*PARÂMETROS!$B$78,0) | AT16: =IFERROR(PARÂMETROS!AQ99*PARÂMETROS!E20*PARÂMETROS!$B$4*PARÂMETROS!$B$5*PARÂMETROS!$B$79,0) | AU16: =IFERROR(PARÂMETROS!AR99*PARÂMETROS!E20*PARÂMETROS!$B$4*PARÂMETROS!$B$5*PARÂMETROS!$B$80,0) | AV16: =IFERROR(PARÂMETROS!AS99*PARÂMETROS!E20*PARÂMETROS!$B$4*PARÂMETROS!$B$5*PARÂMETROS!$B$81,0) | AW16: =IFERROR(PARÂMETROS!AT99*PARÂMETROS!E20*PARÂMETROS!$B$4*PARÂMETROS!$B$5*PARÂMETROS!$B$82,0) | AX16: =IFERROR(PARÂMETROS!AU99*PARÂMETROS!E20*PARÂMETROS!$B$4*PARÂMETROS!$B$5*PARÂMETROS!$B$83,0) | AY16: =IFERROR(PARÂMETROS!AV99*PARÂMETROS!E20*PARÂMETROS!$B$4*PARÂMETROS!$B$5*PARÂMETROS!$B$84,0) | AZ16: =IFERROR(PARÂMETROS!AW99*PARÂMETROS!E20*PARÂMETROS!$B$4*PARÂMETROS!$B$5*PARÂMETROS!$B$85,0) | BA16: =IFERROR(PARÂMETROS!AX99*PARÂMETROS!E20*PARÂMETROS!$B$4*PARÂMETROS!$B$5*PARÂMETROS!$B$86,0) | BB16: =IFERROR(PARÂMETROS!AY99*PARÂMETROS!E20*PARÂMETROS!$B$4*PARÂMETROS!$B$5*PARÂMETROS!$B$87,0) | BC16: =IFERROR(PARÂMETROS!AZ99*PARÂMETROS!E20*PARÂMETROS!$B$4*PARÂMETROS!$B$5*PARÂMETROS!$B$88,0) | BD16: =IFERROR(PARÂMETROS!BA99*PARÂMETROS!E20*PARÂMETROS!$B$4*PARÂMETROS!$B$5*PARÂMETROS!$B$89,0) | BE16: =IFERROR(PARÂMETROS!BB99*PARÂMETROS!E20*PARÂMETROS!$B$4*PARÂMETROS!$B$5*PARÂMETROS!$B$90,0) | BF16: =IFERROR(PARÂMETROS!BC99*PARÂMETROS!E20*PARÂMETROS!$B$4*PARÂMETROS!$B$5*PARÂMETROS!$B$91,0)
F17: Acumulado | G17: =G16 | H17: =G17+H16 | I17: =H17+I16 | J17: =I17+J16 | K17: =J17+K16 | L17: =K17+L16 | M17: =L17+M16 | N17: =M17+N16 | O17: =N17+O16 | ... BF17: =BE17+BF16
F18: % Completude | G18: =IF(PARÂMETROS!D20>0,G17/PARÂMETROS!D20,0) | H18: =IF(PARÂMETROS!D20>0,H17/PARÂMETROS!D20,0) | I18: =IF(PARÂMETROS!D20>0,I17/PARÂMETROS!D20,0) | J18: =IF(PARÂMETROS!D20>0,J17/PARÂMETROS!D20,0) | K18: =IF(PARÂMETROS!D20>0,K17/PARÂMETROS!D20,0) | L18: =IF(PARÂMETROS!D20>0,L17/PARÂMETROS!D20,0) | M18: =IF(PARÂMETROS!D20>0,M17/PARÂMETROS!D20,0) | N18: =IF(PARÂMETROS!D20>0,N17/PARÂMETROS!D20,0) | O18: =IF(PARÂMETROS!D20>0,O17/PARÂMETROS!D20,0) | P18: =IF(PARÂMETROS!D20>0,P17/PARÂMETROS!D20,0) | Q18: =IF(PARÂMETROS!D20>0,Q17/PARÂMETROS!D20,0) | R18: =IF(PARÂMETROS!D20>0,R17/PARÂMETROS!D20,0) | S18: =IF(PARÂMETROS!D20>0,S17/PARÂMETROS!D20,0) | T18: =IF(PARÂMETROS!D20>0,T17/PARÂMETROS!D20,0) | U18: =IF(PARÂMETROS!D20>0,U17/PARÂMETROS!D20,0) | V18: =IF(PARÂMETROS!D20>0,V17/PARÂMETROS!D20,0) | W18: =IF(PARÂMETROS!D20>0,W17/PARÂMETROS!D20,0) | X18: =IF(PARÂMETROS!D20>0,X17/PARÂMETROS!D20,0) | Y18: =IF(PARÂMETROS!D20>0,Y17/PARÂMETROS!D20,0) | Z18: =IF(PARÂMETROS!D20>0,Z17/PARÂMETROS!D20,0) | AA18: =IF(PARÂMETROS!D20>0,AA17/PARÂMETROS!D20,0) | AB18: =IF(PARÂMETROS!D20>0,AB17/PARÂMETROS!D20,0) | AC18: =IF(PARÂMETROS!D20>0,AC17/PARÂMETROS!D20,0) | AD18: =IF(PARÂMETROS!D20>0,AD17/PARÂMETROS!D20,0) | AE18: =IF(PARÂMETROS!D20>0,AE17/PARÂMETROS!D20,0) | AF18: =IF(PARÂMETROS!D20>0,AF17/PARÂMETROS!D20,0) | AG18: =IF(PARÂMETROS!D20>0,AG17/PARÂMETROS!D20,0) | AH18: =IF(PARÂMETROS!D20>0,AH17/PARÂMETROS!D20,0) | AI18: =IF(PARÂMETROS!D20>0,AI17/PARÂMETROS!D20,0) | AJ18: =IF(PARÂMETROS!D20>0,AJ17/PARÂMETROS!D20,0) | AK18: =IF(PARÂMETROS!D20>0,AK17/PARÂMETROS!D20,0) | AL18: =IF(PARÂMETROS!D20>0,AL17/PARÂMETROS!D20,0) | AM18: =IF(PARÂMETROS!D20>0,AM17/PARÂMETROS!D20,0) | AN18: =IF(PARÂMETROS!D20>0,AN17/PARÂMETROS!D20,0) | AO18: =IF(PARÂMETROS!D20>0,AO17/PARÂMETROS!D20,0) | AP18: =IF(PARÂMETROS!D20>0,AP17/PARÂMETROS!D20,0) | AQ18: =IF(PARÂMETROS!D20>0,AQ17/PARÂMETROS!D20,0) | AR18: =IF(PARÂMETROS!D20>0,AR17/PARÂMETROS!D20,0) | AS18: =IF(PARÂMETROS!D20>0,AS17/PARÂMETROS!D20,0) | AT18: =IF(PARÂMETROS!D20>0,AT17/PARÂMETROS!D20,0) | AU18: =IF(PARÂMETROS!D20>0,AU17/PARÂMETROS!D20,0) | AV18: =IF(PARÂMETROS!D20>0,AV17/PARÂMETROS!D20,0) | AW18: =IF(PARÂMETROS!D20>0,AW17/PARÂMETROS!D20,0) | AX18: =IF(PARÂMETROS!D20>0,AX17/PARÂMETROS!D20,0) | AY18: =IF(PARÂMETROS!D20>0,AY17/PARÂMETROS!D20,0) | AZ18: =IF(PARÂMETROS!D20>0,AZ17/PARÂMETROS!D20,0) | BA18: =IF(PARÂMETROS!D20>0,BA17/PARÂMETROS!D20,0) | BB18: =IF(PARÂMETROS!D20>0,BB17/PARÂMETROS!D20,0) | BC18: =IF(PARÂMETROS!D20>0,BC17/PARÂMETROS!D20,0) | BD18: =IF(PARÂMETROS!D20>0,BD17/PARÂMETROS!D20,0) | BE18: =IF(PARÂMETROS!D20>0,BE17/PARÂMETROS!D20,0) | BF18: =IF(PARÂMETROS!D20>0,BF17/PARÂMETROS!D20,0)
A19: eap-1_5 | B19: Esc/carg/transp 3aCat DMT | C19: =PARÂMETROS!D21 | D19: =SUM(G19:BF19) | E19: =IF(C19>0,(D19-C19)/C19,0) | F19: Produção semanal | G19: =IFERROR(PARÂMETROS!D100*PARÂMETROS!E21*PARÂMETROS!$B$4*PARÂMETROS!$B$5*PARÂMETROS!$B$40,0) | H19: =IFERROR(PARÂMETROS!E100*PARÂMETROS!E21*PARÂMETROS!$B$4*PARÂMETROS!$B$5*PARÂMETROS!$B$41,0) | I19: =IFERROR(PARÂMETROS!F100*PARÂMETROS!E21*PARÂMETROS!$B$4*PARÂMETROS!$B$5*PARÂMETROS!$B$42,0) | J19: =IFERROR(PARÂMETROS!G100*PARÂMETROS!E21*PARÂMETROS!$B$4*PARÂMETROS!$B$5*PARÂMETROS!$B$43,0) | K19: =IFERROR(PARÂMETROS!H100*PARÂMETROS!E21*PARÂMETROS!$B$4*PARÂMETROS!$B$5*PARÂMETROS!$B$44,0) | L19: =IFERROR(PARÂMETROS!I100*PARÂMETROS!E21*PARÂMETROS!$B$4*PARÂMETROS!$B$5*PARÂMETROS!$B$45,0) | M19: =IFERROR(PARÂMETROS!J100*PARÂMETROS!E21*PARÂMETROS!$B$4*PARÂMETROS!$B$5*PARÂMETROS!$B$46,0) | N19: =IFERROR(PARÂMETROS!K100*PARÂMETROS!E21*PARÂMETROS!$B$4*PARÂMETROS!$B$5*PARÂMETROS!$B$47,0) | O19: =IFERROR(PARÂMETROS!L100*PARÂMETROS!E21*PARÂMETROS!$B$4*PARÂMETROS!$B$5*PARÂMETROS!$B$48,0) | P19: =IFERROR(PARÂMETROS!M100*PARÂMETROS!E21*PARÂMETROS!$B$4*PARÂMETROS!$B$5*PARÂMETROS!$B$49,0) | Q19: =IFERROR(PARÂMETROS!N100*PARÂMETROS!E21*PARÂMETROS!$B$4*PARÂMETROS!$B$5*PARÂMETROS!$B$50,0) | R19: =IFERROR(PARÂMETROS!O100*PARÂMETROS!E21*PARÂMETROS!$B$4*PARÂMETROS!$B$5*PARÂMETROS!$B$51,0) | S19: =IFERROR(PARÂMETROS!P100*PARÂMETROS!E21*PARÂMETROS!$B$4*PARÂMETROS!$B$5*PARÂMETROS!$B$52,0) | T19: =IFERROR(PARÂMETROS!Q100*PARÂMETROS!E21*PARÂMETROS!$B$4*PARÂMETROS!$B$5*PARÂMETROS!$B$53,0) | U19: =IFERROR(PARÂMETROS!R100*PARÂMETROS!E21*PARÂMETROS!$B$4*PARÂMETROS!$B$5*PARÂMETROS!$B$54,0) | V19: =IFERROR(PARÂMETROS!S100*PARÂMETROS!E21*PARÂMETROS!$B$4*PARÂMETROS!$B$5*PARÂMETROS!$B$55,0) | W19: =IFERROR(PARÂMETROS!T100*PARÂMETROS!E21*PARÂMETROS!$B$4*PARÂMETROS!$B$5*PARÂMETROS!$B$56,0) | X19: =IFERROR(PARÂMETROS!U100*PARÂMETROS!E21*PARÂMETROS!$B$4*PARÂMETROS!$B$5*PARÂMETROS!$B$57,0) | Y19: =IFERROR(PARÂMETROS!V100*PARÂMETROS!E21*PARÂMETROS!$B$4*PARÂMETROS!$B$5*PARÂMETROS!$B$58,0) | Z19: =IFERROR(PARÂMETROS!W100*PARÂMETROS!E21*PARÂMETROS!$B$4*PARÂMETROS!$B$5*PARÂMETROS!$B$59,0) | AA19: =IFERROR(PARÂMETROS!X100*PARÂMETROS!E21*PARÂMETROS!$B$4*PARÂMETROS!$B$5*PARÂMETROS!$B$60,0) | AB19: =IFERROR(PARÂMETROS!Y100*PARÂMETROS!E21*PARÂMETROS!$B$4*PARÂMETROS!$B$5*PARÂMETROS!$B$61,0) | AC19: =IFERROR(PARÂMETROS!Z100*PARÂMETROS!E21*PARÂMETROS!$B$4*PARÂMETROS!$B$5*PARÂMETROS!$B$62,0) | AD19: =IFERROR(PARÂMETROS!AA100*PARÂMETROS!E21*PARÂMETROS!$B$4*PARÂMETROS!$B$5*PARÂMETROS!$B$63,0) | AE19: =IFERROR(PARÂMETROS!AB100*PARÂMETROS!E21*PARÂMETROS!$B$4*PARÂMETROS!$B$5*PARÂMETROS!$B$64,0) | AF19: =IFERROR(PARÂMETROS!AC100*PARÂMETROS!E21*PARÂMETROS!$B$4*PARÂMETROS!$B$5*PARÂMETROS!$B$65,0) | AG19: =IFERROR(PARÂMETROS!AD100*PARÂMETROS!E21*PARÂMETROS!$B$4*PARÂMETROS!$B$5*PARÂMETROS!$B$66,0) | AH19: =IFERROR(PARÂMETROS!AE100*PARÂMETROS!E21*PARÂMETROS!$B$4*PARÂMETROS!$B$5*PARÂMETROS!$B$67,0) | AI19: =IFERROR(PARÂMETROS!AF100*PARÂMETROS!E21*PARÂMETROS!$B$4*PARÂMETROS!$B$5*PARÂMETROS!$B$68,0) | AJ19: =IFERROR(PARÂMETROS!AG100*PARÂMETROS!E21*PARÂMETROS!$B$4*PARÂMETROS!$B$5*PARÂMETROS!$B$69,0) | AK19: =IFERROR(PARÂMETROS!AH100*PARÂMETROS!E21*PARÂMETROS!$B$4*PARÂMETROS!$B$5*PARÂMETROS!$B$70,0) | AL19: =IFERROR(PARÂMETROS!AI100*PARÂMETROS!E21*PARÂMETROS!$B$4*PARÂMETROS!$B$5*PARÂMETROS!$B$71,0) | AM19: =IFERROR(PARÂMETROS!AJ100*PARÂMETROS!E21*PARÂMETROS!$B$4*PARÂMETROS!$B$5*PARÂMETROS!$B$72,0) | AN19: =IFERROR(PARÂMETROS!AK100*PARÂMETROS!E21*PARÂMETROS!$B$4*PARÂMETROS!$B$5*PARÂMETROS!$B$73,0) | AO19: =IFERROR(PARÂMETROS!AL100*PARÂMETROS!E21*PARÂMETROS!$B$4*PARÂMETROS!$B$5*PARÂMETROS!$B$74,0) | AP19: =IFERROR(PARÂMETROS!AM100*PARÂMETROS!E21*PARÂMETROS!$B$4*PARÂMETROS!$B$5*PARÂMETROS!$B$75,0) | AQ19: =IFERROR(PARÂMETROS!AN100*PARÂMETROS!E21*PARÂMETROS!$B$4*PARÂMETROS!$B$5*PARÂMETROS!$B$76,0) | AR19: =IFERROR(PARÂMETROS!AO100*PARÂMETROS!E21*PARÂMETROS!$B$4*PARÂMETROS!$B$5*PARÂMETROS!$B$77,0) | AS19: =IFERROR(PARÂMETROS!AP100*PARÂMETROS!E21*PARÂMETROS!$B$4*PARÂMETROS!$B$5*PARÂMETROS!$B$78,0) | AT19: =IFERROR(PARÂMETROS!AQ100*PARÂMETROS!E21*PARÂMETROS!$B$4*PARÂMETROS!$B$5*PARÂMETROS!$B$79,0) | AU19: =IFERROR(PARÂMETROS!AR100*PARÂMETROS!E21*PARÂMETROS!$B$4*PARÂMETROS!$B$5*PARÂMETROS!$B$80,0) | AV19: =IFERROR(PARÂMETROS!AS100*PARÂMETROS!E21*PARÂMETROS!$B$4*PARÂMETROS!$B$5*PARÂMETROS!$B$81,0) | AW19: =IFERROR(PARÂMETROS!AT100*PARÂMETROS!E21*PARÂMETROS!$B$4*PARÂMETROS!$B$5*PARÂMETROS!$B$82,0) | AX19: =IFERROR(PARÂMETROS!AU100*PARÂMETROS!E21*PARÂMETROS!$B$4*PARÂMETROS!$B$5*PARÂMETROS!$B$83,0) | AY19: =IFERROR(PARÂMETROS!AV100*PARÂMETROS!E21*PARÂMETROS!$B$4*PARÂMETROS!$B$5*PARÂMETROS!$B$84,0) | AZ19: =IFERROR(PARÂMETROS!AW100*PARÂMETROS!E21*PARÂMETROS!$B$4*PARÂMETROS!$B$5*PARÂMETROS!$B$85,0) | BA19: =IFERROR(PARÂMETROS!AX100*PARÂMETROS!E21*PARÂMETROS!$B$4*PARÂMETROS!$B$5*PARÂMETROS!$B$86,0) | BB19: =IFERROR(PARÂMETROS!AY100*PARÂMETROS!E21*PARÂMETROS!$B$4*PARÂMETROS!$B$5*PARÂMETROS!$B$87,0) | BC19: =IFERROR(PARÂMETROS!AZ100*PARÂMETROS!E21*PARÂMETROS!$B$4*PARÂMETROS!$B$5*PARÂMETROS!$B$88,0) | BD19: =IFERROR(PARÂMETROS!BA100*PARÂMETROS!E21*PARÂMETROS!$B$4*PARÂMETROS!$B$5*PARÂMETROS!$B$89,0) | BE19: =IFERROR(PARÂMETROS!BB100*PARÂMETROS!E21*PARÂMETROS!$B$4*PARÂMETROS!$B$5*PARÂMETROS!$B$90,0) | BF19: =IFERROR(PARÂMETROS!BC100*PARÂMETROS!E21*PARÂMETROS!$B$4*PARÂMETROS!$B$5*PARÂMETROS!$B$91,0)
F20: Acumulado | G20: =G19 | H20: =G20+H19 | I20: =H20+I19 | J20: =I20+J19 | K20: =J20+K19 | L20: =K20+L19 | M20: =L20+M19 | N20: =M20+N19 | O20: =N20+O19 | ... BF20: =BE20+BF19
F21: % Completude | G21: =IF(PARÂMETROS!D21>0,G20/PARÂMETROS!D21,0) | H21: =IF(PARÂMETROS!D21>0,H20/PARÂMETROS!D21,0) | I21: =IF(PARÂMETROS!D21>0,I20/PARÂMETROS!D21,0) | J21: =IF(PARÂMETROS!D21>0,J20/PARÂMETROS!D21,0) | K21: =IF(PARÂMETROS!D21>0,K20/PARÂMETROS!D21,0) | L21: =IF(PARÂMETROS!D21>0,L20/PARÂMETROS!D21,0) | M21: =IF(PARÂMETROS!D21>0,M20/PARÂMETROS!D21,0) | N21: =IF(PARÂMETROS!D21>0,N20/PARÂMETROS!D21,0) | O21: =IF(PARÂMETROS!D21>0,O20/PARÂMETROS!D21,0) | P21: =IF(PARÂMETROS!D21>0,P20/PARÂMETROS!D21,0) | Q21: =IF(PARÂMETROS!D21>0,Q20/PARÂMETROS!D21,0) | R21: =IF(PARÂMETROS!D21>0,R20/PARÂMETROS!D21,0) | S21: =IF(PARÂMETROS!D21>0,S20/PARÂMETROS!D21,0) | T21: =IF(PARÂMETROS!D21>0,T20/PARÂMETROS!D21,0) | U21: =IF(PARÂMETROS!D21>0,U20/PARÂMETROS!D21,0) | V21: =IF(PARÂMETROS!D21>0,V20/PARÂMETROS!D21,0) | W21: =IF(PARÂMETROS!D21>0,W20/PARÂMETROS!D21,0) | X21: =IF(PARÂMETROS!D21>0,X20/PARÂMETROS!D21,0) | Y21: =IF(PARÂMETROS!D21>0,Y20/PARÂMETROS!D21,0) | Z21: =IF(PARÂMETROS!D21>0,Z20/PARÂMETROS!D21,0) | AA21: =IF(PARÂMETROS!D21>0,AA20/PARÂMETROS!D21,0) | AB21: =IF(PARÂMETROS!D21>0,AB20/PARÂMETROS!D21,0) | AC21: =IF(PARÂMETROS!D21>0,AC20/PARÂMETROS!D21,0) | AD21: =IF(PARÂMETROS!D21>0,AD20/PARÂMETROS!D21,0) | AE21: =IF(PARÂMETROS!D21>0,AE20/PARÂMETROS!D21,0) | AF21: =IF(PARÂMETROS!D21>0,AF20/PARÂMETROS!D21,0) | AG21: =IF(PARÂMETROS!D21>0,AG20/PARÂMETROS!D21,0) | AH21: =IF(PARÂMETROS!D21>0,AH20/PARÂMETROS!D21,0) | AI21: =IF(PARÂMETROS!D21>0,AI20/PARÂMETROS!D21,0) | AJ21: =IF(PARÂMETROS!D21>0,AJ20/PARÂMETROS!D21,0) | AK21: =IF(PARÂMETROS!D21>0,AK20/PARÂMETROS!D21,0) | AL21: =IF(PARÂMETROS!D21>0,AL20/PARÂMETROS!D21,0) | AM21: =IF(PARÂMETROS!D21>0,AM20/PARÂMETROS!D21,0) | AN21: =IF(PARÂMETROS!D21>0,AN20/PARÂMETROS!D21,0) | AO21: =IF(PARÂMETROS!D21>0,AO20/PARÂMETROS!D21,0) | AP21: =IF(PARÂMETROS!D21>0,AP20/PARÂMETROS!D21,0) | AQ21: =IF(PARÂMETROS!D21>0,AQ20/PARÂMETROS!D21,0) | AR21: =IF(PARÂMETROS!D21>0,AR20/PARÂMETROS!D21,0) | AS21: =IF(PARÂMETROS!D21>0,AS20/PARÂMETROS!D21,0) | AT21: =IF(PARÂMETROS!D21>0,AT20/PARÂMETROS!D21,0) | AU21: =IF(PARÂMETROS!D21>0,AU20/PARÂMETROS!D21,0) | AV21: =IF(PARÂMETROS!D21>0,AV20/PARÂMETROS!D21,0) | AW21: =IF(PARÂMETROS!D21>0,AW20/PARÂMETROS!D21,0) | AX21: =IF(PARÂMETROS!D21>0,AX20/PARÂMETROS!D21,0) | AY21: =IF(PARÂMETROS!D21>0,AY20/PARÂMETROS!D21,0) | AZ21: =IF(PARÂMETROS!D21>0,AZ20/PARÂMETROS!D21,0) | BA21: =IF(PARÂMETROS!D21>0,BA20/PARÂMETROS!D21,0) | BB21: =IF(PARÂMETROS!D21>0,BB20/PARÂMETROS!D21,0) | BC21: =IF(PARÂMETROS!D21>0,BC20/PARÂMETROS!D21,0) | BD21: =IF(PARÂMETROS!D21>0,BD20/PARÂMETROS!D21,0) | BE21: =IF(PARÂMETROS!D21>0,BE20/PARÂMETROS!D21,0) | BF21: =IF(PARÂMETROS!D21>0,BF20/PARÂMETROS!D21,0)
A22: eap-1_6 | B22: Esc/carg/transp 3aCat DMT | C22: =PARÂMETROS!D22 | D22: =SUM(G22:BF22) | E22: =IF(C22>0,(D22-C22)/C22,0) | F22: Produção semanal | G22: =IFERROR(PARÂMETROS!D101*PARÂMETROS!E22*PARÂMETROS!$B$4*PARÂMETROS!$B$5*PARÂMETROS!$B$40,0) | H22: =IFERROR(PARÂMETROS!E101*PARÂMETROS!E22*PARÂMETROS!$B$4*PARÂMETROS!$B$5*PARÂMETROS!$B$41,0) | I22: =IFERROR(PARÂMETROS!F101*PARÂMETROS!E22*PARÂMETROS!$B$4*PARÂMETROS!$B$5*PARÂMETROS!$B$42,0) | J22: =IFERROR(PARÂMETROS!G101*PARÂMETROS!E22*PARÂMETROS!$B$4*PARÂMETROS!$B$5*PARÂMETROS!$B$43,0) | K22: =IFERROR(PARÂMETROS!H101*PARÂMETROS!E22*PARÂMETROS!$B$4*PARÂMETROS!$B$5*PARÂMETROS!$B$44,0) | L22: =IFERROR(PARÂMETROS!I101*PARÂMETROS!E22*PARÂMETROS!$B$4*PARÂMETROS!$B$5*PARÂMETROS!$B$45,0) | M22: =IFERROR(PARÂMETROS!J101*PARÂMETROS!E22*PARÂMETROS!$B$4*PARÂMETROS!$B$5*PARÂMETROS!$B$46,0) | N22: =IFERROR(PARÂMETROS!K101*PARÂMETROS!E22*PARÂMETROS!$B$4*PARÂMETROS!$B$5*PARÂMETROS!$B$47,0) | O22: =IFERROR(PARÂMETROS!L101*PARÂMETROS!E22*PARÂMETROS!$B$4*PARÂMETROS!$B$5*PARÂMETROS!$B$48,0) | P22: =IFERROR(PARÂMETROS!M101*PARÂMETROS!E22*PARÂMETROS!$B$4*PARÂMETROS!$B$5*PARÂMETROS!$B$49,0) | Q22: =IFERROR(PARÂMETROS!N101*PARÂMETROS!E22*PARÂMETROS!$B$4*PARÂMETROS!$B$5*PARÂMETROS!$B$50,0) | R22: =IFERROR(PARÂMETROS!O101*PARÂMETROS!E22*PARÂMETROS!$B$4*PARÂMETROS!$B$5*PARÂMETROS!$B$51,0) | S22: =IFERROR(PARÂMETROS!P101*PARÂMETROS!E22*PARÂMETROS!$B$4*PARÂMETROS!$B$5*PARÂMETROS!$B$52,0) | T22: =IFERROR(PARÂMETROS!Q101*PARÂMETROS!E22*PARÂMETROS!$B$4*PARÂMETROS!$B$5*PARÂMETROS!$B$53,0) | U22: =IFERROR(PARÂMETROS!R101*PARÂMETROS!E22*PARÂMETROS!$B$4*PARÂMETROS!$B$5*PARÂMETROS!$B$54,0) | V22: =IFERROR(PARÂMETROS!S101*PARÂMETROS!E22*PARÂMETROS!$B$4*PARÂMETROS!$B$5*PARÂMETROS!$B$55,0) | W22: =IFERROR(PARÂMETROS!T101*PARÂMETROS!E22*PARÂMETROS!$B$4*PARÂMETROS!$B$5*PARÂMETROS!$B$56,0) | X22: =IFERROR(PARÂMETROS!U101*PARÂMETROS!E22*PARÂMETROS!$B$4*PARÂMETROS!$B$5*PARÂMETROS!$B$57,0) | Y22: =IFERROR(PARÂMETROS!V101*PARÂMETROS!E22*PARÂMETROS!$B$4*PARÂMETROS!$B$5*PARÂMETROS!$B$58,0) | Z22: =IFERROR(PARÂMETROS!W101*PARÂMETROS!E22*PARÂMETROS!$B$4*PARÂMETROS!$B$5*PARÂMETROS!$B$59,0) | AA22: =IFERROR(PARÂMETROS!X101*PARÂMETROS!E22*PARÂMETROS!$B$4*PARÂMETROS!$B$5*PARÂMETROS!$B$60,0) | AB22: =IFERROR(PARÂMETROS!Y101*PARÂMETROS!E22*PARÂMETROS!$B$4*PARÂMETROS!$B$5*PARÂMETROS!$B$61,0) | AC22: =IFERROR(PARÂMETROS!Z101*PARÂMETROS!E22*PARÂMETROS!$B$4*PARÂMETROS!$B$5*PARÂMETROS!$B$62,0) | AD22: =IFERROR(PARÂMETROS!AA101*PARÂMETROS!E22*PARÂMETROS!$B$4*PARÂMETROS!$B$5*PARÂMETROS!$B$63,0) | AE22: =IFERROR(PARÂMETROS!AB101*PARÂMETROS!E22*PARÂMETROS!$B$4*PARÂMETROS!$B$5*PARÂMETROS!$B$64,0) | AF22: =IFERROR(PARÂMETROS!AC101*PARÂMETROS!E22*PARÂMETROS!$B$4*PARÂMETROS!$B$5*PARÂMETROS!$B$65,0) | AG22: =IFERROR(PARÂMETROS!AD101*PARÂMETROS!E22*PARÂMETROS!$B$4*PARÂMETROS!$B$5*PARÂMETROS!$B$66,0) | AH22: =IFERROR(PARÂMETROS!AE101*PARÂMETROS!E22*PARÂMETROS!$B$4*PARÂMETROS!$B$5*PARÂMETROS!$B$67,0) | AI22: =IFERROR(PARÂMETROS!AF101*PARÂMETROS!E22*PARÂMETROS!$B$4*PARÂMETROS!$B$5*PARÂMETROS!$B$68,0) | AJ22: =IFERROR(PARÂMETROS!AG101*PARÂMETROS!E22*PARÂMETROS!$B$4*PARÂMETROS!$B$5*PARÂMETROS!$B$69,0) | AK22: =IFERROR(PARÂMETROS!AH101*PARÂMETROS!E22*PARÂMETROS!$B$4*PARÂMETROS!$B$5*PARÂMETROS!$B$70,0) | AL22: =IFERROR(PARÂMETROS!AI101*PARÂMETROS!E22*PARÂMETROS!$B$4*PARÂMETROS!$B$5*PARÂMETROS!$B$71,0) | AM22: =IFERROR(PARÂMETROS!AJ101*PARÂMETROS!E22*PARÂMETROS!$B$4*PARÂMETROS!$B$5*PARÂMETROS!$B$72,0) | AN22: =IFERROR(PARÂMETROS!AK101*PARÂMETROS!E22*PARÂMETROS!$B$4*PARÂMETROS!$B$5*PARÂMETROS!$B$73,0) | AO22: =IFERROR(PARÂMETROS!AL101*PARÂMETROS!E22*PARÂMETROS!$B$4*PARÂMETROS!$B$5*PARÂMETROS!$B$74,0) | AP22: =IFERROR(PARÂMETROS!AM101*PARÂMETROS!E22*PARÂMETROS!$B$4*PARÂMETROS!$B$5*PARÂMETROS!$B$75,0) | AQ22: =IFERROR(PARÂMETROS!AN101*PARÂMETROS!E22*PARÂMETROS!$B$4*PARÂMETROS!$B$5*PARÂMETROS!$B$76,0) | AR22: =IFERROR(PARÂMETROS!AO101*PARÂMETROS!E22*PARÂMETROS!$B$4*PARÂMETROS!$B$5*PARÂMETROS!$B$77,0) | AS22: =IFERROR(PARÂMETROS!AP101*PARÂMETROS!E22*PARÂMETROS!$B$4*PARÂMETROS!$B$5*PARÂMETROS!$B$78,0) | AT22: =IFERROR(PARÂMETROS!AQ101*PARÂMETROS!E22*PARÂMETROS!$B$4*PARÂMETROS!$B$5*PARÂMETROS!$B$79,0) | AU22: =IFERROR(PARÂMETROS!AR101*PARÂMETROS!E22*PARÂMETROS!$B$4*PARÂMETROS!$B$5*PARÂMETROS!$B$80,0) | AV22: =IFERROR(PARÂMETROS!AS101*PARÂMETROS!E22*PARÂMETROS!$B$4*PARÂMETROS!$B$5*PARÂMETROS!$B$81,0) | AW22: =IFERROR(PARÂMETROS!AT101*PARÂMETROS!E22*PARÂMETROS!$B$4*PARÂMETROS!$B$5*PARÂMETROS!$B$82,0) | AX22: =IFERROR(PARÂMETROS!AU101*PARÂMETROS!E22*PARÂMETROS!$B$4*PARÂMETROS!$B$5*PARÂMETROS!$B$83,0) | AY22: =IFERROR(PARÂMETROS!AV101*PARÂMETROS!E22*PARÂMETROS!$B$4*PARÂMETROS!$B$5*PARÂMETROS!$B$84,0) | AZ22: =IFERROR(PARÂMETROS!AW101*PARÂMETROS!E22*PARÂMETROS!$B$4*PARÂMETROS!$B$5*PARÂMETROS!$B$85,0) | BA22: =IFERROR(PARÂMETROS!AX101*PARÂMETROS!E22*PARÂMETROS!$B$4*PARÂMETROS!$B$5*PARÂMETROS!$B$86,0) | BB22: =IFERROR(PARÂMETROS!AY101*PARÂMETROS!E22*PARÂMETROS!$B$4*PARÂMETROS!$B$5*PARÂMETROS!$B$87,0) | BC22: =IFERROR(PARÂMETROS!AZ101*PARÂMETROS!E22*PARÂMETROS!$B$4*PARÂMETROS!$B$5*PARÂMETROS!$B$88,0) | BD22: =IFERROR(PARÂMETROS!BA101*PARÂMETROS!E22*PARÂMETROS!$B$4*PARÂMETROS!$B$5*PARÂMETROS!$B$89,0) | BE22: =IFERROR(PARÂMETROS!BB101*PARÂMETROS!E22*PARÂMETROS!$B$4*PARÂMETROS!$B$5*PARÂMETROS!$B$90,0) | BF22: =IFERROR(PARÂMETROS!BC101*PARÂMETROS!E22*PARÂMETROS!$B$4*PARÂMETROS!$B$5*PARÂMETROS!$B$91,0)
F23: Acumulado | G23: =G22 | H23: =G23+H22 | I23: =H23+I22 | J23: =I23+J22 | K23: =J23+K22 | L23: =K23+L22 | M23: =L23+M22 | N23: =M23+N22 | O23: =N23+O22 | ... BF23: =BE23+BF22
F24: % Completude | G24: =IF(PARÂMETROS!D22>0,G23/PARÂMETROS!D22,0) | H24: =IF(PARÂMETROS!D22>0,H23/PARÂMETROS!D22,0) | I24: =IF(PARÂMETROS!D22>0,I23/PARÂMETROS!D22,0) | J24: =IF(PARÂMETROS!D22>0,J23/PARÂMETROS!D22,0) | K24: =IF(PARÂMETROS!D22>0,K23/PARÂMETROS!D22,0) | L24: =IF(PARÂMETROS!D22>0,L23/PARÂMETROS!D22,0) | M24: =IF(PARÂMETROS!D22>0,M23/PARÂMETROS!D22,0) | N24: =IF(PARÂMETROS!D22>0,N23/PARÂMETROS!D22,0) | O24: =IF(PARÂMETROS!D22>0,O23/PARÂMETROS!D22,0) | P24: =IF(PARÂMETROS!D22>0,P23/PARÂMETROS!D22,0) | Q24: =IF(PARÂMETROS!D22>0,Q23/PARÂMETROS!D22,0) | R24: =IF(PARÂMETROS!D22>0,R23/PARÂMETROS!D22,0) | S24: =IF(PARÂMETROS!D22>0,S23/PARÂMETROS!D22,0) | T24: =IF(PARÂMETROS!D22>0,T23/PARÂMETROS!D22,0) | U24: =IF(PARÂMETROS!D22>0,U23/PARÂMETROS!D22,0) | V24: =IF(PARÂMETROS!D22>0,V23/PARÂMETROS!D22,0) | W24: =IF(PARÂMETROS!D22>0,W23/PARÂMETROS!D22,0) | X24: =IF(PARÂMETROS!D22>0,X23/PARÂMETROS!D22,0) | Y24: =IF(PARÂMETROS!D22>0,Y23/PARÂMETROS!D22,0) | Z24: =IF(PARÂMETROS!D22>0,Z23/PARÂMETROS!D22,0) | AA24: =IF(PARÂMETROS!D22>0,AA23/PARÂMETROS!D22,0) | AB24: =IF(PARÂMETROS!D22>0,AB23/PARÂMETROS!D22,0) | AC24: =IF(PARÂMETROS!D22>0,AC23/PARÂMETROS!D22,0) | AD24: =IF(PARÂMETROS!D22>0,AD23/PARÂMETROS!D22,0) | AE24: =IF(PARÂMETROS!D22>0,AE23/PARÂMETROS!D22,0) | AF24: =IF(PARÂMETROS!D22>0,AF23/PARÂMETROS!D22,0) | AG24: =IF(PARÂMETROS!D22>0,AG23/PARÂMETROS!D22,0) | AH24: =IF(PARÂMETROS!D22>0,AH23/PARÂMETROS!D22,0) | AI24: =IF(PARÂMETROS!D22>0,AI23/PARÂMETROS!D22,0) | AJ24: =IF(PARÂMETROS!D22>0,AJ23/PARÂMETROS!D22,0) | AK24: =IF(PARÂMETROS!D22>0,AK23/PARÂMETROS!D22,0) | AL24: =IF(PARÂMETROS!D22>0,AL23/PARÂMETROS!D22,0) | AM24: =IF(PARÂMETROS!D22>0,AM23/PARÂMETROS!D22,0) | AN24: =IF(PARÂMETROS!D22>0,AN23/PARÂMETROS!D22,0) | AO24: =IF(PARÂMETROS!D22>0,AO23/PARÂMETROS!D22,0) | AP24: =IF(PARÂMETROS!D22>0,AP23/PARÂMETROS!D22,0) | AQ24: =IF(PARÂMETROS!D22>0,AQ23/PARÂMETROS!D22,0) | AR24: =IF(PARÂMETROS!D22>0,AR23/PARÂMETROS!D22,0) | AS24: =IF(PARÂMETROS!D22>0,AS23/PARÂMETROS!D22,0) | AT24: =IF(PARÂMETROS!D22>0,AT23/PARÂMETROS!D22,0) | AU24: =IF(PARÂMETROS!D22>0,AU23/PARÂMETROS!D22,0) | AV24: =IF(PARÂMETROS!D22>0,AV23/PARÂMETROS!D22,0) | AW24: =IF(PARÂMETROS!D22>0,AW23/PARÂMETROS!D22,0) | AX24: =IF(PARÂMETROS!D22>0,AX23/PARÂMETROS!D22,0) | AY24: =IF(PARÂMETROS!D22>0,AY23/PARÂMETROS!D22,0) | AZ24: =IF(PARÂMETROS!D22>0,AZ23/PARÂMETROS!D22,0) | BA24: =IF(PARÂMETROS!D22>0,BA23/PARÂMETROS!D22,0) | BB24: =IF(PARÂMETROS!D22>0,BB23/PARÂMETROS!D22,0) | BC24: =IF(PARÂMETROS!D22>0,BC23/PARÂMETROS!D22,0) | BD24: =IF(PARÂMETROS!D22>0,BD23/PARÂMETROS!D22,0) | BE24: =IF(PARÂMETROS!D22>0,BE23/PARÂMETROS!D22,0) | BF24: =IF(PARÂMETROS!D22>0,BF23/PARÂMETROS!D22,0)
A25: eap-1_7 | B25: Compactacao aterros 100% | C25: =PARÂMETROS!D23 | D25: =SUM(G25:BF25) | E25: =IF(C25>0,(D25-C25)/C25,0) | F25: Produção semanal | G25: =IFERROR(PARÂMETROS!D102*PARÂMETROS!E23*PARÂMETROS!$B$4*PARÂMETROS!$B$5*PARÂMETROS!$B$40,0) | H25: =IFERROR(PARÂMETROS!E102*PARÂMETROS!E23*PARÂMETROS!$B$4*PARÂMETROS!$B$5*PARÂMETROS!$B$41,0) | I25: =IFERROR(PARÂMETROS!F102*PARÂMETROS!E23*PARÂMETROS!$B$4*PARÂMETROS!$B$5*PARÂMETROS!$B$42,0) | J25: =IFERROR(PARÂMETROS!G102*PARÂMETROS!E23*PARÂMETROS!$B$4*PARÂMETROS!$B$5*PARÂMETROS!$B$43,0) | K25: =IFERROR(PARÂMETROS!H102*PARÂMETROS!E23*PARÂMETROS!$B$4*PARÂMETROS!$B$5*PARÂMETROS!$B$44,0) | L25: =IFERROR(PARÂMETROS!I102*PARÂMETROS!E23*PARÂMETROS!$B$4*PARÂMETROS!$B$5*PARÂMETROS!$B$45,0) | M25: =IFERROR(PARÂMETROS!J102*PARÂMETROS!E23*PARÂMETROS!$B$4*PARÂMETROS!$B$5*PARÂMETROS!$B$46,0) | N25: =IFERROR(PARÂMETROS!K102*PARÂMETROS!E23*PARÂMETROS!$B$4*PARÂMETROS!$B$5*PARÂMETROS!$B$47,0) | O25: =IFERROR(PARÂMETROS!L102*PARÂMETROS!E23*PARÂMETROS!$B$4*PARÂMETROS!$B$5*PARÂMETROS!$B$48,0) | P25: =IFERROR(PARÂMETROS!M102*PARÂMETROS!E23*PARÂMETROS!$B$4*PARÂMETROS!$B$5*PARÂMETROS!$B$49,0) | Q25: =IFERROR(PARÂMETROS!N102*PARÂMETROS!E23*PARÂMETROS!$B$4*PARÂMETROS!$B$5*PARÂMETROS!$B$50,0) | R25: =IFERROR(PARÂMETROS!O102*PARÂMETROS!E23*PARÂMETROS!$B$4*PARÂMETROS!$B$5*PARÂMETROS!$B$51,0) | S25: =IFERROR(PARÂMETROS!P102*PARÂMETROS!E23*PARÂMETROS!$B$4*PARÂMETROS!$B$5*PARÂMETROS!$B$52,0) | T25: =IFERROR(PARÂMETROS!Q102*PARÂMETROS!E23*PARÂMETROS!$B$4*PARÂMETROS!$B$5*PARÂMETROS!$B$53,0) | U25: =IFERROR(PARÂMETROS!R102*PARÂMETROS!E23*PARÂMETROS!$B$4*PARÂMETROS!$B$5*PARÂMETROS!$B$54,0) | V25: =IFERROR(PARÂMETROS!S102*PARÂMETROS!E23*PARÂMETROS!$B$4*PARÂMETROS!$B$5*PARÂMETROS!$B$55,0) | W25: =IFERROR(PARÂMETROS!T102*PARÂMETROS!E23*PARÂMETROS!$B$4*PARÂMETROS!$B$5*PARÂMETROS!$B$56,0) | X25: =IFERROR(PARÂMETROS!U102*PARÂMETROS!E23*PARÂMETROS!$B$4*PARÂMETROS!$B$5*PARÂMETROS!$B$57,0) | Y25: =IFERROR(PARÂMETROS!V102*PARÂMETROS!E23*PARÂMETROS!$B$4*PARÂMETROS!$B$5*PARÂMETROS!$B$58,0) | Z25: =IFERROR(PARÂMETROS!W102*PARÂMETROS!E23*PARÂMETROS!$B$4*PARÂMETROS!$B$5*PARÂMETROS!$B$59,0) | AA25: =IFERROR(PARÂMETROS!X102*PARÂMETROS!E23*PARÂMETROS!$B$4*PARÂMETROS!$B$5*PARÂMETROS!$B$60,0) | AB25: =IFERROR(PARÂMETROS!Y102*PARÂMETROS!E23*PARÂMETROS!$B$4*PARÂMETROS!$B$5*PARÂMETROS!$B$61,0) | AC25: =IFERROR(PARÂMETROS!Z102*PARÂMETROS!E23*PARÂMETROS!$B$4*PARÂMETROS!$B$5*PARÂMETROS!$B$62,0) | AD25: =IFERROR(PARÂMETROS!AA102*PARÂMETROS!E23*PARÂMETROS!$B$4*PARÂMETROS!$B$5*PARÂMETROS!$B$63,0) | AE25: =IFERROR(PARÂMETROS!AB102*PARÂMETROS!E23*PARÂMETROS!$B$4*PARÂMETROS!$B$5*PARÂMETROS!$B$64,0) | AF25: =IFERROR(PARÂMETROS!AC102*PARÂMETROS!E23*PARÂMETROS!$B$4*PARÂMETROS!$B$5*PARÂMETROS!$B$65,0) | AG25: =IFERROR(PARÂMETROS!AD102*PARÂMETROS!E23*PARÂMETROS!$B$4*PARÂMETROS!$B$5*PARÂMETROS!$B$66,0) | AH25: =IFERROR(PARÂMETROS!AE102*PARÂMETROS!E23*PARÂMETROS!$B$4*PARÂMETROS!$B$5*PARÂMETROS!$B$67,0) | AI25: =IFERROR(PARÂMETROS!AF102*PARÂMETROS!E23*PARÂMETROS!$B$4*PARÂMETROS!$B$5*PARÂMETROS!$B$68,0) | AJ25: =IFERROR(PARÂMETROS!AG102*PARÂMETROS!E23*PARÂMETROS!$B$4*PARÂMETROS!$B$5*PARÂMETROS!$B$69,0) | AK25: =IFERROR(PARÂMETROS!AH102*PARÂMETROS!E23*PARÂMETROS!$B$4*PARÂMETROS!$B$5*PARÂMETROS!$B$70,0) | AL25: =IFERROR(PARÂMETROS!AI102*PARÂMETROS!E23*PARÂMETROS!$B$4*PARÂMETROS!$B$5*PARÂMETROS!$B$71,0) | AM25: =IFERROR(PARÂMETROS!AJ102*PARÂMETROS!E23*PARÂMETROS!$B$4*PARÂMETROS!$B$5*PARÂMETROS!$B$72,0) | AN25: =IFERROR(PARÂMETROS!AK102*PARÂMETROS!E23*PARÂMETROS!$B$4*PARÂMETROS!$B$5*PARÂMETROS!$B$73,0) | AO25: =IFERROR(PARÂMETROS!AL102*PARÂMETROS!E23*PARÂMETROS!$B$4*PARÂMETROS!$B$5*PARÂMETROS!$B$74,0) | AP25: =IFERROR(PARÂMETROS!AM102*PARÂMETROS!E23*PARÂMETROS!$B$4*PARÂMETROS!$B$5*PARÂMETROS!$B$75,0) | AQ25: =IFERROR(PARÂMETROS!AN102*PARÂMETROS!E23*PARÂMETROS!$B$4*PARÂMETROS!$B$5*PARÂMETROS!$B$76,0) | AR25: =IFERROR(PARÂMETROS!AO102*PARÂMETROS!E23*PARÂMETROS!$B$4*PARÂMETROS!$B$5*PARÂMETROS!$B$77,0) | AS25: =IFERROR(PARÂMETROS!AP102*PARÂMETROS!E23*PARÂMETROS!$B$4*PARÂMETROS!$B$5*PARÂMETROS!$B$78,0) | AT25: =IFERROR(PARÂMETROS!AQ102*PARÂMETROS!E23*PARÂMETROS!$B$4*PARÂMETROS!$B$5*PARÂMETROS!$B$79,0) | AU25: =IFERROR(PARÂMETROS!AR102*PARÂMETROS!E23*PARÂMETROS!$B$4*PARÂMETROS!$B$5*PARÂMETROS!$B$80,0) | AV25: =IFERROR(PARÂMETROS!AS102*PARÂMETROS!E23*PARÂMETROS!$B$4*PARÂMETROS!$B$5*PARÂMETROS!$B$81,0) | AW25: =IFERROR(PARÂMETROS!AT102*PARÂMETROS!E23*PARÂMETROS!$B$4*PARÂMETROS!$B$5*PARÂMETROS!$B$82,0) | AX25: =IFERROR(PARÂMETROS!AU102*PARÂMETROS!E23*PARÂMETROS!$B$4*PARÂMETROS!$B$5*PARÂMETROS!$B$83,0) | AY25: =IFERROR(PARÂMETROS!AV102*PARÂMETROS!E23*PARÂMETROS!$B$4*PARÂMETROS!$B$5*PARÂMETROS!$B$84,0) | AZ25: =IFERROR(PARÂMETROS!AW102*PARÂMETROS!E23*PARÂMETROS!$B$4*PARÂMETROS!$B$5*PARÂMETROS!$B$85,0) | BA25: =IFERROR(PARÂMETROS!AX102*PARÂMETROS!E23*PARÂMETROS!$B$4*PARÂMETROS!$B$5*PARÂMETROS!$B$86,0) | BB25: =IFERROR(PARÂMETROS!AY102*PARÂMETROS!E23*PARÂMETROS!$B$4*PARÂMETROS!$B$5*PARÂMETROS!$B$87,0) | BC25: =IFERROR(PARÂMETROS!AZ102*PARÂMETROS!E23*PARÂMETROS!$B$4*PARÂMETROS!$B$5*PARÂMETROS!$B$88,0) | BD25: =IFERROR(PARÂMETROS!BA102*PARÂMETROS!E23*PARÂMETROS!$B$4*PARÂMETROS!$B$5*PARÂMETROS!$B$89,0) | BE25: =IFERROR(PARÂMETROS!BB102*PARÂMETROS!E23*PARÂMETROS!$B$4*PARÂMETROS!$B$5*PARÂMETROS!$B$90,0) | BF25: =IFERROR(PARÂMETROS!BC102*PARÂMETROS!E23*PARÂMETROS!$B$4*PARÂMETROS!$B$5*PARÂMETROS!$B$91,0)
F26: Acumulado | G26: =G25 | H26: =G26+H25 | I26: =H26+I25 | J26: =I26+J25 | K26: =J26+K25 | L26: =K26+L25 | M26: =L26+M25 | N26: =M26+N25 | O26: =N26+O25 | ... BF26: =BE26+BF25
F27: % Completude | G27: =IF(PARÂMETROS!D23>0,G26/PARÂMETROS!D23,0) | H27: =IF(PARÂMETROS!D23>0,H26/PARÂMETROS!D23,0) | I27: =IF(PARÂMETROS!D23>0,I26/PARÂMETROS!D23,0) | J27: =IF(PARÂMETROS!D23>0,J26/PARÂMETROS!D23,0) | K27: =IF(PARÂMETROS!D23>0,K26/PARÂMETROS!D23,0) | L27: =IF(PARÂMETROS!D23>0,L26/PARÂMETROS!D23,0) | M27: =IF(PARÂMETROS!D23>0,M26/PARÂMETROS!D23,0) | N27: =IF(PARÂMETROS!D23>0,N26/PARÂMETROS!D23,0) | O27: =IF(PARÂMETROS!D23>0,O26/PARÂMETROS!D23,0) | P27: =IF(PARÂMETROS!D23>0,P26/PARÂMETROS!D23,0) | Q27: =IF(PARÂMETROS!D23>0,Q26/PARÂMETROS!D23,0) | R27: =IF(PARÂMETROS!D23>0,R26/PARÂMETROS!D23,0) | S27: =IF(PARÂMETROS!D23>0,S26/PARÂMETROS!D23,0) | T27: =IF(PARÂMETROS!D23>0,T26/PARÂMETROS!D23,0) | U27: =IF(PARÂMETROS!D23>0,U26/PARÂMETROS!D23,0) | V27: =IF(PARÂMETROS!D23>0,V26/PARÂMETROS!D23,0) | W27: =IF(PARÂMETROS!D23>0,W26/PARÂMETROS!D23,0) | X27: =IF(PARÂMETROS!D23>0,X26/PARÂMETROS!D23,0) | Y27: =IF(PARÂMETROS!D23>0,Y26/PARÂMETROS!D23,0) | Z27: =IF(PARÂMETROS!D23>0,Z26/PARÂMETROS!D23,0) | AA27: =IF(PARÂMETROS!D23>0,AA26/PARÂMETROS!D23,0) | AB27: =IF(PARÂMETROS!D23>0,AB26/PARÂMETROS!D23,0) | AC27: =IF(PARÂMETROS!D23>0,AC26/PARÂMETROS!D23,0) | AD27: =IF(PARÂMETROS!D23>0,AD26/PARÂMETROS!D23,0) | AE27: =IF(PARÂMETROS!D23>0,AE26/PARÂMETROS!D23,0) | AF27: =IF(PARÂMETROS!D23>0,AF26/PARÂMETROS!D23,0) | AG27: =IF(PARÂMETROS!D23>0,AG26/PARÂMETROS!D23,0) | AH27: =IF(PARÂMETROS!D23>0,AH26/PARÂMETROS!D23,0) | AI27: =IF(PARÂMETROS!D23>0,AI26/PARÂMETROS!D23,0) | AJ27: =IF(PARÂMETROS!D23>0,AJ26/PARÂMETROS!D23,0) | AK27: =IF(PARÂMETROS!D23>0,AK26/PARÂMETROS!D23,0) | AL27: =IF(PARÂMETROS!D23>0,AL26/PARÂMETROS!D23,0) | AM27: =IF(PARÂMETROS!D23>0,AM26/PARÂMETROS!D23,0) | AN27: =IF(PARÂMETROS!D23>0,AN26/PARÂMETROS!D23,0) | AO27: =IF(PARÂMETROS!D23>0,AO26/PARÂMETROS!D23,0) | AP27: =IF(PARÂMETROS!D23>0,AP26/PARÂMETROS!D23,0) | AQ27: =IF(PARÂMETROS!D23>0,AQ26/PARÂMETROS!D23,0) | AR27: =IF(PARÂMETROS!D23>0,AR26/PARÂMETROS!D23,0) | AS27: =IF(PARÂMETROS!D23>0,AS26/PARÂMETROS!D23,0) | AT27: =IF(PARÂMETROS!D23>0,AT26/PARÂMETROS!D23,0) | AU27: =IF(PARÂMETROS!D23>0,AU26/PARÂMETROS!D23,0) | AV27: =IF(PARÂMETROS!D23>0,AV26/PARÂMETROS!D23,0) | AW27: =IF(PARÂMETROS!D23>0,AW26/PARÂMETROS!D23,0) | AX27: =IF(PARÂMETROS!D23>0,AX26/PARÂMETROS!D23,0) | AY27: =IF(PARÂMETROS!D23>0,AY26/PARÂMETROS!D23,0) | AZ27: =IF(PARÂMETROS!D23>0,AZ26/PARÂMETROS!D23,0) | BA27: =IF(PARÂMETROS!D23>0,BA26/PARÂMETROS!D23,0) | BB27: =IF(PARÂMETROS!D23>0,BB26/PARÂMETROS!D23,0) | BC27: =IF(PARÂMETROS!D23>0,BC26/PARÂMETROS!D23,0) | BD27: =IF(PARÂMETROS!D23>0,BD26/PARÂMETROS!D23,0) | BE27: =IF(PARÂMETROS!D23>0,BE26/PARÂMETROS!D23,0) | BF27: =IF(PARÂMETROS!D23>0,BF26/PARÂMETROS!D23,0)
A28: eap-1_8 | B28: Compactacao aterros 100% | C28: =PARÂMETROS!D24 | D28: =SUM(G28:BF28) | E28: =IF(C28>0,(D28-C28)/C28,0) | F28: Produção semanal | G28: =IFERROR(PARÂMETROS!D103*PARÂMETROS!E24*PARÂMETROS!$B$4*PARÂMETROS!$B$5*PARÂMETROS!$B$40,0) | H28: =IFERROR(PARÂMETROS!E103*PARÂMETROS!E24*PARÂMETROS!$B$4*PARÂMETROS!$B$5*PARÂMETROS!$B$41,0) | I28: =IFERROR(PARÂMETROS!F103*PARÂMETROS!E24*PARÂMETROS!$B$4*PARÂMETROS!$B$5*PARÂMETROS!$B$42,0) | J28: =IFERROR(PARÂMETROS!G103*PARÂMETROS!E24*PARÂMETROS!$B$4*PARÂMETROS!$B$5*PARÂMETROS!$B$43,0) | K28: =IFERROR(PARÂMETROS!H103*PARÂMETROS!E24*PARÂMETROS!$B$4*PARÂMETROS!$B$5*PARÂMETROS!$B$44,0) | L28: =IFERROR(PARÂMETROS!I103*PARÂMETROS!E24*PARÂMETROS!$B$4*PARÂMETROS!$B$5*PARÂMETROS!$B$45,0) | M28: =IFERROR(PARÂMETROS!J103*PARÂMETROS!E24*PARÂMETROS!$B$4*PARÂMETROS!$B$5*PARÂMETROS!$B$46,0) | N28: =IFERROR(PARÂMETROS!K103*PARÂMETROS!E24*PARÂMETROS!$B$4*PARÂMETROS!$B$5*PARÂMETROS!$B$47,0) | O28: =IFERROR(PARÂMETROS!L103*PARÂMETROS!E24*PARÂMETROS!$B$4*PARÂMETROS!$B$5*PARÂMETROS!$B$48,0) | P28: =IFERROR(PARÂMETROS!M103*PARÂMETROS!E24*PARÂMETROS!$B$4*PARÂMETROS!$B$5*PARÂMETROS!$B$49,0) | Q28: =IFERROR(PARÂMETROS!N103*PARÂMETROS!E24*PARÂMETROS!$B$4*PARÂMETROS!$B$5*PARÂMETROS!$B$50,0) | R28: =IFERROR(PARÂMETROS!O103*PARÂMETROS!E24*PARÂMETROS!$B$4*PARÂMETROS!$B$5*PARÂMETROS!$B$51,0) | S28: =IFERROR(PARÂMETROS!P103*PARÂMETROS!E24*PARÂMETROS!$B$4*PARÂMETROS!$B$5*PARÂMETROS!$B$52,0) | T28: =IFERROR(PARÂMETROS!Q103*PARÂMETROS!E24*PARÂMETROS!$B$4*PARÂMETROS!$B$5*PARÂMETROS!$B$53,0) | U28: =IFERROR(PARÂMETROS!R103*PARÂMETROS!E24*PARÂMETROS!$B$4*PARÂMETROS!$B$5*PARÂMETROS!$B$54,0) | V28: =IFERROR(PARÂMETROS!S103*PARÂMETROS!E24*PARÂMETROS!$B$4*PARÂMETROS!$B$5*PARÂMETROS!$B$55,0) | W28: =IFERROR(PARÂMETROS!T103*PARÂMETROS!E24*PARÂMETROS!$B$4*PARÂMETROS!$B$5*PARÂMETROS!$B$56,0) | X28: =IFERROR(PARÂMETROS!U103*PARÂMETROS!E24*PARÂMETROS!$B$4*PARÂMETROS!$B$5*PARÂMETROS!$B$57,0) | Y28: =IFERROR(PARÂMETROS!V103*PARÂMETROS!E24*PARÂMETROS!$B$4*PARÂMETROS!$B$5*PARÂMETROS!$B$58,0) | Z28: =IFERROR(PARÂMETROS!W103*PARÂMETROS!E24*PARÂMETROS!$B$4*PARÂMETROS!$B$5*PARÂMETROS!$B$59,0) | AA28: =IFERROR(PARÂMETROS!X103*PARÂMETROS!E24*PARÂMETROS!$B$4*PARÂMETROS!$B$5*PARÂMETROS!$B$60,0) | AB28: =IFERROR(PARÂMETROS!Y103*PARÂMETROS!E24*PARÂMETROS!$B$4*PARÂMETROS!$B$5*PARÂMETROS!$B$61,0) | AC28: =IFERROR(PARÂMETROS!Z103*PARÂMETROS!E24*PARÂMETROS!$B$4*PARÂMETROS!$B$5*PARÂMETROS!$B$62,0) | AD28: =IFERROR(PARÂMETROS!AA103*PARÂMETROS!E24*PARÂMETROS!$B$4*PARÂMETROS!$B$5*PARÂMETROS!$B$63,0) | AE28: =IFERROR(PARÂMETROS!AB103*PARÂMETROS!E24*PARÂMETROS!$B$4*PARÂMETROS!$B$5*PARÂMETROS!$B$64,0) | AF28: =IFERROR(PARÂMETROS!AC103*PARÂMETROS!E24*PARÂMETROS!$B$4*PARÂMETROS!$B$5*PARÂMETROS!$B$65,0) | AG28: =IFERROR(PARÂMETROS!AD103*PARÂMETROS!E24*PARÂMETROS!$B$4*PARÂMETROS!$B$5*PARÂMETROS!$B$66,0) | AH28: =IFERROR(PARÂMETROS!AE103*PARÂMETROS!E24*PARÂMETROS!$B$4*PARÂMETROS!$B$5*PARÂMETROS!$B$67,0) | AI28: =IFERROR(PARÂMETROS!AF103*PARÂMETROS!E24*PARÂMETROS!$B$4*PARÂMETROS!$B$5*PARÂMETROS!$B$68,0) | AJ28: =IFERROR(PARÂMETROS!AG103*PARÂMETROS!E24*PARÂMETROS!$B$4*PARÂMETROS!$B$5*PARÂMETROS!$B$69,0) | AK28: =IFERROR(PARÂMETROS!AH103*PARÂMETROS!E24*PARÂMETROS!$B$4*PARÂMETROS!$B$5*PARÂMETROS!$B$70,0) | AL28: =IFERROR(PARÂMETROS!AI103*PARÂMETROS!E24*PARÂMETROS!$B$4*PARÂMETROS!$B$5*PARÂMETROS!$B$71,0) | AM28: =IFERROR(PARÂMETROS!AJ103*PARÂMETROS!E24*PARÂMETROS!$B$4*PARÂMETROS!$B$5*PARÂMETROS!$B$72,0) | AN28: =IFERROR(PARÂMETROS!AK103*PARÂMETROS!E24*PARÂMETROS!$B$4*PARÂMETROS!$B$5*PARÂMETROS!$B$73,0) | AO28: =IFERROR(PARÂMETROS!AL103*PARÂMETROS!E24*PARÂMETROS!$B$4*PARÂMETROS!$B$5*PARÂMETROS!$B$74,0) | AP28: =IFERROR(PARÂMETROS!AM103*PARÂMETROS!E24*PARÂMETROS!$B$4*PARÂMETROS!$B$5*PARÂMETROS!$B$75,0) | AQ28: =IFERROR(PARÂMETROS!AN103*PARÂMETROS!E24*PARÂMETROS!$B$4*PARÂMETROS!$B$5*PARÂMETROS!$B$76,0) | AR28: =IFERROR(PARÂMETROS!AO103*PARÂMETROS!E24*PARÂMETROS!$B$4*PARÂMETROS!$B$5*PARÂMETROS!$B$77,0) | AS28: =IFERROR(PARÂMETROS!AP103*PARÂMETROS!E24*PARÂMETROS!$B$4*PARÂMETROS!$B$5*PARÂMETROS!$B$78,0) | AT28: =IFERROR(PARÂMETROS!AQ103*PARÂMETROS!E24*PARÂMETROS!$B$4*PARÂMETROS!$B$5*PARÂMETROS!$B$79,0) | AU28: =IFERROR(PARÂMETROS!AR103*PARÂMETROS!E24*PARÂMETROS!$B$4*PARÂMETROS!$B$5*PARÂMETROS!$B$80,0) | AV28: =IFERROR(PARÂMETROS!AS103*PARÂMETROS!E24*PARÂMETROS!$B$4*PARÂMETROS!$B$5*PARÂMETROS!$B$81,0) | AW28: =IFERROR(PARÂMETROS!AT103*PARÂMETROS!E24*PARÂMETROS!$B$4*PARÂMETROS!$B$5*PARÂMETROS!$B$82,0) | AX28: =IFERROR(PARÂMETROS!AU103*PARÂMETROS!E24*PARÂMETROS!$B$4*PARÂMETROS!$B$5*PARÂMETROS!$B$83,0) | AY28: =IFERROR(PARÂMETROS!AV103*PARÂMETROS!E24*PARÂMETROS!$B$4*PARÂMETROS!$B$5*PARÂMETROS!$B$84,0) | AZ28: =IFERROR(PARÂMETROS!AW103*PARÂMETROS!E24*PARÂMETROS!$B$4*PARÂMETROS!$B$5*PARÂMETROS!$B$85,0) | BA28: =IFERROR(PARÂMETROS!AX103*PARÂMETROS!E24*PARÂMETROS!$B$4*PARÂMETROS!$B$5*PARÂMETROS!$B$86,0) | BB28: =IFERROR(PARÂMETROS!AY103*PARÂMETROS!E24*PARÂMETROS!$B$4*PARÂMETROS!$B$5*PARÂMETROS!$B$87,0) | BC28: =IFERROR(PARÂMETROS!AZ103*PARÂMETROS!E24*PARÂMETROS!$B$4*PARÂMETROS!$B$5*PARÂMETROS!$B$88,0) | BD28: =IFERROR(PARÂMETROS!BA103*PARÂMETROS!E24*PARÂMETROS!$B$4*PARÂMETROS!$B$5*PARÂMETROS!$B$89,0) | BE28: =IFERROR(PARÂMETROS!BB103*PARÂMETROS!E24*PARÂMETROS!$B$4*PARÂMETROS!$B$5*PARÂMETROS!$B$90,0) | BF28: =IFERROR(PARÂMETROS!BC103*PARÂMETROS!E24*PARÂMETROS!$B$4*PARÂMETROS!$B$5*PARÂMETROS!$B$91,0)
F29: Acumulado | G29: =G28 | H29: =G29+H28 | I29: =H29+I28 | J29: =I29+J28 | K29: =J29+K28 | L29: =K29+L28 | M29: =L29+M28 | N29: =M29+N28 | O29: =N29+O28 | ... BF29: =BE29+BF28
F30: % Completude | G30: =IF(PARÂMETROS!D24>0,G29/PARÂMETROS!D24,0) | H30: =IF(PARÂMETROS!D24>0,H29/PARÂMETROS!D24,0) | I30: =IF(PARÂMETROS!D24>0,I29/PARÂMETROS!D24,0) | J30: =IF(PARÂMETROS!D24>0,J29/PARÂMETROS!D24,0) | K30: =IF(PARÂMETROS!D24>0,K29/PARÂMETROS!D24,0) | L30: =IF(PARÂMETROS!D24>0,L29/PARÂMETROS!D24,0) | M30: =IF(PARÂMETROS!D24>0,M29/PARÂMETROS!D24,0) | N30: =IF(PARÂMETROS!D24>0,N29/PARÂMETROS!D24,0) | O30: =IF(PARÂMETROS!D24>0,O29/PARÂMETROS!D24,0) | P30: =IF(PARÂMETROS!D24>0,P29/PARÂMETROS!D24,0) | Q30: =IF(PARÂMETROS!D24>0,Q29/PARÂMETROS!D24,0) | R30: =IF(PARÂMETROS!D24>0,R29/PARÂMETROS!D24,0) | S30: =IF(PARÂMETROS!D24>0,S29/PARÂMETROS!D24,0) | T30: =IF(PARÂMETROS!D24>0,T29/PARÂMETROS!D24,0) | U30: =IF(PARÂMETROS!D24>0,U29/PARÂMETROS!D24,0) | V30: =IF(PARÂMETROS!D24>0,V29/PARÂMETROS!D24,0) | W30: =IF(PARÂMETROS!D24>0,W29/PARÂMETROS!D24,0) | X30: =IF(PARÂMETROS!D24>0,X29/PARÂMETROS!D24,0) | Y30: =IF(PARÂMETROS!D24>0,Y29/PARÂMETROS!D24,0) | Z30: =IF(PARÂMETROS!D24>0,Z29/PARÂMETROS!D24,0) | AA30: =IF(PARÂMETROS!D24>0,AA29/PARÂMETROS!D24,0) | AB30: =IF(PARÂMETROS!D24>0,AB29/PARÂMETROS!D24,0) | AC30: =IF(PARÂMETROS!D24>0,AC29/PARÂMETROS!D24,0) | AD30: =IF(PARÂMETROS!D24>0,AD29/PARÂMETROS!D24,0) | AE30: =IF(PARÂMETROS!D24>0,AE29/PARÂMETROS!D24,0) | AF30: =IF(PARÂMETROS!D24>0,AF29/PARÂMETROS!D24,0) | AG30: =IF(PARÂMETROS!D24>0,AG29/PARÂMETROS!D24,0) | AH30: =IF(PARÂMETROS!D24>0,AH29/PARÂMETROS!D24,0) | AI30: =IF(PARÂMETROS!D24>0,AI29/PARÂMETROS!D24,0) | AJ30: =IF(PARÂMETROS!D24>0,AJ29/PARÂMETROS!D24,0) | AK30: =IF(PARÂMETROS!D24>0,AK29/PARÂMETROS!D24,0) | AL30: =IF(PARÂMETROS!D24>0,AL29/PARÂMETROS!D24,0) | AM30: =IF(PARÂMETROS!D24>0,AM29/PARÂMETROS!D24,0) | AN30: =IF(PARÂMETROS!D24>0,AN29/PARÂMETROS!D24,0) | AO30: =IF(PARÂMETROS!D24>0,AO29/PARÂMETROS!D24,0) | AP30: =IF(PARÂMETROS!D24>0,AP29/PARÂMETROS!D24,0) | AQ30: =IF(PARÂMETROS!D24>0,AQ29/PARÂMETROS!D24,0) | AR30: =IF(PARÂMETROS!D24>0,AR29/PARÂMETROS!D24,0) | AS30: =IF(PARÂMETROS!D24>0,AS29/PARÂMETROS!D24,0) | AT30: =IF(PARÂMETROS!D24>0,AT29/PARÂMETROS!D24,0) | AU30: =IF(PARÂMETROS!D24>0,AU29/PARÂMETROS!D24,0) | AV30: =IF(PARÂMETROS!D24>0,AV29/PARÂMETROS!D24,0) | AW30: =IF(PARÂMETROS!D24>0,AW29/PARÂMETROS!D24,0) | AX30: =IF(PARÂMETROS!D24>0,AX29/PARÂMETROS!D24,0) | AY30: =IF(PARÂMETROS!D24>0,AY29/PARÂMETROS!D24,0) | AZ30: =IF(PARÂMETROS!D24>0,AZ29/PARÂMETROS!D24,0) | BA30: =IF(PARÂMETROS!D24>0,BA29/PARÂMETROS!D24,0) | BB30: =IF(PARÂMETROS!D24>0,BB29/PARÂMETROS!D24,0) | BC30: =IF(PARÂMETROS!D24>0,BC29/PARÂMETROS!D24,0) | BD30: =IF(PARÂMETROS!D24>0,BD29/PARÂMETROS!D24,0) | BE30: =IF(PARÂMETROS!D24>0,BE29/PARÂMETROS!D24,0) | BF30: =IF(PARÂMETROS!D24>0,BF29/PARÂMETROS!D24,0)
A31: eap-1_9 | B31: Construcao corpo aterro m | C31: =PARÂMETROS!D25 | D31: =SUM(G31:BF31) | E31: =IF(C31>0,(D31-C31)/C31,0) | F31: Produção semanal | G31: =IFERROR(PARÂMETROS!D104*PARÂMETROS!E25*PARÂMETROS!$B$4*PARÂMETROS!$B$5*PARÂMETROS!$B$40,0) | H31: =IFERROR(PARÂMETROS!E104*PARÂMETROS!E25*PARÂMETROS!$B$4*PARÂMETROS!$B$5*PARÂMETROS!$B$41,0) | I31: =IFERROR(PARÂMETROS!F104*PARÂMETROS!E25*PARÂMETROS!$B$4*PARÂMETROS!$B$5*PARÂMETROS!$B$42,0) | J31: =IFERROR(PARÂMETROS!G104*PARÂMETROS!E25*PARÂMETROS!$B$4*PARÂMETROS!$B$5*PARÂMETROS!$B$43,0) | K31: =IFERROR(PARÂMETROS!H104*PARÂMETROS!E25*PARÂMETROS!$B$4*PARÂMETROS!$B$5*PARÂMETROS!$B$44,0) | L31: =IFERROR(PARÂMETROS!I104*PARÂMETROS!E25*PARÂMETROS!$B$4*PARÂMETROS!$B$5*PARÂMETROS!$B$45,0) | M31: =IFERROR(PARÂMETROS!J104*PARÂMETROS!E25*PARÂMETROS!$B$4*PARÂMETROS!$B$5*PARÂMETROS!$B$46,0) | N31: =IFERROR(PARÂMETROS!K104*PARÂMETROS!E25*PARÂMETROS!$B$4*PARÂMETROS!$B$5*PARÂMETROS!$B$47,0) | O31: =IFERROR(PARÂMETROS!L104*PARÂMETROS!E25*PARÂMETROS!$B$4*PARÂMETROS!$B$5*PARÂMETROS!$B$48,0) | P31: =IFERROR(PARÂMETROS!M104*PARÂMETROS!E25*PARÂMETROS!$B$4*PARÂMETROS!$B$5*PARÂMETROS!$B$49,0) | Q31: =IFERROR(PARÂMETROS!N104*PARÂMETROS!E25*PARÂMETROS!$B$4*PARÂMETROS!$B$5*PARÂMETROS!$B$50,0) | R31: =IFERROR(PARÂMETROS!O104*PARÂMETROS!E25*PARÂMETROS!$B$4*PARÂMETROS!$B$5*PARÂMETROS!$B$51,0) | S31: =IFERROR(PARÂMETROS!P104*PARÂMETROS!E25*PARÂMETROS!$B$4*PARÂMETROS!$B$5*PARÂMETROS!$B$52,0) | T31: =IFERROR(PARÂMETROS!Q104*PARÂMETROS!E25*PARÂMETROS!$B$4*PARÂMETROS!$B$5*PARÂMETROS!$B$53,0) | U31: =IFERROR(PARÂMETROS!R104*PARÂMETROS!E25*PARÂMETROS!$B$4*PARÂMETROS!$B$5*PARÂMETROS!$B$54,0) | V31: =IFERROR(PARÂMETROS!S104*PARÂMETROS!E25*PARÂMETROS!$B$4*PARÂMETROS!$B$5*PARÂMETROS!$B$55,0) | W31: =IFERROR(PARÂMETROS!T104*PARÂMETROS!E25*PARÂMETROS!$B$4*PARÂMETROS!$B$5*PARÂMETROS!$B$56,0) | X31: =IFERROR(PARÂMETROS!U104*PARÂMETROS!E25*PARÂMETROS!$B$4*PARÂMETROS!$B$5*PARÂMETROS!$B$57,0) | Y31: =IFERROR(PARÂMETROS!V104*PARÂMETROS!E25*PARÂMETROS!$B$4*PARÂMETROS!$B$5*PARÂMETROS!$B$58,0) | Z31: =IFERROR(PARÂMETROS!W104*PARÂMETROS!E25*PARÂMETROS!$B$4*PARÂMETROS!$B$5*PARÂMETROS!$B$59,0) | AA31: =IFERROR(PARÂMETROS!X104*PARÂMETROS!E25*PARÂMETROS!$B$4*PARÂMETROS!$B$5*PARÂMETROS!$B$60,0) | AB31: =IFERROR(PARÂMETROS!Y104*PARÂMETROS!E25*PARÂMETROS!$B$4*PARÂMETROS!$B$5*PARÂMETROS!$B$61,0) | AC31: =IFERROR(PARÂMETROS!Z104*PARÂMETROS!E25*PARÂMETROS!$B$4*PARÂMETROS!$B$5*PARÂMETROS!$B$62,0) | AD31: =IFERROR(PARÂMETROS!AA104*PARÂMETROS!E25*PARÂMETROS!$B$4*PARÂMETROS!$B$5*PARÂMETROS!$B$63,0) | AE31: =IFERROR(PARÂMETROS!AB104*PARÂMETROS!E25*PARÂMETROS!$B$4*PARÂMETROS!$B$5*PARÂMETROS!$B$64,0) | AF31: =IFERROR(PARÂMETROS!AC104*PARÂMETROS!E25*PARÂMETROS!$B$4*PARÂMETROS!$B$5*PARÂMETROS!$B$65,0) | AG31: =IFERROR(PARÂMETROS!AD104*PARÂMETROS!E25*PARÂMETROS!$B$4*PARÂMETROS!$B$5*PARÂMETROS!$B$66,0) | AH31: =IFERROR(PARÂMETROS!AE104*PARÂMETROS!E25*PARÂMETROS!$B$4*PARÂMETROS!$B$5*PARÂMETROS!$B$67,0) | AI31: =IFERROR(PARÂMETROS!AF104*PARÂMETROS!E25*PARÂMETROS!$B$4*PARÂMETROS!$B$5*PARÂMETROS!$B$68,0) | AJ31: =IFERROR(PARÂMETROS!AG104*PARÂMETROS!E25*PARÂMETROS!$B$4*PARÂMETROS!$B$5*PARÂMETROS!$B$69,0) | AK31: =IFERROR(PARÂMETROS!AH104*PARÂMETROS!E25*PARÂMETROS!$B$4*PARÂMETROS!$B$5*PARÂMETROS!$B$70,0) | AL31: =IFERROR(PARÂMETROS!AI104*PARÂMETROS!E25*PARÂMETROS!$B$4*PARÂMETROS!$B$5*PARÂMETROS!$B$71,0) | AM31: =IFERROR(PARÂMETROS!AJ104*PARÂMETROS!E25*PARÂMETROS!$B$4*PARÂMETROS!$B$5*PARÂMETROS!$B$72,0) | AN31: =IFERROR(PARÂMETROS!AK104*PARÂMETROS!E25*PARÂMETROS!$B$4*PARÂMETROS!$B$5*PARÂMETROS!$B$73,0) | AO31: =IFERROR(PARÂMETROS!AL104*PARÂMETROS!E25*PARÂMETROS!$B$4*PARÂMETROS!$B$5*PARÂMETROS!$B$74,0) | AP31: =IFERROR(PARÂMETROS!AM104*PARÂMETROS!E25*PARÂMETROS!$B$4*PARÂMETROS!$B$5*PARÂMETROS!$B$75,0) | AQ31: =IFERROR(PARÂMETROS!AN104*PARÂMETROS!E25*PARÂMETROS!$B$4*PARÂMETROS!$B$5*PARÂMETROS!$B$76,0) | AR31: =IFERROR(PARÂMETROS!AO104*PARÂMETROS!E25*PARÂMETROS!$B$4*PARÂMETROS!$B$5*PARÂMETROS!$B$77,0) | AS31: =IFERROR(PARÂMETROS!AP104*PARÂMETROS!E25*PARÂMETROS!$B$4*PARÂMETROS!$B$5*PARÂMETROS!$B$78,0) | AT31: =IFERROR(PARÂMETROS!AQ104*PARÂMETROS!E25*PARÂMETROS!$B$4*PARÂMETROS!$B$5*PARÂMETROS!$B$79,0) | AU31: =IFERROR(PARÂMETROS!AR104*PARÂMETROS!E25*PARÂMETROS!$B$4*PARÂMETROS!$B$5*PARÂMETROS!$B$80,0) | AV31: =IFERROR(PARÂMETROS!AS104*PARÂMETROS!E25*PARÂMETROS!$B$4*PARÂMETROS!$B$5*PARÂMETROS!$B$81,0) | AW31: =IFERROR(PARÂMETROS!AT104*PARÂMETROS!E25*PARÂMETROS!$B$4*PARÂMETROS!$B$5*PARÂMETROS!$B$82,0) | AX31: =IFERROR(PARÂMETROS!AU104*PARÂMETROS!E25*PARÂMETROS!$B$4*PARÂMETROS!$B$5*PARÂMETROS!$B$83,0) | AY31: =IFERROR(PARÂMETROS!AV104*PARÂMETROS!E25*PARÂMETROS!$B$4*PARÂMETROS!$B$5*PARÂMETROS!$B$84,0) | AZ31: =IFERROR(PARÂMETROS!AW104*PARÂMETROS!E25*PARÂMETROS!$B$4*PARÂMETROS!$B$5*PARÂMETROS!$B$85,0) | BA31: =IFERROR(PARÂMETROS!AX104*PARÂMETROS!E25*PARÂMETROS!$B$4*PARÂMETROS!$B$5*PARÂMETROS!$B$86,0) | BB31: =IFERROR(PARÂMETROS!AY104*PARÂMETROS!E25*PARÂMETROS!$B$4*PARÂMETROS!$B$5*PARÂMETROS!$B$87,0) | BC31: =IFERROR(PARÂMETROS!AZ104*PARÂMETROS!E25*PARÂMETROS!$B$4*PARÂMETROS!$B$5*PARÂMETROS!$B$88,0) | BD31: =IFERROR(PARÂMETROS!BA104*PARÂMETROS!E25*PARÂMETROS!$B$4*PARÂMETROS!$B$5*PARÂMETROS!$B$89,0) | BE31: =IFERROR(PARÂMETROS!BB104*PARÂMETROS!E25*PARÂMETROS!$B$4*PARÂMETROS!$B$5*PARÂMETROS!$B$90,0) | BF31: =IFERROR(PARÂMETROS!BC104*PARÂMETROS!E25*PARÂMETROS!$B$4*PARÂMETROS!$B$5*PARÂMETROS!$B$91,0)
F32: Acumulado | G32: =G31 | H32: =G32+H31 | I32: =H32+I31 | J32: =I32+J31 | K32: =J32+K31 | L32: =K32+L31 | M32: =L32+M31 | N32: =M32+N31 | O32: =N32+O31 | ... BF32: =BE32+BF31
F33: % Completude | G33: =IF(PARÂMETROS!D25>0,G32/PARÂMETROS!D25,0) | H33: =IF(PARÂMETROS!D25>0,H32/PARÂMETROS!D25,0) | I33: =IF(PARÂMETROS!D25>0,I32/PARÂMETROS!D25,0) | J33: =IF(PARÂMETROS!D25>0,J32/PARÂMETROS!D25,0) | K33: =IF(PARÂMETROS!D25>0,K32/PARÂMETROS!D25,0) | L33: =IF(PARÂMETROS!D25>0,L32/PARÂMETROS!D25,0) | M33: =IF(PARÂMETROS!D25>0,M32/PARÂMETROS!D25,0) | N33: =IF(PARÂMETROS!D25>0,N32/PARÂMETROS!D25,0) | O33: =IF(PARÂMETROS!D25>0,O32/PARÂMETROS!D25,0) | P33: =IF(PARÂMETROS!D25>0,P32/PARÂMETROS!D25,0) | Q33: =IF(PARÂMETROS!D25>0,Q32/PARÂMETROS!D25,0) | R33: =IF(PARÂMETROS!D25>0,R32/PARÂMETROS!D25,0) | S33: =IF(PARÂMETROS!D25>0,S32/PARÂMETROS!D25,0) | T33: =IF(PARÂMETROS!D25>0,T32/PARÂMETROS!D25,0) | U33: =IF(PARÂMETROS!D25>0,U32/PARÂMETROS!D25,0) | V33: =IF(PARÂMETROS!D25>0,V32/PARÂMETROS!D25,0) | W33: =IF(PARÂMETROS!D25>0,W32/PARÂMETROS!D25,0) | X33: =IF(PARÂMETROS!D25>0,X32/PARÂMETROS!D25,0) | Y33: =IF(PARÂMETROS!D25>0,Y32/PARÂMETROS!D25,0) | Z33: =IF(PARÂMETROS!D25>0,Z32/PARÂMETROS!D25,0) | AA33: =IF(PARÂMETROS!D25>0,AA32/PARÂMETROS!D25,0) | AB33: =IF(PARÂMETROS!D25>0,AB32/PARÂMETROS!D25,0) | AC33: =IF(PARÂMETROS!D25>0,AC32/PARÂMETROS!D25,0) | AD33: =IF(PARÂMETROS!D25>0,AD32/PARÂMETROS!D25,0) | AE33: =IF(PARÂMETROS!D25>0,AE32/PARÂMETROS!D25,0) | AF33: =IF(PARÂMETROS!D25>0,AF32/PARÂMETROS!D25,0) | AG33: =IF(PARÂMETROS!D25>0,AG32/PARÂMETROS!D25,0) | AH33: =IF(PARÂMETROS!D25>0,AH32/PARÂMETROS!D25,0) | AI33: =IF(PARÂMETROS!D25>0,AI32/PARÂMETROS!D25,0) | AJ33: =IF(PARÂMETROS!D25>0,AJ32/PARÂMETROS!D25,0) | AK33: =IF(PARÂMETROS!D25>0,AK32/PARÂMETROS!D25,0) | AL33: =IF(PARÂMETROS!D25>0,AL32/PARÂMETROS!D25,0) | AM33: =IF(PARÂMETROS!D25>0,AM32/PARÂMETROS!D25,0) | AN33: =IF(PARÂMETROS!D25>0,AN32/PARÂMETROS!D25,0) | AO33: =IF(PARÂMETROS!D25>0,AO32/PARÂMETROS!D25,0) | AP33: =IF(PARÂMETROS!D25>0,AP32/PARÂMETROS!D25,0) | AQ33: =IF(PARÂMETROS!D25>0,AQ32/PARÂMETROS!D25,0) | AR33: =IF(PARÂMETROS!D25>0,AR32/PARÂMETROS!D25,0) | AS33: =IF(PARÂMETROS!D25>0,AS32/PARÂMETROS!D25,0) | AT33: =IF(PARÂMETROS!D25>0,AT32/PARÂMETROS!D25,0) | AU33: =IF(PARÂMETROS!D25>0,AU32/PARÂMETROS!D25,0) | AV33: =IF(PARÂMETROS!D25>0,AV32/PARÂMETROS!D25,0) | AW33: =IF(PARÂMETROS!D25>0,AW32/PARÂMETROS!D25,0) | AX33: =IF(PARÂMETROS!D25>0,AX32/PARÂMETROS!D25,0) | AY33: =IF(PARÂMETROS!D25>0,AY32/PARÂMETROS!D25,0) | AZ33: =IF(PARÂMETROS!D25>0,AZ32/PARÂMETROS!D25,0) | BA33: =IF(PARÂMETROS!D25>0,BA32/PARÂMETROS!D25,0) | BB33: =IF(PARÂMETROS!D25>0,BB32/PARÂMETROS!D25,0) | BC33: =IF(PARÂMETROS!D25>0,BC32/PARÂMETROS!D25,0) | BD33: =IF(PARÂMETROS!D25>0,BD32/PARÂMETROS!D25,0) | BE33: =IF(PARÂMETROS!D25>0,BE32/PARÂMETROS!D25,0) | BF33: =IF(PARÂMETROS!D25>0,BF32/PARÂMETROS!D25,0)
A34: eap-1_10 | B34: Compactacao camada final | C34: =PARÂMETROS!D26 | D34: =SUM(G34:BF34) | E34: =IF(C34>0,(D34-C34)/C34,0) | F34: Produção semanal | G34: =IFERROR(PARÂMETROS!D105*PARÂMETROS!E26*PARÂMETROS!$B$4*PARÂMETROS!$B$5*PARÂMETROS!$B$40,0) | H34: =IFERROR(PARÂMETROS!E105*PARÂMETROS!E26*PARÂMETROS!$B$4*PARÂMETROS!$B$5*PARÂMETROS!$B$41,0) | I34: =IFERROR(PARÂMETROS!F105*PARÂMETROS!E26*PARÂMETROS!$B$4*PARÂMETROS!$B$5*PARÂMETROS!$B$42,0) | J34: =IFERROR(PARÂMETROS!G105*PARÂMETROS!E26*PARÂMETROS!$B$4*PARÂMETROS!$B$5*PARÂMETROS!$B$43,0) | K34: =IFERROR(PARÂMETROS!H105*PARÂMETROS!E26*PARÂMETROS!$B$4*PARÂMETROS!$B$5*PARÂMETROS!$B$44,0) | L34: =IFERROR(PARÂMETROS!I105*PARÂMETROS!E26*PARÂMETROS!$B$4*PARÂMETROS!$B$5*PARÂMETROS!$B$45,0) | M34: =IFERROR(PARÂMETROS!J105*PARÂMETROS!E26*PARÂMETROS!$B$4*PARÂMETROS!$B$5*PARÂMETROS!$B$46,0) | N34: =IFERROR(PARÂMETROS!K105*PARÂMETROS!E26*PARÂMETROS!$B$4*PARÂMETROS!$B$5*PARÂMETROS!$B$47,0) | O34: =IFERROR(PARÂMETROS!L105*PARÂMETROS!E26*PARÂMETROS!$B$4*PARÂMETROS!$B$5*PARÂMETROS!$B$48,0) | P34: =IFERROR(PARÂMETROS!M105*PARÂMETROS!E26*PARÂMETROS!$B$4*PARÂMETROS!$B$5*PARÂMETROS!$B$49,0) | Q34: =IFERROR(PARÂMETROS!N105*PARÂMETROS!E26*PARÂMETROS!$B$4*PARÂMETROS!$B$5*PARÂMETROS!$B$50,0) | R34: =IFERROR(PARÂMETROS!O105*PARÂMETROS!E26*PARÂMETROS!$B$4*PARÂMETROS!$B$5*PARÂMETROS!$B$51,0) | S34: =IFERROR(PARÂMETROS!P105*PARÂMETROS!E26*PARÂMETROS!$B$4*PARÂMETROS!$B$5*PARÂMETROS!$B$52,0) | T34: =IFERROR(PARÂMETROS!Q105*PARÂMETROS!E26*PARÂMETROS!$B$4*PARÂMETROS!$B$5*PARÂMETROS!$B$53,0) | U34: =IFERROR(PARÂMETROS!R105*PARÂMETROS!E26*PARÂMETROS!$B$4*PARÂMETROS!$B$5*PARÂMETROS!$B$54,0) | V34: =IFERROR(PARÂMETROS!S105*PARÂMETROS!E26*PARÂMETROS!$B$4*PARÂMETROS!$B$5*PARÂMETROS!$B$55,0) | W34: =IFERROR(PARÂMETROS!T105*PARÂMETROS!E26*PARÂMETROS!$B$4*PARÂMETROS!$B$5*PARÂMETROS!$B$56,0) | X34: =IFERROR(PARÂMETROS!U105*PARÂMETROS!E26*PARÂMETROS!$B$4*PARÂMETROS!$B$5*PARÂMETROS!$B$57,0) | Y34: =IFERROR(PARÂMETROS!V105*PARÂMETROS!E26*PARÂMETROS!$B$4*PARÂMETROS!$B$5*PARÂMETROS!$B$58,0) | Z34: =IFERROR(PARÂMETROS!W105*PARÂMETROS!E26*PARÂMETROS!$B$4*PARÂMETROS!$B$5*PARÂMETROS!$B$59,0) | AA34: =IFERROR(PARÂMETROS!X105*PARÂMETROS!E26*PARÂMETROS!$B$4*PARÂMETROS!$B$5*PARÂMETROS!$B$60,0) | AB34: =IFERROR(PARÂMETROS!Y105*PARÂMETROS!E26*PARÂMETROS!$B$4*PARÂMETROS!$B$5*PARÂMETROS!$B$61,0) | AC34: =IFERROR(PARÂMETROS!Z105*PARÂMETROS!E26*PARÂMETROS!$B$4*PARÂMETROS!$B$5*PARÂMETROS!$B$62,0) | AD34: =IFERROR(PARÂMETROS!AA105*PARÂMETROS!E26*PARÂMETROS!$B$4*PARÂMETROS!$B$5*PARÂMETROS!$B$63,0) | AE34: =IFERROR(PARÂMETROS!AB105*PARÂMETROS!E26*PARÂMETROS!$B$4*PARÂMETROS!$B$5*PARÂMETROS!$B$64,0) | AF34: =IFERROR(PARÂMETROS!AC105*PARÂMETROS!E26*PARÂMETROS!$B$4*PARÂMETROS!$B$5*PARÂMETROS!$B$65,0) | AG34: =IFERROR(PARÂMETROS!AD105*PARÂMETROS!E26*PARÂMETROS!$B$4*PARÂMETROS!$B$5*PARÂMETROS!$B$66,0) | AH34: =IFERROR(PARÂMETROS!AE105*PARÂMETROS!E26*PARÂMETROS!$B$4*PARÂMETROS!$B$5*PARÂMETROS!$B$67,0) | AI34: =IFERROR(PARÂMETROS!AF105*PARÂMETROS!E26*PARÂMETROS!$B$4*PARÂMETROS!$B$5*PARÂMETROS!$B$68,0) | AJ34: =IFERROR(PARÂMETROS!AG105*PARÂMETROS!E26*PARÂMETROS!$B$4*PARÂMETROS!$B$5*PARÂMETROS!$B$69,0) | AK34: =IFERROR(PARÂMETROS!AH105*PARÂMETROS!E26*PARÂMETROS!$B$4*PARÂMETROS!$B$5*PARÂMETROS!$B$70,0) | AL34: =IFERROR(PARÂMETROS!AI105*PARÂMETROS!E26*PARÂMETROS!$B$4*PARÂMETROS!$B$5*PARÂMETROS!$B$71,0) | AM34: =IFERROR(PARÂMETROS!AJ105*PARÂMETROS!E26*PARÂMETROS!$B$4*PARÂMETROS!$B$5*PARÂMETROS!$B$72,0) | AN34: =IFERROR(PARÂMETROS!AK105*PARÂMETROS!E26*PARÂMETROS!$B$4*PARÂMETROS!$B$5*PARÂMETROS!$B$73,0) | AO34: =IFERROR(PARÂMETROS!AL105*PARÂMETROS!E26*PARÂMETROS!$B$4*PARÂMETROS!$B$5*PARÂMETROS!$B$74,0) | AP34: =IFERROR(PARÂMETROS!AM105*PARÂMETROS!E26*PARÂMETROS!$B$4*PARÂMETROS!$B$5*PARÂMETROS!$B$75,0) | AQ34: =IFERROR(PARÂMETROS!AN105*PARÂMETROS!E26*PARÂMETROS!$B$4*PARÂMETROS!$B$5*PARÂMETROS!$B$76,0) | AR34: =IFERROR(PARÂMETROS!AO105*PARÂMETROS!E26*PARÂMETROS!$B$4*PARÂMETROS!$B$5*PARÂMETROS!$B$77,0) | AS34: =IFERROR(PARÂMETROS!AP105*PARÂMETROS!E26*PARÂMETROS!$B$4*PARÂMETROS!$B$5*PARÂMETROS!$B$78,0) | AT34: =IFERROR(PARÂMETROS!AQ105*PARÂMETROS!E26*PARÂMETROS!$B$4*PARÂMETROS!$B$5*PARÂMETROS!$B$79,0) | AU34: =IFERROR(PARÂMETROS!AR105*PARÂMETROS!E26*PARÂMETROS!$B$4*PARÂMETROS!$B$5*PARÂMETROS!$B$80,0) | AV34: =IFERROR(PARÂMETROS!AS105*PARÂMETROS!E26*PARÂMETROS!$B$4*PARÂMETROS!$B$5*PARÂMETROS!$B$81,0) | AW34: =IFERROR(PARÂMETROS!AT105*PARÂMETROS!E26*PARÂMETROS!$B$4*PARÂMETROS!$B$5*PARÂMETROS!$B$82,0) | AX34: =IFERROR(PARÂMETROS!AU105*PARÂMETROS!E26*PARÂMETROS!$B$4*PARÂMETROS!$B$5*PARÂMETROS!$B$83,0) | AY34: =IFERROR(PARÂMETROS!AV105*PARÂMETROS!E26*PARÂMETROS!$B$4*PARÂMETROS!$B$5*PARÂMETROS!$B$84,0) | AZ34: =IFERROR(PARÂMETROS!AW105*PARÂMETROS!E26*PARÂMETROS!$B$4*PARÂMETROS!$B$5*PARÂMETROS!$B$85,0) | BA34: =IFERROR(PARÂMETROS!AX105*PARÂMETROS!E26*PARÂMETROS!$B$4*PARÂMETROS!$B$5*PARÂMETROS!$B$86,0) | BB34: =IFERROR(PARÂMETROS!AY105*PARÂMETROS!E26*PARÂMETROS!$B$4*PARÂMETROS!$B$5*PARÂMETROS!$B$87,0) | BC34: =IFERROR(PARÂMETROS!AZ105*PARÂMETROS!E26*PARÂMETROS!$B$4*PARÂMETROS!$B$5*PARÂMETROS!$B$88,0) | BD34: =IFERROR(PARÂMETROS!BA105*PARÂMETROS!E26*PARÂMETROS!$B$4*PARÂMETROS!$B$5*PARÂMETROS!$B$89,0) | BE34: =IFERROR(PARÂMETROS!BB105*PARÂMETROS!E26*PARÂMETROS!$B$4*PARÂMETROS!$B$5*PARÂMETROS!$B$90,0) | BF34: =IFERROR(PARÂMETROS!BC105*PARÂMETROS!E26*PARÂMETROS!$B$4*PARÂMETROS!$B$5*PARÂMETROS!$B$91,0)
F35: Acumulado | G35: =G34 | H35: =G35+H34 | I35: =H35+I34 | J35: =I35+J34 | K35: =J35+K34 | L35: =K35+L34 | M35: =L35+M34 | N35: =M35+N34 | O35: =N35+O34 | ... BF35: =BE35+BF34
F36: % Completude | G36: =IF(PARÂMETROS!D26>0,G35/PARÂMETROS!D26,0) | H36: =IF(PARÂMETROS!D26>0,H35/PARÂMETROS!D26,0) | I36: =IF(PARÂMETROS!D26>0,I35/PARÂMETROS!D26,0) | J36: =IF(PARÂMETROS!D26>0,J35/PARÂMETROS!D26,0) | K36: =IF(PARÂMETROS!D26>0,K35/PARÂMETROS!D26,0) | L36: =IF(PARÂMETROS!D26>0,L35/PARÂMETROS!D26,0) | M36: =IF(PARÂMETROS!D26>0,M35/PARÂMETROS!D26,0) | N36: =IF(PARÂMETROS!D26>0,N35/PARÂMETROS!D26,0) | O36: =IF(PARÂMETROS!D26>0,O35/PARÂMETROS!D26,0) | P36: =IF(PARÂMETROS!D26>0,P35/PARÂMETROS!D26,0) | Q36: =IF(PARÂMETROS!D26>0,Q35/PARÂMETROS!D26,0) | R36: =IF(PARÂMETROS!D26>0,R35/PARÂMETROS!D26,0) | S36: =IF(PARÂMETROS!D26>0,S35/PARÂMETROS!D26,0) | T36: =IF(PARÂMETROS!D26>0,T35/PARÂMETROS!D26,0) | U36: =IF(PARÂMETROS!D26>0,U35/PARÂMETROS!D26,0) | V36: =IF(PARÂMETROS!D26>0,V35/PARÂMETROS!D26,0) | W36: =IF(PARÂMETROS!D26>0,W35/PARÂMETROS!D26,0) | X36: =IF(PARÂMETROS!D26>0,X35/PARÂMETROS!D26,0) | Y36: =IF(PARÂMETROS!D26>0,Y35/PARÂMETROS!D26,0) | Z36: =IF(PARÂMETROS!D26>0,Z35/PARÂMETROS!D26,0) | AA36: =IF(PARÂMETROS!D26>0,AA35/PARÂMETROS!D26,0) | AB36: =IF(PARÂMETROS!D26>0,AB35/PARÂMETROS!D26,0) | AC36: =IF(PARÂMETROS!D26>0,AC35/PARÂMETROS!D26,0) | AD36: =IF(PARÂMETROS!D26>0,AD35/PARÂMETROS!D26,0) | AE36: =IF(PARÂMETROS!D26>0,AE35/PARÂMETROS!D26,0) | AF36: =IF(PARÂMETROS!D26>0,AF35/PARÂMETROS!D26,0) | AG36: =IF(PARÂMETROS!D26>0,AG35/PARÂMETROS!D26,0) | AH36: =IF(PARÂMETROS!D26>0,AH35/PARÂMETROS!D26,0) | AI36: =IF(PARÂMETROS!D26>0,AI35/PARÂMETROS!D26,0) | AJ36: =IF(PARÂMETROS!D26>0,AJ35/PARÂMETROS!D26,0) | AK36: =IF(PARÂMETROS!D26>0,AK35/PARÂMETROS!D26,0) | AL36: =IF(PARÂMETROS!D26>0,AL35/PARÂMETROS!D26,0) | AM36: =IF(PARÂMETROS!D26>0,AM35/PARÂMETROS!D26,0) | AN36: =IF(PARÂMETROS!D26>0,AN35/PARÂMETROS!D26,0) | AO36: =IF(PARÂMETROS!D26>0,AO35/PARÂMETROS!D26,0) | AP36: =IF(PARÂMETROS!D26>0,AP35/PARÂMETROS!D26,0) | AQ36: =IF(PARÂMETROS!D26>0,AQ35/PARÂMETROS!D26,0) | AR36: =IF(PARÂMETROS!D26>0,AR35/PARÂMETROS!D26,0) | AS36: =IF(PARÂMETROS!D26>0,AS35/PARÂMETROS!D26,0) | AT36: =IF(PARÂMETROS!D26>0,AT35/PARÂMETROS!D26,0) | AU36: =IF(PARÂMETROS!D26>0,AU35/PARÂMETROS!D26,0) | AV36: =IF(PARÂMETROS!D26>0,AV35/PARÂMETROS!D26,0) | AW36: =IF(PARÂMETROS!D26>0,AW35/PARÂMETROS!D26,0) | AX36: =IF(PARÂMETROS!D26>0,AX35/PARÂMETROS!D26,0) | AY36: =IF(PARÂMETROS!D26>0,AY35/PARÂMETROS!D26,0) | AZ36: =IF(PARÂMETROS!D26>0,AZ35/PARÂMETROS!D26,0) | BA36: =IF(PARÂMETROS!D26>0,BA35/PARÂMETROS!D26,0) | BB36: =IF(PARÂMETROS!D26>0,BB35/PARÂMETROS!D26,0) | BC36: =IF(PARÂMETROS!D26>0,BC35/PARÂMETROS!D26,0) | BD36: =IF(PARÂMETROS!D26>0,BD35/PARÂMETROS!D26,0) | BE36: =IF(PARÂMETROS!D26>0,BE35/PARÂMETROS!D26,0) | BF36: =IF(PARÂMETROS!D26>0,BF35/PARÂMETROS!D26,0)
A39: CURVA S — PROGRESSÃO ACUMULADA TOTAL (%)
A40: Semana | B40: % Global Acumulado
A41: 2026-W24 | B41: =IF((PARÂMETROS!D16+PARÂMETROS!D17+PARÂMETROS!D18+PARÂMETROS!D19+PARÂMETROS!D20+PARÂMETROS!D21+PARÂMETROS!D22+PARÂMETROS!D23+PARÂMETROS!D24+PARÂMETROS!D25+PARÂMETROS!D26)>0,(PARÂMETROS!D16*G6+PARÂMETROS!D17*G9+PARÂMETROS!D18*G12+PARÂMETROS!D19*G15+PARÂMETROS!D20*G18+PARÂMETROS!D21*G21+PARÂMETROS!D22*G24+PARÂMETROS!D23*G27+PARÂMETROS!D24*G30+PARÂMETROS!D25*G33+PARÂMETROS!D26*G36)/(PARÂMETROS!D16+PARÂMETROS!D17+PARÂMETROS!D18+PARÂMETROS!D19+PARÂMETROS!D20+PARÂMETROS!D21+PARÂMETROS!D22+PARÂMETROS!D23+PARÂMETROS!D24+PARÂMETROS!D25+PARÂMETROS!D26),0)
A42: 2026-W25 | B42: =IF((PARÂMETROS!D16+PARÂMETROS!D17+PARÂMETROS!D18+PARÂMETROS!D19+PARÂMETROS!D20+PARÂMETROS!D21+PARÂMETROS!D22+PARÂMETROS!D23+PARÂMETROS!D24+PARÂMETROS!D25+PARÂMETROS!D26)>0,(PARÂMETROS!D16*H6+PARÂMETROS!D17*H9+PARÂMETROS!D18*H12+PARÂMETROS!D19*H15+PARÂMETROS!D20*H18+PARÂMETROS!D21*H21+PARÂMETROS!D22*H24+PARÂMETROS!D23*H27+PARÂMETROS!D24*H30+PARÂMETROS!D25*H33+PARÂMETROS!D26*H36)/(PARÂMETROS!D16+PARÂMETROS!D17+PARÂMETROS!D18+PARÂMETROS!D19+PARÂMETROS!D20+PARÂMETROS!D21+PARÂMETROS!D22+PARÂMETROS!D23+PARÂMETROS!D24+PARÂMETROS!D25+PARÂMETROS!D26),0)
A43: 2026-W26 | B43: =IF((PARÂMETROS!D16+PARÂMETROS!D17+PARÂMETROS!D18+PARÂMETROS!D19+PARÂMETROS!D20+PARÂMETROS!D21+PARÂMETROS!D22+PARÂMETROS!D23+PARÂMETROS!D24+PARÂMETROS!D25+PARÂMETROS!D26)>0,(PARÂMETROS!D16*I6+PARÂMETROS!D17*I9+PARÂMETROS!D18*I12+PARÂMETROS!D19*I15+PARÂMETROS!D20*I18+PARÂMETROS!D21*I21+PARÂMETROS!D22*I24+PARÂMETROS!D23*I27+PARÂMETROS!D24*I30+PARÂMETROS!D25*I33+PARÂMETROS!D26*I36)/(PARÂMETROS!D16+PARÂMETROS!D17+PARÂMETROS!D18+PARÂMETROS!D19+PARÂMETROS!D20+PARÂMETROS!D21+PARÂMETROS!D22+PARÂMETROS!D23+PARÂMETROS!D24+PARÂMETROS!D25+PARÂMETROS!D26),0)
A44: 2026-W27 | B44: =IF((PARÂMETROS!D16+PARÂMETROS!D17+PARÂMETROS!D18+PARÂMETROS!D19+PARÂMETROS!D20+PARÂMETROS!D21+PARÂMETROS!D22+PARÂMETROS!D23+PARÂMETROS!D24+PARÂMETROS!D25+PARÂMETROS!D26)>0,(PARÂMETROS!D16*J6+PARÂMETROS!D17*J9+PARÂMETROS!D18*J12+PARÂMETROS!D19*J15+PARÂMETROS!D20*J18+PARÂMETROS!D21*J21+PARÂMETROS!D22*J24+PARÂMETROS!D23*J27+PARÂMETROS!D24*J30+PARÂMETROS!D25*J33+PARÂMETROS!D26*J36)/(PARÂMETROS!D16+PARÂMETROS!D17+PARÂMETROS!D18+PARÂMETROS!D19+PARÂMETROS!D20+PARÂMETROS!D21+PARÂMETROS!D22+PARÂMETROS!D23+PARÂMETROS!D24+PARÂMETROS!D25+PARÂMETROS!D26),0)
A45: 2026-W28 | B45: =IF((PARÂMETROS!D16+PARÂMETROS!D17+PARÂMETROS!D18+PARÂMETROS!D19+PARÂMETROS!D20+PARÂMETROS!D21+PARÂMETROS!D22+PARÂMETROS!D23+PARÂMETROS!D24+PARÂMETROS!D25+PARÂMETROS!D26)>0,(PARÂMETROS!D16*K6+PARÂMETROS!D17*K9+PARÂMETROS!D18*K12+PARÂMETROS!D19*K15+PARÂMETROS!D20*K18+PARÂMETROS!D21*K21+PARÂMETROS!D22*K24+PARÂMETROS!D23*K27+PARÂMETROS!D24*K30+PARÂMETROS!D25*K33+PARÂMETROS!D26*K36)/(PARÂMETROS!D16+PARÂMETROS!D17+PARÂMETROS!D18+PARÂMETROS!D19+PARÂMETROS!D20+PARÂMETROS!D21+PARÂMETROS!D22+PARÂMETROS!D23+PARÂMETROS!D24+PARÂMETROS!D25+PARÂMETROS!D26),0)
A46: 2026-W29 | B46: =IF((PARÂMETROS!D16+PARÂMETROS!D17+PARÂMETROS!D18+PARÂMETROS!D19+PARÂMETROS!D20+PARÂMETROS!D21+PARÂMETROS!D22+PARÂMETROS!D23+PARÂMETROS!D24+PARÂMETROS!D25+PARÂMETROS!D26)>0,(PARÂMETROS!D16*L6+PARÂMETROS!D17*L9+PARÂMETROS!D18*L12+PARÂMETROS!D19*L15+PARÂMETROS!D20*L18+PARÂMETROS!D21*L21+PARÂMETROS!D22*L24+PARÂMETROS!D23*L27+PARÂMETROS!D24*L30+PARÂMETROS!D25*L33+PARÂMETROS!D26*L36)/(PARÂMETROS!D16+PARÂMETROS!D17+PARÂMETROS!D18+PARÂMETROS!D19+PARÂMETROS!D20+PARÂMETROS!D21+PARÂMETROS!D22+PARÂMETROS!D23+PARÂMETROS!D24+PARÂMETROS!D25+PARÂMETROS!D26),0)
A47: 2026-W30 | B47: =IF((PARÂMETROS!D16+PARÂMETROS!D17+PARÂMETROS!D18+PARÂMETROS!D19+PARÂMETROS!D20+PARÂMETROS!D21+PARÂMETROS!D22+PARÂMETROS!D23+PARÂMETROS!D24+PARÂMETROS!D25+PARÂMETROS!D26)>0,(PARÂMETROS!D16*M6+PARÂMETROS!D17*M9+PARÂMETROS!D18*M12+PARÂMETROS!D19*M15+PARÂMETROS!D20*M18+PARÂMETROS!D21*M21+PARÂMETROS!D22*M24+PARÂMETROS!D23*M27+PARÂMETROS!D24*M30+PARÂMETROS!D25*M33+PARÂMETROS!D26*M36)/(PARÂMETROS!D16+PARÂMETROS!D17+PARÂMETROS!D18+PARÂMETROS!D19+PARÂMETROS!D20+PARÂMETROS!D21+PARÂMETROS!D22+PARÂMETROS!D23+PARÂMETROS!D24+PARÂMETROS!D25+PARÂMETROS!D26),0)
A48: 2026-W31 | B48: =IF((PARÂMETROS!D16+PARÂMETROS!D17+PARÂMETROS!D18+PARÂMETROS!D19+PARÂMETROS!D20+PARÂMETROS!D21+PARÂMETROS!D22+PARÂMETROS!D23+PARÂMETROS!D24+PARÂMETROS!D25+PARÂMETROS!D26)>0,(PARÂMETROS!D16*N6+PARÂMETROS!D17*N9+PARÂMETROS!D18*N12+PARÂMETROS!D19*N15+PARÂMETROS!D20*N18+PARÂMETROS!D21*N21+PARÂMETROS!D22*N24+PARÂMETROS!D23*N27+PARÂMETROS!D24*N30+PARÂMETROS!D25*N33+PARÂMETROS!D26*N36)/(PARÂMETROS!D16+PARÂMETROS!D17+PARÂMETROS!D18+PARÂMETROS!D19+PARÂMETROS!D20+PARÂMETROS!D21+PARÂMETROS!D22+PARÂMETROS!D23+PARÂMETROS!D24+PARÂMETROS!D25+PARÂMETROS!D26),0)
A49: 2026-W32 | B49: =IF((PARÂMETROS!D16+PARÂMETROS!D17+PARÂMETROS!D18+PARÂMETROS!D19+PARÂMETROS!D20+PARÂMETROS!D21+PARÂMETROS!D22+PARÂMETROS!D23+PARÂMETROS!D24+PARÂMETROS!D25+PARÂMETROS!D26)>0,(PARÂMETROS!D16*O6+PARÂMETROS!D17*O9+PARÂMETROS!D18*O12+PARÂMETROS!D19*O15+PARÂMETROS!D20*O18+PARÂMETROS!D21*O21+PARÂMETROS!D22*O24+PARÂMETROS!D23*O27+PARÂMETROS!D24*O30+PARÂMETROS!D25*O33+PARÂMETROS!D26*O36)/(PARÂMETROS!D16+PARÂMETROS!D17+PARÂMETROS!D18+PARÂMETROS!D19+PARÂMETROS!D20+PARÂMETROS!D21+PARÂMETROS!D22+PARÂMETROS!D23+PARÂMETROS!D24+PARÂMETROS!D25+PARÂMETROS!D26),0)
A50: 2026-W33 | B50: =IF((PARÂMETROS!D16+PARÂMETROS!D17+PARÂMETROS!D18+PARÂMETROS!D19+PARÂMETROS!D20+PARÂMETROS!D21+PARÂMETROS!D22+PARÂMETROS!D23+PARÂMETROS!D24+PARÂMETROS!D25+PARÂMETROS!D26)>0,(PARÂMETROS!D16*P6+PARÂMETROS!D17*P9+PARÂMETROS!D18*P12+PARÂMETROS!D19*P15+PARÂMETROS!D20*P18+PARÂMETROS!D21*P21+PARÂMETROS!D22*P24+PARÂMETROS!D23*P27+PARÂMETROS!D24*P30+PARÂMETROS!D25*P33+PARÂMETROS!D26*P36)/(PARÂMETROS!D16+PARÂMETROS!D17+PARÂMETROS!D18+PARÂMETROS!D19+PARÂMETROS!D20+PARÂMETROS!D21+PARÂMETROS!D22+PARÂMETROS!D23+PARÂMETROS!D24+PARÂMETROS!D25+PARÂMETROS!D26),0)
A51: 2026-W34 | B51: =IF((PARÂMETROS!D16+PARÂMETROS!D17+PARÂMETROS!D18+PARÂMETROS!D19+PARÂMETROS!D20+PARÂMETROS!D21+PARÂMETROS!D22+PARÂMETROS!D23+PARÂMETROS!D24+PARÂMETROS!D25+PARÂMETROS!D26)>0,(PARÂMETROS!D16*Q6+PARÂMETROS!D17*Q9+PARÂMETROS!D18*Q12+PARÂMETROS!D19*Q15+PARÂMETROS!D20*Q18+PARÂMETROS!D21*Q21+PARÂMETROS!D22*Q24+PARÂMETROS!D23*Q27+PARÂMETROS!D24*Q30+PARÂMETROS!D25*Q33+PARÂMETROS!D26*Q36)/(PARÂMETROS!D16+PARÂMETROS!D17+PARÂMETROS!D18+PARÂMETROS!D19+PARÂMETROS!D20+PARÂMETROS!D21+PARÂMETROS!D22+PARÂMETROS!D23+PARÂMETROS!D24+PARÂMETROS!D25+PARÂMETROS!D26),0)
A52: 2026-W35 | B52: =IF((PARÂMETROS!D16+PARÂMETROS!D17+PARÂMETROS!D18+PARÂMETROS!D19+PARÂMETROS!D20+PARÂMETROS!D21+PARÂMETROS!D22+PARÂMETROS!D23+PARÂMETROS!D24+PARÂMETROS!D25+PARÂMETROS!D26)>0,(PARÂMETROS!D16*R6+PARÂMETROS!D17*R9+PARÂMETROS!D18*R12+PARÂMETROS!D19*R15+PARÂMETROS!D20*R18+PARÂMETROS!D21*R21+PARÂMETROS!D22*R24+PARÂMETROS!D23*R27+PARÂMETROS!D24*R30+PARÂMETROS!D25*R33+PARÂMETROS!D26*R36)/(PARÂMETROS!D16+PARÂMETROS!D17+PARÂMETROS!D18+PARÂMETROS!D19+PARÂMETROS!D20+PARÂMETROS!D21+PARÂMETROS!D22+PARÂMETROS!D23+PARÂMETROS!D24+PARÂMETROS!D25+PARÂMETROS!D26),0)
A53: 2026-W36 | B53: =IF((PARÂMETROS!D16+PARÂMETROS!D17+PARÂMETROS!D18+PARÂMETROS!D19+PARÂMETROS!D20+PARÂMETROS!D21+PARÂMETROS!D22+PARÂMETROS!D23+PARÂMETROS!D24+PARÂMETROS!D25+PARÂMETROS!D26)>0,(PARÂMETROS!D16*S6+PARÂMETROS!D17*S9+PARÂMETROS!D18*S12+PARÂMETROS!D19*S15+PARÂMETROS!D20*S18+PARÂMETROS!D21*S21+PARÂMETROS!D22*S24+PARÂMETROS!D23*S27+PARÂMETROS!D24*S30+PARÂMETROS!D25*S33+PARÂMETROS!D26*S36)/(PARÂMETROS!D16+PARÂMETROS!D17+PARÂMETROS!D18+PARÂMETROS!D19+PARÂMETROS!D20+PARÂMETROS!D21+PARÂMETROS!D22+PARÂMETROS!D23+PARÂMETROS!D24+PARÂMETROS!D25+PARÂMETROS!D26),0)
A54: 2026-W37 | B54: =IF((PARÂMETROS!D16+PARÂMETROS!D17+PARÂMETROS!D18+PARÂMETROS!D19+PARÂMETROS!D20+PARÂMETROS!D21+PARÂMETROS!D22+PARÂMETROS!D23+PARÂMETROS!D24+PARÂMETROS!D25+PARÂMETROS!D26)>0,(PARÂMETROS!D16*T6+PARÂMETROS!D17*T9+PARÂMETROS!D18*T12+PARÂMETROS!D19*T15+PARÂMETROS!D20*T18+PARÂMETROS!D21*T21+PARÂMETROS!D22*T24+PARÂMETROS!D23*T27+PARÂMETROS!D24*T30+PARÂMETROS!D25*T33+PARÂMETROS!D26*T36)/(PARÂMETROS!D16+PARÂMETROS!D17+PARÂMETROS!D18+PARÂMETROS!D19+PARÂMETROS!D20+PARÂMETROS!D21+PARÂMETROS!D22+PARÂMETROS!D23+PARÂMETROS!D24+PARÂMETROS!D25+PARÂMETROS!D26),0)
A55: 2026-W38 | B55: =IF((PARÂMETROS!D16+PARÂMETROS!D17+PARÂMETROS!D18+PARÂMETROS!D19+PARÂMETROS!D20+PARÂMETROS!D21+PARÂMETROS!D22+PARÂMETROS!D23+PARÂMETROS!D24+PARÂMETROS!D25+PARÂMETROS!D26)>0,(PARÂMETROS!D16*U6+PARÂMETROS!D17*U9+PARÂMETROS!D18*U12+PARÂMETROS!D19*U15+PARÂMETROS!D20*U18+PARÂMETROS!D21*U21+PARÂMETROS!D22*U24+PARÂMETROS!D23*U27+PARÂMETROS!D24*U30+PARÂMETROS!D25*U33+PARÂMETROS!D26*U36)/(PARÂMETROS!D16+PARÂMETROS!D17+PARÂMETROS!D18+PARÂMETROS!D19+PARÂMETROS!D20+PARÂMETROS!D21+PARÂMETROS!D22+PARÂMETROS!D23+PARÂMETROS!D24+PARÂMETROS!D25+PARÂMETROS!D26),0)
A56: 2026-W39 | B56: =IF((PARÂMETROS!D16+PARÂMETROS!D17+PARÂMETROS!D18+PARÂMETROS!D19+PARÂMETROS!D20+PARÂMETROS!D21+PARÂMETROS!D22+PARÂMETROS!D23+PARÂMETROS!D24+PARÂMETROS!D25+PARÂMETROS!D26)>0,(PARÂMETROS!D16*V6+PARÂMETROS!D17*V9+PARÂMETROS!D18*V12+PARÂMETROS!D19*V15+PARÂMETROS!D20*V18+PARÂMETROS!D21*V21+PARÂMETROS!D22*V24+PARÂMETROS!D23*V27+PARÂMETROS!D24*V30+PARÂMETROS!D25*V33+PARÂMETROS!D26*V36)/(PARÂMETROS!D16+PARÂMETROS!D17+PARÂMETROS!D18+PARÂMETROS!D19+PARÂMETROS!D20+PARÂMETROS!D21+PARÂMETROS!D22+PARÂMETROS!D23+PARÂMETROS!D24+PARÂMETROS!D25+PARÂMETROS!D26),0)
A57: 2026-W40 | B57: =IF((PARÂMETROS!D16+PARÂMETROS!D17+PARÂMETROS!D18+PARÂMETROS!D19+PARÂMETROS!D20+PARÂMETROS!D21+PARÂMETROS!D22+PARÂMETROS!D23+PARÂMETROS!D24+PARÂMETROS!D25+PARÂMETROS!D26)>0,(PARÂMETROS!D16*W6+PARÂMETROS!D17*W9+PARÂMETROS!D18*W12+PARÂMETROS!D19*W15+PARÂMETROS!D20*W18+PARÂMETROS!D21*W21+PARÂMETROS!D22*W24+PARÂMETROS!D23*W27+PARÂMETROS!D24*W30+PARÂMETROS!D25*W33+PARÂMETROS!D26*W36)/(PARÂMETROS!D16+PARÂMETROS!D17+PARÂMETROS!D18+PARÂMETROS!D19+PARÂMETROS!D20+PARÂMETROS!D21+PARÂMETROS!D22+PARÂMETROS!D23+PARÂMETROS!D24+PARÂMETROS!D25+PARÂMETROS!D26),0)
A58: 2026-W41 | B58: =IF((PARÂMETROS!D16+PARÂMETROS!D17+PARÂMETROS!D18+PARÂMETROS!D19+PARÂMETROS!D20+PARÂMETROS!D21+PARÂMETROS!D22+PARÂMETROS!D23+PARÂMETROS!D24+PARÂMETROS!D25+PARÂMETROS!D26)>0,(PARÂMETROS!D16*X6+PARÂMETROS!D17*X9+PARÂMETROS!D18*X12+PARÂMETROS!D19*X15+PARÂMETROS!D20*X18+PARÂMETROS!D21*X21+PARÂMETROS!D22*X24+PARÂMETROS!D23*X27+PARÂMETROS!D24*X30+PARÂMETROS!D25*X33+PARÂMETROS!D26*X36)/(PARÂMETROS!D16+PARÂMETROS!D17+PARÂMETROS!D18+PARÂMETROS!D19+PARÂMETROS!D20+PARÂMETROS!D21+PARÂMETROS!D22+PARÂMETROS!D23+PARÂMETROS!D24+PARÂMETROS!D25+PARÂMETROS!D26),0)
A59: 2026-W42 | B59: =IF((PARÂMETROS!D16+PARÂMETROS!D17+PARÂMETROS!D18+PARÂMETROS!D19+PARÂMETROS!D20+PARÂMETROS!D21+PARÂMETROS!D22+PARÂMETROS!D23+PARÂMETROS!D24+PARÂMETROS!D25+PARÂMETROS!D26)>0,(PARÂMETROS!D16*Y6+PARÂMETROS!D17*Y9+PARÂMETROS!D18*Y12+PARÂMETROS!D19*Y15+PARÂMETROS!D20*Y18+PARÂMETROS!D21*Y21+PARÂMETROS!D22*Y24+PARÂMETROS!D23*Y27+PARÂMETROS!D24*Y30+PARÂMETROS!D25*Y33+PARÂMETROS!D26*Y36)/(PARÂMETROS!D16+PARÂMETROS!D17+PARÂMETROS!D18+PARÂMETROS!D19+PARÂMETROS!D20+PARÂMETROS!D21+PARÂMETROS!D22+PARÂMETROS!D23+PARÂMETROS!D24+PARÂMETROS!D25+PARÂMETROS!D26),0)
A60: 2026-W43 | B60: =IF((PARÂMETROS!D16+PARÂMETROS!D17+PARÂMETROS!D18+PARÂMETROS!D19+PARÂMETROS!D20+PARÂMETROS!D21+PARÂMETROS!D22+PARÂMETROS!D23+PARÂMETROS!D24+PARÂMETROS!D25+PARÂMETROS!D26)>0,(PARÂMETROS!D16*Z6+PARÂMETROS!D17*Z9+PARÂMETROS!D18*Z12+PARÂMETROS!D19*Z15+PARÂMETROS!D20*Z18+PARÂMETROS!D21*Z21+PARÂMETROS!D22*Z24+PARÂMETROS!D23*Z27+PARÂMETROS!D24*Z30+PARÂMETROS!D25*Z33+PARÂMETROS!D26*Z36)/(PARÂMETROS!D16+PARÂMETROS!D17+PARÂMETROS!D18+PARÂMETROS!D19+PARÂMETROS!D20+PARÂMETROS!D21+PARÂMETROS!D22+PARÂMETROS!D23+PARÂMETROS!D24+PARÂMETROS!D25+PARÂMETROS!D26),0)
A61: 2026-W44 | B61: =IF((PARÂMETROS!D16+PARÂMETROS!D17+PARÂMETROS!D18+PARÂMETROS!D19+PARÂMETROS!D20+PARÂMETROS!D21+PARÂMETROS!D22+PARÂMETROS!D23+PARÂMETROS!D24+PARÂMETROS!D25+PARÂMETROS!D26)>0,(PARÂMETROS!D16*AA6+PARÂMETROS!D17*AA9+PARÂMETROS!D18*AA12+PARÂMETROS!D19*AA15+PARÂMETROS!D20*AA18+PARÂMETROS!D21*AA21+PARÂMETROS!D22*AA24+PARÂMETROS!D23*AA27+PARÂMETROS!D24*AA30+PARÂMETROS!D25*AA33+PARÂMETROS!D26*AA36)/(PARÂMETROS!D16+PARÂMETROS!D17+PARÂMETROS!D18+PARÂMETROS!D19+PARÂMETROS!D20+PARÂMETROS!D21+PARÂMETROS!D22+PARÂMETROS!D23+PARÂMETROS!D24+PARÂMETROS!D25+PARÂMETROS!D26),0)
A62: 2026-W45 | B62: =IF((PARÂMETROS!D16+PARÂMETROS!D17+PARÂMETROS!D18+PARÂMETROS!D19+PARÂMETROS!D20+PARÂMETROS!D21+PARÂMETROS!D22+PARÂMETROS!D23+PARÂMETROS!D24+PARÂMETROS!D25+PARÂMETROS!D26)>0,(PARÂMETROS!D16*AB6+PARÂMETROS!D17*AB9+PARÂMETROS!D18*AB12+PARÂMETROS!D19*AB15+PARÂMETROS!D20*AB18+PARÂMETROS!D21*AB21+PARÂMETROS!D22*AB24+PARÂMETROS!D23*AB27+PARÂMETROS!D24*AB30+PARÂMETROS!D25*AB33+PARÂMETROS!D26*AB36)/(PARÂMETROS!D16+PARÂMETROS!D17+PARÂMETROS!D18+PARÂMETROS!D19+PARÂMETROS!D20+PARÂMETROS!D21+PARÂMETROS!D22+PARÂMETROS!D23+PARÂMETROS!D24+PARÂMETROS!D25+PARÂMETROS!D26),0)
A63: 2026-W46 | B63: =IF((PARÂMETROS!D16+PARÂMETROS!D17+PARÂMETROS!D18+PARÂMETROS!D19+PARÂMETROS!D20+PARÂMETROS!D21+PARÂMETROS!D22+PARÂMETROS!D23+PARÂMETROS!D24+PARÂMETROS!D25+PARÂMETROS!D26)>0,(PARÂMETROS!D16*AC6+PARÂMETROS!D17*AC9+PARÂMETROS!D18*AC12+PARÂMETROS!D19*AC15+PARÂMETROS!D20*AC18+PARÂMETROS!D21*AC21+PARÂMETROS!D22*AC24+PARÂMETROS!D23*AC27+PARÂMETROS!D24*AC30+PARÂMETROS!D25*AC33+PARÂMETROS!D26*AC36)/(PARÂMETROS!D16+PARÂMETROS!D17+PARÂMETROS!D18+PARÂMETROS!D19+PARÂMETROS!D20+PARÂMETROS!D21+PARÂMETROS!D22+PARÂMETROS!D23+PARÂMETROS!D24+PARÂMETROS!D25+PARÂMETROS!D26),0)
A64: 2026-W47 | B64: =IF((PARÂMETROS!D16+PARÂMETROS!D17+PARÂMETROS!D18+PARÂMETROS!D19+PARÂMETROS!D20+PARÂMETROS!D21+PARÂMETROS!D22+PARÂMETROS!D23+PARÂMETROS!D24+PARÂMETROS!D25+PARÂMETROS!D26)>0,(PARÂMETROS!D16*AD6+PARÂMETROS!D17*AD9+PARÂMETROS!D18*AD12+PARÂMETROS!D19*AD15+PARÂMETROS!D20*AD18+PARÂMETROS!D21*AD21+PARÂMETROS!D22*AD24+PARÂMETROS!D23*AD27+PARÂMETROS!D24*AD30+PARÂMETROS!D25*AD33+PARÂMETROS!D26*AD36)/(PARÂMETROS!D16+PARÂMETROS!D17+PARÂMETROS!D18+PARÂMETROS!D19+PARÂMETROS!D20+PARÂMETROS!D21+PARÂMETROS!D22+PARÂMETROS!D23+PARÂMETROS!D24+PARÂMETROS!D25+PARÂMETROS!D26),0)
A65: 2026-W48 | B65: =IF((PARÂMETROS!D16+PARÂMETROS!D17+PARÂMETROS!D18+PARÂMETROS!D19+PARÂMETROS!D20+PARÂMETROS!D21+PARÂMETROS!D22+PARÂMETROS!D23+PARÂMETROS!D24+PARÂMETROS!D25+PARÂMETROS!D26)>0,(PARÂMETROS!D16*AE6+PARÂMETROS!D17*AE9+PARÂMETROS!D18*AE12+PARÂMETROS!D19*AE15+PARÂMETROS!D20*AE18+PARÂMETROS!D21*AE21+PARÂMETROS!D22*AE24+PARÂMETROS!D23*AE27+PARÂMETROS!D24*AE30+PARÂMETROS!D25*AE33+PARÂMETROS!D26*AE36)/(PARÂMETROS!D16+PARÂMETROS!D17+PARÂMETROS!D18+PARÂMETROS!D19+PARÂMETROS!D20+PARÂMETROS!D21+PARÂMETROS!D22+PARÂMETROS!D23+PARÂMETROS!D24+PARÂMETROS!D25+PARÂMETROS!D26),0)
A66: 2026-W49 | B66: =IF((PARÂMETROS!D16+PARÂMETROS!D17+PARÂMETROS!D18+PARÂMETROS!D19+PARÂMETROS!D20+PARÂMETROS!D21+PARÂMETROS!D22+PARÂMETROS!D23+PARÂMETROS!D24+PARÂMETROS!D25+PARÂMETROS!D26)>0,(PARÂMETROS!D16*AF6+PARÂMETROS!D17*AF9+PARÂMETROS!D18*AF12+PARÂMETROS!D19*AF15+PARÂMETROS!D20*AF18+PARÂMETROS!D21*AF21+PARÂMETROS!D22*AF24+PARÂMETROS!D23*AF27+PARÂMETROS!D24*AF30+PARÂMETROS!D25*AF33+PARÂMETROS!D26*AF36)/(PARÂMETROS!D16+PARÂMETROS!D17+PARÂMETROS!D18+PARÂMETROS!D19+PARÂMETROS!D20+PARÂMETROS!D21+PARÂMETROS!D22+PARÂMETROS!D23+PARÂMETROS!D24+PARÂMETROS!D25+PARÂMETROS!D26),0)
A67: 2026-W50 | B67: =IF((PARÂMETROS!D16+PARÂMETROS!D17+PARÂMETROS!D18+PARÂMETROS!D19+PARÂMETROS!D20+PARÂMETROS!D21+PARÂMETROS!D22+PARÂMETROS!D23+PARÂMETROS!D24+PARÂMETROS!D25+PARÂMETROS!D26)>0,(PARÂMETROS!D16*AG6+PARÂMETROS!D17*AG9+PARÂMETROS!D18*AG12+PARÂMETROS!D19*AG15+PARÂMETROS!D20*AG18+PARÂMETROS!D21*AG21+PARÂMETROS!D22*AG24+PARÂMETROS!D23*AG27+PARÂMETROS!D24*AG30+PARÂMETROS!D25*AG33+PARÂMETROS!D26*AG36)/(PARÂMETROS!D16+PARÂMETROS!D17+PARÂMETROS!D18+PARÂMETROS!D19+PARÂMETROS!D20+PARÂMETROS!D21+PARÂMETROS!D22+PARÂMETROS!D23+PARÂMETROS!D24+PARÂMETROS!D25+PARÂMETROS!D26),0)
A68: 2026-W51 | B68: =IF((PARÂMETROS!D16+PARÂMETROS!D17+PARÂMETROS!D18+PARÂMETROS!D19+PARÂMETROS!D20+PARÂMETROS!D21+PARÂMETROS!D22+PARÂMETROS!D23+PARÂMETROS!D24+PARÂMETROS!D25+PARÂMETROS!D26)>0,(PARÂMETROS!D16*AH6+PARÂMETROS!D17*AH9+PARÂMETROS!D18*AH12+PARÂMETROS!D19*AH15+PARÂMETROS!D20*AH18+PARÂMETROS!D21*AH21+PARÂMETROS!D22*AH24+PARÂMETROS!D23*AH27+PARÂMETROS!D24*AH30+PARÂMETROS!D25*AH33+PARÂMETROS!D26*AH36)/(PARÂMETROS!D16+PARÂMETROS!D17+PARÂMETROS!D18+PARÂMETROS!D19+PARÂMETROS!D20+PARÂMETROS!D21+PARÂMETROS!D22+PARÂMETROS!D23+PARÂMETROS!D24+PARÂMETROS!D25+PARÂMETROS!D26),0)
A69: 2026-W52 | B69: =IF((PARÂMETROS!D16+PARÂMETROS!D17+PARÂMETROS!D18+PARÂMETROS!D19+PARÂMETROS!D20+PARÂMETROS!D21+PARÂMETROS!D22+PARÂMETROS!D23+PARÂMETROS!D24+PARÂMETROS!D25+PARÂMETROS!D26)>0,(PARÂMETROS!D16*AI6+PARÂMETROS!D17*AI9+PARÂMETROS!D18*AI12+PARÂMETROS!D19*AI15+PARÂMETROS!D20*AI18+PARÂMETROS!D21*AI21+PARÂMETROS!D22*AI24+PARÂMETROS!D23*AI27+PARÂMETROS!D24*AI30+PARÂMETROS!D25*AI33+PARÂMETROS!D26*AI36)/(PARÂMETROS!D16+PARÂMETROS!D17+PARÂMETROS!D18+PARÂMETROS!D19+PARÂMETROS!D20+PARÂMETROS!D21+PARÂMETROS!D22+PARÂMETROS!D23+PARÂMETROS!D24+PARÂMETROS!D25+PARÂMETROS!D26),0)
A70: 2026-W53 | B70: =IF((PARÂMETROS!D16+PARÂMETROS!D17+PARÂMETROS!D18+PARÂMETROS!D19+PARÂMETROS!D20+PARÂMETROS!D21+PARÂMETROS!D22+PARÂMETROS!D23+PARÂMETROS!D24+PARÂMETROS!D25+PARÂMETROS!D26)>0,(PARÂMETROS!D16*AJ6+PARÂMETROS!D17*AJ9+PARÂMETROS!D18*AJ12+PARÂMETROS!D19*AJ15+PARÂMETROS!D20*AJ18+PARÂMETROS!D21*AJ21+PARÂMETROS!D22*AJ24+PARÂMETROS!D23*AJ27+PARÂMETROS!D24*AJ30+PARÂMETROS!D25*AJ33+PARÂMETROS!D26*AJ36)/(PARÂMETROS!D16+PARÂMETROS!D17+PARÂMETROS!D18+PARÂMETROS!D19+PARÂMETROS!D20+PARÂMETROS!D21+PARÂMETROS!D22+PARÂMETROS!D23+PARÂMETROS!D24+PARÂMETROS!D25+PARÂMETROS!D26),0)
A71: 2027-W01 | B71: =IF((PARÂMETROS!D16+PARÂMETROS!D17+PARÂMETROS!D18+PARÂMETROS!D19+PARÂMETROS!D20+PARÂMETROS!D21+PARÂMETROS!D22+PARÂMETROS!D23+PARÂMETROS!D24+PARÂMETROS!D25+PARÂMETROS!D26)>0,(PARÂMETROS!D16*AK6+PARÂMETROS!D17*AK9+PARÂMETROS!D18*AK12+PARÂMETROS!D19*AK15+PARÂMETROS!D20*AK18+PARÂMETROS!D21*AK21+PARÂMETROS!D22*AK24+PARÂMETROS!D23*AK27+PARÂMETROS!D24*AK30+PARÂMETROS!D25*AK33+PARÂMETROS!D26*AK36)/(PARÂMETROS!D16+PARÂMETROS!D17+PARÂMETROS!D18+PARÂMETROS!D19+PARÂMETROS!D20+PARÂMETROS!D21+PARÂMETROS!D22+PARÂMETROS!D23+PARÂMETROS!D24+PARÂMETROS!D25+PARÂMETROS!D26),0)
A72: 2027-W02 | B72: =IF((PARÂMETROS!D16+PARÂMETROS!D17+PARÂMETROS!D18+PARÂMETROS!D19+PARÂMETROS!D20+PARÂMETROS!D21+PARÂMETROS!D22+PARÂMETROS!D23+PARÂMETROS!D24+PARÂMETROS!D25+PARÂMETROS!D26)>0,(PARÂMETROS!D16*AL6+PARÂMETROS!D17*AL9+PARÂMETROS!D18*AL12+PARÂMETROS!D19*AL15+PARÂMETROS!D20*AL18+PARÂMETROS!D21*AL21+PARÂMETROS!D22*AL24+PARÂMETROS!D23*AL27+PARÂMETROS!D24*AL30+PARÂMETROS!D25*AL33+PARÂMETROS!D26*AL36)/(PARÂMETROS!D16+PARÂMETROS!D17+PARÂMETROS!D18+PARÂMETROS!D19+PARÂMETROS!D20+PARÂMETROS!D21+PARÂMETROS!D22+PARÂMETROS!D23+PARÂMETROS!D24+PARÂMETROS!D25+PARÂMETROS!D26),0)
A73: 2027-W03 | B73: =IF((PARÂMETROS!D16+PARÂMETROS!D17+PARÂMETROS!D18+PARÂMETROS!D19+PARÂMETROS!D20+PARÂMETROS!D21+PARÂMETROS!D22+PARÂMETROS!D23+PARÂMETROS!D24+PARÂMETROS!D25+PARÂMETROS!D26)>0,(PARÂMETROS!D16*AM6+PARÂMETROS!D17*AM9+PARÂMETROS!D18*AM12+PARÂMETROS!D19*AM15+PARÂMETROS!D20*AM18+PARÂMETROS!D21*AM21+PARÂMETROS!D22*AM24+PARÂMETROS!D23*AM27+PARÂMETROS!D24*AM30+PARÂMETROS!D25*AM33+PARÂMETROS!D26*AM36)/(PARÂMETROS!D16+PARÂMETROS!D17+PARÂMETROS!D18+PARÂMETROS!D19+PARÂMETROS!D20+PARÂMETROS!D21+PARÂMETROS!D22+PARÂMETROS!D23+PARÂMETROS!D24+PARÂMETROS!D25+PARÂMETROS!D26),0)
A74: 2027-W04 | B74: =IF((PARÂMETROS!D16+PARÂMETROS!D17+PARÂMETROS!D18+PARÂMETROS!D19+PARÂMETROS!D20+PARÂMETROS!D21+PARÂMETROS!D22+PARÂMETROS!D23+PARÂMETROS!D24+PARÂMETROS!D25+PARÂMETROS!D26)>0,(PARÂMETROS!D16*AN6+PARÂMETROS!D17*AN9+PARÂMETROS!D18*AN12+PARÂMETROS!D19*AN15+PARÂMETROS!D20*AN18+PARÂMETROS!D21*AN21+PARÂMETROS!D22*AN24+PARÂMETROS!D23*AN27+PARÂMETROS!D24*AN30+PARÂMETROS!D25*AN33+PARÂMETROS!D26*AN36)/(PARÂMETROS!D16+PARÂMETROS!D17+PARÂMETROS!D18+PARÂMETROS!D19+PARÂMETROS!D20+PARÂMETROS!D21+PARÂMETROS!D22+PARÂMETROS!D23+PARÂMETROS!D24+PARÂMETROS!D25+PARÂMETROS!D26),0)
A75: 2027-W05 | B75: =IF((PARÂMETROS!D16+PARÂMETROS!D17+PARÂMETROS!D18+PARÂMETROS!D19+PARÂMETROS!D20+PARÂMETROS!D21+PARÂMETROS!D22+PARÂMETROS!D23+PARÂMETROS!D24+PARÂMETROS!D25+PARÂMETROS!D26)>0,(PARÂMETROS!D16*AO6+PARÂMETROS!D17*AO9+PARÂMETROS!D18*AO12+PARÂMETROS!D19*AO15+PARÂMETROS!D20*AO18+PARÂMETROS!D21*AO21+PARÂMETROS!D22*AO24+PARÂMETROS!D23*AO27+PARÂMETROS!D24*AO30+PARÂMETROS!D25*AO33+PARÂMETROS!D26*AO36)/(PARÂMETROS!D16+PARÂMETROS!D17+PARÂMETROS!D18+PARÂMETROS!D19+PARÂMETROS!D20+PARÂMETROS!D21+PARÂMETROS!D22+PARÂMETROS!D23+PARÂMETROS!D24+PARÂMETROS!D25+PARÂMETROS!D26),0)
A76: 2027-W06 | B76: =IF((PARÂMETROS!D16+PARÂMETROS!D17+PARÂMETROS!D18+PARÂMETROS!D19+PARÂMETROS!D20+PARÂMETROS!D21+PARÂMETROS!D22+PARÂMETROS!D23+PARÂMETROS!D24+PARÂMETROS!D25+PARÂMETROS!D26)>0,(PARÂMETROS!D16*AP6+PARÂMETROS!D17*AP9+PARÂMETROS!D18*AP12+PARÂMETROS!D19*AP15+PARÂMETROS!D20*AP18+PARÂMETROS!D21*AP21+PARÂMETROS!D22*AP24+PARÂMETROS!D23*AP27+PARÂMETROS!D24*AP30+PARÂMETROS!D25*AP33+PARÂMETROS!D26*AP36)/(PARÂMETROS!D16+PARÂMETROS!D17+PARÂMETROS!D18+PARÂMETROS!D19+PARÂMETROS!D20+PARÂMETROS!D21+PARÂMETROS!D22+PARÂMETROS!D23+PARÂMETROS!D24+PARÂMETROS!D25+PARÂMETROS!D26),0)
A77: 2027-W07 | B77: =IF((PARÂMETROS!D16+PARÂMETROS!D17+PARÂMETROS!D18+PARÂMETROS!D19+PARÂMETROS!D20+PARÂMETROS!D21+PARÂMETROS!D22+PARÂMETROS!D23+PARÂMETROS!D24+PARÂMETROS!D25+PARÂMETROS!D26)>0,(PARÂMETROS!D16*AQ6+PARÂMETROS!D17*AQ9+PARÂMETROS!D18*AQ12+PARÂMETROS!D19*AQ15+PARÂMETROS!D20*AQ18+PARÂMETROS!D21*AQ21+PARÂMETROS!D22*AQ24+PARÂMETROS!D23*AQ27+PARÂMETROS!D24*AQ30+PARÂMETROS!D25*AQ33+PARÂMETROS!D26*AQ36)/(PARÂMETROS!D16+PARÂMETROS!D17+PARÂMETROS!D18+PARÂMETROS!D19+PARÂMETROS!D20+PARÂMETROS!D21+PARÂMETROS!D22+PARÂMETROS!D23+PARÂMETROS!D24+PARÂMETROS!D25+PARÂMETROS!D26),0)
A78: 2027-W08 | B78: =IF((PARÂMETROS!D16+PARÂMETROS!D17+PARÂMETROS!D18+PARÂMETROS!D19+PARÂMETROS!D20+PARÂMETROS!D21+PARÂMETROS!D22+PARÂMETROS!D23+PARÂMETROS!D24+PARÂMETROS!D25+PARÂMETROS!D26)>0,(PARÂMETROS!D16*AR6+PARÂMETROS!D17*AR9+PARÂMETROS!D18*AR12+PARÂMETROS!D19*AR15+PARÂMETROS!D20*AR18+PARÂMETROS!D21*AR21+PARÂMETROS!D22*AR24+PARÂMETROS!D23*AR27+PARÂMETROS!D24*AR30+PARÂMETROS!D25*AR33+PARÂMETROS!D26*AR36)/(PARÂMETROS!D16+PARÂMETROS!D17+PARÂMETROS!D18+PARÂMETROS!D19+PARÂMETROS!D20+PARÂMETROS!D21+PARÂMETROS!D22+PARÂMETROS!D23+PARÂMETROS!D24+PARÂMETROS!D25+PARÂMETROS!D26),0)
A79: 2027-W09 | B79: =IF((PARÂMETROS!D16+PARÂMETROS!D17+PARÂMETROS!D18+PARÂMETROS!D19+PARÂMETROS!D20+PARÂMETROS!D21+PARÂMETROS!D22+PARÂMETROS!D23+PARÂMETROS!D24+PARÂMETROS!D25+PARÂMETROS!D26)>0,(PARÂMETROS!D16*AS6+PARÂMETROS!D17*AS9+PARÂMETROS!D18*AS12+PARÂMETROS!D19*AS15+PARÂMETROS!D20*AS18+PARÂMETROS!D21*AS21+PARÂMETROS!D22*AS24+PARÂMETROS!D23*AS27+PARÂMETROS!D24*AS30+PARÂMETROS!D25*AS33+PARÂMETROS!D26*AS36)/(PARÂMETROS!D16+PARÂMETROS!D17+PARÂMETROS!D18+PARÂMETROS!D19+PARÂMETROS!D20+PARÂMETROS!D21+PARÂMETROS!D22+PARÂMETROS!D23+PARÂMETROS!D24+PARÂMETROS!D25+PARÂMETROS!D26),0)
A80: 2027-W10 | B80: =IF((PARÂMETROS!D16+PARÂMETROS!D17+PARÂMETROS!D18+PARÂMETROS!D19+PARÂMETROS!D20+PARÂMETROS!D21+PARÂMETROS!D22+PARÂMETROS!D23+PARÂMETROS!D24+PARÂMETROS!D25+PARÂMETROS!D26)>0,(PARÂMETROS!D16*AT6+PARÂMETROS!D17*AT9+PARÂMETROS!D18*AT12+PARÂMETROS!D19*AT15+PARÂMETROS!D20*AT18+PARÂMETROS!D21*AT21+PARÂMETROS!D22*AT24+PARÂMETROS!D23*AT27+PARÂMETROS!D24*AT30+PARÂMETROS!D25*AT33+PARÂMETROS!D26*AT36)/(PARÂMETROS!D16+PARÂMETROS!D17+PARÂMETROS!D18+PARÂMETROS!D19+PARÂMETROS!D20+PARÂMETROS!D21+PARÂMETROS!D22+PARÂMETROS!D23+PARÂMETROS!D24+PARÂMETROS!D25+PARÂMETROS!D26),0)
A81: 2027-W11 | B81: =IF((PARÂMETROS!D16+PARÂMETROS!D17+PARÂMETROS!D18+PARÂMETROS!D19+PARÂMETROS!D20+PARÂMETROS!D21+PARÂMETROS!D22+PARÂMETROS!D23+PARÂMETROS!D24+PARÂMETROS!D25+PARÂMETROS!D26)>0,(PARÂMETROS!D16*AU6+PARÂMETROS!D17*AU9+PARÂMETROS!D18*AU12+PARÂMETROS!D19*AU15+PARÂMETROS!D20*AU18+PARÂMETROS!D21*AU21+PARÂMETROS!D22*AU24+PARÂMETROS!D23*AU27+PARÂMETROS!D24*AU30+PARÂMETROS!D25*AU33+PARÂMETROS!D26*AU36)/(PARÂMETROS!D16+PARÂMETROS!D17+PARÂMETROS!D18+PARÂMETROS!D19+PARÂMETROS!D20+PARÂMETROS!D21+PARÂMETROS!D22+PARÂMETROS!D23+PARÂMETROS!D24+PARÂMETROS!D25+PARÂMETROS!D26),0)
A82: 2027-W12 | B82: =IF((PARÂMETROS!D16+PARÂMETROS!D17+PARÂMETROS!D18+PARÂMETROS!D19+PARÂMETROS!D20+PARÂMETROS!D21+PARÂMETROS!D22+PARÂMETROS!D23+PARÂMETROS!D24+PARÂMETROS!D25+PARÂMETROS!D26)>0,(PARÂMETROS!D16*AV6+PARÂMETROS!D17*AV9+PARÂMETROS!D18*AV12+PARÂMETROS!D19*AV15+PARÂMETROS!D20*AV18+PARÂMETROS!D21*AV21+PARÂMETROS!D22*AV24+PARÂMETROS!D23*AV27+PARÂMETROS!D24*AV30+PARÂMETROS!D25*AV33+PARÂMETROS!D26*AV36)/(PARÂMETROS!D16+PARÂMETROS!D17+PARÂMETROS!D18+PARÂMETROS!D19+PARÂMETROS!D20+PARÂMETROS!D21+PARÂMETROS!D22+PARÂMETROS!D23+PARÂMETROS!D24+PARÂMETROS!D25+PARÂMETROS!D26),0)
A83: 2027-W13 | B83: =IF((PARÂMETROS!D16+PARÂMETROS!D17+PARÂMETROS!D18+PARÂMETROS!D19+PARÂMETROS!D20+PARÂMETROS!D21+PARÂMETROS!D22+PARÂMETROS!D23+PARÂMETROS!D24+PARÂMETROS!D25+PARÂMETROS!D26)>0,(PARÂMETROS!D16*AW6+PARÂMETROS!D17*AW9+PARÂMETROS!D18*AW12+PARÂMETROS!D19*AW15+PARÂMETROS!D20*AW18+PARÂMETROS!D21*AW21+PARÂMETROS!D22*AW24+PARÂMETROS!D23*AW27+PARÂMETROS!D24*AW30+PARÂMETROS!D25*AW33+PARÂMETROS!D26*AW36)/(PARÂMETROS!D16+PARÂMETROS!D17+PARÂMETROS!D18+PARÂMETROS!D19+PARÂMETROS!D20+PARÂMETROS!D21+PARÂMETROS!D22+PARÂMETROS!D23+PARÂMETROS!D24+PARÂMETROS!D25+PARÂMETROS!D26),0)
A84: 2027-W14 | B84: =IF((PARÂMETROS!D16+PARÂMETROS!D17+PARÂMETROS!D18+PARÂMETROS!D19+PARÂMETROS!D20+PARÂMETROS!D21+PARÂMETROS!D22+PARÂMETROS!D23+PARÂMETROS!D24+PARÂMETROS!D25+PARÂMETROS!D26)>0,(PARÂMETROS!D16*AX6+PARÂMETROS!D17*AX9+PARÂMETROS!D18*AX12+PARÂMETROS!D19*AX15+PARÂMETROS!D20*AX18+PARÂMETROS!D21*AX21+PARÂMETROS!D22*AX24+PARÂMETROS!D23*AX27+PARÂMETROS!D24*AX30+PARÂMETROS!D25*AX33+PARÂMETROS!D26*AX36)/(PARÂMETROS!D16+PARÂMETROS!D17+PARÂMETROS!D18+PARÂMETROS!D19+PARÂMETROS!D20+PARÂMETROS!D21+PARÂMETROS!D22+PARÂMETROS!D23+PARÂMETROS!D24+PARÂMETROS!D25+PARÂMETROS!D26),0)
A85: 2027-W15 | B85: =IF((PARÂMETROS!D16+PARÂMETROS!D17+PARÂMETROS!D18+PARÂMETROS!D19+PARÂMETROS!D20+PARÂMETROS!D21+PARÂMETROS!D22+PARÂMETROS!D23+PARÂMETROS!D24+PARÂMETROS!D25+PARÂMETROS!D26)>0,(PARÂMETROS!D16*AY6+PARÂMETROS!D17*AY9+PARÂMETROS!D18*AY12+PARÂMETROS!D19*AY15+PARÂMETROS!D20*AY18+PARÂMETROS!D21*AY21+PARÂMETROS!D22*AY24+PARÂMETROS!D23*AY27+PARÂMETROS!D24*AY30+PARÂMETROS!D25*AY33+PARÂMETROS!D26*AY36)/(PARÂMETROS!D16+PARÂMETROS!D17+PARÂMETROS!D18+PARÂMETROS!D19+PARÂMETROS!D20+PARÂMETROS!D21+PARÂMETROS!D22+PARÂMETROS!D23+PARÂMETROS!D24+PARÂMETROS!D25+PARÂMETROS!D26),0)
A86: 2027-W16 | B86: =IF((PARÂMETROS!D16+PARÂMETROS!D17+PARÂMETROS!D18+PARÂMETROS!D19+PARÂMETROS!D20+PARÂMETROS!D21+PARÂMETROS!D22+PARÂMETROS!D23+PARÂMETROS!D24+PARÂMETROS!D25+PARÂMETROS!D26)>0,(PARÂMETROS!D16*AZ6+PARÂMETROS!D17*AZ9+PARÂMETROS!D18*AZ12+PARÂMETROS!D19*AZ15+PARÂMETROS!D20*AZ18+PARÂMETROS!D21*AZ21+PARÂMETROS!D22*AZ24+PARÂMETROS!D23*AZ27+PARÂMETROS!D24*AZ30+PARÂMETROS!D25*AZ33+PARÂMETROS!D26*AZ36)/(PARÂMETROS!D16+PARÂMETROS!D17+PARÂMETROS!D18+PARÂMETROS!D19+PARÂMETROS!D20+PARÂMETROS!D21+PARÂMETROS!D22+PARÂMETROS!D23+PARÂMETROS!D24+PARÂMETROS!D25+PARÂMETROS!D26),0)
A87: 2027-W17 | B87: =IF((PARÂMETROS!D16+PARÂMETROS!D17+PARÂMETROS!D18+PARÂMETROS!D19+PARÂMETROS!D20+PARÂMETROS!D21+PARÂMETROS!D22+PARÂMETROS!D23+PARÂMETROS!D24+PARÂMETROS!D25+PARÂMETROS!D26)>0,(PARÂMETROS!D16*BA6+PARÂMETROS!D17*BA9+PARÂMETROS!D18*BA12+PARÂMETROS!D19*BA15+PARÂMETROS!D20*BA18+PARÂMETROS!D21*BA21+PARÂMETROS!D22*BA24+PARÂMETROS!D23*BA27+PARÂMETROS!D24*BA30+PARÂMETROS!D25*BA33+PARÂMETROS!D26*BA36)/(PARÂMETROS!D16+PARÂMETROS!D17+PARÂMETROS!D18+PARÂMETROS!D19+PARÂMETROS!D20+PARÂMETROS!D21+PARÂMETROS!D22+PARÂMETROS!D23+PARÂMETROS!D24+PARÂMETROS!D25+PARÂMETROS!D26),0)
A88: 2027-W18 | B88: =IF((PARÂMETROS!D16+PARÂMETROS!D17+PARÂMETROS!D18+PARÂMETROS!D19+PARÂMETROS!D20+PARÂMETROS!D21+PARÂMETROS!D22+PARÂMETROS!D23+PARÂMETROS!D24+PARÂMETROS!D25+PARÂMETROS!D26)>0,(PARÂMETROS!D16*BB6+PARÂMETROS!D17*BB9+PARÂMETROS!D18*BB12+PARÂMETROS!D19*BB15+PARÂMETROS!D20*BB18+PARÂMETROS!D21*BB21+PARÂMETROS!D22*BB24+PARÂMETROS!D23*BB27+PARÂMETROS!D24*BB30+PARÂMETROS!D25*BB33+PARÂMETROS!D26*BB36)/(PARÂMETROS!D16+PARÂMETROS!D17+PARÂMETROS!D18+PARÂMETROS!D19+PARÂMETROS!D20+PARÂMETROS!D21+PARÂMETROS!D22+PARÂMETROS!D23+PARÂMETROS!D24+PARÂMETROS!D25+PARÂMETROS!D26),0)
A89: 2027-W19 | B89: =IF((PARÂMETROS!D16+PARÂMETROS!D17+PARÂMETROS!D18+PARÂMETROS!D19+PARÂMETROS!D20+PARÂMETROS!D21+PARÂMETROS!D22+PARÂMETROS!D23+PARÂMETROS!D24+PARÂMETROS!D25+PARÂMETROS!D26)>0,(PARÂMETROS!D16*BC6+PARÂMETROS!D17*BC9+PARÂMETROS!D18*BC12+PARÂMETROS!D19*BC15+PARÂMETROS!D20*BC18+PARÂMETROS!D21*BC21+PARÂMETROS!D22*BC24+PARÂMETROS!D23*BC27+PARÂMETROS!D24*BC30+PARÂMETROS!D25*BC33+PARÂMETROS!D26*BC36)/(PARÂMETROS!D16+PARÂMETROS!D17+PARÂMETROS!D18+PARÂMETROS!D19+PARÂMETROS!D20+PARÂMETROS!D21+PARÂMETROS!D22+PARÂMETROS!D23+PARÂMETROS!D24+PARÂMETROS!D25+PARÂMETROS!D26),0)
A90: 2027-W20 | B90: =IF((PARÂMETROS!D16+PARÂMETROS!D17+PARÂMETROS!D18+PARÂMETROS!D19+PARÂMETROS!D20+PARÂMETROS!D21+PARÂMETROS!D22+PARÂMETROS!D23+PARÂMETROS!D24+PARÂMETROS!D25+PARÂMETROS!D26)>0,(PARÂMETROS!D16*BD6+PARÂMETROS!D17*BD9+PARÂMETROS!D18*BD12+PARÂMETROS!D19*BD15+PARÂMETROS!D20*BD18+PARÂMETROS!D21*BD21+PARÂMETROS!D22*BD24+PARÂMETROS!D23*BD27+PARÂMETROS!D24*BD30+PARÂMETROS!D25*BD33+PARÂMETROS!D26*BD36)/(PARÂMETROS!D16+PARÂMETROS!D17+PARÂMETROS!D18+PARÂMETROS!D19+PARÂMETROS!D20+PARÂMETROS!D21+PARÂMETROS!D22+PARÂMETROS!D23+PARÂMETROS!D24+PARÂMETROS!D25+PARÂMETROS!D26),0)
A91: 2027-W21 | B91: =IF((PARÂMETROS!D16+PARÂMETROS!D17+PARÂMETROS!D18+PARÂMETROS!D19+PARÂMETROS!D20+PARÂMETROS!D21+PARÂMETROS!D22+PARÂMETROS!D23+PARÂMETROS!D24+PARÂMETROS!D25+PARÂMETROS!D26)>0,(PARÂMETROS!D16*BE6+PARÂMETROS!D17*BE9+PARÂMETROS!D18*BE12+PARÂMETROS!D19*BE15+PARÂMETROS!D20*BE18+PARÂMETROS!D21*BE21+PARÂMETROS!D22*BE24+PARÂMETROS!D23*BE27+PARÂMETROS!D24*BE30+PARÂMETROS!D25*BE33+PARÂMETROS!D26*BE36)/(PARÂMETROS!D16+PARÂMETROS!D17+PARÂMETROS!D18+PARÂMETROS!D19+PARÂMETROS!D20+PARÂMETROS!D21+PARÂMETROS!D22+PARÂMETROS!D23+PARÂMETROS!D24+PARÂMETROS!D25+PARÂMETROS!D26),0)
A92: 2027-W22 | B92: =IF((PARÂMETROS!D16+PARÂMETROS!D17+PARÂMETROS!D18+PARÂMETROS!D19+PARÂMETROS!D20+PARÂMETROS!D21+PARÂMETROS!D22+PARÂMETROS!D23+PARÂMETROS!D24+PARÂMETROS!D25+PARÂMETROS!D26)>0,(PARÂMETROS!D16*BF6+PARÂMETROS!D17*BF9+PARÂMETROS!D18*BF12+PARÂMETROS!D19*BF15+PARÂMETROS!D20*BF18+PARÂMETROS!D21*BF21+PARÂMETROS!D22*BF24+PARÂMETROS!D23*BF27+PARÂMETROS!D24*BF30+PARÂMETROS!D25*BF33+PARÂMETROS!D26*BF36)/(PARÂMETROS!D16+PARÂMETROS!D17+PARÂMETROS!D18+PARÂMETROS!D19+PARÂMETROS!D20+PARÂMETROS!D21+PARÂMETROS!D22+PARÂMETROS!D23+PARÂMETROS!D24+PARÂMETROS!D25+PARÂMETROS!D26),0)

Sheet INDIRETOS
A1: INDIRETOS — FÓRMULAS SOBRE PARÂMETROS
A2: Categoria | B2: Custo Mensal | C2: Permanência (mes.) | D2: Total s/BDI | E2: BDI Indireto | F2: Total c/BDI
A3: =PARÂMETROS!A31 | B3: =PARÂMETROS!B31 | C3: =PARÂMETROS!C31 | D3: =B3*C3 | E3: =PARÂMETROS!$B$12 | F3: =D3*(1+E3)
A4: =PARÂMETROS!A32 | B4: =PARÂMETROS!B32 | C4: =PARÂMETROS!C32 | D4: =B4*C4 | E4: =PARÂMETROS!$B$12 | F4: =D4*(1+E4)
A5: =PARÂMETROS!A33 | B5: =PARÂMETROS!B33 | C5: =PARÂMETROS!C33 | D5: =B5*C5 | E5: =PARÂMETROS!$B$12 | F5: =D5*(1+E5)
A6: =PARÂMETROS!A34 | B6: =PARÂMETROS!B34 | C6: =PARÂMETROS!C34 | D6: =B6*C6 | E6: =PARÂMETROS!$B$12 | F6: =D6*(1+E6)
A7: =PARÂMETROS!A35 | B7: =PARÂMETROS!B35 | C7: =PARÂMETROS!C35 | D7: =B7*C7 | E7: =PARÂMETROS!$B$12 | F7: =D7*(1+E7)
A8: TOTAL | D8: =SUM(D3:D7) | F8: =SUM(F3:F7)

Sheet CONSOLIDAÇÃO
A1: CONSOLIDAÇÃO FINANCEIRA — FÓRMULAS CROSS-SHEET
A2: Indicador | B2: Concilium (R$) | C2: Referência (R$) | D2: Delta (R$) | E2: Delta (%)
A4: DIRETO
A5: s/BDI (catálogo) | B5: =ORÇAMENTO!I14 | C5: 46771430 | D5: =B5-C5 | E5: =IF(C5<>0,(B5-C5)/C5,0)
A6: c/BDI (catálogo) | B6: =ORÇAMENTO!J14 | C6: 76753981 | D6: =B6-C6 | E6: =IF(C6<>0,(B6-C6)/C6,0)
A7: Custo equipes (running) | B7: ='CUSTOS DIR.'!I14
A9: INDIRETO
A10: s/BDI | B10: =INDIRETOS!D8
A11: c/BDI | B11: =INDIRETOS!F8
A13: CUSTO TOTAL (catálogo) | B13: =B5+B10 | C13: 66275960 | D13: =B13-C13 | E13: =IF(C13<>0,(B13-C13)/C13,0)
A14: PREÇO DE VENDA | B14: =B6+B11 | C14: 76753981 | D14: =B14-C14 | E14: =IF(C14<>0,(B14-C14)/C14,0)
A16: MARGEM | B16: =IF(B14>0,(B14-B13)/B14,0)

Sheet FLUXO DE CX
A1: FLUXO DE CAIXA MENSAL — RECEITA E DESPESA (FÓRMULAS)
C2: 2026-06 | D2: 2026-07 | E2: 2026-08 | F2: 2026-09 | G2: 2026-10 | H2: 2026-11 | I2: 2026-12 | J2: 2027-01 | K2: 2027-02 | L2: 2027-03 | M2: 2027-04 | N2: 2027-05 | O2: TOTAL
A3: RECEITA (cron. × P.U. c/BDI) | C3: 9662535.1 | D3: 8781698.4 | E3: 8957201.7 | F3: 5252999.8 | G3: 4843614.2 | H3: 5479042.6 | I3: 2719442 | J3: 2173481 | K3: 1944970.4 | L3: 1955979.2 | M3: 1112905.7 | N3: 1796.54 | O3: =SUM(C3:N3)
A4: CUSTO DIRETO (equipes) | C4: 2762159.7 | D4: 2397614.4 | E4: 2308890.2 | F4: 2308890.2 | G4: 2308890.2 | H4: 2308890.2 | I4: 1815207 | J4: 1815207 | K4: 1815207 | L4: 1815207 | M4: 1815207 | N4: 1611133.4 | O4: =SUM(C4:N4)
A5: CUSTO INDIRETO (mensal) | C5: 1506782.5 | D5: 1506782.5 | E5: 1506782.5 | F5: 1506782.5 | G5: 1506782.5 | H5: 1506782.5 | I5: 1506782.5 | J5: 1506782.5 | K5: 1506782.5 | L5: 1506782.5 | M5: 1506782.5 | N5: 1506782.5 | O5: =SUM(C5:N5)
A6: SALDO MENSAL | C6: =C3-C4-C5 | D6: =D3-D4-D5 | E6: =E3-E4-E5 | F6: =F3-F4-F5 | G6: =G3-G4-G5 | H6: =H3-H4-H5 | I6: =I3-I4-I5 | J6: =J3-J4-J5 | ... N6: =N3-N4-N5 | O6: =SUM(C6:N6)
A7: SALDO ACUMULADO | C7: =C6 | D7: =C7+D6 | E7: =D7+E6 | F7: =E7+F6 | G7: =F7+G6 | H7: =G7+H6 | I7: =H7+I6 | J7: =I7+J6 | K7: =J7+K6 | ... N7: =M7+N6

Sheet REFERÊNCIA
A1: REFERÊNCIA — VALORES CALCULADOS PELO CONCILIUM
A2: Indicador | B2: Valor calculado (R$) | C2: Base de cálculo
A3: Custo Direto — Catálogo (s/BDI) | B3: 46771430 | C3: Σ(qtd × P.U.s/BDI)
A4: Custo Direto — Equipes (running cost) | B4: 74540391 | C4: Σ(fixo_mensal × permanência)
A5: Custo Indireto | B5: 19504530 | C5: Σ por categoria
A6: Custo Total (catálogo + indireto) | B6: 66275960 | C6: direto_cat + indireto
A7: Preço de Venda (catálogo c/BDI + indireto) | B7: 76753981 | C7: Σ(qtd×P.U.c/BDI) + ind×(1+BDI_ind)
A8: Margem | B8: 0.13651436 | C8: (preco_venda - custo_total) / preco_venda
