Workbook
Name TOTAL_DIRETO: 'DIRETOS.DET'!$I$99
Name DIRETOS_RES_SEM_BDI: 'DIRETOS.RES'!$I$15
Name DIRETOS_RES_COM_BDI: 'DIRETOS.RES'!$N$15
Name TOTAL_ADM: 'INDIRETOS.DET'!$H$5
Name TOTAL_TOP: 'INDIRETOS.DET'!$H$8
Name TOTAL_LAB: 'INDIRETOS.DET'!$H$11
Name TOTAL_QSMS: 'INDIRETOS.DET'!$H$14
Name TOTAL_MOB: 'INDIRETOS.DET'!$H$17
Name TOTAL_INDIRETO: 'INDIRETOS.DET'!$H$19
Name TOTAL_SEM_BDI: PLANEJAMENTO!$M$15
Name TOTAL_COM_BDI: PLANEJAMENTO!$N$15

Sheet BDI
A1: BDI — BONIFICAÇÕES E DESPESAS INDIRETAS (FÓRMULA TCU AC.2622/2013)
A2: Categoria | B2: AC (%) | C2: DF (%) | D2: R (%) | E2: CR (%) | F2: Lucro L (%) | G2: COFINS (%) | H2: ISS (%) | I2: PIS (%) | J2: CSSL (%) | K2: IR (%) | L2: T=Tributos (%) | M2: BDI Total (%)
A3: MÃO DE OBRA | B3: 5 | C3: 1.5 | D3: 1 | E3: 0 | F3: 9 | G3: 3 | H3: 5 | I3: 0.65 | J3: 1.99 | K3: 2.74 | L3: 13.38 | M3: 34.5
A4: MATERIAL | B4: 5 | C4: 0 | D4: 0 | E4: 0 | F4: 0 | G4: 0 | H4: 0 | I4: 0 | J4: 0 | K4: 0 | L4: 0 | M4: 5
A5: SERVIÇOS | B5: 5 | C5: 1.5 | D5: 1 | E5: 0 | F5: 9 | G5: 3 | H5: 5 | I5: 0.65 | J5: 1.99 | K5: 2.74 | L5: 13.38 | M5: 34.5
A6: INDIRETO | B6: 4 | C6: 0 | D6: 0 | E6: 0 | F6: 2 | G6: 3 | H6: 5 | I6: 0.65 | J6: 1.99 | K6: 2.74 | L6: 13.38 | M6: 22.37
A7: DIESEL | B7: 4 | C7: 0 | D7: 0 | E7: 0 | F7: 5 | G7: 3 | H7: 5 | I7: 0.65 | J7: 1.99 | K7: 2.74 | L7: 13.38 | M7: 25.84
A9: Fórmula: BDI = (1 + AC + DF + R + CR + L) / (1 - T) - 1 | T = COFINS+ISS+PIS+CSSL+IR

Sheet DIRETOS.DET
A1: DIRETOS — EQUIPES E RECURSOS
A2: Tipo | B2: Código | C2: Descrição | D2: Papel | E2: Qtd | F2: Custo Unit/Mês (R$) | G2: Custo Total/Mês (R$) | H2: Perm. (meses) | I2: Custo Total (R$)
A3: eap-1_0 — Desmatamento e limpeza de area vegetada
A4: MÃO DE OBRA | B4: P0040 | C4: Operador de Escavadeira | D4: DIRETO | E4: 1 | F4: 10300 | G4: =E4*F4 | H4: 5.75 | I4: =G4*H4
A5: MÃO DE OBRA | B5: P0048 | C5: Operador de Trator de Esteiras | D5: DIRETO | E5: 6 | F5: 10300 | G5: =E5*F5 | H5: 5.75 | I5: =G5*H5
A6: MÃO DE OBRA | B6: P0062 | C6: Operador de motosserra | D6: DIRETO | E6: 6 | F6: 7307.65 | G6: =E6*F6 | H6: 5.75 | I6: =G6*H6
A7: MÃO DE OBRA | B7: P0001 | C7: Ajudante | D7: DIRETO | E7: 6 | F7: 4209.32 | G7: =E7*F7 | H7: 5.75 | I7: =G7*H7
A8: MÃO DE OBRA | B8: P0079 | C8: SINALEIRO | D8: DIRETO | E8: 6 | F8: 6341.17 | G8: =E8*F8 | H8: 5.75 | I8: =G8*H8
A9: MÃO DE OBRA | B9: P0065 | C9: Encarregado de Frente | D9: DIRETO | E9: 1 | F9: 7500 | G9: =E9*F9 | H9: 5.75 | I9: =G9*H9
A10: MÃO DE OBRA | B10: P0072 | C10: Apontador | D10: DIRETO | E10: 1 | F10: 6341.17 | G10: =E10*F10 | H10: 5.75 | I10: =G10*H10
A11: EQUIPAMENTO | B11: EQ-E0016 | C11: Escavadeira Hidráulica 22t | D11: — | E11: 1 | F11: 35639.3 | G11: =E11*F11 | H11: 5.75 | I11: =G11*H11
A12: EQUIPAMENTO | B12: EQ-E0035 | C12: Trator de esteiras 20T | D12: — | E12: 6 | F12: 21683.2 | G12: =E12*F12 | H12: 5.75 | I12: =G12*H12
A13: COMBUSTÍVEL | B13: EQ-E0035 | C13: Diesel S-10 (18.0 L/h) | D13: — | E13: 6 | F13: 22957.71 | G13: =E13*F13 | H13: 5.75 | I13: =G13*H13
A14: Subtotal eap-1_0 | G14: =SUM(G4:G13) | H14: 5.75 | I14: =SUM(I4:I13)
A15: eap-1_1 — Esc/carg/transp 1aCat DMT<=2000m
A16: MÃO DE OBRA | B16: P0040 | C16: Operador de Escavadeira | D16: DIRETO | E16: 1 | F16: 10300 | G16: =E16*F16 | H16: 10.35 | I16: =G16*H16
A17: MÃO DE OBRA | B17: P0001 | C17: Ajudante | D17: DIRETO | E17: 1 | F17: 4209.32 | G17: =E17*F17 | H17: 10.35 | I17: =G17*H17
A18: MÃO DE OBRA | B18: P0065 | C18: Encarregado de Frente | D18: DIRETO | E18: 1 | F18: 7500 | G18: =E18*F18 | H18: 10.35 | I18: =G18*H18
A19: MÃO DE OBRA | B19: P0032 | C19: Motorista de Caminhão Basculante | D19: DIRETO | E19: 7 | F19: 6341.17 | G19: =E19*F19 | H19: 10.35 | I19: =G19*H19
A20: EQUIPAMENTO | B20: EQ-E0016 | C20: Escavadeira Hidráulica 22t | D20: — | E20: 1 | F20: 35639.3 | G20: =E20*F20 | H20: 10.35 | I20: =G20*H20
A21: Subtotal eap-1_1 | G21: =SUM(G16:G20) | H21: 10.35 | I21: =SUM(I16:I20)
A22: eap-1_2 — Esc/carg/transp 1aCat DMT<=3000m
A23: MÃO DE OBRA | B23: P0040 | C23: Operador de Escavadeira | D23: DIRETO | E23: 1 | F23: 10300 | G23: =E23*F23 | H23: 10.35 | I23: =G23*H23
A24: MÃO DE OBRA | B24: P0032 | C24: Motorista de Caminhão Basculante | D24: DIRETO | E24: 7 | F24: 6341.17 | G24: =E24*F24 | H24: 10.35 | I24: =G24*H24
A25: MÃO DE OBRA | B25: P0001 | C25: Ajudante | D25: DIRETO | E25: 1 | F25: 4209.32 | G25: =E25*F25 | H25: 10.35 | I25: =G25*H25
A26: MÃO DE OBRA | B26: P0065 | C26: Encarregado de Frente | D26: DIRETO | E26: 1 | F26: 7500 | G26: =E26*F26 | H26: 10.35 | I26: =G26*H26
A27: EQUIPAMENTO | B27: EQ-E0016 | C27: Escavadeira Hidráulica 22t | D27: — | E27: 1 | F27: 35639.3 | G27: =E27*F27 | H27: 10.35 | I27: =G27*H27
A28: Subtotal eap-1_2 | G28: =SUM(G23:G27) | H28: 10.35 | I28: =SUM(I23:I27)
A29: eap-1_3 — Esc/carg/transp 2aCat DMT<=2000m
A30: MÃO DE OBRA | B30: P0040 | C30: Operador de Escavadeira | D30: DIRETO | E30: 2 | F30: 10300 | G30: =E30*F30 | H30: 11.73 | I30: =G30*H30
A31: MÃO DE OBRA | B31: P0032 | C31: Motorista de Caminhão Basculante | D31: DIRETO | E31: 11 | F31: 6341.17 | G31: =E31*F31 | H31: 11.73 | I31: =G31*H31
A32: MÃO DE OBRA | B32: P0001 | C32: Ajudante | D32: DIRETO | E32: 2 | F32: 4209.32 | G32: =E32*F32 | H32: 11.73 | I32: =G32*H32
A33: MÃO DE OBRA | B33: P0065 | C33: Encarregado de Frente | D33: DIRETO | E33: 1 | F33: 7500 | G33: =E33*F33 | H33: 11.73 | I33: =G33*H33
A34: EQUIPAMENTO | B34: EQ-E0016 | C34: Escavadeira Hidráulica 22t | D34: — | E34: 2 | F34: 35639.3 | G34: =E34*F34 | H34: 11.73 | I34: =G34*H34
A35: Subtotal eap-1_3 | G35: =SUM(G30:G34) | H35: 11.73 | I35: =SUM(I30:I34)
A36: eap-1_4 — Esc/carg/transp 2aCat DMT<=3000m
A37: MÃO DE OBRA | B37: P0040 | C37: Operador de Escavadeira | D37: DIRETO | E37: 2 | F37: 10300 | G37: =E37*F37 | H37: 11.73 | I37: =G37*H37
A38: MÃO DE OBRA | B38: P0032 | C38: Motorista de Caminhão Basculante | D38: DIRETO | E38: 11 | F38: 6341.17 | G38: =E38*F38 | H38: 11.73 | I38: =G38*H38
A39: MÃO DE OBRA | B39: P0001 | C39: Ajudante | D39: DIRETO | E39: 2 | F39: 4209.32 | G39: =E39*F39 | H39: 11.73 | I39: =G39*H39
A40: MÃO DE OBRA | B40: P0065 | C40: Encarregado de Frente | D40: DIRETO | E40: 1 | F40: 7500 | G40: =E40*F40 | H40: 11.73 | I40: =G40*H40
A41: EQUIPAMENTO | B41: EQ-E0016 | C41: Escavadeira Hidráulica 22t | D41: — | E41: 2 | F41: 35639.3 | G41: =E41*F41 | H41: 11.73 | I41: =G41*H41
A42: Subtotal eap-1_4 | G42: =SUM(G37:G41) | H42: 11.73 | I42: =SUM(I37:I41)
A43: eap-1_5 — Esc/carg/transp 3aCat DMT<=2000m
A44: MÃO DE OBRA | B44: P0040 | C44: Operador de Escavadeira | D44: DIRETO | E44: 4 | F44: 10300 | G44: =E44*F44 | H44: 11.27 | I44: =G44*H44
A45: MÃO DE OBRA | B45: P0032 | C45: Motorista de Caminhão Basculante | D45: DIRETO | E45: 25 | F45: 6341.17 | G45: =E45*F45 | H45: 11.27 | I45: =G45*H45
A46: MÃO DE OBRA | B46: P0001 | C46: Ajudante | D46: DIRETO | E46: 4 | F46: 4209.32 | G46: =E46*F46 | H46: 11.27 | I46: =G46*H46
A47: EQUIPAMENTO | B47: EQ-E0016 | C47: Escavadeira Hidráulica 22t | D47: — | E47: 4 | F47: 35639.3 | G47: =E47*F47 | H47: 11.27 | I47: =G47*H47
A48: Subtotal eap-1_5 | G48: =SUM(G44:G47) | H48: 11.27 | I48: =SUM(I44:I47)
A49: eap-1_6 — Esc/carg/transp 3aCat DMT<=3000m
A50: MÃO DE OBRA | B50: P0040 | C50: Operador de Escavadeira | D50: DIRETO | E50: 4 | F50: 10300 | G50: =E50*F50 | H50: 11.27 | I50: =G50*H50
A51: MÃO DE OBRA | B51: P0032 | C51: Motorista de Caminhão Basculante | D51: DIRETO | E51: 25 | F51: 6341.17 | G51: =E51*F51 | H51: 11.27 | I51: =G51*H51
A52: MÃO DE OBRA | B52: P0001 | C52: Ajudante | D52: DIRETO | E52: 4 | F52: 4209.32 | G52: =E52*F52 | H52: 11.27 | I52: =G52*H52
A53: EQUIPAMENTO | B53: EQ-E0016 | C53: Escavadeira Hidráulica 22t | D53: — | E53: 4 | F53: 35639.3 | G53: =E53*F53 | H53: 11.27 | I53: =G53*H53
A54: Subtotal eap-1_6 | G54: =SUM(G50:G53) | H54: 11.27 | I54: =SUM(I50:I53)
A55: eap-1_7 — Compactacao aterros 100% Proctor Normal
A56: MÃO DE OBRA | B56: P0043 | C56: Operador de Motoniveladora | D56: DIRETO | E56: 3 | F56: 10300 | G56: =E56*F56 | H56: 11.73 | I56: =G56*H56
A57: MÃO DE OBRA | B57: P0049 | C57: Operador de Trator de Pneu | D57: DIRETO | E57: 3 | F57: 6341.17 | G57: =E57*F57 | H57: 11.73 | I57: =G57*H57
A58: MÃO DE OBRA | B58: P0033 | C58: Motorista de Caminhão Pipa | D58: DIRETO | E58: 3 | F58: 6341.17 | G58: =E58*F58 | H58: 11.73 | I58: =G58*H58
A59: MÃO DE OBRA | B59: P0046 | C59: Operador de Rolo Compactador | D59: DIRETO | E59: 6 | F59: 6341.17 | G59: =E59*F59 | H59: 11.73 | I59: =G59*H59
A60: MÃO DE OBRA | B60: P0001 | C60: Ajudante | D60: DIRETO | E60: 6 | F60: 4209.32 | G60: =E60*F60 | H60: 11.73 | I60: =G60*H60
A61: MÃO DE OBRA | B61: P0029 | C61: Gredista | D61: DIRETO | E61: 3 | F61: 6341.17 | G61: =E61*F61 | H61: 11.73 | I61: =G61*H61
A62: MÃO DE OBRA | B62: P0065 | C62: Encarregado de Frente | D62: DIRETO | E62: 2 | F62: 7500 | G62: =E62*F62 | H62: 11.73 | I62: =G62*H62
A63: EQUIPAMENTO | B63: EQ-E0028 | C63: Motoniveladora 120HP | D63: — | E63: 3 | F63: 36664.32 | G63: =E63*F63 | H63: 11.73 | I63: =G63*H63
A64: COMBUSTÍVEL | B64: EQ-E0028 | C64: Diesel S-10 (9.0 L/h) | D64: — | E64: 3 | F64: 11478.86 | G64: =E64*F64 | H64: 11.73 | I64: =G64*H64
A65: EQUIPAMENTO | B65: EQ-E0034 | C65: Trator de pneus com grade | D65: — | E65: 3 | F65: 7744 | G65: =E65*F65 | H65: 11.73 | I65: =G65*H65
A66: COMBUSTÍVEL | B66: EQ-E0034 | C66: Diesel S-10 (8.0 L/h) | D66: — | E66: 3 | F66: 10203.43 | G66: =E66*F66 | H66: 11.73 | I66: =G66*H66
A67: Subtotal eap-1_7 | G67: =SUM(G56:G66) | H67: 11.73 | I67: =SUM(I56:I66)
A68: eap-1_8 — Compactacao aterros 100% Proctor Intermediario
A69: MÃO DE OBRA | B69: P0043 | C69: Operador de Motoniveladora | D69: DIRETO | E69: 3 | F69: 10300 | G69: =E69*F69 | H69: 0.69 | I69: =G69*H69
A70: MÃO DE OBRA | B70: P0049 | C70: Operador de Trator de Pneu | D70: DIRETO | E70: 3 | F70: 6341.17 | G70: =E70*F70 | H70: 0.69 | I70: =G70*H70
A71: MÃO DE OBRA | B71: P0033 | C71: Motorista de Caminhão Pipa | D71: DIRETO | E71: 3 | F71: 6341.17 | G71: =E71*F71 | H71: 0.69 | I71: =G71*H71
A72: MÃO DE OBRA | B72: P0046 | C72: Operador de Rolo Compactador | D72: DIRETO | E72: 6 | F72: 6341.17 | G72: =E72*F72 | H72: 0.69 | I72: =G72*H72
A73: MÃO DE OBRA | B73: P0001 | C73: Ajudante | D73: DIRETO | E73: 6 | F73: 4209.32 | G73: =E73*F73 | H73: 0.69 | I73: =G73*H73
A74: MÃO DE OBRA | B74: P0029 | C74: Gredista | D74: DIRETO | E74: 3 | F74: 6341.17 | G74: =E74*F74 | H74: 0.69 | I74: =G74*H74
A75: MÃO DE OBRA | B75: P0065 | C75: Encarregado de Frente | D75: DIRETO | E75: 2 | F75: 7500 | G75: =E75*F75 | H75: 0.69 | I75: =G75*H75
A76: EQUIPAMENTO | B76: EQ-E0028 | C76: Motoniveladora 120HP | D76: — | E76: 3 | F76: 36664.32 | G76: =E76*F76 | H76: 0.69 | I76: =G76*H76
A77: COMBUSTÍVEL | B77: EQ-E0028 | C77: Diesel S-10 (9.0 L/h) | D77: — | E77: 3 | F77: 11478.86 | G77: =E77*F77 | H77: 0.69 | I77: =G77*H77
A78: EQUIPAMENTO | B78: EQ-E0034 | C78: Trator de pneus com grade | D78: — | E78: 3 | F78: 7744 | G78: =E78*F78 | H78: 0.69 | I78: =G78*H78
A79: COMBUSTÍVEL | B79: EQ-E0034 | C79: Diesel S-10 (8.0 L/h) | D79: — | E79: 3 | F79: 10203.43 | G79: =E79*F79 | H79: 0.69 | I79: =G79*H79
A80: Subtotal eap-1_8 | G80: =SUM(G69:G79) | H80: 0.69 | I80: =SUM(I69:I79)
A81: eap-1_9 — Construcao corpo aterro material 3a categoria
A82: MÃO DE OBRA | B82: P0048 | C82: Operador de Trator de Esteiras | D82: DIRETO | E82: 2 | F82: 10300 | G82: =E82*F82 | H82: 11.96 | I82: =G82*H82
A83: MÃO DE OBRA | B83: P0046 | C83: Operador de Rolo Compactador | D83: DIRETO | E83: 4 | F83: 6341.17 | G83: =E83*F83 | H83: 11.96 | I83: =G83*H83
A84: MÃO DE OBRA | B84: P0001 | C84: Ajudante | D84: DIRETO | E84: 4 | F84: 4209.32 | G84: =E84*F84 | H84: 11.96 | I84: =G84*H84
A85: MÃO DE OBRA | B85: P0029 | C85: Gredista | D85: DIRETO | E85: 2 | F85: 6341.17 | G85: =E85*F85 | H85: 11.96 | I85: =G85*H85
A86: MÃO DE OBRA | B86: P0065 | C86: Encarregado de Frente | D86: DIRETO | E86: 1 | F86: 7500 | G86: =E86*F86 | H86: 11.96 | I86: =G86*H86
A87: EQUIPAMENTO | B87: EQ-E0037 | C87: Trator de esteiras 40T | D87: — | E87: 2 | F87: 20421.63 | G87: =E87*F87 | H87: 11.96 | I87: =G87*H87
A88: COMBUSTÍVEL | B88: EQ-E0037 | C88: Diesel S-10 (24.0 L/h) | D88: — | E88: 2 | F88: 30610.29 | G88: =E88*F88 | H88: 11.96 | I88: =G88*H88
A89: Subtotal eap-1_9 | G89: =SUM(G82:G88) | H89: 11.96 | I89: =SUM(I82:I88)
A90: eap-1_10 — Compactacao camada final aterro sobre rocha
A91: MÃO DE OBRA | B91: P0048 | C91: Operador de Trator de Esteiras | D91: DIRETO | E91: 1 | F91: 10300 | G91: =E91*F91 | H91: 1.38 | I91: =G91*H91
A92: MÃO DE OBRA | B92: P0046 | C92: Operador de Rolo Compactador | D92: DIRETO | E92: 3 | F92: 6341.17 | G92: =E92*F92 | H92: 1.38 | I92: =G92*H92
A93: MÃO DE OBRA | B93: P0033 | C93: Motorista de Caminhão Pipa | D93: DIRETO | E93: 1 | F93: 6341.17 | G93: =E93*F93 | H93: 1.38 | I93: =G93*H93
A94: MÃO DE OBRA | B94: P0001 | C94: Ajudante | D94: DIRETO | E94: 2 | F94: 4209.32 | G94: =E94*F94 | H94: 1.38 | I94: =G94*H94
A95: EQUIPAMENTO | B95: EQ-E0035 | C95: Trator de esteiras 20T | D95: — | E95: 1 | F95: 21683.2 | G95: =E95*F95 | H95: 1.38 | I95: =G95*H95
A96: COMBUSTÍVEL | B96: EQ-E0035 | C96: Diesel S-10 (18.0 L/h) | D96: — | E96: 1 | F96: 22957.71 | G96: =E96*F96 | H96: 1.38 | I96: =G96*H96
A97: Subtotal eap-1_10 | G97: =SUM(G91:G96) | H97: 1.38 | I97: =SUM(I91:I96)
A99: TOTAL DIRETO | I99: =I14+I21+I28+I35+I42+I48+I54+I67+I80+I89+I97

Sheet DIRETOS.RES
A1: DIRETOS RESUMIDO — COMPONENTES MO/EQ/COMB/MAT s/BDI e c/BDI
A2: Item ID | B2: Descrição | C2: Un. | D2: Quantitativo | E2: MO s/BDI | F2: EQ s/BDI | G2: Comb. s/BDI | H2: MAT s/BDI | I2: Total s/BDI | J2: MO c/BDI | K2: EQ c/BDI | L2: Comb. c/BDI | M2: MAT c/BDI | N2: Total c/BDI
A3: eap-1_0 | B3: Desmatamento e limpeza de area vegetada | C3: m2 | D3: 2400000 | E3: 1390675.2 | F3: 0 | G3: 706032 | H3: 0 | I3: 2096707.2 | J3: 1794767.9 | K3: 0 | L3: 734273.28 | M3: 0 | N3: 2529041.1
A4: eap-1_1 | B4: Esc/carg/transp 1aCat DMT<=2000m | C4: m3 | D4: 107463.11 | E4: 316847.44 | F4: 0 | G4: 506137.58 | H4: 0 | I4: 822985.02 | J4: 408914.76 | K4: 0 | L4: 526383.08 | M4: 0 | N4: 935297.84
A5: eap-1_2 | B5: Esc/carg/transp 1aCat DMT<=3000m | C5: m3 | D5: 336915.09 | E5: 1106689.3 | F5: 0 | G5: 1743983.7 | H5: 0 | I5: 2850673 | J5: 1428263.3 | K5: 0 | L5: 1813743.1 | M5: 0 | N5: 3242006.4
A6: eap-1_3 | B6: Esc/carg/transp 2aCat DMT<=2000m | C6: m3 | D6: 105311.33 | E6: 405065.09 | F6: 0 | G6: 657938.66 | H6: 0 | I6: 1063003.7 | J6: 522766.06 | K6: 0 | L6: 684256.2 | M6: 0 | N6: 1207022.3
A7: eap-1_4 | B7: Esc/carg/transp 2aCat DMT<=3000m | C7: m3 | D7: 585945.77 | E7: 2353941 | F7: 0 | G7: 3883884.1 | H7: 0 | I7: 6237825.1 | J7: 3037932.7 | K7: 0 | L7: 4039239.5 | M7: 0 | N7: 7077172.2
A8: eap-1_5 | B8: Esc/carg/transp 3aCat DMT<=2000m | C8: m3 | D8: 304634.46 | E8: 1579816.6 | F8: 0 | G8: 2950561.4 | H8: 0 | I8: 4530378 | J8: 2038868.7 | K8: 0 | L8: 3068583.9 | M8: 0 | N8: 5107452.5
A9: eap-1_6 | B9: Esc/carg/transp 3aCat DMT<=3000m | C9: m3 | D9: 676519.04 | E9: 4349961.3 | F9: 0 | G9: 7979214 | H9: 0 | I9: 12329175 | J9: 5613942.6 | K9: 0 | L9: 8298382.6 | M9: 0 | N9: 13912325
A10: eap-1_7 | B10: Compactacao aterros 100% Proctor Normal | C10: m3 | D10: 1135635.3 | E10: 3333102.1 | F10: 0 | G10: 7037169.7 | H10: 0 | I10: 10370272 | J10: 4301611.6 | K10: 0 | L10: 7318656.5 | M10: 0 | N10: 11620268
A11: eap-1_8 | B11: Compactacao aterros 100% Proctor Intermediario | C11: m3 | D11: 29411 | E11: 112866.01 | F11: 0 | G11: 238293.75 | H11: 0 | I11: 351159.75 | J11: 145661.82 | K11: 0 | L11: 247825.5 | M11: 0 | N11: 393487.32
A12: eap-1_9 | B12: Construcao corpo aterro material 3a categoria | C12: m3 | D12: 981153.5 | E12: 1768479.1 | F12: 0 | G12: 3993867.7 | H12: 0 | I12: 5762346.9 | J12: 2282351.4 | K12: 0 | L12: 4153622.5 | M12: 0 | N12: 6435973.9
A13: eap-1_10 | B13: Compactacao camada final aterro sobre rocha | C13: m3 | D13: 24721.17 | E13: 216935.21 | F13: 0 | G13: 139968.79 | H13: 0 | I13: 356904.01 | J13: 279970.73 | K13: 0 | L13: 145567.54 | M13: 0 | N13: 425538.27
A15: TOTAL DIRETO | E15: =SUM(E3:E14) | F15: =SUM(F3:F14) | G15: =SUM(G3:G14) | H15: =SUM(H3:H14) | I15: =SUM(I3:I14) | J15: =SUM(J3:J14) | K15: =SUM(K3:K14) | L15: =SUM(L3:L14) | ... N15: =SUM(N3:N14)

Sheet INDIRETOS.DET
A1: INDIRETOS — CUSTOS INDIRETOS DETALHADOS
A2: Categoria | B2: Tipo | C2: Código/Função | D2: Descrição | E2: Qtd | F2: Custo Mensal (R$) | G2: Perm. (m) | H2: Custo Total (R$)
A3: ADM — Administracao de obra
A4: ADM | B4: CUSTO TOTAL | C4: — | D4: Administracao de obra | E4: 1 | F4: 0 | G4: 12.93 | H4: 13695825
A5: Subtotal ADM | H5: =SUM(H4:H4)
A6: TOP — Topografia
A7: TOP | B7: CUSTO TOTAL | C7: — | D7: Topografia | E7: 1 | F7: 0 | G7: 12.93 | H7: 858758.32
A8: Subtotal TOP | H8: =SUM(H7:H7)
A9: LAB — Laboratorio de solos e materiais
A10: LAB | B10: CUSTO TOTAL | C10: — | D10: Laboratorio de solos e materiais | E10: 1 | F10: 0 | G10: 12.93 | H10: 139568.24
A11: Subtotal LAB | H11: =SUM(H10:H10)
A12: QSMS — Qualidade, Saude, Seguranca e Meio Ambiente
A13: QSMS | B13: CUSTO TOTAL | C13: — | D13: Qualidade, Saude, Seguranca e Meio Ambiente | E13: 1 | F13: 0 | G13: 12.93 | H13: 755777.68
A14: Subtotal QSMS | H14: =SUM(H13:H13)
A15: MOB — Mobilizacao e desmobilizacao
A16: MOB | B16: CUSTO TOTAL | C16: — | D16: Mobilizacao e desmobilizacao | E16: 1 | F16: 0 | G16: 13 | H16: 4054600.4
A17: Subtotal MOB | H17: =SUM(H16:H16)
A19: TOTAL INDIRETO | H19: =H5+H8+H11+H14+H17
A22: Distribuição Mensal de Indiretos
A23: Mês | B23: Despesa Indireta (R$)
A24: Jun/26 | B24: 5342094.6
A25: Jul/26 | B25: 1287494.1
A26: Ago/26 | B26: 1287494.1
A27: Set/26 | B27: 1287494.1
A28: Out/26 | B28: 1287494.1
A29: Nov/26 | B29: 1287494.1
A30: Dez/26 | B30: 1287494.1
A31: Jan/27 | B31: 1287494.1
A32: Fev/27 | B32: 1287494.1
A33: Mar/27 | B33: 1287494.1
A34: Abr/27 | B34: 1287494.1
A35: Mai/27 | B35: 1287494.1

Sheet INDIRETOS.RES
A1: INDIRETOS RESUMIDO — CATEGORIAS + INDICADORES
A2: Categoria | B2: Descrição | C2: Custo s/BDI (R$) | D2: BDI (%) | E2: Custo c/BDI (R$) | F2: % do Total
A3: ADM | B3: Administracao de obra | C3: 13695825 | D3: 22.37 | E3: 16760075 | F3: 70.22
A4: TOP | B4: Topografia | C4: 858758.32 | D4: 22.37 | E4: 1050893.5 | F4: 4.4
A5: LAB | B5: Laboratorio de solos e materiais | C5: 139568.24 | D5: 22.37 | E5: 170794.68 | F5: 0.72
A6: QSMS | B6: Qualidade, Saude, Seguranca e Meio Ambiente | C6: 755777.68 | D6: 22.37 | E6: 924872.36 | F6: 3.87
A7: MOB | B7: Mobilizacao e desmobilizacao | C7: 4054600.4 | D7: 22.37 | E7: 4961760.5 | F7: 20.79
A9: TOTAL INDIRETO | C9: =C3+C4+C5+C6+C7 | E9: =E3+E4+E5+E6+E7
A12: INDICADORES DE COMPOSIÇÃO DE CUSTO
A13: TOTAL DIRETO (catálogo s/BDI) | C13: 46771430
A14: TOTAL INDIRETO s/BDI | C14: 19504530
A15: RAZÃO CI / CD | C15: 41.7
A16: PREÇO DE VENDA TOTAL | C16: 76753981
A17: CI / PVT | C17: 25.41

Sheet PLANEJAMENTO
A1: PLANEJAMENTO — ORÇAMENTO POR EAP (COMPONENTES s/BDI e c/BDI)
A2: Item ID | B2: Descrição | C2: Un. | D2: Quantitativo | E2: MO s/BDI (R$) | F2: MO c/BDI (R$) | G2: EQ s/BDI (R$) | H2: EQ c/BDI (R$) | I2: Comb. s/BDI (R$) | J2: Comb. c/BDI (R$) | K2: MAT s/BDI (R$) | L2: MAT c/BDI (R$) | M2: Total s/BDI (R$) | N2: Total c/BDI (R$) | O2: Criticidade
A3: eap-1_0 | B3: Desmatamento e limpeza de area vegetada | C3: m2 | D3: 2400000 | E3: 1390675.2 | F3: =E3*(1+BDI!$M$3) | G3: 0 | H3: =G3*(1+BDI!$M$5) | I3: 706032 | J3: =I3*(1+BDI!$M$7) | K3: 0 | L3: =K3*(1+BDI!$M$4) | M3: =E3+G3+I3+K3 | N3: =F3+H3+J3+L3 | O3: B
A4: eap-1_1 | B4: Esc/carg/transp 1aCat DMT<=2000m | C4: m3 | D4: 107463.11 | E4: 316847.44 | F4: =E4*(1+BDI!$M$3) | G4: 0 | H4: =G4*(1+BDI!$M$5) | I4: 506137.58 | J4: =I4*(1+BDI!$M$7) | K4: 0 | L4: =K4*(1+BDI!$M$4) | M4: =E4+G4+I4+K4 | N4: =F4+H4+J4+L4 | O4: C
A5: eap-1_2 | B5: Esc/carg/transp 1aCat DMT<=3000m | C5: m3 | D5: 336915.09 | E5: 1106689.3 | F5: =E5*(1+BDI!$M$3) | G5: 0 | H5: =G5*(1+BDI!$M$5) | I5: 1743983.7 | J5: =I5*(1+BDI!$M$7) | K5: 0 | L5: =K5*(1+BDI!$M$4) | M5: =E5+G5+I5+K5 | N5: =F5+H5+J5+L5 | O5: C
A6: eap-1_3 | B6: Esc/carg/transp 2aCat DMT<=2000m | C6: m3 | D6: 105311.33 | E6: 405065.09 | F6: =E6*(1+BDI!$M$3) | G6: 0 | H6: =G6*(1+BDI!$M$5) | I6: 657938.66 | J6: =I6*(1+BDI!$M$7) | K6: 0 | L6: =K6*(1+BDI!$M$4) | M6: =E6+G6+I6+K6 | N6: =F6+H6+J6+L6 | O6: C
A7: eap-1_4 | B7: Esc/carg/transp 2aCat DMT<=3000m | C7: m3 | D7: 585945.77 | E7: 2353941 | F7: =E7*(1+BDI!$M$3) | G7: 0 | H7: =G7*(1+BDI!$M$5) | I7: 3883884.1 | J7: =I7*(1+BDI!$M$7) | K7: 0 | L7: =K7*(1+BDI!$M$4) | M7: =E7+G7+I7+K7 | N7: =F7+H7+J7+L7 | O7: C
A8: eap-1_5 | B8: Esc/carg/transp 3aCat DMT<=2000m | C8: m3 | D8: 304634.46 | E8: 1579816.6 | F8: =E8*(1+BDI!$M$3) | G8: 0 | H8: =G8*(1+BDI!$M$5) | I8: 2950561.4 | J8: =I8*(1+BDI!$M$7) | K8: 0 | L8: =K8*(1+BDI!$M$4) | M8: =E8+G8+I8+K8 | N8: =F8+H8+J8+L8 | O8: A
A9: eap-1_6 | B9: Esc/carg/transp 3aCat DMT<=3000m | C9: m3 | D9: 676519.04 | E9: 4349961.3 | F9: =E9*(1+BDI!$M$3) | G9: 0 | H9: =G9*(1+BDI!$M$5) | I9: 7979214 | J9: =I9*(1+BDI!$M$7) | K9: 0 | L9: =K9*(1+BDI!$M$4) | M9: =E9+G9+I9+K9 | N9: =F9+H9+J9+L9 | O9: A
A10: eap-1_7 | B10: Compactacao aterros 100% Proctor Normal | C10: m3 | D10: 1135635.3 | E10: 3333102.1 | F10: =E10*(1+BDI!$M$3) | G10: 0 | H10: =G10*(1+BDI!$M$5) | I10: 7037169.7 | J10: =I10*(1+BDI!$M$7) | K10: 0 | L10: =K10*(1+BDI!$M$4) | M10: =E10+G10+I10+K10 | N10: =F10+H10+J10+L10 | O10: B
A11: eap-1_8 | B11: Compactacao aterros 100% Proctor Intermediario | C11: m3 | D11: 29411 | E11: 112866.01 | F11: =E11*(1+BDI!$M$3) | G11: 0 | H11: =G11*(1+BDI!$M$5) | I11: 238293.75 | J11: =I11*(1+BDI!$M$7) | K11: 0 | L11: =K11*(1+BDI!$M$4) | M11: =E11+G11+I11+K11 | N11: =F11+H11+J11+L11 | O11: C
A12: eap-1_9 | B12: Construcao corpo aterro material 3a categoria | C12: m3 | D12: 981153.5 | E12: 1768479.1 | F12: =E12*(1+BDI!$M$3) | G12: 0 | H12: =G12*(1+BDI!$M$5) | I12: 3993867.7 | J12: =I12*(1+BDI!$M$7) | K12: 0 | L12: =K12*(1+BDI!$M$4) | M12: =E12+G12+I12+K12 | N12: =F12+H12+J12+L12 | O12: B
A13: eap-1_10 | B13: Compactacao camada final aterro sobre rocha | C13: m3 | D13: 24721.17 | E13: 216935.21 | F13: =E13*(1+BDI!$M$3) | G13: 0 | H13: =G13*(1+BDI!$M$5) | I13: 139968.79 | J13: =I13*(1+BDI!$M$7) | K13: 0 | L13: =K13*(1+BDI!$M$4) | M13: =E13+G13+I13+K13 | N13: =F13+H13+J13+L13 | O13: C
A15: TOTAL | E15: =SUM(E3:E14) | F15: =SUM(F3:F14) | G15: =SUM(G3:G14) | H15: =SUM(H3:H14) | I15: =SUM(I3:I14) | J15: =SUM(J3:J14) | K15: =SUM(K3:K14) | L15: =SUM(L3:L14) | ... N15: =SUM(N3:N14)

Sheet CRONOGRAMA.DET
A1: CRONOGRAMA SEMANAL — ACOMPANHAMENTO FÍSICO DE PRODUÇÃO
A2: Item ID | B2: Descrição | C2: Un. | D2: Quantitativo | E2: Métrica | F2: 08/Jun | G2: 15/Jun | H2: 22/Jun | I2: 29/Jun | J2: 06/Jul | K2: 13/Jul | L2: 20/Jul | M2: 27/Jul | N2: 03/Ago | O2: 10/Ago | P2: 17/Ago | Q2: 24/Ago | R2: 31/Ago | S2: 07/Set | T2: 14/Set | U2: 21/Set | V2: 28/Set | W2: 05/Out | X2: 12/Out | Y2: 19/Out | Z2: 26/Out | AA2: 02/Nov | AB2: 09/Nov | AC2: 16/Nov | AD2: 23/Nov | AE2: 30/Nov | AF2: 07/Dez | AG2: 14/Dez | AH2: 21/Dez | AI2: 28/Dez | AJ2: 04/Jan | AK2: 11/Jan | AL2: 18/Jan | AM2: 25/Jan | AN2: 01/Fev | AO2: 08/Fev | AP2: 15/Fev | AQ2: 22/Fev | AR2: 01/Mar | AS2: 08/Mar | AT2: 15/Mar | AU2: 22/Mar | AV2: 29/Mar | AW2: 05/Abr | AX2: 12/Abr | AY2: 19/Abr | AZ2: 26/Abr | BA2: 03/Mai | BB2: 10/Mai | BC2: 17/Mai | BD2: 24/Mai | BE2: 31/Mai
E3: Praticabilidade | F3: 1 | G3: 1 | H3: 1 | I3: 1 | J3: 1 | K3: 1 | L3: 1 | M3: 1 | N3: 1 | O3: 1 | P3: 1 | Q3: 1 | R3: 1 | S3: 1 | T3: 1 | U3: 1 | V3: 1 | W3: 1 | X3: 1 | Y3: 1 | Z3: 1 | AA3: 1 | AB3: 1 | AC3: 1 | AD3: 1 | AE3: 1 | AF3: 1 | AG3: 1 | AH3: 1 | AI3: 1 | AJ3: 1 | AK3: 1 | AL3: 1 | AM3: 1 | AN3: 1 | AO3: 1 | AP3: 1 | AQ3: 1 | AR3: 1 | AS3: 1 | AT3: 1 | AU3: 1 | AV3: 1 | AW3: 1 | AX3: 1 | AY3: 1 | AZ3: 1 | BA3: 1 | BB3: 1 | BC3: 1 | BD3: 1 | BE3: 1
A4: eap-1_0 | B4: Desmatamento e limpeza de area vegetada | C4: m2 | D4: 2400000 | E4: Dias Trabalhados | F4: 6 | G4: 6 | H4: 6 | I4: 6 | J4: 6 | K4: 6 | L4: 6 | M4: 6 | N4: 6 | O4: 6 | P4: 6 | Q4: 6 | R4: 6 | S4: 6 | T4: 6 | U4: 6 | V4: 6 | W4: 6 | X4: 6 | Y4: 6 | Z4: 6 | AA4: 6 | AB4: 6 | AC4: 6 | AD4: 6
E5: Nº De Equipes | F5: 5 | G5: 5 | H5: 5 | I5: 5 | J5: 5 | K5: 5 | L5: 5 | M5: 5 | N5: 5 | O5: 5 | P5: 5 | Q5: 5 | R5: 5 | S5: 5 | T5: 5 | U5: 5 | V5: 5 | W5: 5 | X5: 5 | Y5: 5 | Z5: 5 | AA5: 5 | AB5: 5 | AC5: 5 | AD5: 5
E6: Qtd. Planejada | F6: 180000 | G6: 180000 | H6: 180000 | I6: 180000 | J6: 180000 | K6: 180000 | L6: 180000 | M6: 180000 | N6: 180000 | O6: 180000 | P6: 180000 | Q6: 180000 | R6: 180000 | S6: 60000
E7: Qtd Plan. Acumulada | F7: 180000 | G7: 360000 | H7: 540000 | I7: 720000 | J7: 900000 | K7: 1080000 | L7: 1260000 | M7: 1440000 | N7: 1620000 | O7: 1800000 | P7: 1980000 | Q7: 2160000 | R7: 2340000 | S7: 2400000 | T7: 2400000 | U7: 2400000 | V7: 2400000 | W7: 2400000 | X7: 2400000 | Y7: 2400000 | Z7: 2400000 | AA7: 2400000 | AB7: 2400000 | AC7: 2400000 | AD7: 2400000 | AE7: 2400000 | AF7: 2400000 | AG7: 2400000 | AH7: 2400000 | AI7: 2400000 | AJ7: 2400000 | AK7: 2400000 | AL7: 2400000 | AM7: 2400000 | AN7: 2400000 | AO7: 2400000 | AP7: 2400000 | AQ7: 2400000 | AR7: 2400000 | AS7: 2400000 | AT7: 2400000 | AU7: 2400000 | AV7: 2400000 | AW7: 2400000 | AX7: 2400000 | AY7: 2400000 | AZ7: 2400000 | BA7: 2400000 | BB7: 2400000 | BC7: 2400000 | BD7: 2400000 | BE7: 2400000
E8: % Semanal | F8: 0.075 | G8: 0.075 | H8: 0.075 | I8: 0.075 | J8: 0.075 | K8: 0.075 | L8: 0.075 | M8: 0.075 | N8: 0.075 | O8: 0.075 | P8: 0.075 | Q8: 0.075 | R8: 0.075 | S8: 0.025
E9: % Acumulado | F9: 0.075 | G9: 0.15 | H9: 0.225 | I9: 0.3 | J9: 0.375 | K9: 0.45 | L9: 0.525 | M9: 0.6 | N9: 0.675 | O9: 0.75 | P9: 0.825 | Q9: 0.9 | R9: 0.975 | S9: 1 | T9: 1 | U9: 1 | V9: 1 | W9: 1 | X9: 1 | Y9: 1 | Z9: 1 | AA9: 1 | AB9: 1 | AC9: 1 | AD9: 1 | AE9: 1 | AF9: 1 | AG9: 1 | AH9: 1 | AI9: 1 | AJ9: 1 | AK9: 1 | AL9: 1 | AM9: 1 | AN9: 1 | AO9: 1 | AP9: 1 | AQ9: 1 | AR9: 1 | AS9: 1 | AT9: 1 | AU9: 1 | AV9: 1 | AW9: 1 | AX9: 1 | AY9: 1 | AZ9: 1 | BA9: 1 | BB9: 1 | BC9: 1 | BD9: 1 | BE9: 1
A10: eap-1_1 | B10: Esc/carg/transp 1aCat DMT<=2000m | C10: m3 | D10: 107463.11 | E10: Dias Trabalhados | F10: 6 | G10: 6 | H10: 6 | I10: 6 | J10: 6 | K10: 6 | L10: 6 | M10: 6 | N10: 6 | O10: 6 | P10: 6 | Q10: 6 | R10: 6 | S10: 6 | T10: 6 | U10: 6 | V10: 6 | W10: 6 | X10: 6 | Y10: 6 | Z10: 6 | AA10: 6 | AB10: 6 | AC10: 6 | AD10: 6 | AE10: 6 | AF10: 6 | AG10: 6 | AH10: 6 | AI10: 6 | AJ10: 6 | AK10: 6 | AL10: 6 | AM10: 6 | AN10: 6 | AO10: 6 | AP10: 6 | AQ10: 6 | AR10: 6 | AS10: 6 | AT10: 6 | AU10: 6 | AV10: 6 | AW10: 6 | AX10: 6
E11: Nº De Equipes | F11: 1 | G11: 1 | H11: 1 | I11: 1 | J11: 1 | K11: 1 | L11: 1 | M11: 1 | N11: 1 | O11: 1 | P11: 1 | Q11: 1 | R11: 1 | S11: 1 | T11: 1 | U11: 1 | V11: 1 | W11: 1 | X11: 1 | Y11: 1 | Z11: 1 | AA11: 1 | AB11: 1 | AC11: 1 | AD11: 1 | AE11: 1 | AF11: 1 | AG11: 1 | AH11: 1 | AI11: 1 | AJ11: 1 | AK11: 1 | AL11: 1 | AM11: 1 | AN11: 1 | AO11: 1 | AP11: 1 | AQ11: 1 | AR11: 1 | AS11: 1 | AT11: 1 | AU11: 1 | AV11: 1 | AW11: 1 | AX11: 1
E12: Qtd. Planejada | F12: 11473.92 | G12: 11473.92 | H12: 11473.92 | I12: 11473.92 | J12: 11473.92 | K12: 11473.92 | L12: 11473.92 | M12: 11473.92 | N12: 11473.92 | O12: 4197.83
E13: Qtd Plan. Acumulada | F13: 11473.92 | G13: 22947.84 | H13: 34421.76 | I13: 45895.68 | J13: 57369.6 | K13: 68843.52 | L13: 80317.44 | M13: 91791.36 | N13: 103265.28 | O13: 107463.11 | P13: 107463.11 | Q13: 107463.11 | R13: 107463.11 | S13: 107463.11 | T13: 107463.11 | U13: 107463.11 | V13: 107463.11 | W13: 107463.11 | X13: 107463.11 | Y13: 107463.11 | Z13: 107463.11 | AA13: 107463.11 | AB13: 107463.11 | AC13: 107463.11 | AD13: 107463.11 | AE13: 107463.11 | AF13: 107463.11 | AG13: 107463.11 | AH13: 107463.11 | AI13: 107463.11 | AJ13: 107463.11 | AK13: 107463.11 | AL13: 107463.11 | AM13: 107463.11 | AN13: 107463.11 | AO13: 107463.11 | AP13: 107463.11 | AQ13: 107463.11 | AR13: 107463.11 | AS13: 107463.11 | AT13: 107463.11 | AU13: 107463.11 | AV13: 107463.11 | AW13: 107463.11 | AX13: 107463.11 | AY13: 107463.11 | AZ13: 107463.11 | BA13: 107463.11 | BB13: 107463.11 | BC13: 107463.11 | BD13: 107463.11 | BE13: 107463.11
E14: % Semanal | F14: 0.1068 | G14: 0.1068 | H14: 0.1068 | I14: 0.1068 | J14: 0.1068 | K14: 0.1068 | L14: 0.1068 | M14: 0.1068 | N14: 0.1068 | O14: 0.0391
E15: % Acumulado | F15: 0.1068 | G15: 0.2135 | H15: 0.3203 | I15: 0.4271 | J15: 0.5339 | K15: 0.6406 | L15: 0.7474 | M15: 0.8542 | N15: 0.9609 | O15: 1 | P15: 1 | Q15: 1 | R15: 1 | S15: 1 | T15: 1 | U15: 1 | V15: 1 | W15: 1 | X15: 1 | Y15: 1 | Z15: 1 | AA15: 1 | AB15: 1 | AC15: 1 | AD15: 1 | AE15: 1 | AF15: 1 | AG15: 1 | AH15: 1 | AI15: 1 | AJ15: 1 | AK15: 1 | AL15: 1 | AM15: 1 | AN15: 1 | AO15: 1 | AP15: 1 | AQ15: 1 | AR15: 1 | AS15: 1 | AT15: 1 | AU15: 1 | AV15: 1 | AW15: 1 | AX15: 1 | AY15: 1 | AZ15: 1 | BA15: 1 | BB15: 1 | BC15: 1 | BD15: 1 | BE15: 1
A16: eap-1_2 | B16: Esc/carg/transp 1aCat DMT<=3000m | C16: m3 | D16: 336915.09 | E16: Dias Trabalhados | F16: 6 | G16: 6 | H16: 6 | I16: 6 | J16: 6 | K16: 6 | L16: 6 | M16: 6 | N16: 6 | O16: 6 | P16: 6 | Q16: 6 | R16: 6 | S16: 6 | T16: 6 | U16: 6 | V16: 6 | W16: 6 | X16: 6 | Y16: 6 | Z16: 6 | AA16: 6 | AB16: 6 | AC16: 6 | AD16: 6 | AE16: 6 | AF16: 6 | AG16: 6 | AH16: 6 | AI16: 6 | AJ16: 6 | AK16: 6 | AL16: 6 | AM16: 6 | AN16: 6 | AO16: 6 | AP16: 6 | AQ16: 6 | AR16: 6 | AS16: 6 | AT16: 6 | AU16: 6 | AV16: 6 | AW16: 6 | AX16: 6
E17: Nº De Equipes | F17: 1 | G17: 1 | H17: 1 | I17: 1 | J17: 1 | K17: 1 | L17: 1 | M17: 1 | N17: 1 | O17: 1 | P17: 1 | Q17: 1 | R17: 1 | S17: 1 | T17: 1 | U17: 1 | V17: 1 | W17: 1 | X17: 1 | Y17: 1 | Z17: 1 | AA17: 1 | AB17: 1 | AC17: 1 | AD17: 1 | AE17: 1 | AF17: 1 | AG17: 1 | AH17: 1 | AI17: 1 | AJ17: 1 | AK17: 1 | AL17: 1 | AM17: 1 | AN17: 1 | AO17: 1 | AP17: 1 | AQ17: 1 | AR17: 1 | AS17: 1 | AT17: 1 | AU17: 1 | AV17: 1 | AW17: 1 | AX17: 1
E18: Qtd. Planejada | F18: 11210.02 | G18: 11210.02 | H18: 11210.02 | I18: 11210.02 | J18: 11210.02 | K18: 11210.02 | L18: 11210.02 | M18: 11210.02 | N18: 11210.02 | O18: 11210.02 | P18: 11210.02 | Q18: 11210.02 | R18: 11210.02 | S18: 11210.02 | T18: 11210.02 | U18: 11210.02 | V18: 11210.02 | W18: 10462.31 | X18: 10462.31 | Y18: 10462.31 | Z18: 10462.31 | AA18: 10486.97 | AB18: 10486.97 | AC18: 10486.97 | AD18: 10486.97 | AE18: 10486.97 | AF18: 10486.97 | AG18: 10486.97 | AH18: 10486.97 | AI18: 10486.97 | AJ18: 9401.84 | AK18: 710.91
E19: Qtd Plan. Acumulada | F19: 11210.02 | G19: 22420.04 | H19: 33630.06 | I19: 44840.08 | J19: 56050.1 | K19: 67260.12 | L19: 78470.14 | M19: 89680.16 | N19: 100890.18 | O19: 112100.2 | P19: 123310.22 | Q19: 134520.24 | R19: 145730.26 | S19: 156940.28 | T19: 168150.3 | U19: 179360.32 | V19: 190570.34 | W19: 201032.65 | X19: 211494.96 | Y19: 221957.27 | Z19: 232419.58 | AA19: 242906.56 | AB19: 253393.53 | AC19: 263880.5 | AD19: 274367.48 | AE19: 284854.45 | AF19: 295341.42 | AG19: 305828.4 | AH19: 316315.37 | AI19: 326802.35 | AJ19: 336204.19 | AK19: 336915.09 | AL19: 336915.09 | AM19: 336915.09 | AN19: 336915.09 | AO19: 336915.09 | AP19: 336915.09 | AQ19: 336915.09 | AR19: 336915.09 | AS19: 336915.09 | AT19: 336915.09 | AU19: 336915.09 | AV19: 336915.09 | AW19: 336915.09 | AX19: 336915.09 | AY19: 336915.09 | AZ19: 336915.09 | BA19: 336915.09 | BB19: 336915.09 | BC19: 336915.09 | BD19: 336915.09 | BE19: 336915.09
E20: % Semanal | F20: 0.0333 | G20: 0.0333 | H20: 0.0333 | I20: 0.0333 | J20: 0.0333 | K20: 0.0333 | L20: 0.0333 | M20: 0.0333 | N20: 0.0333 | O20: 0.0333 | P20: 0.0333 | Q20: 0.0333 | R20: 0.0333 | S20: 0.0333 | T20: 0.0333 | U20: 0.0333 | V20: 0.0333 | W20: 0.0311 | X20: 0.0311 | Y20: 0.0311 | Z20: 0.0311 | AA20: 0.0311 | AB20: 0.0311 | AC20: 0.0311 | AD20: 0.0311 | AE20: 0.0311 | AF20: 0.0311 | AG20: 0.0311 | AH20: 0.0311 | AI20: 0.0311 | AJ20: 0.0279 | AK20: 0.0021
E21: % Acumulado | F21: 0.0333 | G21: 0.0665 | H21: 0.0998 | I21: 0.1331 | J21: 0.1664 | K21: 0.1996 | L21: 0.2329 | M21: 0.2662 | N21: 0.2995 | O21: 0.3327 | P21: 0.366 | Q21: 0.3993 | R21: 0.4325 | S21: 0.4658 | T21: 0.4991 | U21: 0.5324 | V21: 0.5656 | W21: 0.5967 | X21: 0.6277 | Y21: 0.6588 | Z21: 0.6898 | AA21: 0.721 | AB21: 0.7521 | AC21: 0.7832 | AD21: 0.8144 | AE21: 0.8455 | AF21: 0.8766 | AG21: 0.9077 | AH21: 0.9389 | AI21: 0.97 | AJ21: 0.9979 | AK21: 1 | AL21: 1 | AM21: 1 | AN21: 1 | AO21: 1 | AP21: 1 | AQ21: 1 | AR21: 1 | AS21: 1 | AT21: 1 | AU21: 1 | AV21: 1 | AW21: 1 | AX21: 1 | AY21: 1 | AZ21: 1 | BA21: 1 | BB21: 1 | BC21: 1 | BD21: 1 | BE21: 1
A22: eap-1_3 | B22: Esc/carg/transp 2aCat DMT<=2000m | C22: m3 | D22: 105311.33 | E22: Dias Trabalhados | F22: 6 | G22: 6 | H22: 6 | I22: 6 | J22: 6 | K22: 6 | L22: 6 | M22: 6 | N22: 6 | O22: 6 | P22: 6 | Q22: 6 | R22: 6 | S22: 6 | T22: 6 | U22: 6 | V22: 6 | W22: 6 | X22: 6 | Y22: 6 | Z22: 6 | AA22: 6 | AB22: 6 | AC22: 6 | AD22: 6 | AE22: 6 | AF22: 6 | AG22: 6 | AH22: 6 | AI22: 6 | AJ22: 6 | AK22: 6 | AL22: 6 | AM22: 6 | AN22: 6 | AO22: 6 | AP22: 6 | AQ22: 6 | AR22: 6 | AS22: 6 | AT22: 6 | AU22: 6 | AV22: 6 | AW22: 6 | AX22: 6 | AY22: 6 | AZ22: 6 | BA22: 6 | BB22: 6 | BC22: 6 | BD22: 6
E23: Nº De Equipes | F23: 2 | G23: 2 | H23: 2 | I23: 2 | J23: 2 | K23: 2 | L23: 2 | M23: 2 | N23: 2 | O23: 2 | P23: 2 | Q23: 2 | R23: 2 | S23: 2 | T23: 2 | U23: 2 | V23: 2 | W23: 2 | X23: 2 | Y23: 2 | Z23: 2 | AA23: 2 | AB23: 2 | AC23: 2 | AD23: 2 | AE23: 2 | AF23: 2 | AG23: 2 | AH23: 2 | AI23: 2 | AJ23: 2 | AK23: 2 | AL23: 2 | AM23: 2 | AN23: 2 | AO23: 2 | AP23: 2 | AQ23: 2 | AR23: 2 | AS23: 2 | AT23: 2 | AU23: 2 | AV23: 2 | AW23: 2 | AX23: 2 | AY23: 2 | AZ23: 2 | BA23: 2 | BB23: 2 | BC23: 2 | BD23: 2
E24: Qtd. Planejada | F24: 15911.04 | G24: 15911.04 | H24: 15911.04 | I24: 15911.04 | J24: 15911.04 | K24: 15911.04 | L24: 9845.09
E25: Qtd Plan. Acumulada | F25: 15911.04 | G25: 31822.08 | H25: 47733.12 | I25: 63644.16 | J25: 79555.2 | K25: 95466.24 | L25: 105311.33 | M25: 105311.33 | N25: 105311.33 | O25: 105311.33 | P25: 105311.33 | Q25: 105311.33 | R25: 105311.33 | S25: 105311.33 | T25: 105311.33 | U25: 105311.33 | V25: 105311.33 | W25: 105311.33 | X25: 105311.33 | Y25: 105311.33 | Z25: 105311.33 | AA25: 105311.33 | AB25: 105311.33 | AC25: 105311.33 | AD25: 105311.33 | AE25: 105311.33 | AF25: 105311.33 | AG25: 105311.33 | AH25: 105311.33 | AI25: 105311.33 | AJ25: 105311.33 | AK25: 105311.33 | AL25: 105311.33 | AM25: 105311.33 | AN25: 105311.33 | AO25: 105311.33 | AP25: 105311.33 | AQ25: 105311.33 | AR25: 105311.33 | AS25: 105311.33 | AT25: 105311.33 | AU25: 105311.33 | AV25: 105311.33 | AW25: 105311.33 | AX25: 105311.33 | AY25: 105311.33 | AZ25: 105311.33 | BA25: 105311.33 | BB25: 105311.33 | BC25: 105311.33 | BD25: 105311.33 | BE25: 105311.33
E26: % Semanal | F26: 0.1511 | G26: 0.1511 | H26: 0.1511 | I26: 0.1511 | J26: 0.1511 | K26: 0.1511 | L26: 0.0935
E27: % Acumulado | F27: 0.1511 | G27: 0.3022 | H27: 0.4533 | I27: 0.6043 | J27: 0.7554 | K27: 0.9065 | L27: 1 | M27: 1 | N27: 1 | O27: 1 | P27: 1 | Q27: 1 | R27: 1 | S27: 1 | T27: 1 | U27: 1 | V27: 1 | W27: 1 | X27: 1 | Y27: 1 | Z27: 1 | AA27: 1 | AB27: 1 | AC27: 1 | AD27: 1 | AE27: 1 | AF27: 1 | AG27: 1 | AH27: 1 | AI27: 1 | AJ27: 1 | AK27: 1 | AL27: 1 | AM27: 1 | AN27: 1 | AO27: 1 | AP27: 1 | AQ27: 1 | AR27: 1 | AS27: 1 | AT27: 1 | AU27: 1 | AV27: 1 | AW27: 1 | AX27: 1 | AY27: 1 | AZ27: 1 | BA27: 1 | BB27: 1 | BC27: 1 | BD27: 1 | BE27: 1
A28: eap-1_4 | B28: Esc/carg/transp 2aCat DMT<=3000m | C28: m3 | D28: 585945.77 | E28: Dias Trabalhados | F28: 6 | G28: 6 | H28: 6 | I28: 6 | J28: 6 | K28: 6 | L28: 6 | M28: 6 | N28: 6 | O28: 6 | P28: 6 | Q28: 6 | R28: 6 | S28: 6 | T28: 6 | U28: 6 | V28: 6 | W28: 6 | X28: 6 | Y28: 6 | Z28: 6 | AA28: 6 | AB28: 6 | AC28: 6 | AD28: 6 | AE28: 6 | AF28: 6 | AG28: 6 | AH28: 6 | AI28: 6 | AJ28: 6 | AK28: 6 | AL28: 6 | AM28: 6 | AN28: 6 | AO28: 6 | AP28: 6 | AQ28: 6 | AR28: 6 | AS28: 6 | AT28: 6 | AU28: 6 | AV28: 6 | AW28: 6 | AX28: 6 | AY28: 6 | AZ28: 6 | BA28: 6 | BB28: 6 | BC28: 6 | BD28: 6
E29: Nº De Equipes | F29: 2 | G29: 2 | H29: 2 | I29: 2 | J29: 2 | K29: 2 | L29: 2 | M29: 2 | N29: 2 | O29: 2 | P29: 2 | Q29: 2 | R29: 2 | S29: 2 | T29: 2 | U29: 2 | V29: 2 | W29: 2 | X29: 2 | Y29: 2 | Z29: 2 | AA29: 2 | AB29: 2 | AC29: 2 | AD29: 2 | AE29: 2 | AF29: 2 | AG29: 2 | AH29: 2 | AI29: 2 | AJ29: 2 | AK29: 2 | AL29: 2 | AM29: 2 | AN29: 2 | AO29: 2 | AP29: 2 | AQ29: 2 | AR29: 2 | AS29: 2 | AT29: 2 | AU29: 2 | AV29: 2 | AW29: 2 | AX29: 2 | AY29: 2 | AZ29: 2 | BA29: 2 | BB29: 2 | BC29: 2 | BD29: 2
E30: Qtd. Planejada | F30: 15274.46 | G30: 15274.46 | H30: 15274.46 | I30: 15274.46 | J30: 15274.46 | K30: 15274.46 | L30: 15274.46 | M30: 15274.46 | N30: 15274.46 | O30: 15274.46 | P30: 15274.46 | Q30: 15274.46 | R30: 15274.46 | S30: 15274.46 | T30: 15274.46 | U30: 15274.46 | V30: 15274.46 | W30: 14255.65 | X30: 14255.65 | Y30: 14255.65 | Z30: 14255.65 | AA30: 14289.25 | AB30: 14289.25 | AC30: 14289.25 | AD30: 14289.25 | AE30: 14289.25 | AF30: 14289.25 | AG30: 14289.25 | AH30: 14289.25 | AI30: 14289.25 | AJ30: 12810.69 | AK30: 12810.69 | AL30: 12810.69 | AM30: 12810.69 | AN30: 12001.14 | AO30: 12001.14 | AP30: 12001.14 | AQ30: 12001.14 | AR30: 9361.71 | AS30: 9361.71 | AT30: 9361.71 | AU30: 9361.71 | AV30: 3959.95
E31: Qtd Plan. Acumulada | F31: 15274.46 | G31: 30548.91 | H31: 45823.37 | I31: 61097.83 | J31: 76372.28 | K31: 91646.74 | L31: 106921.2 | M31: 122195.65 | N31: 137470.11 | O31: 152744.57 | P31: 168019.02 | Q31: 183293.48 | R31: 198567.94 | S31: 213842.39 | T31: 229116.85 | U31: 244391.31 | V31: 259665.76 | W31: 273921.41 | X31: 288177.06 | Y31: 302432.71 | Z31: 316688.36 | AA31: 330977.62 | AB31: 345266.87 | AC31: 359556.13 | AD31: 373845.38 | AE31: 388134.63 | AF31: 402423.89 | AG31: 416713.14 | AH31: 431002.4 | AI31: 445291.65 | AJ31: 458102.34 | AK31: 470913.02 | AL31: 483723.71 | AM31: 496534.4 | AN31: 508535.54 | AO31: 520536.68 | AP31: 532537.82 | AQ31: 544538.96 | AR31: 553900.67 | AS31: 563262.39 | AT31: 572624.1 | AU31: 581985.82 | AV31: 585945.77 | AW31: 585945.77 | AX31: 585945.77 | AY31: 585945.77 | AZ31: 585945.77 | BA31: 585945.77 | BB31: 585945.77 | BC31: 585945.77 | BD31: 585945.77 | BE31: 585945.77
E32: % Semanal | F32: 0.0261 | G32: 0.0261 | H32: 0.0261 | I32: 0.0261 | J32: 0.0261 | K32: 0.0261 | L32: 0.0261 | M32: 0.0261 | N32: 0.0261 | O32: 0.0261 | P32: 0.0261 | Q32: 0.0261 | R32: 0.0261 | S32: 0.0261 | T32: 0.0261 | U32: 0.0261 | V32: 0.0261 | W32: 0.0243 | X32: 0.0243 | Y32: 0.0243 | Z32: 0.0243 | AA32: 0.0244 | AB32: 0.0244 | AC32: 0.0244 | AD32: 0.0244 | AE32: 0.0244 | AF32: 0.0244 | AG32: 0.0244 | AH32: 0.0244 | AI32: 0.0244 | AJ32: 0.0219 | AK32: 0.0219 | AL32: 0.0219 | AM32: 0.0219 | AN32: 0.0205 | AO32: 0.0205 | AP32: 0.0205 | AQ32: 0.0205 | AR32: 0.016 | AS32: 0.016 | AT32: 0.016 | AU32: 0.016 | AV32: 0.0068
E33: % Acumulado | F33: 0.0261 | G33: 0.0521 | H33: 0.0782 | I33: 0.1043 | J33: 0.1303 | K33: 0.1564 | L33: 0.1825 | M33: 0.2085 | N33: 0.2346 | O33: 0.2607 | P33: 0.2867 | Q33: 0.3128 | R33: 0.3389 | S33: 0.365 | T33: 0.391 | U33: 0.4171 | V33: 0.4432 | W33: 0.4675 | X33: 0.4918 | Y33: 0.5161 | Z33: 0.5405 | AA33: 0.5649 | AB33: 0.5892 | AC33: 0.6136 | AD33: 0.638 | AE33: 0.6624 | AF33: 0.6868 | AG33: 0.7112 | AH33: 0.7356 | AI33: 0.76 | AJ33: 0.7818 | AK33: 0.8037 | AL33: 0.8255 | AM33: 0.8474 | AN33: 0.8679 | AO33: 0.8884 | AP33: 0.9089 | AQ33: 0.9293 | AR33: 0.9453 | AS33: 0.9613 | AT33: 0.9773 | AU33: 0.9932 | AV33: 1 | AW33: 1 | AX33: 1 | AY33: 1 | AZ33: 1 | BA33: 1 | BB33: 1 | BC33: 1 | BD33: 1 | BE33: 1
A34: eap-1_5 | B34: Esc/carg/transp 3aCat DMT<=2000m | C34: m3 | D34: 304634.46 | E34: Dias Trabalhados | F34: 6 | G34: 6 | H34: 6 | I34: 6 | J34: 6 | K34: 6 | L34: 6 | M34: 6 | N34: 6 | O34: 6 | P34: 6 | Q34: 6 | R34: 6 | S34: 6 | T34: 6 | U34: 6 | V34: 6 | W34: 6 | X34: 6 | Y34: 6 | Z34: 6 | AA34: 6 | AB34: 6 | AC34: 6 | AD34: 6 | AE34: 6 | AF34: 6 | AG34: 6 | AH34: 6 | AI34: 6 | AJ34: 6 | AK34: 6 | AL34: 6 | AM34: 6 | AN34: 6 | AO34: 6 | AP34: 6 | AQ34: 6 | AR34: 6 | AS34: 6 | AT34: 6 | AU34: 6 | AV34: 6 | AW34: 6 | AX34: 6 | AY34: 6 | AZ34: 6 | BA34: 6 | BB34: 6
E35: Nº De Equipes | F35: 4 | G35: 4 | H35: 4 | I35: 4 | J35: 4 | K35: 4 | L35: 4 | M35: 4 | N35: 4 | O35: 4 | P35: 4 | Q35: 4 | R35: 4 | S35: 4 | T35: 4 | U35: 4 | V35: 4 | W35: 4 | X35: 4 | Y35: 4 | Z35: 4 | AA35: 4 | AB35: 4 | AC35: 4 | AD35: 4 | AE35: 4 | AF35: 4 | AG35: 4 | AH35: 4 | AI35: 4 | AJ35: 4 | AK35: 4 | AL35: 4 | AM35: 4 | AN35: 4 | AO35: 4 | AP35: 4 | AQ35: 4 | AR35: 4 | AS35: 4 | AT35: 4 | AU35: 4 | AV35: 4 | AW35: 4 | AX35: 4 | AY35: 4 | AZ35: 4 | BA35: 4 | BB35: 4
E36: Qtd. Planejada | F36: 27751.96 | G36: 27751.96 | H36: 27751.96 | I36: 27751.96 | J36: 27751.96 | K36: 27751.96 | L36: 27751.96 | M36: 27751.96 | N36: 27751.96 | O36: 27751.96 | P36: 27114.83
E37: Qtd Plan. Acumulada | F37: 27751.96 | G37: 55503.93 | H37: 83255.89 | I37: 111007.85 | J37: 138759.81 | K37: 166511.78 | L37: 194263.74 | M37: 222015.7 | N37: 249767.67 | O37: 277519.63 | P37: 304634.46 | Q37: 304634.46 | R37: 304634.46 | S37: 304634.46 | T37: 304634.46 | U37: 304634.46 | V37: 304634.46 | W37: 304634.46 | X37: 304634.46 | Y37: 304634.46 | Z37: 304634.46 | AA37: 304634.46 | AB37: 304634.46 | AC37: 304634.46 | AD37: 304634.46 | AE37: 304634.46 | AF37: 304634.46 | AG37: 304634.46 | AH37: 304634.46 | AI37: 304634.46 | AJ37: 304634.46 | AK37: 304634.46 | AL37: 304634.46 | AM37: 304634.46 | AN37: 304634.46 | AO37: 304634.46 | AP37: 304634.46 | AQ37: 304634.46 | AR37: 304634.46 | AS37: 304634.46 | AT37: 304634.46 | AU37: 304634.46 | AV37: 304634.46 | AW37: 304634.46 | AX37: 304634.46 | AY37: 304634.46 | AZ37: 304634.46 | BA37: 304634.46 | BB37: 304634.46 | BC37: 304634.46 | BD37: 304634.46 | BE37: 304634.46
E38: % Semanal | F38: 0.0911 | G38: 0.0911 | H38: 0.0911 | I38: 0.0911 | J38: 0.0911 | K38: 0.0911 | L38: 0.0911 | M38: 0.0911 | N38: 0.0911 | O38: 0.0911 | P38: 0.089
E39: % Acumulado | F39: 0.0911 | G39: 0.1822 | H39: 0.2733 | I39: 0.3644 | J39: 0.4555 | K39: 0.5466 | L39: 0.6377 | M39: 0.7288 | N39: 0.8199 | O39: 0.911 | P39: 1 | Q39: 1 | R39: 1 | S39: 1 | T39: 1 | U39: 1 | V39: 1 | W39: 1 | X39: 1 | Y39: 1 | Z39: 1 | AA39: 1 | AB39: 1 | AC39: 1 | AD39: 1 | AE39: 1 | AF39: 1 | AG39: 1 | AH39: 1 | AI39: 1 | AJ39: 1 | AK39: 1 | AL39: 1 | AM39: 1 | AN39: 1 | AO39: 1 | AP39: 1 | AQ39: 1 | AR39: 1 | AS39: 1 | AT39: 1 | AU39: 1 | AV39: 1 | AW39: 1 | AX39: 1 | AY39: 1 | AZ39: 1 | BA39: 1 | BB39: 1 | BC39: 1 | BD39: 1 | BE39: 1
A40: eap-1_6 | B40: Esc/carg/transp 3aCat DMT<=3000m | C40: m3 | D40: 676519.04 | E40: Dias Trabalhados | F40: 6 | G40: 6 | H40: 6 | I40: 6 | J40: 6 | K40: 6 | L40: 6 | M40: 6 | N40: 6 | O40: 6 | P40: 6 | Q40: 6 | R40: 6 | S40: 6 | T40: 6 | U40: 6 | V40: 6 | W40: 6 | X40: 6 | Y40: 6 | Z40: 6 | AA40: 6 | AB40: 6 | AC40: 6 | AD40: 6 | AE40: 6 | AF40: 6 | AG40: 6 | AH40: 6 | AI40: 6 | AJ40: 6 | AK40: 6 | AL40: 6 | AM40: 6 | AN40: 6 | AO40: 6 | AP40: 6 | AQ40: 6 | AR40: 6 | AS40: 6 | AT40: 6 | AU40: 6 | AV40: 6 | AW40: 6 | AX40: 6 | AY40: 6 | AZ40: 6 | BA40: 6 | BB40: 6
E41: Nº De Equipes | F41: 4 | G41: 4 | H41: 4 | I41: 4 | J41: 4 | K41: 4 | L41: 4 | M41: 4 | N41: 4 | O41: 4 | P41: 4 | Q41: 4 | R41: 4 | S41: 4 | T41: 4 | U41: 4 | V41: 4 | W41: 4 | X41: 4 | Y41: 4 | Z41: 4 | AA41: 4 | AB41: 4 | AC41: 4 | AD41: 4 | AE41: 4 | AF41: 4 | AG41: 4 | AH41: 4 | AI41: 4 | AJ41: 4 | AK41: 4 | AL41: 4 | AM41: 4 | AN41: 4 | AO41: 4 | AP41: 4 | AQ41: 4 | AR41: 4 | AS41: 4 | AT41: 4 | AU41: 4 | AV41: 4 | AW41: 4 | AX41: 4 | AY41: 4 | AZ41: 4 | BA41: 4 | BB41: 4
E42: Qtd. Planejada | F42: 27751.96 | G42: 27751.96 | H42: 27751.96 | I42: 27751.96 | J42: 27751.96 | K42: 27751.96 | L42: 27751.96 | M42: 27751.96 | N42: 27751.96 | O42: 27751.96 | P42: 27751.96 | Q42: 27751.96 | R42: 27751.96 | S42: 27751.96 | T42: 27751.96 | U42: 27751.96 | V42: 27751.96 | W42: 25900.91 | X42: 25900.91 | Y42: 25900.91 | Z42: 25900.91 | AA42: 25961.96 | AB42: 25961.96 | AC42: 25961.96 | AD42: 23246.17
E43: Qtd Plan. Acumulada | F43: 27751.96 | G43: 55503.93 | H43: 83255.89 | I43: 111007.85 | J43: 138759.81 | K43: 166511.78 | L43: 194263.74 | M43: 222015.7 | N43: 249767.67 | O43: 277519.63 | P43: 305271.59 | Q43: 333023.55 | R43: 360775.52 | S43: 388527.48 | T43: 416279.44 | U43: 444031.41 | V43: 471783.37 | W43: 497684.27 | X43: 523585.18 | Y43: 549486.09 | Z43: 575387 | AA43: 601348.96 | AB43: 627310.92 | AC43: 653272.88 | AD43: 676519.04 | AE43: 676519.04 | AF43: 676519.04 | AG43: 676519.04 | AH43: 676519.04 | AI43: 676519.04 | AJ43: 676519.04 | AK43: 676519.04 | AL43: 676519.04 | AM43: 676519.04 | AN43: 676519.04 | AO43: 676519.04 | AP43: 676519.04 | AQ43: 676519.04 | AR43: 676519.04 | AS43: 676519.04 | AT43: 676519.04 | AU43: 676519.04 | AV43: 676519.04 | AW43: 676519.04 | AX43: 676519.04 | AY43: 676519.04 | AZ43: 676519.04 | BA43: 676519.04 | BB43: 676519.04 | BC43: 676519.04 | BD43: 676519.04 | BE43: 676519.04
E44: % Semanal | F44: 0.041 | G44: 0.041 | H44: 0.041 | I44: 0.041 | J44: 0.041 | K44: 0.041 | L44: 0.041 | M44: 0.041 | N44: 0.041 | O44: 0.041 | P44: 0.041 | Q44: 0.041 | R44: 0.041 | S44: 0.041 | T44: 0.041 | U44: 0.041 | V44: 0.041 | W44: 0.0383 | X44: 0.0383 | Y44: 0.0383 | Z44: 0.0383 | AA44: 0.0384 | AB44: 0.0384 | AC44: 0.0384 | AD44: 0.0344
E45: % Acumulado | F45: 0.041 | G45: 0.082 | H45: 0.1231 | I45: 0.1641 | J45: 0.2051 | K45: 0.2461 | L45: 0.2872 | M45: 0.3282 | N45: 0.3692 | O45: 0.4102 | P45: 0.4512 | Q45: 0.4923 | R45: 0.5333 | S45: 0.5743 | T45: 0.6153 | U45: 0.6563 | V45: 0.6974 | W45: 0.7357 | X45: 0.7739 | Y45: 0.8122 | Z45: 0.8505 | AA45: 0.8889 | AB45: 0.9273 | AC45: 0.9656 | AD45: 1 | AE45: 1 | AF45: 1 | AG45: 1 | AH45: 1 | AI45: 1 | AJ45: 1 | AK45: 1 | AL45: 1 | AM45: 1 | AN45: 1 | AO45: 1 | AP45: 1 | AQ45: 1 | AR45: 1 | AS45: 1 | AT45: 1 | AU45: 1 | AV45: 1 | AW45: 1 | AX45: 1 | AY45: 1 | AZ45: 1 | BA45: 1 | BB45: 1 | BC45: 1 | BD45: 1 | BE45: 1
A46: eap-1_7 | B46: Compactacao aterros 100% Proctor Normal | C46: m3 | D46: 1135635.3 | E46: Dias Trabalhados | F46: 6 | G46: 6 | H46: 6 | I46: 6 | J46: 6 | K46: 6 | L46: 6 | M46: 6 | N46: 6 | O46: 6 | P46: 6 | Q46: 6 | R46: 6 | S46: 6 | T46: 6 | U46: 6 | V46: 6 | W46: 6 | X46: 6 | Y46: 6 | Z46: 6 | AA46: 6 | AB46: 6 | AC46: 6 | AD46: 6 | AE46: 6 | AF46: 6 | AG46: 6 | AH46: 6 | AI46: 6 | AJ46: 6 | AK46: 6 | AL46: 6 | AM46: 6 | AN46: 6 | AO46: 6 | AP46: 6 | AQ46: 6 | AR46: 6 | AS46: 6 | AT46: 6 | AU46: 6 | AV46: 6 | AW46: 6 | AX46: 6 | AY46: 6 | AZ46: 6 | BA46: 6 | BB46: 6 | BC46: 6 | BD46: 6
E47: Nº De Equipes | F47: 3 | G47: 3 | H47: 3 | I47: 3 | J47: 3 | K47: 3 | L47: 3 | M47: 3 | N47: 3 | O47: 3 | P47: 3 | Q47: 3 | R47: 3 | S47: 3 | T47: 3 | U47: 3 | V47: 3 | W47: 3 | X47: 3 | Y47: 3 | Z47: 3 | AA47: 3 | AB47: 3 | AC47: 3 | AD47: 3 | AE47: 3 | AF47: 3 | AG47: 3 | AH47: 3 | AI47: 3 | AJ47: 3 | AK47: 3 | AL47: 3 | AM47: 3 | AN47: 3 | AO47: 3 | AP47: 3 | AQ47: 3 | AR47: 3 | AS47: 3 | AT47: 3 | AU47: 3 | AV47: 3 | AW47: 3 | AX47: 3 | AY47: 3 | AZ47: 3 | BA47: 3 | BB47: 3 | BC47: 3 | BD47: 3
E48: Qtd. Planejada | F48: 27681.12 | G48: 27681.12 | H48: 27681.12 | I48: 27681.12 | J48: 27681.12 | K48: 27681.12 | L48: 27681.12 | M48: 27681.12 | N48: 27681.12 | O48: 27681.12 | P48: 27681.12 | Q48: 27681.12 | R48: 27681.12 | S48: 27681.12 | T48: 27681.12 | U48: 27681.12 | V48: 27681.12 | W48: 25834.79 | X48: 25834.79 | Y48: 25834.79 | Z48: 25834.79 | AA48: 25895.69 | AB48: 25895.69 | AC48: 25895.69 | AD48: 25895.69 | AE48: 25895.69 | AF48: 25895.69 | AG48: 25895.69 | AH48: 25895.69 | AI48: 25895.69 | AJ48: 23216.16 | AK48: 23216.16 | AL48: 23216.16 | AM48: 23216.16 | AN48: 21749.06 | AO48: 21749.06 | AP48: 21749.06 | AQ48: 21749.06 | AR48: 16965.76 | AS48: 16965.76 | AT48: 16965.76 | AU48: 16965.76 | AV48: 24913.01 | AW48: 24913.01 | AX48: 24913.01 | AY48: 6193.01
E49: Qtd Plan. Acumulada | F49: 27681.12 | G49: 55362.24 | H49: 83043.36 | I49: 110724.48 | J49: 138405.6 | K49: 166086.72 | L49: 193767.84 | M49: 221448.96 | N49: 249130.08 | O49: 276811.2 | P49: 304492.32 | Q49: 332173.44 | R49: 359854.56 | S49: 387535.68 | T49: 415216.8 | U49: 442897.92 | V49: 470579.04 | W49: 496413.83 | X49: 522248.62 | Y49: 548083.41 | Z49: 573918.2 | AA49: 599813.88 | AB49: 625709.57 | AC49: 651605.26 | AD49: 677500.95 | AE49: 703396.64 | AF49: 729292.32 | AG49: 755188.01 | AH49: 781083.7 | AI49: 806979.39 | AJ49: 830195.54 | AK49: 853411.7 | AL49: 876627.85 | AM49: 899844.01 | AN49: 921593.06 | AO49: 943342.12 | AP49: 965091.18 | AQ49: 986840.23 | AR49: 1003806 | AS49: 1020771.8 | AT49: 1037737.5 | AU49: 1054703.3 | AV49: 1079616.3 | AW49: 1104529.3 | AX49: 1129442.3 | AY49: 1135635.3 | AZ49: 1135635.3 | BA49: 1135635.3 | BB49: 1135635.3 | BC49: 1135635.3 | BD49: 1135635.3 | BE49: 1135635.3
E50: % Semanal | F50: 0.0244 | G50: 0.0244 | H50: 0.0244 | I50: 0.0244 | J50: 0.0244 | K50: 0.0244 | L50: 0.0244 | M50: 0.0244 | N50: 0.0244 | O50: 0.0244 | P50: 0.0244 | Q50: 0.0244 | R50: 0.0244 | S50: 0.0244 | T50: 0.0244 | U50: 0.0244 | V50: 0.0244 | W50: 0.0227 | X50: 0.0227 | Y50: 0.0227 | Z50: 0.0227 | AA50: 0.0228 | AB50: 0.0228 | AC50: 0.0228 | AD50: 0.0228 | AE50: 0.0228 | AF50: 0.0228 | AG50: 0.0228 | AH50: 0.0228 | AI50: 0.0228 | AJ50: 0.0204 | AK50: 0.0204 | AL50: 0.0204 | AM50: 0.0204 | AN50: 0.0192 | AO50: 0.0192 | AP50: 0.0192 | AQ50: 0.0192 | AR50: 0.0149 | AS50: 0.0149 | AT50: 0.0149 | AU50: 0.0149 | AV50: 0.0219 | AW50: 0.0219 | AX50: 0.0219 | AY50: 0.0055
E51: % Acumulado | F51: 0.0244 | G51: 0.0488 | H51: 0.0731 | I51: 0.0975 | J51: 0.1219 | K51: 0.1463 | L51: 0.1706 | M51: 0.195 | N51: 0.2194 | O51: 0.2438 | P51: 0.2681 | Q51: 0.2925 | R51: 0.3169 | S51: 0.3413 | T51: 0.3656 | U51: 0.39 | V51: 0.4144 | W51: 0.4371 | X51: 0.4599 | Y51: 0.4826 | Z51: 0.5054 | AA51: 0.5282 | AB51: 0.551 | AC51: 0.5738 | AD51: 0.5966 | AE51: 0.6194 | AF51: 0.6422 | AG51: 0.665 | AH51: 0.6878 | AI51: 0.7106 | AJ51: 0.731 | AK51: 0.7515 | AL51: 0.7719 | AM51: 0.7924 | AN51: 0.8115 | AO51: 0.8307 | AP51: 0.8498 | AQ51: 0.869 | AR51: 0.8839 | AS51: 0.8989 | AT51: 0.9138 | AU51: 0.9287 | AV51: 0.9507 | AW51: 0.9726 | AX51: 0.9945 | AY51: 1 | AZ51: 1 | BA51: 1 | BB51: 1 | BC51: 1 | BD51: 1 | BE51: 1
A52: eap-1_8 | B52: Compactacao aterros 100% Proctor Intermediario | C52: m3 | D52: 29411 | E52: Dias Trabalhados | F52: 6 | G52: 6 | H52: 6
E53: Nº De Equipes | F53: 2 | G53: 2 | H53: 2
E54: Qtd. Planejada | F54: 14352.96 | G54: 14352.96 | H54: 705.08
E55: Qtd Plan. Acumulada | F55: 14352.96 | G55: 28705.92 | H55: 29411 | I55: 29411 | J55: 29411 | K55: 29411 | L55: 29411 | M55: 29411 | N55: 29411 | O55: 29411 | P55: 29411 | Q55: 29411 | R55: 29411 | S55: 29411 | T55: 29411 | U55: 29411 | V55: 29411 | W55: 29411 | X55: 29411 | Y55: 29411 | Z55: 29411 | AA55: 29411 | AB55: 29411 | AC55: 29411 | AD55: 29411 | AE55: 29411 | AF55: 29411 | AG55: 29411 | AH55: 29411 | AI55: 29411 | AJ55: 29411 | AK55: 29411 | AL55: 29411 | AM55: 29411 | AN55: 29411 | AO55: 29411 | AP55: 29411 | AQ55: 29411 | AR55: 29411 | AS55: 29411 | AT55: 29411 | AU55: 29411 | AV55: 29411 | AW55: 29411 | AX55: 29411 | AY55: 29411 | AZ55: 29411 | BA55: 29411 | BB55: 29411 | BC55: 29411 | BD55: 29411 | BE55: 29411
E56: % Semanal | F56: 0.488 | G56: 0.488 | H56: 0.024
E57: % Acumulado | F57: 0.488 | G57: 0.976 | H57: 1 | I57: 1 | J57: 1 | K57: 1 | L57: 1 | M57: 1 | N57: 1 | O57: 1 | P57: 1 | Q57: 1 | R57: 1 | S57: 1 | T57: 1 | U57: 1 | V57: 1 | W57: 1 | X57: 1 | Y57: 1 | Z57: 1 | AA57: 1 | AB57: 1 | AC57: 1 | AD57: 1 | AE57: 1 | AF57: 1 | AG57: 1 | AH57: 1 | AI57: 1 | AJ57: 1 | AK57: 1 | AL57: 1 | AM57: 1 | AN57: 1 | AO57: 1 | AP57: 1 | AQ57: 1 | AR57: 1 | AS57: 1 | AT57: 1 | AU57: 1 | AV57: 1 | AW57: 1 | AX57: 1 | AY57: 1 | AZ57: 1 | BA57: 1 | BB57: 1 | BC57: 1 | BD57: 1 | BE57: 1
A58: eap-1_9 | B58: Construcao corpo aterro material 3a categoria | C58: m3 | D58: 981153.5 | E58: Dias Trabalhados | F58: 6 | G58: 6 | H58: 6 | I58: 6 | J58: 6 | K58: 6 | L58: 6 | M58: 6 | N58: 6 | O58: 6 | P58: 6 | Q58: 6 | R58: 6 | S58: 6 | T58: 6 | U58: 6 | V58: 6 | W58: 6 | X58: 6 | Y58: 6 | Z58: 6 | AA58: 6 | AB58: 6 | AC58: 6 | AD58: 6 | AE58: 6 | AF58: 6 | AG58: 6 | AH58: 6 | AI58: 6 | AJ58: 6 | AK58: 6 | AL58: 6 | AM58: 6 | AN58: 6 | AO58: 6 | AP58: 6 | AQ58: 6 | AR58: 6 | AS58: 6 | AT58: 6 | AU58: 6 | AV58: 6 | AW58: 6 | AX58: 6 | AY58: 6 | AZ58: 6 | BA58: 6 | BB58: 6 | BC58: 6 | BD58: 6 | BE58: 6
E59: Nº De Equipes | F59: 2 | G59: 2 | H59: 2 | I59: 2 | J59: 2 | K59: 2 | L59: 2 | M59: 2 | N59: 2 | O59: 2 | P59: 2 | Q59: 2 | R59: 2 | S59: 2 | T59: 2 | U59: 2 | V59: 2 | W59: 2 | X59: 2 | Y59: 2 | Z59: 2 | AA59: 2 | AB59: 2 | AC59: 2 | AD59: 2 | AE59: 2 | AF59: 2 | AG59: 2 | AH59: 2 | AI59: 2 | AJ59: 2 | AK59: 2 | AL59: 2 | AM59: 2 | AN59: 2 | AO59: 2 | AP59: 2 | AQ59: 2 | AR59: 2 | AS59: 2 | AT59: 2 | AU59: 2 | AV59: 2 | AW59: 2 | AX59: 2 | AY59: 2 | AZ59: 2 | BA59: 2 | BB59: 2 | BC59: 2 | BD59: 2 | BE59: 2
E60: Qtd. Planejada | F60: 23040 | G60: 23040 | H60: 23040 | I60: 23040 | J60: 23040 | K60: 23040 | L60: 23040 | M60: 23040 | N60: 23040 | O60: 23040 | P60: 23040 | Q60: 23040 | R60: 23040 | S60: 23040 | T60: 23040 | U60: 23040 | V60: 23040 | W60: 21503.23 | X60: 21503.23 | Y60: 21503.23 | Z60: 21503.23 | AA60: 21553.92 | AB60: 21553.92 | AC60: 21553.92 | AD60: 21553.92 | AE60: 21553.92 | AF60: 21553.92 | AG60: 21553.92 | AH60: 21553.92 | AI60: 21553.92 | AJ60: 19323.65 | AK60: 19323.65 | AL60: 19323.65 | AM60: 19323.65 | AN60: 18102.53 | AO60: 18102.53 | AP60: 18102.53 | AQ60: 18102.53 | AR60: 14121.22 | AS60: 14121.22 | AT60: 14121.22 | AU60: 14121.22 | AV60: 20736 | AW60: 20736 | AX60: 20736 | AY60: 20736 | AZ60: 20067.84 | BA60: 273.88
E61: Qtd Plan. Acumulada | F61: 23040 | G61: 46080 | H61: 69120 | I61: 92160 | J61: 115200 | K61: 138240 | L61: 161280 | M61: 184320 | N61: 207360 | O61: 230400 | P61: 253440 | Q61: 276480 | R61: 299520 | S61: 322560 | T61: 345600 | U61: 368640 | V61: 391680 | W61: 413183.23 | X61: 434686.46 | Y61: 456189.7 | Z61: 477692.93 | AA61: 499246.85 | AB61: 520800.77 | AC61: 542354.69 | AD61: 563908.61 | AE61: 585462.53 | AF61: 607016.45 | AG61: 628570.37 | AH61: 650124.29 | AI61: 671678.21 | AJ61: 691001.86 | AK61: 710325.5 | AL61: 729649.15 | AM61: 748972.8 | AN61: 767075.33 | AO61: 785177.86 | AP61: 803280.38 | AQ61: 821382.91 | AR61: 835504.13 | AS61: 849625.34 | AT61: 863746.56 | AU61: 877867.78 | AV61: 898603.78 | AW61: 919339.78 | AX61: 940075.78 | AY61: 960811.78 | AZ61: 980879.62 | BA61: 981153.5 | BB61: 981153.5 | BC61: 981153.5 | BD61: 981153.5 | BE61: 981153.5
E62: % Semanal | F62: 0.0235 | G62: 0.0235 | H62: 0.0235 | I62: 0.0235 | J62: 0.0235 | K62: 0.0235 | L62: 0.0235 | M62: 0.0235 | N62: 0.0235 | O62: 0.0235 | P62: 0.0235 | Q62: 0.0235 | R62: 0.0235 | S62: 0.0235 | T62: 0.0235 | U62: 0.0235 | V62: 0.0235 | W62: 0.0219 | X62: 0.0219 | Y62: 0.0219 | Z62: 0.0219 | AA62: 0.022 | AB62: 0.022 | AC62: 0.022 | AD62: 0.022 | AE62: 0.022 | AF62: 0.022 | AG62: 0.022 | AH62: 0.022 | AI62: 0.022 | AJ62: 0.0197 | AK62: 0.0197 | AL62: 0.0197 | AM62: 0.0197 | AN62: 0.0185 | AO62: 0.0185 | AP62: 0.0185 | AQ62: 0.0185 | AR62: 0.0144 | AS62: 0.0144 | AT62: 0.0144 | AU62: 0.0144 | AV62: 0.0211 | AW62: 0.0211 | AX62: 0.0211 | AY62: 0.0211 | AZ62: 0.0205 | BA62: 0.0003
E63: % Acumulado | F63: 0.0235 | G63: 0.047 | H63: 0.0704 | I63: 0.0939 | J63: 0.1174 | K63: 0.1409 | L63: 0.1644 | M63: 0.1879 | N63: 0.2113 | O63: 0.2348 | P63: 0.2583 | Q63: 0.2818 | R63: 0.3053 | S63: 0.3288 | T63: 0.3522 | U63: 0.3757 | V63: 0.3992 | W63: 0.4211 | X63: 0.443 | Y63: 0.465 | Z63: 0.4869 | AA63: 0.5088 | AB63: 0.5308 | AC63: 0.5528 | AD63: 0.5747 | AE63: 0.5967 | AF63: 0.6187 | AG63: 0.6406 | AH63: 0.6626 | AI63: 0.6846 | AJ63: 0.7043 | AK63: 0.724 | AL63: 0.7437 | AM63: 0.7634 | AN63: 0.7818 | AO63: 0.8003 | AP63: 0.8187 | AQ63: 0.8372 | AR63: 0.8516 | AS63: 0.8659 | AT63: 0.8803 | AU63: 0.8947 | AV63: 0.9159 | AW63: 0.937 | AX63: 0.9581 | AY63: 0.9793 | AZ63: 0.9997 | BA63: 1 | BB63: 1 | BC63: 1 | BD63: 1 | BE63: 1
A64: eap-1_10 | B64: Compactacao camada final aterro sobre rocha | C64: m3 | D64: 24721.17 | E64: Dias Trabalhados | F64: 6 | G64: 6 | H64: 6 | I64: 6 | J64: 6 | K64: 6
E65: Nº De Equipes | F65: 1 | G65: 1 | H65: 1 | I65: 1 | J65: 1 | K65: 1
E66: Qtd. Planejada | F66: 4800 | G66: 4800 | H66: 4800 | I66: 4800 | J66: 4800 | K66: 721.17
E67: Qtd Plan. Acumulada | F67: 4800 | G67: 9600 | H67: 14400 | I67: 19200 | J67: 24000 | K67: 24721.17 | L67: 24721.17 | M67: 24721.17 | N67: 24721.17 | O67: 24721.17 | P67: 24721.17 | Q67: 24721.17 | R67: 24721.17 | S67: 24721.17 | T67: 24721.17 | U67: 24721.17 | V67: 24721.17 | W67: 24721.17 | X67: 24721.17 | Y67: 24721.17 | Z67: 24721.17 | AA67: 24721.17 | AB67: 24721.17 | AC67: 24721.17 | AD67: 24721.17 | AE67: 24721.17 | AF67: 24721.17 | AG67: 24721.17 | AH67: 24721.17 | AI67: 24721.17 | AJ67: 24721.17 | AK67: 24721.17 | AL67: 24721.17 | AM67: 24721.17 | AN67: 24721.17 | AO67: 24721.17 | AP67: 24721.17 | AQ67: 24721.17 | AR67: 24721.17 | AS67: 24721.17 | AT67: 24721.17 | AU67: 24721.17 | AV67: 24721.17 | AW67: 24721.17 | AX67: 24721.17 | AY67: 24721.17 | AZ67: 24721.17 | BA67: 24721.17 | BB67: 24721.17 | BC67: 24721.17 | BD67: 24721.17 | BE67: 24721.17
E68: % Semanal | F68: 0.1942 | G68: 0.1942 | H68: 0.1942 | I68: 0.1942 | J68: 0.1942 | K68: 0.0292
E69: % Acumulado | F69: 0.1942 | G69: 0.3883 | H69: 0.5825 | I69: 0.7767 | J69: 0.9708 | K69: 1 | L69: 1 | M69: 1 | N69: 1 | O69: 1 | P69: 1 | Q69: 1 | R69: 1 | S69: 1 | T69: 1 | U69: 1 | V69: 1 | W69: 1 | X69: 1 | Y69: 1 | Z69: 1 | AA69: 1 | AB69: 1 | AC69: 1 | AD69: 1 | AE69: 1 | AF69: 1 | AG69: 1 | AH69: 1 | AI69: 1 | AJ69: 1 | AK69: 1 | AL69: 1 | AM69: 1 | AN69: 1 | AO69: 1 | AP69: 1 | AQ69: 1 | AR69: 1 | AS69: 1 | AT69: 1 | AU69: 1 | AV69: 1 | AW69: 1 | AX69: 1 | AY69: 1 | AZ69: 1 | BA69: 1 | BB69: 1 | BC69: 1 | BD69: 1 | BE69: 1

Sheet CRONOGRAMA.RES
A1: CRONOGRAMA RESUMIDO — PRODUÇÃO MENSAL POR EAP
A2: Item ID | B2: Descrição | C2: Un. | D2: Total Qtd | E2: Jun/26 | F2: Jul/26 | G2: Ago/26 | H2: Set/26 | I2: Out/26 | J2: Nov/26 | K2: Dez/26 | L2: Jan/27 | M2: Fev/27 | N2: Mar/27 | O2: Abr/27 | P2: Mai/27
A3: eap-1_0 | B3: Desmatamento e limpeza de area vegetada | C3: m2 | D3: 2400000 | E3: 720000 | F3: 720000 | G3: 900000 | H3: 60000
A4: eap-1_1 | B4: Esc/carg/transp 1aCat DMT<=2000m | C4: m3 | D4: 107463.11 | E4: 45895.68 | F4: 45895.68 | G4: 15671.75
A5: eap-1_2 | B5: Esc/carg/transp 1aCat DMT<=3000m | C5: m3 | D5: 336915.09 | E5: 44840.08 | F5: 44840.08 | G5: 56050.1 | H5: 44840.08 | I5: 41849.24 | J5: 52434.85 | K5: 41947.88 | L5: 10112.75
A6: eap-1_3 | B6: Esc/carg/transp 2aCat DMT<=2000m | C6: m3 | D6: 105311.33 | E6: 63644.16 | F6: 41667.17
A7: eap-1_4 | B7: Esc/carg/transp 2aCat DMT<=3000m | C7: m3 | D7: 585945.77 | E7: 61097.84 | F7: 61097.84 | G7: 76372.3 | H7: 61097.84 | I7: 57022.6 | J7: 71446.25 | K7: 57157 | L7: 51242.76 | M7: 48004.56 | N7: 41406.79
A8: eap-1_5 | B8: Esc/carg/transp 3aCat DMT<=2000m | C8: m3 | D8: 304634.46 | E8: 111007.84 | F8: 111007.84 | G8: 82618.75
A9: eap-1_6 | B9: Esc/carg/transp 3aCat DMT<=3000m | C9: m3 | D9: 676519.04 | E9: 111007.84 | F9: 111007.84 | G9: 138759.8 | H9: 111007.84 | I9: 103603.64 | J9: 101132.05
A10: eap-1_7 | B10: Compactacao aterros 100% Proctor Normal | C10: m3 | D10: 1135635.3 | E10: 110724.48 | F10: 110724.48 | G10: 138405.6 | H10: 110724.48 | I10: 103339.16 | J10: 129478.45 | K10: 103582.76 | L10: 92864.64 | M10: 86996.24 | N10: 92776.05 | O10: 56019.03
A11: eap-1_8 | B11: Compactacao aterros 100% Proctor Intermediario | C11: m3 | D11: 29411 | E11: 29411
A12: eap-1_9 | B12: Construcao corpo aterro material 3a categoria | C12: m3 | D12: 981153.5 | E12: 92160 | F12: 92160 | G12: 115200 | H12: 92160 | I12: 86012.92 | J12: 107769.6 | K12: 86215.68 | L12: 77294.6 | M12: 72410.12 | N12: 77220.88 | O12: 82275.84 | P12: 273.88
A13: eap-1_10 | B13: Compactacao camada final aterro sobre rocha | C13: m3 | D13: 24721.17 | E13: 19200 | F13: 5521.17

Sheet EQUIPE
A1: EQUIPE — COMPOSIÇÃO DE RECURSOS DIRETOS POR ATIVIDADE
A2: Item ID | B2: CPU ID | C2: Nome / Tipo | D2: Papel | E2: Qtd | F2: Custo Mensal (R$) | G2: Perm. (m) | H2: Nº Eq. | I2: Custo Total (R$)
A3: eap-1_0 — Desmatamento e limpeza de area vegetada
A4: eap-1_0 | B4: CPU-TERRA-ATI-003 | C4: Operador de Escavadeira | D4: DIRETO | E4: 1 | F4: 10300 | G4: 5.75 | H4: 1 | I4: 59225
A5: eap-1_0 | B5: CPU-TERRA-ATI-003 | C5: Operador de Trator de Esteiras | D5: DIRETO | E5: 6 | F5: 61800 | G5: 5.75 | H5: 1 | I5: 355350
A6: eap-1_0 | B6: CPU-TERRA-ATI-003 | C6: Operador de motosserra | D6: DIRETO | E6: 6 | F6: 43845.9 | G6: 5.75 | H6: 1 | I6: 252113.92
A7: eap-1_0 | B7: CPU-TERRA-ATI-003 | C7: Ajudante | D7: DIRETO | E7: 6 | F7: 25255.92 | G7: 5.75 | H7: 1 | I7: 145221.54
A8: eap-1_0 | B8: CPU-TERRA-ATI-003 | C8: SINALEIRO | D8: DIRETO | E8: 6 | F8: 38047.02 | G8: 5.75 | H8: 1 | I8: 218770.37
A9: eap-1_0 | B9: CPU-TERRA-ATI-003 | C9: Encarregado de Frente | D9: DIRETO | E9: 1 | F9: 7500 | G9: 5.75 | H9: 1 | I9: 43125
A10: eap-1_0 | B10: CPU-TERRA-ATI-003 | C10: Apontador | D10: DIRETO | E10: 1 | F10: 6341.17 | G10: 5.75 | H10: 1 | I10: 36461.73
A11: eap-1_0 | B11: EQ-E0016 | C11: Escavadeira Hidráulica 22t [EQ] | D11: EQ | E11: 1 | F11: 35639.3 | G11: 5.75 | H11: 1 | I11: 204925.98
A12: eap-1_0 | B12: EQ-E0035 | C12: Trator de esteiras 20T [EQ] | D12: EQ | E12: 6 | F12: 21683.2 | G12: 5.75 | H12: 1 | I12: 124678.4
A13: eap-1_0 | B13: EQ-E0035 | C13: Diesel — Trator de esteiras 20T | D13: COMB | E13: 6 | F13: 22957.71 | G13: 5.75 | H13: 1 | I13: 132006.83
A14: Subtotal eap-1_0 | I14: 14192824
A15: eap-1_1 — Esc/carg/transp 1aCat DMT<=2000m
A16: eap-1_1 | B16: CPU-TERRA-ESCO-CARGA-1CAT-DMT2000 | C16: Operador de Escavadeira | D16: DIRETO | E16: 1 | F16: 10300 | G16: 10.35 | H16: 1 | I16: 106605
A17: eap-1_1 | B17: CPU-TERRA-ESCO-CARGA-1CAT-DMT2000 | C17: Ajudante | D17: DIRETO | E17: 1 | F17: 4209.32 | G17: 10.35 | H17: 1 | I17: 43566.46
A18: eap-1_1 | B18: CPU-TERRA-ESCO-CARGA-1CAT-DMT2000 | C18: Encarregado de Frente | D18: DIRETO | E18: 1 | F18: 7500 | G18: 10.35 | H18: 1 | I18: 77625
A19: eap-1_1 | B19: CPU-TERRA-ESCO-CARGA-1CAT-DMT2000 | C19: Motorista de Caminhão Basculante | D19: DIRETO | E19: 7 | F19: 44388.19 | G19: 10.35 | H19: 1 | I19: 459417.77
A20: eap-1_1 | B20: EQ-E0016 | C20: Escavadeira Hidráulica 22t [EQ] | D20: EQ | E20: 1 | F20: 35639.3 | G20: 10.35 | H20: 1 | I20: 368866.76
A21: Subtotal eap-1_1 | I21: 1056038.7
A22: eap-1_2 — Esc/carg/transp 1aCat DMT<=3000m
A23: eap-1_2 | B23: CPU-TERRA-ESCO-CARGA-1CAT-DMT3000 | C23: Operador de Escavadeira | D23: DIRETO | E23: 1 | F23: 10300 | G23: 10.35 | H23: 1 | I23: 106605
A24: eap-1_2 | B24: CPU-TERRA-ESCO-CARGA-1CAT-DMT3000 | C24: Motorista de Caminhão Basculante | D24: DIRETO | E24: 7 | F24: 44388.19 | G24: 10.35 | H24: 1 | I24: 459417.77
A25: eap-1_2 | B25: CPU-TERRA-ESCO-CARGA-1CAT-DMT3000 | C25: Ajudante | D25: DIRETO | E25: 1 | F25: 4209.32 | G25: 10.35 | H25: 1 | I25: 43566.46
A26: eap-1_2 | B26: CPU-TERRA-ESCO-CARGA-1CAT-DMT3000 | C26: Encarregado de Frente | D26: DIRETO | E26: 1 | F26: 7500 | G26: 10.35 | H26: 1 | I26: 77625
A27: eap-1_2 | B27: EQ-E0016 | C27: Escavadeira Hidráulica 22t [EQ] | D27: EQ | E27: 1 | F27: 35639.3 | G27: 10.35 | H27: 1 | I27: 368866.76
A28: Subtotal eap-1_2 | I28: 1056038.7
A29: eap-1_3 — Esc/carg/transp 2aCat DMT<=2000m
A30: eap-1_3 | B30: CPU-TERRA-ESCO-CARGA-2CAT-DMT2000 | C30: Operador de Escavadeira | D30: DIRETO | E30: 2 | F30: 20600 | G30: 11.73 | H30: 1 | I30: 241638
A31: eap-1_3 | B31: CPU-TERRA-ESCO-CARGA-2CAT-DMT2000 | C31: Motorista de Caminhão Basculante | D31: DIRETO | E31: 11 | F31: 69752.87 | G31: 11.73 | H31: 1 | I31: 818201.17
A32: eap-1_3 | B32: CPU-TERRA-ESCO-CARGA-2CAT-DMT2000 | C32: Ajudante | D32: DIRETO | E32: 2 | F32: 8418.64 | G32: 11.73 | H32: 1 | I32: 98750.65
A33: eap-1_3 | B33: CPU-TERRA-ESCO-CARGA-2CAT-DMT2000 | C33: Encarregado de Frente | D33: DIRETO | E33: 1 | F33: 7500 | G33: 11.73 | H33: 1 | I33: 87975
A34: eap-1_3 | B34: EQ-E0016 | C34: Escavadeira Hidráulica 22t [EQ] | D34: EQ | E34: 2 | F34: 35639.3 | G34: 11.73 | H34: 1 | I34: 418048.99
A35: Subtotal eap-1_3 | I35: 4165159
A36: eap-1_4 — Esc/carg/transp 2aCat DMT<=3000m
A37: eap-1_4 | B37: CPU-TERRA-ESCO-CARGA-2CAT-DMT3000 | C37: Operador de Escavadeira | D37: DIRETO | E37: 2 | F37: 20600 | G37: 11.73 | H37: 1 | I37: 241638
A38: eap-1_4 | B38: CPU-TERRA-ESCO-CARGA-2CAT-DMT3000 | C38: Motorista de Caminhão Basculante | D38: DIRETO | E38: 11 | F38: 69752.87 | G38: 11.73 | H38: 1 | I38: 818201.17
A39: eap-1_4 | B39: CPU-TERRA-ESCO-CARGA-2CAT-DMT3000 | C39: Ajudante | D39: DIRETO | E39: 2 | F39: 8418.64 | G39: 11.73 | H39: 1 | I39: 98750.65
A40: eap-1_4 | B40: CPU-TERRA-ESCO-CARGA-2CAT-DMT3000 | C40: Encarregado de Frente | D40: DIRETO | E40: 1 | F40: 7500 | G40: 11.73 | H40: 1 | I40: 87975
A41: eap-1_4 | B41: EQ-E0016 | C41: Escavadeira Hidráulica 22t [EQ] | D41: EQ | E41: 2 | F41: 35639.3 | G41: 11.73 | H41: 1 | I41: 418048.99
A42: Subtotal eap-1_4 | I42: 4165159
A43: eap-1_5 — Esc/carg/transp 3aCat DMT<=2000m
A44: eap-1_5 | B44: CPU-TERRA-ESCO-CARGA-3CAT-DMT2000 | C44: Operador de Escavadeira | D44: DIRETO | E44: 4 | F44: 41200 | G44: 11.27 | H44: 1 | I44: 464324
A45: eap-1_5 | B45: CPU-TERRA-ESCO-CARGA-3CAT-DMT2000 | C45: Motorista de Caminhão Basculante | D45: DIRETO | E45: 25 | F45: 158529.25 | G45: 11.27 | H45: 1 | I45: 1786624.6
A46: eap-1_5 | B46: CPU-TERRA-ESCO-CARGA-3CAT-DMT2000 | C46: Ajudante | D46: DIRETO | E46: 4 | F46: 16837.28 | G46: 11.27 | H46: 1 | I46: 189756.15
A47: eap-1_5 | B47: EQ-E0016 | C47: Escavadeira Hidráulica 22t [EQ] | D47: EQ | E47: 4 | F47: 35639.3 | G47: 11.27 | H47: 1 | I47: 401654.91
A48: Subtotal eap-1_5 | I48: 16188650
A49: eap-1_6 — Esc/carg/transp 3aCat DMT<=3000m
A50: eap-1_6 | B50: CPU-TERRA-ESCO-CARGA-3CAT-DMT3000 | C50: Operador de Escavadeira | D50: DIRETO | E50: 4 | F50: 41200 | G50: 11.27 | H50: 1 | I50: 464324
A51: eap-1_6 | B51: CPU-TERRA-ESCO-CARGA-3CAT-DMT3000 | C51: Motorista de Caminhão Basculante | D51: DIRETO | E51: 25 | F51: 158529.25 | G51: 11.27 | H51: 1 | I51: 1786624.6
A52: eap-1_6 | B52: CPU-TERRA-ESCO-CARGA-3CAT-DMT3000 | C52: Ajudante | D52: DIRETO | E52: 4 | F52: 16837.28 | G52: 11.27 | H52: 1 | I52: 189756.15
A53: eap-1_6 | B53: EQ-E0016 | C53: Escavadeira Hidráulica 22t [EQ] | D53: EQ | E53: 4 | F53: 35639.3 | G53: 11.27 | H53: 1 | I53: 401654.91
A54: Subtotal eap-1_6 | I54: 16188650
A55: eap-1_7 — Compactacao aterros 100% Proctor Normal
A56: eap-1_7 | B56: CPU-TERRA-COMPAC-PN | C56: Operador de Motoniveladora | D56: DIRETO | E56: 3 | F56: 30900 | G56: 11.73 | H56: 1 | I56: 362457
A57: eap-1_7 | B57: CPU-TERRA-COMPAC-PN | C57: Operador de Trator de Pneu | D57: DIRETO | E57: 3 | F57: 19023.51 | G57: 11.73 | H57: 1 | I57: 223145.77
A58: eap-1_7 | B58: CPU-TERRA-COMPAC-PN | C58: Motorista de Caminhão Pipa | D58: DIRETO | E58: 3 | F58: 19023.51 | G58: 11.73 | H58: 1 | I58: 223145.77
A59: eap-1_7 | B59: CPU-TERRA-COMPAC-PN | C59: Operador de Rolo Compactador | D59: DIRETO | E59: 6 | F59: 38047.02 | G59: 11.73 | H59: 1 | I59: 446291.54
A60: eap-1_7 | B60: CPU-TERRA-COMPAC-PN | C60: Ajudante | D60: DIRETO | E60: 6 | F60: 25255.92 | G60: 11.73 | H60: 1 | I60: 296251.94
A61: eap-1_7 | B61: CPU-TERRA-COMPAC-PN | C61: Gredista | D61: DIRETO | E61: 3 | F61: 19023.51 | G61: 11.73 | H61: 1 | I61: 223145.77
A62: eap-1_7 | B62: CPU-TERRA-COMPAC-PN | C62: Encarregado de Frente | D62: DIRETO | E62: 2 | F62: 15000 | G62: 11.73 | H62: 1 | I62: 175950
A63: eap-1_7 | B63: EQ-E0028 | C63: Motoniveladora 120HP [EQ] | D63: EQ | E63: 3 | F63: 36664.32 | G63: 11.73 | H63: 1 | I63: 430072.47
A64: eap-1_7 | B64: EQ-E0028 | C64: Diesel — Motoniveladora 120HP | D64: COMB | E64: 3 | F64: 11478.86 | G64: 11.73 | H64: 1 | I64: 134647.03
A65: eap-1_7 | B65: EQ-E0034 | C65: Trator de pneus com grade [EQ] | D65: EQ | E65: 3 | F65: 7744 | G65: 11.73 | H65: 1 | I65: 90837.12
A66: eap-1_7 | B66: EQ-E0034 | C66: Diesel — Trator de pneus com grade | D66: COMB | E66: 3 | F66: 10203.43 | G66: 11.73 | H66: 1 | I66: 119686.23
A67: Subtotal eap-1_7 | I67: 12611777
A68: eap-1_8 — Compactacao aterros 100% Proctor Intermediario
A69: eap-1_8 | B69: CPU-TERRA-COMPAC-PI | C69: Operador de Motoniveladora | D69: DIRETO | E69: 3 | F69: 30900 | G69: 0.69 | H69: 1 | I69: 21321
A70: eap-1_8 | B70: CPU-TERRA-COMPAC-PI | C70: Operador de Trator de Pneu | D70: DIRETO | E70: 3 | F70: 19023.51 | G70: 0.69 | H70: 1 | I70: 13126.22
A71: eap-1_8 | B71: CPU-TERRA-COMPAC-PI | C71: Motorista de Caminhão Pipa | D71: DIRETO | E71: 3 | F71: 19023.51 | G71: 0.69 | H71: 1 | I71: 13126.22
A72: eap-1_8 | B72: CPU-TERRA-COMPAC-PI | C72: Operador de Rolo Compactador | D72: DIRETO | E72: 6 | F72: 38047.02 | G72: 0.69 | H72: 1 | I72: 26252.44
A73: eap-1_8 | B73: CPU-TERRA-COMPAC-PI | C73: Ajudante | D73: DIRETO | E73: 6 | F73: 25255.92 | G73: 0.69 | H73: 1 | I73: 17426.58
A74: eap-1_8 | B74: CPU-TERRA-COMPAC-PI | C74: Gredista | D74: DIRETO | E74: 3 | F74: 19023.51 | G74: 0.69 | H74: 1 | I74: 13126.22
A75: eap-1_8 | B75: CPU-TERRA-COMPAC-PI | C75: Encarregado de Frente | D75: DIRETO | E75: 2 | F75: 15000 | G75: 0.69 | H75: 1 | I75: 10350
A76: eap-1_8 | B76: EQ-E0028 | C76: Motoniveladora 120HP [EQ] | D76: EQ | E76: 3 | F76: 36664.32 | G76: 0.69 | H76: 1 | I76: 25298.38
A77: eap-1_8 | B77: EQ-E0028 | C77: Diesel — Motoniveladora 120HP | D77: COMB | E77: 3 | F77: 11478.86 | G77: 0.69 | H77: 1 | I77: 7920.41
A78: eap-1_8 | B78: EQ-E0034 | C78: Trator de pneus com grade [EQ] | D78: EQ | E78: 3 | F78: 7744 | G78: 0.69 | H78: 1 | I78: 5343.36
A79: eap-1_8 | B79: EQ-E0034 | C79: Diesel — Trator de pneus com grade | D79: COMB | E79: 3 | F79: 10203.43 | G79: 0.69 | H79: 1 | I79: 7040.37
A80: Subtotal eap-1_8 | I80: 503052.39
A81: eap-1_9 — Construcao corpo aterro material 3a categoria
A82: eap-1_9 | B82: CPU-TERRA-CORPO-ATERRO-3CAT | C82: Operador de Trator de Esteiras | D82: DIRETO | E82: 2 | F82: 20600 | G82: 11.96 | H82: 1 | I82: 246376
A83: eap-1_9 | B83: CPU-TERRA-CORPO-ATERRO-3CAT | C83: Operador de Rolo Compactador | D83: DIRETO | E83: 4 | F83: 25364.68 | G83: 11.96 | H83: 1 | I83: 303361.57
A84: eap-1_9 | B84: CPU-TERRA-CORPO-ATERRO-3CAT | C84: Ajudante | D84: DIRETO | E84: 4 | F84: 16837.28 | G84: 11.96 | H84: 1 | I84: 201373.87
A85: eap-1_9 | B85: CPU-TERRA-CORPO-ATERRO-3CAT | C85: Gredista | D85: DIRETO | E85: 2 | F85: 12682.34 | G85: 11.96 | H85: 1 | I85: 151680.79
A86: eap-1_9 | B86: CPU-TERRA-CORPO-ATERRO-3CAT | C86: Encarregado de Frente | D86: DIRETO | E86: 1 | F86: 7500 | G86: 11.96 | H86: 1 | I86: 89700
A87: eap-1_9 | B87: EQ-E0037 | C87: Trator de esteiras 40T [EQ] | D87: EQ | E87: 2 | F87: 20421.63 | G87: 11.96 | H87: 1 | I87: 244242.69
A88: eap-1_9 | B88: EQ-E0037 | C88: Diesel — Trator de esteiras 40T | D88: COMB | E88: 2 | F88: 30610.29 | G88: 11.96 | H88: 1 | I88: 366099.07
A89: Subtotal eap-1_9 | I89: 4290607.8
A90: eap-1_10 — Compactacao camada final aterro sobre rocha
A91: eap-1_10 | B91: CPU-TERRA-COMPAC-FINAL-ROCHA | C91: Operador de Trator de Esteiras | D91: DIRETO | E91: 1 | F91: 10300 | G91: 1.38 | H91: 1 | I91: 14214
A92: eap-1_10 | B92: CPU-TERRA-COMPAC-FINAL-ROCHA | C92: Operador de Rolo Compactador | D92: DIRETO | E92: 3 | F92: 19023.51 | G92: 1.38 | H92: 1 | I92: 26252.44
A93: eap-1_10 | B93: CPU-TERRA-COMPAC-FINAL-ROCHA | C93: Motorista de Caminhão Pipa | D93: DIRETO | E93: 1 | F93: 6341.17 | G93: 1.38 | H93: 1 | I93: 8750.81
A94: eap-1_10 | B94: CPU-TERRA-COMPAC-FINAL-ROCHA | C94: Ajudante | D94: DIRETO | E94: 2 | F94: 8418.64 | G94: 1.38 | H94: 1 | I94: 11617.72
A95: eap-1_10 | B95: EQ-E0035 | C95: Trator de esteiras 20T [EQ] | D95: EQ | E95: 1 | F95: 21683.2 | G95: 1.38 | H95: 1 | I95: 29922.82
A96: eap-1_10 | B96: EQ-E0035 | C96: Diesel — Trator de esteiras 20T | D96: COMB | E96: 1 | F96: 22957.71 | G96: 1.38 | H96: 1 | I96: 31681.64
A97: Subtotal eap-1_10 | I97: 122434.54
A99: TOTAL EQUIPES DIRETAS | I99: =I14+I21+I28+I35+I42+I48+I54+I67+I80+I89+I97

Sheet EQUILIBRIO
A1: PONTO DE EQUILÍBRIO — CUSTO FIXO vs PREÇO DE VENDA (CPU)
A2: Item ID | B2: CPU ID | C2: Custo Fixo Equipe (R$) | D2: Preço Venda CPU (R$) | E2: Delta (R$) | F2: Status
A3: eap-1_0 | B3: CPU-TERRA-ATI-003 | C3: 2838678.4 | D3: 2529041.1 | E3: -309637.26 | F3: ERRO
A4: eap-1_1 | B4: CPU-TERRA-ESCO-CARGA-1CAT-DMT2000 | C4: 1056081 | D4: 935297.84 | E4: -120783.14 | F4: ERRO
A5: eap-1_2 | B5: CPU-TERRA-ESCO-CARGA-1CAT-DMT3000 | C5: 1056081 | D5: 3242006.4 | E5: 2185925.4 | F5: OK
A6: eap-1_3 | B6: CPU-TERRA-ESCO-CARGA-2CAT-DMT2000 | C6: 2082662.8 | D6: 1207022.3 | E6: -875640.52 | F6: ERRO
A7: eap-1_4 | B7: CPU-TERRA-ESCO-CARGA-2CAT-DMT3000 | C7: 2082662.8 | D7: 7077172.2 | E7: 4994509.4 | F7: OK
A8: eap-1_5 | B8: CPU-TERRA-ESCO-CARGA-3CAT-DMT2000 | C8: 4047324.4 | D8: 5107452.5 | E8: 1060128.1 | F8: OK
A9: eap-1_6 | B9: CPU-TERRA-ESCO-CARGA-3CAT-DMT3000 | C9: 4047324.4 | D9: 13912325 | E9: 9865000.8 | F9: OK
A10: eap-1_7 | B10: CPU-TERRA-COMPAC-PN | C10: 4204093.7 | D10: 11620268 | E10: 7416174.3 | F10: OK
A11: eap-1_8 | B11: CPU-TERRA-COMPAC-PI | C11: 251536.26 | D11: 393487.32 | E11: 141951.06 | F11: OK
A12: eap-1_9 | B12: CPU-TERRA-CORPO-ATERRO-3CAT | C12: 2145389.7 | D12: 6435973.9 | E12: 4290584.2 | F12: OK
A13: eap-1_10 | B13: CPU-TERRA-COMPAC-FINAL-ROCHA | C13: 122439.44 | D13: 425538.27 | E13: 303098.83 | F13: OK

Sheet RESULTADO
A1: RESULTADO FINANCEIRO — MENDESLOBO CONSTRUTORA
A3: PROJETO
A4: Nome | B4: AGIS - Ferrovia Nova Transnordestina (Supressao e Terraplanagem)
A5: Tipo de obra | B5: terraplenagem
A6: Localização | B6: Ceara, Brasil
A7: Período | B7: 2026-06-01 -> 2027-06-27
A8: Regime | B8: 6 dias/sem · 8 h/dia
A10: RECEITA CONTRATUAL (COM BDI)
A11: Preço de venda s/ BDI | B11: =PLANEJAMENTO!$M$15
A12: Preço de venda c/ BDI | B12: 76753981
A14: CUSTOS
A15: Custo direto (catálogo s/BDI) | B15: =PLANEJAMENTO!$M$15
A16: ADM | B16: ='INDIRETOS.DET'!$H$5
A17: TOP | B17: ='INDIRETOS.DET'!$H$8
A18: LAB | B18: ='INDIRETOS.DET'!$H$11
A19: QSMS | B19: ='INDIRETOS.DET'!$H$14
A20: MOB | B20: ='INDIRETOS.DET'!$H$17
A21: Custo indireto (subtotal) | B21: ='INDIRETOS.DET'!$H$19
A22: CUSTO TOTAL | B22: =B15+B21
A24: RESULTADO
A25: Resultado bruto (R$) | B25: =B12-B22
A26: Margem bruta (%) | B26: =IF(B12>0, B25/B12, 0)
A28: STATUS: VERDE
A30: COMPOSIÇÃO DE CUSTO
A31: Total Direto (catálogo s/BDI) | B31: =PLANEJAMENTO!$M$15
A32: Total Direto (c/BDI) | B32: 76753981
A33: RAZÃO CI / CD (%) | B33: 41.7
A34: CI / PVT (%) | B34: 25.41
A36: CAPITAL DE GIRO
A37: Exposição máxima | B37: 19260514
A38: Parcela mensal (meses 2 a n) | B38: 6396165
A39: Resíduo (mês n+1) | B39: 6396165.6
A40: Duração da execução (meses) | B40: 12
A41: ALAVANCAS DE REAJUSTE
A42: Preço de venda total | B42: 76753981 | C42: Depende de MO/EQ/MAT/DIESEL + BDI indireto
A43: Base catálogo s/BDI | B43: 46771430 | C43: Knob de partida para precificação
A44: Markup efetivo | B44: -0.18385832 | C44: Resultado consolidado, não a fórmula de composição
A45: Custo direto de equipes | B45: 74540391 | C45: Sensível a permanência, produtividade e nº de frentes
A46: Custo fixo mensal de equipes | B46: 2762159.7 | C46: Multiplica diretamente pela permanência
A47: Permanência média (meses) | B47: 8.9281818 | C47: Reduzir prazo reduz custo fixo e mobilização
A48: Pico de equipes | B48: 1 | C48: Se subir, pressiona custo fixo e mobilização
A49: Praticabilidade média | B49: 0.9083434 | C49: Baixa praticabilidade aumenta permanência

Sheet ANALISE.FC_CAIXA
A1: FLUXO DE CAIXA — ACOMPANHAMENTO MENSAL
A2: Mês | B2: Despesa (R$) | C2: Receita (R$) | D2: Rec. Acumulada (R$) | E2: Saldo do Mês (R$) | F2: Saldo Atual (R$) | G2: Exposição Acum. (R$)
A3: Jun/26 | B3: 13849461 | C3: 0 | D3: 0 | E3: -13849461 | F3: -13849461 | G3: 13849461
A4: Jul/26 | B4: 9024383.4 | C4: 6396165 | D4: 6396165 | E4: -2628218.4 | F4: -16477680 | G4: 16477680
A5: Ago/26 | B5: 9178999.3 | C5: 6396165 | D5: 12792330 | E5: -2782834.3 | F5: -19260514 | G5: 19260514
A6: Set/26 | B6: 5945155.3 | C6: 6396165 | D6: 19188495 | E6: 451009.7 | F6: -18809504 | G6: 18809504
A7: Out/26 | B7: 5585568.1 | C7: 6396165 | D7: 25584660 | E7: 810596.93 | F7: -17998907 | G7: 17998907
A8: Nov/26 | B8: 6150114.7 | C8: 6396165 | D8: 31980825 | E8: 246050.28 | F8: -17752857 | G8: 17752857
A9: Dez/26 | B9: 3703131.3 | C9: 6396165 | D9: 38376990 | E9: 2693033.7 | F9: -15059823 | G9: 15059823
A10: Jan/27 | B10: 3220541.2 | C10: 6396165 | D10: 44773155 | E10: 3175623.8 | F10: -11884199 | G10: 11884199
A11: Fev/27 | B11: 3018228 | C11: 6396165 | D11: 51169320 | E11: 3377937 | F11: -8506262.4 | G11: 8506262.4
A12: Mar/27 | B12: 3029023.1 | C12: 6396165 | D12: 57565485 | E12: 3367141.9 | F12: -5139120.4 | G12: 5139120.4
A13: Abr/27 | B13: 2282251.4 | C13: 6396165 | D13: 63961650 | E13: 4113913.6 | F13: -1025206.8 | G13: 1025206.8
A14: Mai/27 | B14: 1289102.6 | C14: 6396165 | D14: 70357815 | E14: 5107062.4 | F14: 4081855.5 | G14: -4081855.5
A15: Jun/27 | B15: 0 | C15: 6396165.6 | D15: 76753981 | E15: 6396165.6 | F15: 10478021 | G15: -10478021
A17: TOTAL | B17: 66275959 | C17: 76753981 | D17: 76753981 | E17: 10478021 | F17: 10478021
A20: MÉTRICAS DO FLUXO DE CAIXA
A21: Duração da execução (meses) | C21: 12
A22: Parcela mensal (meses 2 a n) | C22: 6396165
A23: Resíduo (mês n+1) | C23: 6396165.6
A24: Exposição máxima | C24: 19260514
A25: Mês da exposição máxima | C25: Ago/26
A26: Saldo final do projeto | C26: 10478021
A28: Mês 1: receita = 0. Meses 2..n: ⌊M/n⌋ cada. Mês n+1: resíduo M − ⌊M/n⌋×(n−1). Saldo Atual = Rec. Acumulada − Desp. Acumulada. Exposição Acum. = −Saldo Atual (positivo = empresa precisa de capital de giro).

Sheet HIST.EQUIPAMENTOS
A1: HISTOGRAMA DE EQUIPAMENTOS — DEMANDA SEMANAL (UN.)
A2: Equip. ID | B2: Descrição | C2: Un. | D2: 08/Jun | E2: 15/Jun | F2: 22/Jun | G2: 29/Jun | H2: 06/Jul | I2: 13/Jul | J2: 20/Jul | K2: 27/Jul | L2: 03/Ago | M2: 10/Ago | N2: 17/Ago | O2: 24/Ago | P2: 31/Ago | Q2: 07/Set | R2: 14/Set | S2: 21/Set | T2: 28/Set | U2: 05/Out | V2: 12/Out | W2: 19/Out | X2: 26/Out | Y2: 02/Nov | Z2: 09/Nov | AA2: 16/Nov | AB2: 23/Nov | AC2: 30/Nov | AD2: 07/Dez | AE2: 14/Dez | AF2: 21/Dez | AG2: 28/Dez | AH2: 04/Jan | AI2: 11/Jan | AJ2: 18/Jan | AK2: 25/Jan | AL2: 01/Fev | AM2: 08/Fev | AN2: 15/Fev | AO2: 22/Fev | AP2: 01/Mar | AQ2: 08/Mar | AR2: 15/Mar | AS2: 22/Mar | AT2: 29/Mar | AU2: 05/Abr | AV2: 12/Abr | AW2: 19/Abr | AX2: 26/Abr | AY2: 03/Mai | AZ2: 10/Mai | BA2: 17/Mai | BB2: 24/Mai | BC2: 31/Mai
A3: EQ-E0016 | B3: Escavadeira Hidráulica 22t | C3: un | D3: 19 | E3: 19 | F3: 19 | G3: 19 | H3: 19 | I3: 19 | J3: 19 | K3: 19 | L3: 19 | M3: 19 | N3: 19 | O3: 19 | P3: 19 | Q3: 19 | R3: 19 | S3: 19 | T3: 19 | U3: 19 | V3: 19 | W3: 19 | X3: 19 | Y3: 19 | Z3: 19 | AA3: 19 | AB3: 19 | AC3: 14 | AD3: 14 | AE3: 14 | AF3: 14 | AG3: 14 | AH3: 14 | AI3: 14 | AJ3: 14 | AK3: 14 | AL3: 14 | AM3: 14 | AN3: 14 | AO3: 14 | AP3: 14 | AQ3: 14 | AR3: 14 | AS3: 14 | AT3: 14 | AU3: 14 | AV3: 14 | AW3: 12 | AX3: 12 | AY3: 12 | AZ3: 12 | BA3: 4 | BB3: 4
A4: EQ-E0028 | B4: Motoniveladora 120HP | C4: un | D4: 5 | E4: 5 | F4: 5 | G4: 3 | H4: 3 | I4: 3 | J4: 3 | K4: 3 | L4: 3 | M4: 3 | N4: 3 | O4: 3 | P4: 3 | Q4: 3 | R4: 3 | S4: 3 | T4: 3 | U4: 3 | V4: 3 | W4: 3 | X4: 3 | Y4: 3 | Z4: 3 | AA4: 3 | AB4: 3 | AC4: 3 | AD4: 3 | AE4: 3 | AF4: 3 | AG4: 3 | AH4: 3 | AI4: 3 | AJ4: 3 | AK4: 3 | AL4: 3 | AM4: 3 | AN4: 3 | AO4: 3 | AP4: 3 | AQ4: 3 | AR4: 3 | AS4: 3 | AT4: 3 | AU4: 3 | AV4: 3 | AW4: 3 | AX4: 3 | AY4: 3 | AZ4: 3 | BA4: 3 | BB4: 3
A5: EQ-E0034 | B5: Trator de pneus com grade | C5: un | D5: 5 | E5: 5 | F5: 5 | G5: 3 | H5: 3 | I5: 3 | J5: 3 | K5: 3 | L5: 3 | M5: 3 | N5: 3 | O5: 3 | P5: 3 | Q5: 3 | R5: 3 | S5: 3 | T5: 3 | U5: 3 | V5: 3 | W5: 3 | X5: 3 | Y5: 3 | Z5: 3 | AA5: 3 | AB5: 3 | AC5: 3 | AD5: 3 | AE5: 3 | AF5: 3 | AG5: 3 | AH5: 3 | AI5: 3 | AJ5: 3 | AK5: 3 | AL5: 3 | AM5: 3 | AN5: 3 | AO5: 3 | AP5: 3 | AQ5: 3 | AR5: 3 | AS5: 3 | AT5: 3 | AU5: 3 | AV5: 3 | AW5: 3 | AX5: 3 | AY5: 3 | AZ5: 3 | BA5: 3 | BB5: 3
A6: EQ-E0035 | B6: Trator de esteiras 20T | C6: un | D6: 31 | E6: 31 | F6: 31 | G6: 31 | H6: 31 | I6: 31 | J6: 30 | K6: 30 | L6: 30 | M6: 30 | N6: 30 | O6: 30 | P6: 30 | Q6: 30 | R6: 30 | S6: 30 | T6: 30 | U6: 30 | V6: 30 | W6: 30 | X6: 30 | Y6: 30 | Z6: 30 | AA6: 30 | AB6: 30
A7: EQ-E0037 | B7: Trator de esteiras 40T | C7: un | D7: 2 | E7: 2 | F7: 2 | G7: 2 | H7: 2 | I7: 2 | J7: 2 | K7: 2 | L7: 2 | M7: 2 | N7: 2 | O7: 2 | P7: 2 | Q7: 2 | R7: 2 | S7: 2 | T7: 2 | U7: 2 | V7: 2 | W7: 2 | X7: 2 | Y7: 2 | Z7: 2 | AA7: 2 | AB7: 2 | AC7: 2 | AD7: 2 | AE7: 2 | AF7: 2 | AG7: 2 | AH7: 2 | AI7: 2 | AJ7: 2 | AK7: 2 | AL7: 2 | AM7: 2 | AN7: 2 | AO7: 2 | AP7: 2 | AQ7: 2 | AR7: 2 | AS7: 2 | AT7: 2 | AU7: 2 | AV7: 2 | AW7: 2 | AX7: 2 | AY7: 2 | AZ7: 2 | BA7: 2 | BB7: 2 | BC7: 2
A9: TOTAL SEMANAL | D9: 62 | E9: 62 | F9: 62 | G9: 58 | H9: 58 | I9: 58 | J9: 57 | K9: 57 | L9: 57 | M9: 57 | N9: 57 | O9: 57 | P9: 57 | Q9: 57 | R9: 57 | S9: 57 | T9: 57 | U9: 57 | V9: 57 | W9: 57 | X9: 57 | Y9: 57 | Z9: 57 | AA9: 57 | AB9: 57 | AC9: 22 | AD9: 22 | AE9: 22 | AF9: 22 | AG9: 22 | AH9: 22 | AI9: 22 | AJ9: 22 | AK9: 22 | AL9: 22 | AM9: 22 | AN9: 22 | AO9: 22 | AP9: 22 | AQ9: 22 | AR9: 22 | AS9: 22 | AT9: 22 | AU9: 22 | AV9: 22 | AW9: 20 | AX9: 20 | AY9: 20 | AZ9: 20 | BA9: 12 | BB9: 12 | BC9: 2

Sheet HIST.MAO_OBRA
A1: HISTOGRAMA DE MÃO DE OBRA — DEMANDA SEMANAL (PESSOAS)
A2: Função ID | B2: Descrição | C2: Un. | D2: 08/Jun | E2: 15/Jun | F2: 22/Jun | G2: 29/Jun | H2: 06/Jul | I2: 13/Jul | J2: 20/Jul | K2: 27/Jul | L2: 03/Ago | M2: 10/Ago | N2: 17/Ago | O2: 24/Ago | P2: 31/Ago | Q2: 07/Set | R2: 14/Set | S2: 21/Set | T2: 28/Set | U2: 05/Out | V2: 12/Out | W2: 19/Out | X2: 26/Out | Y2: 02/Nov | Z2: 09/Nov | AA2: 16/Nov | AB2: 23/Nov | AC2: 30/Nov | AD2: 07/Dez | AE2: 14/Dez | AF2: 21/Dez | AG2: 28/Dez | AH2: 04/Jan | AI2: 11/Jan | AJ2: 18/Jan | AK2: 25/Jan | AL2: 01/Fev | AM2: 08/Fev | AN2: 15/Fev | AO2: 22/Fev | AP2: 01/Mar | AQ2: 08/Mar | AR2: 15/Mar | AS2: 22/Mar | AT2: 29/Mar | AU2: 05/Abr | AV2: 12/Abr | AW2: 19/Abr | AX2: 26/Abr | AY2: 03/Mai | AZ2: 10/Mai | BA2: 17/Mai | BB2: 24/Mai | BC2: 31/Mai
A3: P0001 | B3: Ajudante | C3: pax | D3: 60 | E3: 60 | F3: 60 | G3: 56 | H3: 56 | I3: 56 | J3: 54 | K3: 54 | L3: 54 | M3: 54 | N3: 54 | O3: 54 | P3: 54 | Q3: 54 | R3: 54 | S3: 54 | T3: 54 | U3: 54 | V3: 54 | W3: 54 | X3: 54 | Y3: 54 | Z3: 54 | AA3: 54 | AB3: 54 | AC3: 24 | AD3: 24 | AE3: 24 | AF3: 24 | AG3: 24 | AH3: 24 | AI3: 24 | AJ3: 24 | AK3: 24 | AL3: 24 | AM3: 24 | AN3: 24 | AO3: 24 | AP3: 24 | AQ3: 24 | AR3: 24 | AS3: 24 | AT3: 24 | AU3: 24 | AV3: 24 | AW3: 22 | AX3: 22 | AY3: 22 | AZ3: 22 | BA3: 14 | BB3: 14 | BC3: 4
A4: P0029 | B4: Gredista | C4: pax | D4: 7 | E4: 7 | F4: 7 | G4: 5 | H4: 5 | I4: 5 | J4: 5 | K4: 5 | L4: 5 | M4: 5 | N4: 5 | O4: 5 | P4: 5 | Q4: 5 | R4: 5 | S4: 5 | T4: 5 | U4: 5 | V4: 5 | W4: 5 | X4: 5 | Y4: 5 | Z4: 5 | AA4: 5 | AB4: 5 | AC4: 5 | AD4: 5 | AE4: 5 | AF4: 5 | AG4: 5 | AH4: 5 | AI4: 5 | AJ4: 5 | AK4: 5 | AL4: 5 | AM4: 5 | AN4: 5 | AO4: 5 | AP4: 5 | AQ4: 5 | AR4: 5 | AS4: 5 | AT4: 5 | AU4: 5 | AV4: 5 | AW4: 5 | AX4: 5 | AY4: 5 | AZ4: 5 | BA4: 5 | BB4: 5 | BC4: 2
A5: P0032 | B5: Motorista de Caminhão Basculante | C5: pax | D5: 86 | E5: 86 | F5: 86 | G5: 86 | H5: 86 | I5: 86 | J5: 86 | K5: 86 | L5: 86 | M5: 86 | N5: 86 | O5: 86 | P5: 86 | Q5: 86 | R5: 86 | S5: 86 | T5: 86 | U5: 86 | V5: 86 | W5: 86 | X5: 86 | Y5: 86 | Z5: 86 | AA5: 86 | AB5: 86 | AC5: 86 | AD5: 86 | AE5: 86 | AF5: 86 | AG5: 86 | AH5: 86 | AI5: 86 | AJ5: 86 | AK5: 86 | AL5: 86 | AM5: 86 | AN5: 86 | AO5: 86 | AP5: 86 | AQ5: 86 | AR5: 86 | AS5: 86 | AT5: 86 | AU5: 86 | AV5: 86 | AW5: 72 | AX5: 72 | AY5: 72 | AZ5: 72 | BA5: 22 | BB5: 22
A6: P0033 | B6: Motorista de Caminhão Pipa | C6: pax | D6: 6 | E6: 6 | F6: 6 | G6: 4 | H6: 4 | I6: 4 | J6: 3 | K6: 3 | L6: 3 | M6: 3 | N6: 3 | O6: 3 | P6: 3 | Q6: 3 | R6: 3 | S6: 3 | T6: 3 | U6: 3 | V6: 3 | W6: 3 | X6: 3 | Y6: 3 | Z6: 3 | AA6: 3 | AB6: 3 | AC6: 3 | AD6: 3 | AE6: 3 | AF6: 3 | AG6: 3 | AH6: 3 | AI6: 3 | AJ6: 3 | AK6: 3 | AL6: 3 | AM6: 3 | AN6: 3 | AO6: 3 | AP6: 3 | AQ6: 3 | AR6: 3 | AS6: 3 | AT6: 3 | AU6: 3 | AV6: 3 | AW6: 3 | AX6: 3 | AY6: 3 | AZ6: 3 | BA6: 3 | BB6: 3
A7: P0040 | B7: Operador de Escavadeira | C7: pax | D7: 19 | E7: 19 | F7: 19 | G7: 19 | H7: 19 | I7: 19 | J7: 19 | K7: 19 | L7: 19 | M7: 19 | N7: 19 | O7: 19 | P7: 19 | Q7: 19 | R7: 19 | S7: 19 | T7: 19 | U7: 19 | V7: 19 | W7: 19 | X7: 19 | Y7: 19 | Z7: 19 | AA7: 19 | AB7: 19 | AC7: 14 | AD7: 14 | AE7: 14 | AF7: 14 | AG7: 14 | AH7: 14 | AI7: 14 | AJ7: 14 | AK7: 14 | AL7: 14 | AM7: 14 | AN7: 14 | AO7: 14 | AP7: 14 | AQ7: 14 | AR7: 14 | AS7: 14 | AT7: 14 | AU7: 14 | AV7: 14 | AW7: 12 | AX7: 12 | AY7: 12 | AZ7: 12 | BA7: 4 | BB7: 4
A8: P0043 | B8: Operador de Motoniveladora | C8: pax | D8: 5 | E8: 5 | F8: 5 | G8: 3 | H8: 3 | I8: 3 | J8: 3 | K8: 3 | L8: 3 | M8: 3 | N8: 3 | O8: 3 | P8: 3 | Q8: 3 | R8: 3 | S8: 3 | T8: 3 | U8: 3 | V8: 3 | W8: 3 | X8: 3 | Y8: 3 | Z8: 3 | AA8: 3 | AB8: 3 | AC8: 3 | AD8: 3 | AE8: 3 | AF8: 3 | AG8: 3 | AH8: 3 | AI8: 3 | AJ8: 3 | AK8: 3 | AL8: 3 | AM8: 3 | AN8: 3 | AO8: 3 | AP8: 3 | AQ8: 3 | AR8: 3 | AS8: 3 | AT8: 3 | AU8: 3 | AV8: 3 | AW8: 3 | AX8: 3 | AY8: 3 | AZ8: 3 | BA8: 3 | BB8: 3
A9: P0046 | B9: Operador de Rolo Compactador | C9: pax | D9: 17 | E9: 17 | F9: 17 | G9: 13 | H9: 13 | I9: 13 | J9: 10 | K9: 10 | L9: 10 | M9: 10 | N9: 10 | O9: 10 | P9: 10 | Q9: 10 | R9: 10 | S9: 10 | T9: 10 | U9: 10 | V9: 10 | W9: 10 | X9: 10 | Y9: 10 | Z9: 10 | AA9: 10 | AB9: 10 | AC9: 10 | AD9: 10 | AE9: 10 | AF9: 10 | AG9: 10 | AH9: 10 | AI9: 10 | AJ9: 10 | AK9: 10 | AL9: 10 | AM9: 10 | AN9: 10 | AO9: 10 | AP9: 10 | AQ9: 10 | AR9: 10 | AS9: 10 | AT9: 10 | AU9: 10 | AV9: 10 | AW9: 10 | AX9: 10 | AY9: 10 | AZ9: 10 | BA9: 10 | BB9: 10 | BC9: 4
A10: P0048 | B10: Operador de Trator de Esteiras | C10: pax | D10: 33 | E10: 33 | F10: 33 | G10: 33 | H10: 33 | I10: 33 | J10: 32 | K10: 32 | L10: 32 | M10: 32 | N10: 32 | O10: 32 | P10: 32 | Q10: 32 | R10: 32 | S10: 32 | T10: 32 | U10: 32 | V10: 32 | W10: 32 | X10: 32 | Y10: 32 | Z10: 32 | AA10: 32 | AB10: 32 | AC10: 2 | AD10: 2 | AE10: 2 | AF10: 2 | AG10: 2 | AH10: 2 | AI10: 2 | AJ10: 2 | AK10: 2 | AL10: 2 | AM10: 2 | AN10: 2 | AO10: 2 | AP10: 2 | AQ10: 2 | AR10: 2 | AS10: 2 | AT10: 2 | AU10: 2 | AV10: 2 | AW10: 2 | AX10: 2 | AY10: 2 | AZ10: 2 | BA10: 2 | BB10: 2 | BC10: 2
A11: P0049 | B11: Operador de Trator de Pneu | C11: pax | D11: 5 | E11: 5 | F11: 5 | G11: 3 | H11: 3 | I11: 3 | J11: 3 | K11: 3 | L11: 3 | M11: 3 | N11: 3 | O11: 3 | P11: 3 | Q11: 3 | R11: 3 | S11: 3 | T11: 3 | U11: 3 | V11: 3 | W11: 3 | X11: 3 | Y11: 3 | Z11: 3 | AA11: 3 | AB11: 3 | AC11: 3 | AD11: 3 | AE11: 3 | AF11: 3 | AG11: 3 | AH11: 3 | AI11: 3 | AJ11: 3 | AK11: 3 | AL11: 3 | AM11: 3 | AN11: 3 | AO11: 3 | AP11: 3 | AQ11: 3 | AR11: 3 | AS11: 3 | AT11: 3 | AU11: 3 | AV11: 3 | AW11: 3 | AX11: 3 | AY11: 3 | AZ11: 3 | BA11: 3 | BB11: 3
A12: P0062 | B12: Operador de motosserra | C12: pax | D12: 30 | E12: 30 | F12: 30 | G12: 30 | H12: 30 | I12: 30 | J12: 30 | K12: 30 | L12: 30 | M12: 30 | N12: 30 | O12: 30 | P12: 30 | Q12: 30 | R12: 30 | S12: 30 | T12: 30 | U12: 30 | V12: 30 | W12: 30 | X12: 30 | Y12: 30 | Z12: 30 | AA12: 30 | AB12: 30
A13: P0065 | B13: Encarregado de Frente | C13: pax | D13: 13 | E13: 13 | F13: 13 | G13: 12 | H13: 12 | I13: 12 | J13: 12 | K13: 12 | L13: 12 | M13: 12 | N13: 12 | O13: 12 | P13: 12 | Q13: 12 | R13: 12 | S13: 12 | T13: 12 | U13: 12 | V13: 12 | W13: 12 | X13: 12 | Y13: 12 | Z13: 12 | AA13: 12 | AB13: 12 | AC13: 7 | AD13: 7 | AE13: 7 | AF13: 7 | AG13: 7 | AH13: 7 | AI13: 7 | AJ13: 7 | AK13: 7 | AL13: 7 | AM13: 7 | AN13: 7 | AO13: 7 | AP13: 7 | AQ13: 7 | AR13: 7 | AS13: 7 | AT13: 7 | AU13: 7 | AV13: 7 | AW13: 5 | AX13: 5 | AY13: 5 | AZ13: 5 | BA13: 5 | BB13: 5 | BC13: 1
A14: P0072 | B14: Apontador | C14: pax | D14: 5 | E14: 5 | F14: 5 | G14: 5 | H14: 5 | I14: 5 | J14: 5 | K14: 5 | L14: 5 | M14: 5 | N14: 5 | O14: 5 | P14: 5 | Q14: 5 | R14: 5 | S14: 5 | T14: 5 | U14: 5 | V14: 5 | W14: 5 | X14: 5 | Y14: 5 | Z14: 5 | AA14: 5 | AB14: 5
A15: P0079 | B15: SINALEIRO | C15: pax | D15: 30 | E15: 30 | F15: 30 | G15: 30 | H15: 30 | I15: 30 | J15: 30 | K15: 30 | L15: 30 | M15: 30 | N15: 30 | O15: 30 | P15: 30 | Q15: 30 | R15: 30 | S15: 30 | T15: 30 | U15: 30 | V15: 30 | W15: 30 | X15: 30 | Y15: 30 | Z15: 30 | AA15: 30 | AB15: 30
A17: TOTAL SEMANAL | D17: 316 | E17: 316 | F17: 316 | G17: 299 | H17: 299 | I17: 299 | J17: 292 | K17: 292 | L17: 292 | M17: 292 | N17: 292 | O17: 292 | P17: 292 | Q17: 292 | R17: 292 | S17: 292 | T17: 292 | U17: 292 | V17: 292 | W17: 292 | X17: 292 | Y17: 292 | Z17: 292 | AA17: 292 | AB17: 292 | AC17: 157 | AD17: 157 | AE17: 157 | AF17: 157 | AG17: 157 | AH17: 157 | AI17: 157 | AJ17: 157 | AK17: 157 | AL17: 157 | AM17: 157 | AN17: 157 | AO17: 157 | AP17: 157 | AQ17: 157 | AR17: 157 | AS17: 157 | AT17: 157 | AU17: 157 | AV17: 157 | AW17: 137 | AX17: 137 | AY17: 137 | AZ17: 137 | BA17: 71 | BB17: 71 | BC17: 13
