Workbook
Name TOTAL_DIRETO: 'DIRETOS.DET'!$I$136
Name DIRETOS_RES_SEM_BDI: 'DIRETOS.RES'!$I$15
Name DIRETOS_RES_COM_BDI: 'DIRETOS.RES'!$N$15
Name TOTAL_ADM: 'INDIRETOS.DET'!$H$26
Name TOTAL_TOP: 'INDIRETOS.DET'!$H$32
Name TOTAL_LAB: 'INDIRETOS.DET'!$H$36
Name TOTAL_QSMS: 'INDIRETOS.DET'!$H$43
Name TOTAL_MOB: 'INDIRETOS.DET'!$H$46
Name TOTAL_INDIRETO: 'INDIRETOS.DET'!$H$48
Name TOTAL_SEM_BDI: PLANEJAMENTO!$M$15
Name TOTAL_COM_BDI: PLANEJAMENTO!$N$15

Sheet MEMORIAL.BDI
A1: MEMORIAL DE CALCULO BDI - AUDITORIA PONTA A PONTA (ADR-057)
A2: Projeto: AGIS - Ferrovia Nova Transnordestina (Supressao e Terraplanagem) | Gerado: 2026-06-01T23:08:44 | Regime: pre_reforma | Vigencia: 2026-04-01
A4: 1. ENCARGOS SOCIAIS - Grupos A-F + Judicial (vigencia abril/2026)
A5: Regime | B5: Grp A | C5: Grp B | D5: Grp C | E5: Grp D | F5: Grp E | G5: Grp F | H5: Judicial | I5: TOTAL
A6: Horista CLT | B6: 37.8 | C6: 47.84 | D6: 40.53 | E6: 19.07 | F6: 10.22 | G6: 19.24 | H6: 3 | I6: 177.7
A7: Mensalista CLT | B7: 37.8 | C7: 9.94 | D7: 40.3 | E7: 4.74 | F7: 10.22 | G7: 0 | H7: 3 | I7: 106
A8: Nota: encargos aplicados ANTES do BDI. Custo MO = Salario x (1 + Encargos)
A10: 2. BDI POR CATEGORIA - Formulacao TCU Ac.2622/2013: BDI=(1+OH)/(1-T)-1
A11: Categoria | B11: AC(%) | C11: DF(%) | D11: R(%) | E11: CR(%) | F11: L(%) | G11: OH(%) | H11: COFINS | I11: ISS | J11: PIS | K11: CSSL | L11: IR | M11: T(%) | N11: BDI(%)
A12: MAO DE OBRA [inputs.tabela_bdi] | B12: 5 | C12: 1.5 | D12: 1 | E12: 0 | F12: 9 | G12: 16.5 | H12: 0 | I12: 5 | J12: 0 | K12: 1.99 | L12: 2.74 | M12: 9.73 | N12: 29.975
A13: MATERIAL [inputs.tabela_bdi] | B13: 0 | C13: 0 | D13: 0 | E13: 0 | F13: 4 | G13: 4 | H13: 0 | I13: 0 | J13: 0 | K13: 0 | L13: 0 | M13: 0 | N13: 4
A14: SERVICOS [inputs.tabela_bdi] | B14: 5 | C14: 1.5 | D14: 1 | E14: 0 | F14: 9 | G14: 16.5 | H14: 0 | I14: 5 | J14: 0 | K14: 1.99 | L14: 2.74 | M14: 9.73 | N14: 29.975
A15: INDIRETO [inputs.tabela_bdi] | B15: 5 | C15: 1.5 | D15: 1 | E15: 0 | F15: 5 | G15: 12.5 | H15: 0 | I15: 5 | J15: 0 | K15: 1.99 | L15: 2.74 | M15: 9.73 | N15: 25.2053
A16: DIESEL [inputs.tabela_bdi] | B16: 0 | C16: 0 | D16: 0 | E16: 0 | F16: 4 | G16: 4 | H16: 0 | I16: 0 | J16: 0 | K16: 0 | L16: 0 | M16: 0 | N16: 4
A18: 3. DECOMPOSICAO NO PRECO DE VENDA - De cada R$1,00 cobrado
A19: Categoria | B19: Custo Dir. | C19: OH-AC | D19: OH-DF | E19: OH-R | F19: OH-CR | G19: Margem L | H19: COFINS | I19: ISS | J19: PIS | K19: CSSL | L19: IR | M19: T Total | N19: SOMA
A20: MAO DE OBRA | B20: 77.48 | C20: 3.87 | D20: 1.16 | E20: 0.77 | F20: 0 | G20: 6.97 | H20: 0 | I20: 5 | J20: 0 | K20: 1.99 | L20: 2.74 | M20: 9.73 | N20: 100
A21: MATERIAL | B21: 96.15 | C21: 0 | D21: 0 | E21: 0 | F21: 0 | G21: 3.85 | H21: 0 | I21: 0 | J21: 0 | K21: 0 | L21: 0 | M21: 0 | N21: 100
A22: SERVICOS | B22: 77.48 | C22: 3.87 | D22: 1.16 | E22: 0.77 | F22: 0 | G22: 6.97 | H22: 0 | I22: 5 | J22: 0 | K22: 1.99 | L22: 2.74 | M22: 9.73 | N22: 100
A23: INDIRETO | B23: 80.24 | C23: 4.01 | D23: 1.2 | E23: 0.8 | F23: 0 | G23: 4.01 | H23: 0 | I23: 5 | J23: 0 | K23: 1.99 | L23: 2.74 | M23: 9.73 | N23: 100
A24: DIESEL | B24: 96.15 | C24: 0 | D24: 0 | E24: 0 | F24: 0 | G24: 3.85 | H24: 0 | I24: 0 | J24: 0 | K24: 0 | L24: 0 | M24: 0 | N24: 100
A26: 4. APLICACAO POR ITEM DA EAP - BDI efetivo x preco unitario
A27: Item | B27: Descricao | C27: CPU | D27: Un. | E27: Qtd. | F27: PU s/BDI | G27: BDI(%) | H27: PU c/BDI | I27: Sub. s/BDI | J27: Sub. c/BDI | K27: MO (R$) | L27: EQ (R$) | M27: MAT (R$) | N27: DIESEL (R$)
A28: eap-1_0 | B28: Desmatamento e limpeza de area vegetada | C28: CPU-TERRA-ATI-003 | D28: m2 | E28: 2400000 | F28: 0.8767 | G28: 17.76 | H28: 1.0324 | I28: 2104003.2 | J28: 2477673.2 | K28: 0.1929 | L28: 0.3879 | M28: 0 | N28: 0.2959
A29: eap-1_1 | B29: Esc/carg/transp 1aCat DMT<=2000m | C29: CPU-TERRA-ESCO-CARGA-1CAT-DMT2000 | D29: m3 | E29: 107463.11 | F29: 7.6583 | G29: 20.59 | H29: 9.2349 | I29: 822980.08 | J29: 992406.46 | K29: 1.4918 | L29: 4.8551 | M29: 0 | N29: 1.3114
A30: eap-1_2 | B30: Esc/carg/transp 1aCat DMT<=3000m | C30: CPU-TERRA-ESCO-CARGA-1CAT-DMT3000 | D30: m3 | E30: 336915.09 | F30: 8.4612 | G30: 20.72 | H30: 10.2145 | I30: 2850705 | J30: 3441418.8 | K30: 1.663 | L30: 5.4057 | M30: 0 | N30: 1.3925
A31: eap-1_3 | B31: Esc/carg/transp 2aCat DMT<=2000m | C31: CPU-TERRA-ESCO-CARGA-2CAT-DMT2000 | D31: m3 | E31: 105311.33 | F31: 10.0939 | G31: 20.42 | H31: 12.1553 | I31: 1063003.6 | J31: 1280092 | K31: 1.9446 | L31: 6.3386 | M31: 0 | N31: 1.8107
A32: eap-1_4 | B32: Esc/carg/transp 2aCat DMT<=3000m | C32: CPU-TERRA-ESCO-CARGA-2CAT-DMT3000 | D32: m3 | E32: 585945.77 | F32: 10.7574 | G32: 20.53 | H32: 12.9657 | I32: 6303250.1 | J32: 7597204.5 | K32: 2.0873 | L32: 6.7969 | M32: 0 | N32: 1.8732
A33: eap-1_5 | B33: Esc/carg/transp 3aCat DMT<=2000m | C33: CPU-TERRA-ESCO-CARGA-3CAT-DMT2000 | D33: m3 | E33: 304634.46 | F33: 14.8713 | G33: 20.37 | H33: 17.9001 | I33: 4530306.1 | J33: 5452981.8 | K33: 2.0472 | L33: 10.4616 | M33: 0 | N33: 2.3625
A34: eap-1_6 | B34: Esc/carg/transp 3aCat DMT<=3000m | C34: CPU-TERRA-ESCO-CARGA-3CAT-DMT3000 | D34: m3 | E34: 676519.04 | F34: 18.2248 | G34: 20.61 | H34: 21.9805 | I34: 12329412 | J34: 14870247 | K34: 2.5128 | L34: 13.0568 | M34: 0 | N34: 2.6552
A35: eap-1_7 | B35: Compactacao aterros 100% Proctor Normal | C35: CPU-TERRA-COMPAC-PN | D35: m3 | E35: 1135635.3 | F35: 9.1313 | G35: 17.23 | H35: 10.7048 | I35: 10369820 | J35: 12156798 | K35: 1.647 | L35: 4.2925 | M35: 0 | N35: 3.1918
A36: eap-1_8 | B36: Compactacao aterros 100% Proctor Intermediario | C36: CPU-TERRA-COMPAC-PI | D36: m3 | E36: 29411 | F36: 11.9393 | G36: 17.23 | H36: 13.9967 | I36: 351146.05 | J36: 411657.26 | K36: 2.1535 | L36: 5.6125 | M36: 0 | N36: 4.1733
A37: eap-1_9 | B37: Construcao corpo aterro material 3a categoria | C37: CPU-TERRA-CORPO-ATERRO-3CAT | D37: m3 | E37: 981153.5 | F37: 5.873 | G37: 17 | H37: 6.8713 | I37: 5762268.4 | J37: 6741771.1 | K37: 0.9499 | L37: 2.8415 | M37: 0 | N37: 2.0815
A38: eap-1_10 | B38: Compactacao camada final aterro sobre rocha | C38: CPU-TERRA-COMPAC-FINAL-ROCHA | D38: m3 | E38: 24721.17 | F38: 14.4369 | G38: 16.31 | H38: 16.7922 | I38: 356897.06 | J38: 415123.69 | K38: 2.34 | L38: 6.435 | M38: 0 | N38: 5.6619

Sheet CURVA.ABC
A1: CURVA ABC POR INSUMO — ANALISE DE PARETO (80/20) — ADR-058
A2: Total custo direto: R$ 12,936,539.03 | Classe A: 17 itens (78.5%) | B: 9 | C: 13
A4: Insumo ID | B4: Descricao | C4: Categoria | D4: Custo Total (R$) | E4: % Custo | F4: % Acumulado | G4: Classe | H4: Atividades
A5: AGIS-FN-MOTOR-BASC | B5: Motorista de Caminhão Basculante | C5: MAO_OBRA | D5: 1918220.7 | E5: 14.8279 | F5: 14.8279 | G5: A | H5: eap-1_1, eap-1_2, eap-1_3, eap-1_4, eap-1_5
A6: AGIS-E0015 | B6: Escavadeira Hidráulica sobre esteira 38T | C6: EQUIPAMENTO | D6: 1181550.5 | E6: 9.1334 | F6: 23.9614 | G6: A | H6: eap-1_1, eap-1_2, eap-1_3, eap-1_4
A7: AGIS-E0016 | B7: Escavadeira Hidráulica sobre esteira 48T | C7: EQUIPAMENTO | D7: 928659.27 | E7: 7.1786 | F7: 31.1399 | G7: A | H7: eap-1_5, eap-1_6
A8: AGIS-E0015__DIESEL | B8: Diesel: Escavadeira Hidráulica sobre esteira 38T | C8: DIESEL | D8: 663554.41 | E8: 5.1293 | F8: 36.2692 | G8: A | H8: eap-1_1, eap-1_2, eap-1_3, eap-1_4
A9: AGIS-TRAT-EST-40T | B9: Trator de Esteiras 40T | C9: EQUIPAMENTO | D9: 632621.44 | E9: 4.8902 | F9: 41.1594 | G9: A | H9: eap-1_9
A10: AGIS-E0002 | B10: Caminhão Basculante 14 m³ | C10: EQUIPAMENTO | D10: 539181.46 | E10: 4.1679 | F10: 45.3273 | G10: A | H10: eap-1_1, eap-1_2, eap-1_3, eap-1_4
A11: AGIS-MOTON-140K | B11: Motoniveladora 140K | C11: EQUIPAMENTO | D11: 489621.79 | E11: 3.7848 | F11: 49.1121 | G11: A | H11: eap-1_7, eap-1_8
A12: AGIS-TRAT-EST-20T | B12: Trator de Esteiras 20T | C12: EQUIPAMENTO | D12: 482724 | E12: 3.7315 | F12: 52.8436 | G12: A | H12: eap-1_0, eap-1_10
A13: AGIS-E0004 | B13: Caminhão Basculante 14 m³ - Rochas | C13: EQUIPAMENTO | D13: 459184.88 | E13: 3.5495 | F13: 56.3931 | G13: A | H13: eap-1_5, eap-1_6
A14: AGIS-E0016__DIESEL | B14: Diesel: Escavadeira Hidráulica sobre esteira 48T | C14: DIESEL | D14: 431222.43 | E14: 3.3334 | F14: 59.7265 | G14: A | H14: eap-1_5, eap-1_6
A15: AGIS-ROLO-PC-10T | B15: Rolo Compactador Pé de Carneiro 10T | C15: EQUIPAMENTO | D15: 423016 | E15: 3.2699 | F15: 62.9964 | G15: A | H15: eap-1_10, eap-1_7, eap-1_8, eap-1_9
A16: AGIS-FN-OPER-ESCAV | B16: Operador de Escavadeira | C16: MAO_OBRA | D16: 367305.4 | E16: 2.8393 | F16: 65.8357 | G16: A | H16: eap-1_0, eap-1_1, eap-1_2, eap-1_3, eap-1_4
... A43: AGIS-MOTOSSERRA__DIESEL | B43: Diesel: Motosserra a Gasolina | C43: DIESEL | D43: 14960.75 | E43: 0.1156 | F43: 100 | G43: C | H43: eap-1_0

Sheet S-CURVE
A1: CURVA S — DESEMBOLSO ACUMULADO PLANEJADO (ADR-058)
A2: Total projeto: R$ 64,505,448.17 | Direto: R$ 47,225,529.25 | Indireto: R$ 17,279,918.92
A4: Semana ISO | B4: Equip. Unicos | C4: Equipes Total | D4: Custo Semana (R$) | E4: Custo Acum. (R$) | F4: % Acumulado | G4: C. Direto | H4: C. Indireto
A5: 2026-W23 | B5: 3 | C5: 2 | D5: 2366319.1 | E5: 2366319.1 | F5: 3.6684 | G5: 61698.54 | H5: 2304620.6
A6: 2026-W24 | B6: 3 | C6: 2 | D6: 339018.88 | E6: 2705338 | F6: 4.194 | G6: 61698.54 | H6: 277320.34
A7: 2026-W25 | B7: 7 | C7: 10 | D7: 1201796.6 | E7: 3907134.6 | F7: 6.0571 | G7: 924476.26 | H7: 277320.34
A8: 2026-W26 | B8: 7 | C8: 10 | D8: 1201796.6 | E8: 5108931.2 | F8: 7.9202 | G8: 924476.26 | H8: 277320.34
A9: 2026-W27 | B9: 7 | C9: 10 | D9: 1201796.6 | E9: 6310727.8 | F9: 9.7832 | G9: 924476.26 | H9: 277320.34
A10: 2026-W28 | B10: 7 | C10: 10 | D10: 1201796.6 | E10: 7512524.4 | F10: 11.6463 | G10: 924476.26 | H10: 277320.34
A11: 2026-W29 | B11: 7 | C11: 10 | D11: 1201796.6 | E11: 8714321 | F11: 13.5094 | G11: 924476.26 | H11: 277320.34
A12: 2026-W30 | B12: 7 | C12: 10 | D12: 1201796.6 | E12: 9916117.6 | F12: 15.3725 | G12: 924476.26 | H12: 277320.34
A13: 2026-W31 | B13: 7 | C13: 10 | D13: 1201796.6 | E13: 11117914 | F13: 17.2356 | G13: 924476.26 | H13: 277320.34
A14: 2026-W32 | B14: 7 | C14: 10 | D14: 1201796.6 | E14: 12319711 | F14: 19.0987 | G14: 924476.26 | H14: 277320.34
A15: 2026-W33 | B15: 7 | C15: 10 | D15: 1201796.6 | E15: 13521507 | F15: 20.9618 | G15: 924476.26 | H15: 277320.34
A16: 2026-W34 | B16: 7 | C16: 10 | D16: 1201796.6 | E16: 14723304 | F16: 22.8249 | G16: 924476.26 | H16: 277320.34
... A59: 2027-W24 | B59: 4 | C59: 1 | D59: 330459.75 | E59: 64505448 | F59: 100 | G59: 53139.41 | H59: 277320.34

Sheet CAMPANHA.FROTA
A1: CAMPANHAS DE PERMANENCIA DE EQUIPAMENTOS (ADR-059)
A2: Campanhas: 0 | Economia vs. dismissal: R$ 0.00 | Standby total: R$ 0.00 | Economia liquida: R$ 0.00
A4: Instancia | B4: Tipo Equip. | C4: Sem. Entrada | D4: Sem. Saida | E4: Sem. Ativas | F4: Sem. Standby | G4: Mob (R$) | H4: Demob (R$) | I4: Standby Total | J4: Custo Camp. | K4: Economia | L4: Atividades

Sheet CUBO.COMP
A1: COMPOSICAO DO PRECO DE VENDA — CUBO 4D (CATEGORIA x ATIVIDADE x TEMPO x BDI)
A2: Regime BDI: pre_reforma | Total PV: R$ 59,931,222.93 | Custo Direto: 80.9% | Margem: 6.4% | Tributos: 8.0%
A4: 1. SUMARIO POR COMPONENTE BDI (total do projeto)
A5: Componente | B5: R$ Total | C5: % PV
A6: Custo Direto | B6: 48468762 | C6: 80.87
A7: Overhead Total | B7: 2850563.3 | C7: 4.76
A8: Margem L | B8: 3839131.9 | C8: 6.41
A9: Tributos Total | B9: 4772766 | C9: 7.96
A11: 2. EXPOSICAO TRIBUTARIA POR TIPO (projeto inteiro)
A12: Tributo | B12: R$ Total | C12: % PV
A13: ISS | B13: 2452603.1 | C13: 4.09
A14: IR | B14: 1344027.2 | C14: 2.24
A15: CSSL | B15: 976135.6 | C15: 1.63
A17: 3. MARGEM (L) POR ATIVIDADE
A18: Atividade | B18: Margem (R$) | C18: % Margem Total
A19: eap-1_6 | B19: 792971.46 | C19: 20.65
A20: eap-1_7 | B20: 785195.95 | C20: 20.45
A21: eap-1_9 | B21: 746326.08 | C21: 19.44
A22: eap-1_4 | B22: 537881.76 | C22: 14.01
A23: eap-1_5 | B23: 349840.35 | C23: 9.11
A24: eap-1_2 | B24: 242942.66 | C24: 6.33
A25: eap-1_0 | B25: 158585.18 | C25: 4.13
A26: eap-1_3 | B26: 96542.88 | C26: 2.51
A27: eap-1_1 | B27: 78368.6 | C27: 2.04
A28: eap-1_10 | B28: 33651.3 | C28: 0.88
A29: eap-1_8 | B29: 16825.65 | C29: 0.44
A31: 4. COMPOSICAO DO PRECO POR SEMANA (custo | overhead | margem | tributos)
A32: Semana ISO | B32: Custo Direto | C32: Overhead | D32: Margem L | E32: Tributos | F32: Total Semana | G32: % Acumulado | H32: % Semana/Total
A33: 2026-W23 | B33: 62006.96 | C33: 3275.98 | D33: 4664.27 | E33: 5485.03 | F33: 75432.24 | G33: 0.13 | H33: 0.13
A34: 2026-W24 | B34: 62006.96 | C34: 3275.98 | D34: 4664.27 | E34: 5485.03 | F34: 75432.24 | G34: 0.25 | H34: 0.13
A35: 2026-W25 | B35: 811901.15 | C35: 48938.04 | D35: 65101.49 | E35: 81938.12 | F35: 1007878.8 | G35: 1.93 | H35: 1.68
A36: 2026-W26 | B36: 811901.15 | C36: 48938.04 | D36: 65101.49 | E36: 81938.12 | F36: 1007878.8 | G36: 3.62 | H36: 1.68
A37: 2026-W27 | B37: 811901.15 | C37: 48938.04 | D37: 65101.49 | E37: 81938.12 | F37: 1007878.8 | G37: 5.3 | H37: 1.68
A38: 2026-W28 | B38: 811901.15 | C38: 48938.04 | D38: 65101.49 | E38: 81938.12 | F38: 1007878.8 | G38: 6.98 | H38: 1.68
A39: 2026-W29 | B39: 811901.15 | C39: 48938.04 | D39: 65101.49 | E39: 81938.12 | F39: 1007878.8 | G39: 8.66 | H39: 1.68
A40: 2026-W30 | B40: 811901.15 | C40: 48938.04 | D40: 65101.49 | E40: 81938.12 | F40: 1007878.8 | G40: 10.34 | H40: 1.68
A41: 2026-W31 | B41: 811901.15 | C41: 48938.04 | D41: 65101.49 | E41: 81938.12 | F41: 1007878.8 | G41: 12.02 | H41: 1.68
A42: 2026-W32 | B42: 811901.15 | C42: 48938.04 | D42: 65101.49 | E42: 81938.12 | F42: 1007878.8 | G42: 13.71 | H42: 1.68
A43: 2026-W33 | B43: 811901.15 | C43: 48938.04 | D43: 65101.49 | E43: 81938.12 | F43: 1007878.8 | G43: 15.39 | H43: 1.68
A44: 2026-W34 | B44: 811901.15 | C44: 48938.04 | D44: 65101.49 | E44: 81938.12 | F44: 1007878.8 | G44: 17.07 | H44: 1.68
... A87: 2027-W24 | B87: 75155.09 | C87: 3903.48 | D87: 5608.55 | E87: 6535.72 | F87: 91202.84 | G87: 100 | H87: 0.15

Sheet DIRETOS.DET
A1: DIRETOS — EQUIPES E RECURSOS
A2: Tipo | B2: Código | C2: Descrição | D2: Papel | E2: Qtd | F2: Custo Unit/Mês (R$) | G2: Custo Total/Mês (R$) | H2: Perm. (meses) | I2: Custo Total (R$)
A3: eap-1_0 — Desmatamento e limpeza de area vegetada
A4: MÃO DE OBRA | B4: AGIS-FN-OPER-TRAT-EST | C4: Operador de Trator de Esteiras | D4: DIRETO | E4: 1 | F4: 9394 | G4: =E4*F4 | H4: 7.82 | I4: =G4*H4
A5: MÃO DE OBRA | B5: AGIS-FN-OPER-ESCAV | C5: Operador de Escavadeira | D5: DIRETO | E5: 1 | F5: 9394 | G5: =E5*F5 | H5: 7.82 | I5: =G5*H5
A6: MÃO DE OBRA | B6: AGIS-FN-OPER-MOTOSSERRA | C6: Operador de Motosserra | D6: DIRETO | E6: 1 | F6: 9394 | G6: =E6*F6 | H6: 7.82 | I6: =G6*H6
A7: MÃO DE OBRA | B7: AGIS-FN-AJUD | C7: Ajudante | D7: DIRETO | E7: 1 | F7: 4279 | G7: =E7*F7 | H7: 7.82 | I7: =G7*H7
A8: MÃO DE OBRA | B8: AGIS-FN-ENCAR | C8: Encarregado de Frente | D8: DIRETO | E8: 1 | F8: 7499.8 | G8: =E8*F8 | H8: 7.82 | I8: =G8*H8
A9: MÃO DE OBRA | B9: AGIS-FN-APONTADOR | C9: Apontador | D9: DIRETO | E9: 1 | F9: 6448.2 | G9: =E9*F9 | H9: 7.82 | I9: =G9*H9
A10: MÃO DE OBRA | B10: AGIS-FN-SINALEIRO | C10: Sinaleiro | D10: DIRETO | E10: 1 | F10: 4279 | G10: =E10*F10 | H10: 7.82 | I10: =G10*H10
A11: EQUIPAMENTO | B11: AGIS-TRAT-EST-20T | C11: Trator de Esteiras 20T | D11: — | E11: 1 | F11: 52470 | G11: =E11*F11 | H11: 7.82 | I11: =G11*H11
A12: COMBUSTÍVEL | B12: AGIS-TRAT-EST-20T | C12: Diesel S-10 (26.0 L/h) | D12: — | E12: 1 | F12: 33161.14 | G12: =E12*F12 | H12: 7.82 | I12: =G12*H12
A13: EQUIPAMENTO | B13: AGIS-ESCAV-22T | C13: Escavadeira Hidráulica sobre esteira 22T | D13: — | E13: 1 | F13: 42416 | G13: =E13*F13 | H13: 7.82 | I13: =G13*H13
A14: COMBUSTÍVEL | B14: AGIS-ESCAV-22T | C14: Diesel S-10 (22.0 L/h) | D14: — | E14: 1 | F14: 28059.43 | G14: =E14*F14 | H14: 7.82 | I14: =G14*H14
A15: EQUIPAMENTO | B15: AGIS-MOTOSSERRA | C15: Motosserra a Gasolina | D15: — | E15: 1 | F15: 3300 | G15: =E15*F15 | H15: 7.82 | I15: =G15*H15
A16: COMBUSTÍVEL | B16: AGIS-MOTOSSERRA | C16: Diesel S-10 (1.5 L/h) | D16: — | E16: 1 | F16: 1913.14 | G16: =E16*F16 | H16: 7.82 | I16: =G16*H16
A17: Subtotal eap-1_0 | G17: =SUM(G4:G16) | H17: 7.82 | I17: =SUM(I4:I16)
A18: eap-1_1 — Esc/carg/transp 1aCat DMT<=2000m
A19: MÃO DE OBRA | B19: AGIS-FN-OPER-ESCAV | C19: Operador de Escavadeira | D19: DIRETO | E19: 1 | F19: 9394 | G19: =E19*F19 | H19: 2.3 | I19: =G19*H19
A20: MÃO DE OBRA | B20: AGIS-FN-AJUD | C20: Ajudante | D20: DIRETO | E20: 1 | F20: 4279 | G20: =E20*F20 | H20: 2.3 | I20: =G20*H20
A21: MÃO DE OBRA | B21: AGIS-FN-ENCAR | C21: Encarregado de Frente | D21: DIRETO | E21: 1 | F21: 7499.8 | G21: =E21*F21 | H21: 2.3 | I21: =G21*H21
A22: MÃO DE OBRA | B22: AGIS-FN-MOTOR-BASC | C22: Motorista de Caminhão Basculante | D22: DIRETO | E22: 7 | F22: 8382 | G22: =E22*F22 | H22: 2.3 | I22: =G22*H22
A23: EQUIPAMENTO | B23: AGIS-E0015 | C23: Escavadeira Hidráulica sobre esteira 38T | D23: — | E23: 1 | F23: 59048 | G23: =E23*F23 | H23: 2.3 | I23: =G23*H23
A24: COMBUSTÍVEL | B24: AGIS-E0015 | C24: Diesel S-10 (26.0 L/h) | D24: — | E24: 1 | F24: 33161.14 | G24: =E24*F24 | H24: 2.3 | I24: =G24*H24
A25: EQUIPAMENTO | B25: AGIS-E0002 | C25: Caminhão Basculante 14 m³ | D25: — | E25: 7 | F25: 26945.6 | G25: =E25*F25 | H25: 2.3 | I25: =G25*H25
A26: COMBUSTÍVEL | B26: AGIS-E0002 | C26: Diesel S-10 (2.5 L/h) | D26: — | E26: 7 | F26: 3188.57 | G26: =E26*F26 | H26: 2.3 | I26: =G26*H26
A27: Subtotal eap-1_1 | G27: =SUM(G19:G26) | H27: 2.3 | I27: =SUM(I19:I26)
A28: eap-1_2 — Esc/carg/transp 1aCat DMT<=3000m
A29: MÃO DE OBRA | B29: AGIS-FN-OPER-ESCAV | C29: Operador de Escavadeira | D29: DIRETO | E29: 1 | F29: 9394 | G29: =E29*F29 | H29: 7.13 | I29: =G29*H29
A30: MÃO DE OBRA | B30: AGIS-FN-AJUD | C30: Ajudante | D30: DIRETO | E30: 1 | F30: 4279 | G30: =E30*F30 | H30: 7.13 | I30: =G30*H30
A31: MÃO DE OBRA | B31: AGIS-FN-ENCAR | C31: Encarregado de Frente | D31: DIRETO | E31: 1 | F31: 7499.8 | G31: =E31*F31 | H31: 7.13 | I31: =G31*H31
A32: MÃO DE OBRA | B32: AGIS-FN-MOTOR-BASC | C32: Motorista de Caminhão Basculante | D32: DIRETO | E32: 8 | F32: 8382 | G32: =E32*F32 | H32: 7.13 | I32: =G32*H32
A33: EQUIPAMENTO | B33: AGIS-E0015 | C33: Escavadeira Hidráulica sobre esteira 38T | D33: — | E33: 1 | F33: 59048 | G33: =E33*F33 | H33: 7.13 | I33: =G33*H33
A34: COMBUSTÍVEL | B34: AGIS-E0015 | C34: Diesel S-10 (26.0 L/h) | D34: — | E34: 1 | F34: 33161.14 | G34: =E34*F34 | H34: 7.13 | I34: =G34*H34
A35: EQUIPAMENTO | B35: AGIS-E0002 | C35: Caminhão Basculante 14 m³ | D35: — | E35: 8 | F35: 26945.6 | G35: =E35*F35 | H35: 7.13 | I35: =G35*H35
A36: COMBUSTÍVEL | B36: AGIS-E0002 | C36: Diesel S-10 (2.5 L/h) | D36: — | E36: 8 | F36: 3188.57 | G36: =E36*F36 | H36: 7.13 | I36: =G36*H36
A37: Subtotal eap-1_2 | G37: =SUM(G29:G36) | H37: 7.13 | I37: =SUM(I29:I36)
A38: eap-1_3 — Esc/carg/transp 2aCat DMT<=2000m
A39: MÃO DE OBRA | B39: AGIS-FN-OPER-ESCAV | C39: Operador de Escavadeira | D39: DIRETO | E39: 1 | F39: 9394 | G39: =E39*F39 | H39: 1.61 | I39: =G39*H39
A40: MÃO DE OBRA | B40: AGIS-FN-AJUD | C40: Ajudante | D40: DIRETO | E40: 1 | F40: 4279 | G40: =E40*F40 | H40: 1.61 | I40: =G40*H40
A41: MÃO DE OBRA | B41: AGIS-FN-ENCAR | C41: Encarregado de Frente | D41: DIRETO | E41: 1 | F41: 7499.8 | G41: =E41*F41 | H41: 1.61 | I41: =G41*H41
A42: MÃO DE OBRA | B42: AGIS-FN-MOTOR-BASC | C42: Motorista de Caminhão Basculante | D42: DIRETO | E42: 6 | F42: 8382 | G42: =E42*F42 | H42: 1.61 | I42: =G42*H42
A43: EQUIPAMENTO | B43: AGIS-E0015 | C43: Escavadeira Hidráulica sobre esteira 38T | D43: — | E43: 1 | F43: 59048 | G43: =E43*F43 | H43: 1.61 | I43: =G43*H43
A44: COMBUSTÍVEL | B44: AGIS-E0015 | C44: Diesel S-10 (26.0 L/h) | D44: — | E44: 1 | F44: 33161.14 | G44: =E44*F44 | H44: 1.61 | I44: =G44*H44
A45: EQUIPAMENTO | B45: AGIS-E0002 | C45: Caminhão Basculante 14 m³ | D45: — | E45: 6 | F45: 26945.6 | G45: =E45*F45 | H45: 1.61 | I45: =G45*H45
A46: COMBUSTÍVEL | B46: AGIS-E0002 | C46: Diesel S-10 (2.5 L/h) | D46: — | E46: 6 | F46: 3188.57 | G46: =E46*F46 | H46: 1.61 | I46: =G46*H46
A47: Subtotal eap-1_3 | G47: =SUM(G39:G46) | H47: 1.61 | I47: =SUM(I39:I46)
A48: eap-1_4 — Esc/carg/transp 2aCat DMT<=3000m
A49: MÃO DE OBRA | B49: AGIS-FN-OPER-ESCAV | C49: Operador de Escavadeira | D49: DIRETO | E49: 1 | F49: 9394 | G49: =E49*F49 | H49: 8.97 | I49: =G49*H49
A50: MÃO DE OBRA | B50: AGIS-FN-AJUD | C50: Ajudante | D50: DIRETO | E50: 1 | F50: 4279 | G50: =E50*F50 | H50: 8.97 | I50: =G50*H50
A51: MÃO DE OBRA | B51: AGIS-FN-ENCAR | C51: Encarregado de Frente | D51: DIRETO | E51: 1 | F51: 7499.8 | G51: =E51*F51 | H51: 8.97 | I51: =G51*H51
A52: MÃO DE OBRA | B52: AGIS-FN-MOTOR-BASC | C52: Motorista de Caminhão Basculante | D52: DIRETO | E52: 7 | F52: 8382 | G52: =E52*F52 | H52: 8.97 | I52: =G52*H52
A53: EQUIPAMENTO | B53: AGIS-E0015 | C53: Escavadeira Hidráulica sobre esteira 38T | D53: — | E53: 1 | F53: 59048 | G53: =E53*F53 | H53: 8.97 | I53: =G53*H53
A54: COMBUSTÍVEL | B54: AGIS-E0015 | C54: Diesel S-10 (26.0 L/h) | D54: — | E54: 1 | F54: 33161.14 | G54: =E54*F54 | H54: 8.97 | I54: =G54*H54
A55: EQUIPAMENTO | B55: AGIS-E0002 | C55: Caminhão Basculante 14 m³ | D55: — | E55: 7 | F55: 26945.6 | G55: =E55*F55 | H55: 8.97 | I55: =G55*H55
A56: COMBUSTÍVEL | B56: AGIS-E0002 | C56: Diesel S-10 (2.5 L/h) | D56: — | E56: 7 | F56: 3188.57 | G56: =E56*F56 | H56: 8.97 | I56: =G56*H56
A57: Subtotal eap-1_4 | G57: =SUM(G49:G56) | H57: 8.97 | I57: =SUM(I49:I56)
A58: eap-1_5 — Esc/carg/transp 3aCat DMT<=2000m
A59: MÃO DE OBRA | B59: AGIS-FN-OPER-ESCAV | C59: Operador de Escavadeira | D59: DIRETO | E59: 1 | F59: 9394 | G59: =E59*F59 | H59: 3.45 | I59: =G59*H59
A60: MÃO DE OBRA | B60: AGIS-FN-AJUD | C60: Ajudante | D60: DIRETO | E60: 1 | F60: 4279 | G60: =E60*F60 | H60: 3.45 | I60: =G60*H60
A61: MÃO DE OBRA | B61: AGIS-FN-MOTOR-BASC | C61: Motorista de Caminhão Basculante | D61: DIRETO | E61: 6 | F61: 8382 | G61: =E61*F61 | H61: 3.45 | I61: =G61*H61
A62: EQUIPAMENTO | B62: AGIS-E0016 | C62: Escavadeira Hidráulica sobre esteira 48T | D62: — | E62: 1 | F62: 82401 | G62: =E62*F62 | H62: 3.45 | I62: =G62*H62
A63: COMBUSTÍVEL | B63: AGIS-E0016 | C63: Diesel S-10 (30.0 L/h) | D63: — | E63: 1 | F63: 38262.86 | G63: =E63*F63 | H63: 3.45 | I63: =G63*H63
A64: EQUIPAMENTO | B64: AGIS-E0004 | C64: Caminhão Basculante 14 m³ - Rochas | D64: — | E64: 6 | F64: 40744 | G64: =E64*F64 | H64: 3.45 | I64: =G64*H64
A65: COMBUSTÍVEL | B65: AGIS-E0004 | C65: Diesel S-10 (3.0 L/h) | D65: — | E65: 6 | F65: 3826.29 | G65: =E65*F65 | H65: 3.45 | I65: =G65*H65
A66: Subtotal eap-1_5 | G66: =SUM(G59:G65) | H66: 3.45 | I66: =SUM(I59:I65)
A67: eap-1_6 — Esc/carg/transp 3aCat DMT<=3000m
A68: MÃO DE OBRA | B68: AGIS-FN-OPER-ESCAV | C68: Operador de Escavadeira | D68: DIRETO | E68: 1 | F68: 9394 | G68: =E68*F68 | H68: 7.82 | I68: =G68*H68
A69: MÃO DE OBRA | B69: AGIS-FN-AJUD | C69: Ajudante | D69: DIRETO | E69: 1 | F69: 4279 | G69: =E69*F69 | H69: 7.82 | I69: =G69*H69
A70: MÃO DE OBRA | B70: AGIS-FN-MOTOR-BASC | C70: Motorista de Caminhão Basculante | D70: DIRETO | E70: 8 | F70: 8382 | G70: =E70*F70 | H70: 7.82 | I70: =G70*H70
A71: EQUIPAMENTO | B71: AGIS-E0016 | C71: Escavadeira Hidráulica sobre esteira 48T | D71: — | E71: 1 | F71: 82401 | G71: =E71*F71 | H71: 7.82 | I71: =G71*H71
A72: COMBUSTÍVEL | B72: AGIS-E0016 | C72: Diesel S-10 (30.0 L/h) | D72: — | E72: 1 | F72: 38262.86 | G72: =E72*F72 | H72: 7.82 | I72: =G72*H72
A73: EQUIPAMENTO | B73: AGIS-E0004 | C73: Caminhão Basculante 14 m³ - Rochas | D73: — | E73: 8 | F73: 40744 | G73: =E73*F73 | H73: 7.82 | I73: =G73*H73
A74: COMBUSTÍVEL | B74: AGIS-E0004 | C74: Diesel S-10 (3.0 L/h) | D74: — | E74: 8 | F74: 3826.29 | G74: =E74*F74 | H74: 7.82 | I74: =G74*H74
A75: Subtotal eap-1_6 | G75: =SUM(G68:G74) | H75: 7.82 | I75: =SUM(I68:I74)
A76: eap-1_7 — Compactacao aterros 100% Proctor Normal
A77: MÃO DE OBRA | B77: AGIS-FN-OPER-ROLO | C77: Operador de Rolo Compactador | D77: DIRETO | E77: 2 | F77: 8382 | G77: =E77*F77 | H77: 8.05 | I77: =G77*H77
A78: MÃO DE OBRA | B78: AGIS-FN-OPER-TRAT-PNEU | C78: Operador de Trator de Pneus | D78: DIRETO | E78: 1 | F78: 9394 | G78: =E78*F78 | H78: 8.05 | I78: =G78*H78
A79: MÃO DE OBRA | B79: AGIS-FN-OPER-MOTON | C79: Operador de Motoniveladora | D79: DIRETO | E79: 1 | F79: 9394 | G79: =E79*F79 | H79: 8.05 | I79: =G79*H79
A80: MÃO DE OBRA | B80: AGIS-FN-MOTOR-PIPA | C80: Motorista de Caminhão Pipa | D80: DIRETO | E80: 1 | F80: 8382 | G80: =E80*F80 | H80: 8.05 | I80: =G80*H80
A81: MÃO DE OBRA | B81: AGIS-FN-AJUD | C81: Ajudante | D81: DIRETO | E81: 2 | F81: 4279 | G81: =E81*F81 | H81: 8.05 | I81: =G81*H81
A82: MÃO DE OBRA | B82: AGIS-FN-GREDISTA | C82: Gredista | D82: DIRETO | E82: 1 | F82: 6448.2 | G82: =E82*F82 | H82: 8.05 | I82: =G82*H82
A83: MÃO DE OBRA | B83: AGIS-FN-ENCAR | C83: Encarregado de Frente | D83: DIRETO | E83: 1 | F83: 7499.8 | G83: =E83*F83 | H83: 8.05 | I83: =G83*H83
A84: EQUIPAMENTO | B84: AGIS-ROLO-PC-10T | C84: Rolo Compactador Pé de Carneiro 10T | D84: — | E84: 2 | F84: 24200 | G84: =E84*F84 | H84: 8.05 | I84: =G84*H84
A85: COMBUSTÍVEL | B85: AGIS-ROLO-PC-10T | C85: Diesel S-10 (16.0 L/h) | D85: — | E85: 2 | F85: 20406.86 | G85: =E85*F85 | H85: 8.05 | I85: =G85*H85
A86: EQUIPAMENTO | B86: AGIS-TRATOR-PNEU-GRADE | C86: Trator de Pneus com Grade | D86: — | E86: 1 | F86: 33660 | G86: =E86*F86 | H86: 8.05 | I86: =G86*H86
A87: COMBUSTÍVEL | B87: AGIS-TRATOR-PNEU-GRADE | C87: Diesel S-10 (18.0 L/h) | D87: — | E87: 1 | F87: 22957.71 | G87: =E87*F87 | H87: 8.05 | I87: =G87*H87
A88: EQUIPAMENTO | B88: AGIS-MOTON-140K | C88: Motoniveladora 140K | D88: — | E88: 1 | F88: 56020.8 | G88: =E88*F88 | H88: 8.05 | I88: =G88*H88
... A91: COMBUSTÍVEL | B91: AGIS-CAM-PIPA-18K | C91: Diesel S-10 (7.0 L/h) | D91: — | E91: 1 | F91: 8928 | G91: =E91*F91 | H91: 8.05 | I91: =G91*H91
A92: Subtotal eap-1_7 | G92: =SUM(G77:G91) | H92: 8.05 | I92: =SUM(I77:I91)
A93: eap-1_8 — Compactacao aterros 100% Proctor Intermediario
A94: MÃO DE OBRA | B94: AGIS-FN-OPER-ROLO | C94: Operador de Rolo Compactador | D94: DIRETO | E94: 2 | F94: 8382 | G94: =E94*F94 | H94: 0.69 | I94: =G94*H94
A95: MÃO DE OBRA | B95: AGIS-FN-OPER-TRAT-PNEU | C95: Operador de Trator de Pneus | D95: DIRETO | E95: 1 | F95: 9394 | G95: =E95*F95 | H95: 0.69 | I95: =G95*H95
A96: MÃO DE OBRA | B96: AGIS-FN-OPER-MOTON | C96: Operador de Motoniveladora | D96: DIRETO | E96: 1 | F96: 9394 | G96: =E96*F96 | H96: 0.69 | I96: =G96*H96
A97: MÃO DE OBRA | B97: AGIS-FN-MOTOR-PIPA | C97: Motorista de Caminhão Pipa | D97: DIRETO | E97: 1 | F97: 8382 | G97: =E97*F97 | H97: 0.69 | I97: =G97*H97
A98: MÃO DE OBRA | B98: AGIS-FN-AJUD | C98: Ajudante | D98: DIRETO | E98: 2 | F98: 4279 | G98: =E98*F98 | H98: 0.69 | I98: =G98*H98
A99: MÃO DE OBRA | B99: AGIS-FN-GREDISTA | C99: Gredista | D99: DIRETO | E99: 1 | F99: 6448.2 | G99: =E99*F99 | H99: 0.69 | I99: =G99*H99
A100: MÃO DE OBRA | B100: AGIS-FN-ENCAR | C100: Encarregado de Frente | D100: DIRETO | E100: 1 | F100: 7499.8 | G100: =E100*F100 | H100: 0.69 | I100: =G100*H100
A101: EQUIPAMENTO | B101: AGIS-ROLO-PC-10T | C101: Rolo Compactador Pé de Carneiro 10T | D101: — | E101: 2 | F101: 24200 | G101: =E101*F101 | H101: 0.69 | I101: =G101*H101
A102: COMBUSTÍVEL | B102: AGIS-ROLO-PC-10T | C102: Diesel S-10 (16.0 L/h) | D102: — | E102: 2 | F102: 20406.86 | G102: =E102*F102 | H102: 0.69 | I102: =G102*H102
...

Sheet DIRETOS.RES
A1: DIRETOS RESUMIDO — COMPONENTES MO/EQ/COMB/MAT s/BDI e c/BDI
A2: Item ID | B2: Descrição | C2: Un. | D2: Quantitativo | E2: MO s/BDI | F2: EQ s/BDI | G2: Comb. s/BDI | H2: MAT s/BDI | I2: Total s/BDI | J2: MO c/BDI | K2: EQ c/BDI | L2: Comb. c/BDI | M2: MAT c/BDI | N2: Total c/BDI
A3: eap-1_0 | B3: Desmatamento e limpeza de area vegetada | C3: m2 | D3: 2400000 | E3: 462885.6 | F3: 930979.2 | G3: 710138.4 | H3: 0 | I3: 2104003.2 | J3: 601635.56 | K3: 1137493.7 | L3: 738543.94 | M3: 0 | N3: 2477673.2
A4: eap-1_1 | B4: Esc/carg/transp 1aCat DMT<=2000m | C4: m3 | D4: 107463.11 | E4: 160309.48 | F4: 521747.78 | G4: 140922.82 | H4: 0 | I4: 822980.08 | J4: 208362.25 | K4: 637484.48 | L4: 146559.73 | M4: 0 | N4: 992406.46
A5: eap-1_2 | B5: Esc/carg/transp 1aCat DMT<=3000m | C5: m3 | D5: 336915.09 | E5: 560277.67 | F5: 1821276.1 | G5: 469151.24 | H5: 0 | I5: 2850705 | J5: 728220.91 | K5: 2225280.6 | L5: 487917.29 | M5: 0 | N5: 3441418.8
A6: eap-1_3 | B6: Esc/carg/transp 2aCat DMT<=2000m | C6: m3 | D6: 105311.33 | E6: 204790.84 | F6: 667530.62 | G6: 190682.17 | H6: 0 | I6: 1063003.6 | J6: 266176.89 | K6: 815605.6 | L6: 198309.46 | M6: 0 | N6: 1280092
A7: eap-1_4 | B7: Esc/carg/transp 2aCat DMT<=3000m | C7: m3 | D7: 585945.77 | E7: 1223028.2 | F7: 3982636.5 | G7: 1097585.4 | H7: 0 | I7: 6303250.1 | J7: 1589630.9 | K7: 4866084.8 | L7: 1141488.8 | M7: 0 | N7: 7597204.5
A8: eap-1_5 | B8: Esc/carg/transp 3aCat DMT<=2000m | C8: m3 | D8: 304634.46 | E8: 623661.98 | F8: 3186950.1 | G8: 719694.03 | H8: 0 | I8: 4530306.1 | J8: 810604.65 | K8: 3893895.3 | L8: 748481.79 | M8: 0 | N8: 5452981.8
A9: eap-1_6 | B9: Esc/carg/transp 3aCat DMT<=3000m | C9: m3 | D9: 676519.04 | E9: 1699982.8 | F9: 8833151.5 | G9: 1796277.8 | H9: 0 | I9: 12329412 | J9: 2209552.6 | K9: 10792565 | L9: 1868128.9 | M9: 0 | N9: 14870247
A10: eap-1_7 | B10: Compactacao aterros 100% Proctor Normal | C10: m3 | D10: 1135635.3 | E10: 1870441.3 | F10: 4874679.3 | G10: 3624699.2 | H10: 0 | I10: 10369820 | J10: 2431106.1 | K10: 5956005.1 | L10: 3769687.1 | M10: 0 | N10: 12156798
A11: eap-1_8 | B11: Compactacao aterros 100% Proctor Intermediario | C11: m3 | D11: 29411 | E11: 63337.44 | F11: 165067.91 | G11: 122740.69 | H11: 0 | I11: 351146.05 | J11: 82322.84 | K11: 201684.1 | L11: 127650.32 | M11: 0 | N11: 411657.26
A12: eap-1_9 | B12: Construcao corpo aterro material 3a categoria | C12: m3 | D12: 981153.5 | E12: 932009.48 | F12: 2787969.3 | G12: 2042289.6 | H12: 0 | I12: 5762268.4 | J12: 1211379.3 | K12: 3406410.5 | L12: 2123981.2 | M12: 0 | N12: 6741771.1
A13: eap-1_10 | B13: Compactacao camada final aterro sobre rocha | C13: m3 | D13: 24721.17 | E13: 57847.54 | F13: 159080.73 | G13: 139968.79 | H13: 0 | I13: 356897.06 | J13: 75187.34 | K13: 194368.81 | L13: 145567.54 | M13: 0 | N13: 415123.69
A15: TOTAL DIRETO | E15: =SUM(E3:E14) | F15: =SUM(F3:F14) | G15: =SUM(G3:G14) | H15: =SUM(H3:H14) | I15: =SUM(I3:I14) | J15: =SUM(J3:J14) | K15: =SUM(K3:K14) | L15: =SUM(L3:L14) | ... N15: =SUM(N3:N14)

Sheet INDIRETOS.DET
A1: INDIRETOS — CUSTOS INDIRETOS DETALHADOS
A2: Categoria | B2: Tipo | C2: Código/Função | D2: Descrição | E2: Qtd | F2: Custo Mensal (R$) | G2: Perm. (m) | H2: Custo Total (R$)
A3: ADM — Administracao de obra
A4: ADM | B4: MÃO DE OBRA | C4: ADMINISTRATIVO | D4: ADMINISTRATIVO | E4: 1 | F4: 10000 | G4: 13 | H4: =E4*F4*G4
A5: ADM | B5: MÃO DE OBRA | C5: AUXILIAR ADMINISTRATIVO | D5: AUXILIAR ADMINISTRATIVO | E5: 3 | F5: 20277.36 | G5: 13 | H5: =E5*F5*G5
A6: ADM | B6: MÃO DE OBRA | C6: ALMOXARIFE | D6: ALMOXARIFE | E6: 1 | F6: 6194.96 | G6: 13 | H6: =E6*F6*G6
A7: ADM | B7: MÃO DE OBRA | C7: AUXILIAR DE ALMOXARIFE | D7: AUXILIAR DE ALMOXARIFE | E7: 1 | F7: 4463.06 | G7: 13 | H7: =E7*F7*G7
A8: ADM | B8: MÃO DE OBRA | C8: GERENTE DE CONTRATO | D8: GERENTE DE CONTRATO | E8: 1 | F8: 30000 | G8: 13 | H8: =E8*F8*G8
A9: ADM | B9: MÃO DE OBRA | C9: TÉCNICO DE PLANEJAMENTO | D9: TÉCNICO DE PLANEJAMENTO | E9: 1 | F9: 14000 | G9: 13 | H9: =E9*F9*G9
A10: ADM | B10: MÃO DE OBRA | C10: ENCARREGADO GERAL | D10: ENCARREGADO GERAL | E10: 2 | F10: 36000 | G10: 13 | H10: =E10*F10*G10
A11: ADM | B11: MÃO DE OBRA | C11: ENGENHEIRO CIVIL | D11: ENGENHEIRO CIVIL | E11: 1 | F11: 22000 | G11: 13 | H11: =E11*F11*G11
A12: ADM | B12: MÃO DE OBRA | C12: MECÂNICO | D12: MECÂNICO | E12: 2 | F12: 28987.2 | G12: 13 | H12: =E12*F12*G12
A13: ADM | B13: MÃO DE OBRA | C13: AUXILIAR MECÂNICO | D13: AUXILIAR MECÂNICO | E13: 2 | F13: 8926.12 | G13: 13 | H13: =E13*F13*G13
A14: ADM | B14: MÃO DE OBRA | C14: ENCARREGADO DE MECÂNICA | D14: ENCARREGADO DE MECÂNICA | E14: 1 | F14: 9027.16 | G14: 13 | H14: =E14*F14*G14
A15: ADM | B15: MÃO DE OBRA | C15: BORRACHEIRO | D15: BORRACHEIRO | E15: 2 | F15: 12389.92 | G15: 13 | H15: =E15*F15*G15
... A25: ADM | B25: MÃO DE OBRA | C25: PREFEITO DE ALOJAMENTO | D25: PREFEITO DE ALOJAMENTO | E25: 3 | F25: 24153 | G25: 13 | H25: =E25*F25*G25
A26: Subtotal ADM | H26: =SUM(H4:H25)
A27: TOP — Topografia
A28: TOP | B28: MÃO DE OBRA | C28: TOPÓGRAFO | D28: TOPÓGRAFO | E28: 2 | F28: 36000 | G28: 13 | H28: =E28*F28*G28
A29: TOP | B29: MÃO DE OBRA | C29: AUXILIAR DE TOPOGRAFIA | D29: AUXILIAR DE TOPOGRAFIA | E29: 2 | F29: 8926.12 | G29: 13 | H29: =E29*F29*G29
A30: TOP | B30: MÃO DE OBRA | C30: SALA TÉCNICA | D30: SALA TÉCNICA | E30: 1 | F30: 12000 | G30: 13 | H30: =E30*F30*G30
A31: TOP | B31: MÃO DE OBRA | C31: AJUDANTE | D31: AJUDANTE | E31: 1 | F31: 4112.26 | G31: 13 | H31: =E31*F31*G31
A32: Subtotal TOP | H32: =SUM(H28:H31)
A33: LAB — Laboratorio de solos e materiais
A34: LAB | B34: MÃO DE OBRA | C34: LABORATORISTA | D34: LABORATORISTA | E34: 1 | F34: 9000 | G34: 13 | H34: =E34*F34*G34
A35: LAB | B35: MÃO DE OBRA | C35: AUXILIAR DE LABORATÓRIO | D35: AUXILIAR DE LABORATÓRIO | E35: 1 | F35: 4463.06 | G35: 13 | H35: =E35*F35*G35
A36: Subtotal LAB | H36: =SUM(H34:H35)
A37: QSMS — Qualidade, Saude, Seguranca e Meio Ambiente
A38: QSMS | B38: MÃO DE OBRA | C38: TÉCNICO DE SEGURANÇA DO TRABALHO | D38: TÉCNICO DE SEGURANÇA DO TRABALHO | E38: 2 | F38: 15000 | G38: 13 | H38: =E38*F38*G38
A39: QSMS | B39: MÃO DE OBRA | C39: AJUDANTE ESPECIALIZADO | D39: AJUDANTE ESPECIALIZADO | E39: 1 | F39: 4463.06 | G39: 13 | H39: =E39*F39*G39
A40: QSMS | B40: MÃO DE OBRA | C40: GERENTE DE QSMS | D40: GERENTE DE QSMS | E40: 1 | F40: 15000 | G40: 13 | H40: =E40*F40*G40
A41: QSMS | B41: MÃO DE OBRA | C41: BIÓLOGO DE CAMPO | D41: BIÓLOGO DE CAMPO | E41: 1 | F41: 7500 | G41: 13 | H41: =E41*F41*G41
A42: QSMS | B42: MÃO DE OBRA | C42: BOTÂNICO DE CAMPO | D42: BOTÂNICO DE CAMPO | E42: 1 | F42: 7500 | G42: 13 | H42: =E42*F42*G42
A43: Subtotal QSMS | H43: =SUM(H38:H42)
A44: MOB — Mobilizacao e desmobilizacao
A45: MOB | B45: CUSTO TOTAL | C45: — | D45: Mobilizacao e desmobilizacao | E45: 1 | F45: 0 | G45: 13 | H45: 4054600.4
A46: Subtotal MOB | H46: =SUM(H45:H45)
A48: TOTAL INDIRETO | H48: =H26+H32+H36+H43+H46
A51: Distribuição Mensal de Indiretos
A52: Mês | B52: Despesa Indireta (R$)
A53: Jun/26 | B53: 5249211.1
A54: Jul/26 | B54: 1194610.7
A55: Ago/26 | B55: 1194610.7
A56: Set/26 | B56: 1194610.7
A57: Out/26 | B57: 1194610.7
A58: Nov/26 | B58: 1194610.7
A59: Dez/26 | B59: 1194610.7
A60: Jan/27 | B60: 1194610.7
A61: Fev/27 | B61: 1194610.7
A62: Mar/27 | B62: 1194610.7
A63: Abr/27 | B63: 1194610.7
A64: Mai/27 | B64: 1194610.7
A65: Jun/27 | B65: 1194610.7

Sheet INDIRETOS.RES
A1: INDIRETOS RESUMIDO — CATEGORIAS + INDICADORES
A2: Categoria | B2: Descrição | C2: Custo s/BDI (R$) | D2: BDI (%) | E2: Custo c/BDI (R$) | F2: % do Total
A3: ADM | B3: Administracao de obra | C3: 13766750 | D3: 25.21 | E3: 17236701 | F3: 70.29
A4: TOP | B4: Topografia | C4: 863205.59 | D4: 25.21 | E4: 1080779.1 | F4: 4.41
A5: LAB | B5: Laboratorio de solos e materiais | C5: 140291.06 | D5: 25.21 | E5: 175651.84 | F5: 0.72
A6: QSMS | B6: Qualidade, Saude, Seguranca e Meio Ambiente | C6: 759691.79 | D6: 25.21 | E6: 951174.38 | F6: 3.88
A7: MOB | B7: Mobilizacao e desmobilizacao | C7: 4054600.4 | D7: 25.21 | E7: 5076574.6 | F7: 20.7
A9: TOTAL INDIRETO | C9: =C3+C4+C5+C6+C7 | E9: =E3+E4+E5+E6+E7
A12: INDICADORES DE COMPOSIÇÃO DE CUSTO
A13: TOTAL DIRETO (catálogo s/BDI) | C13: 46843791
A14: TOTAL INDIRETO s/BDI | C14: 21284966
A15: RAZÃO CI / CD | C15: 45.44
A16: PREÇO DE VENDA TOTAL | C16: 85639774
A17: CI / PVT | C17: 24.85

Sheet PLANEJAMENTO
A1: PLANEJAMENTO — ORÇAMENTO POR EAP (COMPONENTES s/BDI e c/BDI)
A2: Item ID | B2: Descrição | C2: Un. | D2: Quantitativo | E2: MO s/BDI (R$) | F2: MO c/BDI (R$) | G2: EQ s/BDI (R$) | H2: EQ c/BDI (R$) | I2: Comb. s/BDI (R$) | J2: Comb. c/BDI (R$) | K2: MAT s/BDI (R$) | L2: MAT c/BDI (R$) | M2: Total s/BDI (R$) | N2: Total c/BDI (R$) | O2: Criticidade
A3: eap-1_0 | B3: Desmatamento e limpeza de area vegetada | C3: m2 | D3: 2400000 | E3: 462885.6 | F3: =E3*(1+BDI!$M$3) | G3: 930979.2 | H3: =G3*(1+BDI!$M$5) | I3: 710138.4 | J3: =I3*(1+BDI!$M$7) | K3: 0 | L3: =K3*(1+BDI!$M$4) | M3: =E3+G3+I3+K3 | N3: =F3+H3+J3+L3 | O3: B
A4: eap-1_1 | B4: Esc/carg/transp 1aCat DMT<=2000m | C4: m3 | D4: 107463.11 | E4: 160309.48 | F4: =E4*(1+BDI!$M$3) | G4: 521747.78 | H4: =G4*(1+BDI!$M$5) | I4: 140922.82 | J4: =I4*(1+BDI!$M$7) | K4: 0 | L4: =K4*(1+BDI!$M$4) | M4: =E4+G4+I4+K4 | N4: =F4+H4+J4+L4 | O4: B
A5: eap-1_2 | B5: Esc/carg/transp 1aCat DMT<=3000m | C5: m3 | D5: 336915.09 | E5: 560277.67 | F5: =E5*(1+BDI!$M$3) | G5: 1821276.1 | H5: =G5*(1+BDI!$M$5) | I5: 469151.24 | J5: =I5*(1+BDI!$M$7) | K5: 0 | L5: =K5*(1+BDI!$M$4) | M5: =E5+G5+I5+K5 | N5: =F5+H5+J5+L5 | O5: A
A6: eap-1_3 | B6: Esc/carg/transp 2aCat DMT<=2000m | C6: m3 | D6: 105311.33 | E6: 204790.84 | F6: =E6*(1+BDI!$M$3) | G6: 667530.62 | H6: =G6*(1+BDI!$M$5) | I6: 190682.17 | J6: =I6*(1+BDI!$M$7) | K6: 0 | L6: =K6*(1+BDI!$M$4) | M6: =E6+G6+I6+K6 | N6: =F6+H6+J6+L6 | O6: C
A7: eap-1_4 | B7: Esc/carg/transp 2aCat DMT<=3000m | C7: m3 | D7: 585945.77 | E7: 1223028.2 | F7: =E7*(1+BDI!$M$3) | G7: 3982636.5 | H7: =G7*(1+BDI!$M$5) | I7: 1097585.4 | J7: =I7*(1+BDI!$M$7) | K7: 0 | L7: =K7*(1+BDI!$M$4) | M7: =E7+G7+I7+K7 | N7: =F7+H7+J7+L7 | O7: A+
A8: eap-1_5 | B8: Esc/carg/transp 3aCat DMT<=2000m | C8: m3 | D8: 304634.46 | E8: 623661.98 | F8: =E8*(1+BDI!$M$3) | G8: 3186950.1 | H8: =G8*(1+BDI!$M$5) | I8: 719694.03 | J8: =I8*(1+BDI!$M$7) | K8: 0 | L8: =K8*(1+BDI!$M$4) | M8: =E8+G8+I8+K8 | N8: =F8+H8+J8+L8 | O8: B
A9: eap-1_6 | B9: Esc/carg/transp 3aCat DMT<=3000m | C9: m3 | D9: 676519.04 | E9: 1699982.8 | F9: =E9*(1+BDI!$M$3) | G9: 8833151.5 | H9: =G9*(1+BDI!$M$5) | I9: 1796277.8 | J9: =I9*(1+BDI!$M$7) | K9: 0 | L9: =K9*(1+BDI!$M$4) | M9: =E9+G9+I9+K9 | N9: =F9+H9+J9+L9 | O9: A+
A10: eap-1_7 | B10: Compactacao aterros 100% Proctor Normal | C10: m3 | D10: 1135635.3 | E10: 1870441.3 | F10: =E10*(1+BDI!$M$3) | G10: 4874679.3 | H10: =G10*(1+BDI!$M$5) | I10: 3624699.2 | J10: =I10*(1+BDI!$M$7) | K10: 0 | L10: =K10*(1+BDI!$M$4) | M10: =E10+G10+I10+K10 | N10: =F10+H10+J10+L10 | O10: A+
A11: eap-1_8 | B11: Compactacao aterros 100% Proctor Intermediario | C11: m3 | D11: 29411 | E11: 63337.44 | F11: =E11*(1+BDI!$M$3) | G11: 165067.91 | H11: =G11*(1+BDI!$M$5) | I11: 122740.69 | J11: =I11*(1+BDI!$M$7) | K11: 0 | L11: =K11*(1+BDI!$M$4) | M11: =E11+G11+I11+K11 | N11: =F11+H11+J11+L11 | O11: C
A12: eap-1_9 | B12: Construcao corpo aterro material 3a categoria | C12: m3 | D12: 981153.5 | E12: 932009.48 | F12: =E12*(1+BDI!$M$3) | G12: 2787969.3 | H12: =G12*(1+BDI!$M$5) | I12: 2042289.6 | J12: =I12*(1+BDI!$M$7) | K12: 0 | L12: =K12*(1+BDI!$M$4) | M12: =E12+G12+I12+K12 | N12: =F12+H12+J12+L12 | O12: A
A13: eap-1_10 | B13: Compactacao camada final aterro sobre rocha | C13: m3 | D13: 24721.17 | E13: 57847.54 | F13: =E13*(1+BDI!$M$3) | G13: 159080.73 | H13: =G13*(1+BDI!$M$5) | I13: 139968.79 | J13: =I13*(1+BDI!$M$7) | K13: 0 | L13: =K13*(1+BDI!$M$4) | M13: =E13+G13+I13+K13 | N13: =F13+H13+J13+L13 | O13: C
A15: TOTAL | E15: =SUM(E3:E14) | F15: =SUM(F3:F14) | G15: =SUM(G3:G14) | H15: =SUM(H3:H14) | I15: =SUM(I3:I14) | J15: =SUM(J3:J14) | K15: =SUM(K3:K14) | L15: =SUM(L3:L14) | ... N15: =SUM(N3:N14)

Sheet CRONOGRAMA.DET
A1: CRONOGRAMA SEMANAL — ACOMPANHAMENTO FÍSICO DE PRODUÇÃO
A2: Item ID | B2: Descrição | C2: Un. | D2: Quantitativo | E2: Métrica | F2: 01/Jun | G2: 08/Jun | H2: 15/Jun | I2: 22/Jun | J2: 29/Jun | K2: 06/Jul | L2: 13/Jul | M2: 20/Jul | N2: 27/Jul | O2: 03/Ago | P2: 10/Ago | Q2: 17/Ago | R2: 24/Ago | S2: 31/Ago | T2: 07/Set | U2: 14/Set | V2: 21/Set | W2: 28/Set | X2: 05/Out | Y2: 12/Out | Z2: 19/Out | AA2: 26/Out | AB2: 02/Nov | AC2: 09/Nov | AD2: 16/Nov | AE2: 23/Nov | AF2: 30/Nov | AG2: 07/Dez | AH2: 14/Dez | AI2: 21/Dez | AJ2: 28/Dez | AK2: 04/Jan | AL2: 11/Jan | AM2: 18/Jan | AN2: 25/Jan | AO2: 01/Fev | AP2: 08/Fev | AQ2: 15/Fev | AR2: 22/Fev | AS2: 01/Mar | AT2: 08/Mar | AU2: 15/Mar | AV2: 22/Mar | AW2: 29/Mar | AX2: 05/Abr | AY2: 12/Abr | AZ2: 19/Abr | BA2: 26/Abr | BB2: 03/Mai | BC2: 10/Mai | BD2: 17/Mai | BE2: 24/Mai | BF2: 31/Mai | BG2: 07/Jun | BH2: 14/Jun
E3: Praticabilidade | F3: 1 | G3: 1 | H3: 1 | I3: 1 | J3: 1 | K3: 1 | L3: 1 | M3: 1 | N3: 1 | O3: 1 | P3: 1 | Q3: 1 | R3: 1 | S3: 1 | T3: 1 | U3: 1 | V3: 1 | W3: 1 | X3: 1 | Y3: 1 | Z3: 1 | AA3: 1 | AB3: 1 | AC3: 1 | AD3: 1 | AE3: 1 | AF3: 1 | AG3: 1 | AH3: 1 | AI3: 1 | AJ3: 1 | AK3: 1 | AL3: 1 | AM3: 1 | AN3: 1 | AO3: 1 | AP3: 1 | AQ3: 1 | AR3: 1 | AS3: 1 | AT3: 1 | AU3: 1 | AV3: 1 | AW3: 1 | AX3: 1 | AY3: 1 | AZ3: 1 | BA3: 1 | BB3: 1 | BC3: 1 | BD3: 1 | BE3: 1 | BF3: 1 | BG3: 1 | BH3: 1
A4: eap-1_0 | B4: Desmatamento e limpeza de area vegetada | C4: m2 | D4: 2400000 | E4: Dias Trabalhados | F4: 6 | G4: 6 | H4: 6 | I4: 6 | J4: 6 | K4: 6 | L4: 6 | M4: 6 | N4: 6 | O4: 6 | P4: 6 | Q4: 6 | R4: 6 | S4: 6 | T4: 6 | U4: 6 | V4: 6 | W4: 6 | X4: 6 | Y4: 6 | Z4: 6 | AA4: 6 | AB4: 6 | AC4: 6 | AD4: 6 | AE4: 6 | AF4: 6 | AG4: 6 | AH4: 6 | AI4: 6 | AJ4: 6 | AK4: 6 | AL4: 6 | AM4: 6
E5: Nº De Equipes | F5: 2 | G5: 2 | H5: 2 | I5: 2 | J5: 2 | K5: 2 | L5: 2 | M5: 2 | N5: 2 | O5: 2 | P5: 2 | Q5: 2 | R5: 2 | S5: 2 | T5: 2 | U5: 2 | V5: 2 | W5: 2 | X5: 2 | Y5: 2 | Z5: 2 | AA5: 2 | AB5: 2 | AC5: 2 | AD5: 2 | AE5: 2 | AF5: 2 | AG5: 2 | AH5: 2 | AI5: 2 | AJ5: 2 | AK5: 2 | AL5: 2 | AM5: 2
E6: Qtd. Planejada | F6: 70848 | G6: 70848 | H6: 70848 | I6: 70848 | J6: 70848 | K6: 70848 | L6: 70848 | M6: 70848 | N6: 70848 | O6: 70848 | P6: 70848 | Q6: 70848 | R6: 70848 | S6: 70848 | T6: 70848 | U6: 70848 | V6: 70848 | W6: 70848 | X6: 66122.44 | Y6: 66122.44 | Z6: 66122.44 | AA6: 66122.44 | AB6: 66278.3 | AC6: 66278.3 | AD6: 66278.3 | AE6: 66278.3 | AF6: 66278.3 | AG6: 66278.3 | AH6: 66278.3 | AI6: 66278.3 | AJ6: 66278.3 | AK6: 59420.22 | AL6: 59420.22 | AM6: 59420.22
E7: Qtd Plan. Acumulada | F7: 70848 | G7: 141696 | H7: 212544 | I7: 283392 | J7: 354240 | K7: 425088 | L7: 495936 | M7: 566784 | N7: 637632 | O7: 708480 | P7: 779328 | Q7: 850176 | R7: 921024 | S7: 991872 | T7: 1062720 | U7: 1133568 | V7: 1204416 | W7: 1275264 | X7: 1341386.4 | Y7: 1407508.9 | Z7: 1473631.3 | AA7: 1539753.8 | AB7: 1606032.1 | AC7: 1672310.4 | AD7: 1738588.7 | AE7: 1804867 | AF7: 1871145.3 | AG7: 1937423.6 | AH7: 2003701.9 | AI7: 2069980.2 | AJ7: 2136258.5 | AK7: 2195678.7 | AL7: 2255098.9 | AM7: 2314519.1 | AN7: 2314519.1 | AO7: 2314519.1 | AP7: 2314519.1 | AQ7: 2314519.1 | AR7: 2314519.1 | AS7: 2314519.1 | AT7: 2314519.1 | AU7: 2314519.1 | AV7: 2314519.1 | AW7: 2314519.1 | AX7: 2314519.1 | AY7: 2314519.1 | AZ7: 2314519.1 | BA7: 2314519.1 | BB7: 2314519.1 | BC7: 2314519.1 | BD7: 2314519.1 | BE7: 2314519.1 | BF7: 2314519.1 | BG7: 2314519.1 | BH7: 2314519.1
E8: % Semanal | F8: 0.0306 | G8: 0.0306 | H8: 0.0306 | I8: 0.0306 | J8: 0.0306 | K8: 0.0306 | L8: 0.0306 | M8: 0.0306 | N8: 0.0306 | O8: 0.0306 | P8: 0.0306 | Q8: 0.0306 | R8: 0.0306 | S8: 0.0306 | T8: 0.0306 | U8: 0.0306 | V8: 0.0306 | W8: 0.0306 | X8: 0.0286 | Y8: 0.0286 | Z8: 0.0286 | AA8: 0.0286 | AB8: 0.0286 | AC8: 0.0286 | AD8: 0.0286 | AE8: 0.0286 | AF8: 0.0286 | AG8: 0.0286 | AH8: 0.0286 | AI8: 0.0286 | AJ8: 0.0286 | AK8: 0.0257 | AL8: 0.0257 | AM8: 0.0257
E9: % Acumulado | F9: 0.0306 | G9: 0.0612 | H9: 0.0918 | I9: 0.1224 | J9: 0.1531 | K9: 0.1837 | L9: 0.2143 | M9: 0.2449 | N9: 0.2755 | O9: 0.3061 | P9: 0.3367 | Q9: 0.3673 | R9: 0.3979 | S9: 0.4285 | T9: 0.4592 | U9: 0.4898 | V9: 0.5204 | W9: 0.551 | X9: 0.5796 | Y9: 0.6081 | Z9: 0.6367 | AA9: 0.6653 | AB9: 0.6939 | AC9: 0.7225 | AD9: 0.7512 | AE9: 0.7798 | AF9: 0.8084 | AG9: 0.8371 | AH9: 0.8657 | AI9: 0.8943 | AJ9: 0.923 | AK9: 0.9487 | AL9: 0.9743 | AM9: 1 | AN9: 1 | AO9: 1 | AP9: 1 | AQ9: 1 | AR9: 1 | AS9: 1 | AT9: 1 | AU9: 1 | AV9: 1 | AW9: 1 | AX9: 1 | AY9: 1 | AZ9: 1 | BA9: 1 | BB9: 1 | BC9: 1 | BD9: 1 | BE9: 1 | BF9: 1 | BG9: 1 | BH9: 1
A10: eap-1_1 | B10: Esc/carg/transp 1aCat DMT<=2000m | C10: m3 | D10: 107463.11 | E10: Dias Trabalhados | R10: 6 | S10: 6 | T10: 6 | U10: 6 | V10: 6 | W10: 6 | X10: 6 | Y10: 6 | Z10: 6 | AA10: 6
E11: Nº De Equipes | R11: 1 | S11: 1 | T11: 1 | U11: 1 | V11: 1 | W11: 1 | X11: 1 | Y11: 1 | Z11: 1 | AA11: 1
E12: Qtd. Planejada | R12: 11129.76 | S12: 11129.76 | T12: 11129.76 | U12: 11129.76 | V12: 11129.76 | W12: 11129.76 | X12: 10387.41 | Y12: 10387.41 | Z12: 10387.41 | AA12: 9522.32
E13: Qtd Plan. Acumulada | R13: 11129.76 | S13: 22259.52 | T13: 33389.28 | U13: 44519.04 | V13: 55648.8 | W13: 66778.56 | X13: 77165.97 | Y13: 87553.38 | Z13: 97940.79 | AA13: 107463.11 | AB13: 107463.11 | AC13: 107463.11 | AD13: 107463.11 | AE13: 107463.11 | AF13: 107463.11 | AG13: 107463.11 | AH13: 107463.11 | AI13: 107463.11 | AJ13: 107463.11 | AK13: 107463.11 | AL13: 107463.11 | AM13: 107463.11 | AN13: 107463.11 | AO13: 107463.11 | AP13: 107463.11 | AQ13: 107463.11 | AR13: 107463.11 | AS13: 107463.11 | AT13: 107463.11 | AU13: 107463.11 | AV13: 107463.11 | AW13: 107463.11 | AX13: 107463.11 | AY13: 107463.11 | AZ13: 107463.11 | BA13: 107463.11 | BB13: 107463.11 | BC13: 107463.11 | BD13: 107463.11 | BE13: 107463.11 | BF13: 107463.11 | BG13: 107463.11 | BH13: 107463.11
E14: % Semanal | R14: 0.1036 | S14: 0.1036 | T14: 0.1036 | U14: 0.1036 | V14: 0.1036 | W14: 0.1036 | X14: 0.0967 | Y14: 0.0967 | Z14: 0.0967 | AA14: 0.0886
E15: % Acumulado | R15: 0.1036 | S15: 0.2071 | T15: 0.3107 | U15: 0.4143 | V15: 0.5178 | W15: 0.6214 | X15: 0.7181 | Y15: 0.8147 | Z15: 0.9114 | AA15: 1 | AB15: 1 | AC15: 1 | AD15: 1 | AE15: 1 | AF15: 1 | AG15: 1 | AH15: 1 | AI15: 1 | AJ15: 1 | AK15: 1 | AL15: 1 | AM15: 1 | AN15: 1 | AO15: 1 | AP15: 1 | AQ15: 1 | AR15: 1 | AS15: 1 | AT15: 1 | AU15: 1 | AV15: 1 | AW15: 1 | AX15: 1 | AY15: 1 | AZ15: 1 | BA15: 1 | BB15: 1 | BC15: 1 | BD15: 1 | BE15: 1 | BF15: 1 | BG15: 1 | BH15: 1
A16: eap-1_2 | B16: Esc/carg/transp 1aCat DMT<=3000m | C16: m3 | D16: 336915.09 | E16: Dias Trabalhados | S16: 6 | T16: 6 | U16: 6 | V16: 6 | W16: 6 | X16: 6 | Y16: 6 | Z16: 6 | AA16: 6 | AB16: 6 | AC16: 6 | AD16: 6 | AE16: 6 | AF16: 6 | AG16: 6 | AH16: 6 | AI16: 6 | AJ16: 6 | AK16: 6 | AL16: 6 | AM16: 6 | AN16: 6 | AO16: 6 | AP16: 6 | AQ16: 6 | AR16: 6 | AS16: 6 | AT16: 6 | AU16: 6 | AV16: 6 | AW16: 6
E17: Nº De Equipes | S17: 1 | T17: 1 | U17: 1 | V17: 1 | W17: 1 | X17: 1 | Y17: 1 | Z17: 1 | AA17: 1 | AB17: 1 | AC17: 1 | AD17: 1 | AE17: 1 | AF17: 1 | AG17: 1 | AH17: 1 | AI17: 1 | AJ17: 1 | AK17: 1 | AL17: 1 | AM17: 1 | AN17: 1 | AO17: 1 | AP17: 1 | AQ17: 1 | AR17: 1 | AS17: 1 | AT17: 1 | AU17: 1 | AV17: 1 | AW17: 1
E18: Qtd. Planejada | S18: 11083.68 | T18: 11083.68 | U18: 11083.68 | V18: 11083.68 | W18: 11083.68 | X18: 10344.4 | Y18: 10344.4 | Z18: 10344.4 | AA18: 10344.4 | AB18: 10368.78 | AC18: 10368.78 | AD18: 10368.78 | AE18: 10368.78 | AF18: 10368.78 | AG18: 10368.78 | AH18: 10368.78 | AI18: 10368.78 | AJ18: 10368.78 | AK18: 9295.88 | AL18: 9295.88 | AM18: 9295.88 | AN18: 9295.88 | AO18: 8708.45 | AP18: 8708.45 | AQ18: 8708.45 | AR18: 8708.45 | AS18: 6793.19 | AT18: 6793.19 | AU18: 6793.19 | AV18: 6793.19 | AW18: 9975.31
E19: Qtd Plan. Acumulada | S19: 11083.68 | T19: 22167.36 | U19: 33251.04 | V19: 44334.72 | W19: 55418.4 | X19: 65762.8 | Y19: 76107.2 | Z19: 86451.6 | AA19: 96796 | AB19: 107164.78 | AC19: 117533.56 | AD19: 127902.34 | AE19: 138271.12 | AF19: 148639.9 | AG19: 159008.68 | AH19: 169377.46 | AI19: 179746.24 | AJ19: 190115.02 | AK19: 199410.9 | AL19: 208706.78 | AM19: 218002.66 | AN19: 227298.54 | AO19: 236006.99 | AP19: 244715.44 | AQ19: 253423.89 | AR19: 262132.34 | AS19: 268925.53 | AT19: 275718.72 | AU19: 282511.91 | AV19: 289305.1 | AW19: 299280.41 | AX19: 299280.41 | AY19: 299280.41 | AZ19: 299280.41 | BA19: 299280.41 | BB19: 299280.41 | BC19: 299280.41 | BD19: 299280.41 | BE19: 299280.41 | BF19: 299280.41 | BG19: 299280.41 | BH19: 299280.41
E20: % Semanal | S20: 0.037 | T20: 0.037 | U20: 0.037 | V20: 0.037 | W20: 0.037 | X20: 0.0346 | Y20: 0.0346 | Z20: 0.0346 | AA20: 0.0346 | AB20: 0.0346 | AC20: 0.0346 | AD20: 0.0346 | AE20: 0.0346 | AF20: 0.0346 | AG20: 0.0346 | AH20: 0.0346 | AI20: 0.0346 | AJ20: 0.0346 | AK20: 0.0311 | AL20: 0.0311 | AM20: 0.0311 | AN20: 0.0311 | AO20: 0.0291 | AP20: 0.0291 | AQ20: 0.0291 | AR20: 0.0291 | AS20: 0.0227 | AT20: 0.0227 | AU20: 0.0227 | AV20: 0.0227 | AW20: 0.0333
E21: % Acumulado | S21: 0.037 | T21: 0.0741 | U21: 0.1111 | V21: 0.1481 | W21: 0.1852 | X21: 0.2197 | Y21: 0.2543 | Z21: 0.2889 | AA21: 0.3234 | AB21: 0.3581 | AC21: 0.3927 | AD21: 0.4274 | AE21: 0.462 | AF21: 0.4967 | AG21: 0.5313 | AH21: 0.5659 | AI21: 0.6006 | AJ21: 0.6352 | AK21: 0.6663 | AL21: 0.6974 | AM21: 0.7284 | AN21: 0.7595 | AO21: 0.7886 | AP21: 0.8177 | AQ21: 0.8468 | AR21: 0.8759 | AS21: 0.8986 | AT21: 0.9213 | AU21: 0.944 | AV21: 0.9667 | AW21: 1 | AX21: 1 | AY21: 1 | AZ21: 1 | BA21: 1 | BB21: 1 | BC21: 1 | BD21: 1 | BE21: 1 | BF21: 1 | BG21: 1 | BH21: 1
A22: eap-1_3 | B22: Esc/carg/transp 2aCat DMT<=2000m | C22: m3 | D22: 105311.33 | E22: Dias Trabalhados | AU22: 6 | AV22: 6 | AW22: 6 | AX22: 6 | AY22: 6 | AZ22: 6 | BA22: 6
E23: Nº De Equipes | AU23: 2 | AV23: 2 | AW23: 2 | AX23: 2 | AY23: 2 | AZ23: 2 | BA23: 2
E24: Qtd. Planejada | AU24: 9312.94 | AV24: 9312.94 | AW24: 13675.39 | AX24: 13675.39 | AY24: 13675.39 | AZ24: 13675.39 | BA24: 13234.74
E25: Qtd Plan. Acumulada | AU25: 9312.94 | AV25: 18625.88 | AW25: 32301.27 | AX25: 45976.66 | AY25: 59652.05 | AZ25: 73327.44 | BA25: 86562.18 | BB25: 86562.18 | BC25: 86562.18 | BD25: 86562.18 | BE25: 86562.18 | BF25: 86562.18 | BG25: 86562.18 | BH25: 86562.18
E26: % Semanal | AU26: 0.1076 | AV26: 0.1076 | AW26: 0.158 | AX26: 0.158 | AY26: 0.158 | AZ26: 0.158 | BA26: 0.1529
E27: % Acumulado | AU27: 0.1076 | AV27: 0.2152 | AW27: 0.3732 | AX27: 0.5311 | AY27: 0.6891 | AZ27: 0.8471 | BA27: 1 | BB27: 1 | BC27: 1 | BD27: 1 | BE27: 1 | BF27: 1 | BG27: 1 | BH27: 1
A28: eap-1_4 | B28: Esc/carg/transp 2aCat DMT<=3000m | C28: m3 | D28: 585945.77 | E28: Dias Trabalhados | H28: 6 | I28: 6 | J28: 6 | K28: 6 | L28: 6 | M28: 6 | N28: 6 | O28: 6 | P28: 6 | Q28: 6 | R28: 6 | S28: 6 | T28: 6 | U28: 6 | V28: 6 | W28: 6 | X28: 6 | Y28: 6 | Z28: 6 | AA28: 6 | AB28: 6 | AC28: 6 | AD28: 6 | AE28: 6 | AF28: 6 | AG28: 6 | AH28: 6 | AI28: 6 | AJ28: 6 | AK28: 6 | AL28: 6 | AM28: 6 | AN28: 6 | AO28: 6 | AP28: 6 | AQ28: 6 | AR28: 6 | AS28: 6 | AT28: 6
E29: Nº De Equipes | H29: 2 | I29: 2 | J29: 2 | K29: 2 | L29: 2 | M29: 2 | N29: 2 | O29: 2 | P29: 2 | Q29: 2 | R29: 2 | S29: 2 | T29: 2 | U29: 2 | V29: 2 | W29: 2 | X29: 2 | Y29: 2 | Z29: 2 | AA29: 2 | AB29: 2 | AC29: 2 | AD29: 2 | AE29: 2 | AF29: 2 | AG29: 2 | AH29: 2 | AI29: 2 | AJ29: 2 | AK29: 2 | AL29: 2 | AM29: 2 | AN29: 2 | AO29: 2 | AP29: 2 | AQ29: 2 | AR29: 2 | AS29: 2 | AT29: 2
E30: Qtd. Planejada | H30: 15242.88 | I30: 15242.88 | J30: 15242.88 | K30: 15242.88 | L30: 15242.88 | M30: 15242.88 | N30: 15242.88 | O30: 15242.88 | P30: 15242.88 | Q30: 15242.88 | R30: 15242.88 | S30: 15242.88 | T30: 15242.88 | U30: 15242.88 | V30: 15242.88 | W30: 15242.88 | X30: 14226.18 | Y30: 14226.18 | Z30: 14226.18 | AA30: 14226.18 | AB30: 14259.71 | AC30: 14259.71 | AD30: 14259.71 | AE30: 14259.71 | AF30: 14259.71 | AG30: 14259.71 | AH30: 14259.71 | AI30: 14259.71 | AJ30: 14259.71 | AK30: 12784.2 | AL30: 12784.2 | AM30: 12784.2 | AN30: 12784.2 | AO30: 11976.33 | AP30: 11976.33 | AQ30: 11976.33 | AR30: 11976.33 | AS30: 9342.36 | AT30: 9342.36
E31: Qtd Plan. Acumulada | H31: 15242.88 | I31: 30485.76 | J31: 45728.64 | K31: 60971.52 | L31: 76214.4 | M31: 91457.28 | N31: 106700.16 | O31: 121943.04 | P31: 137185.92 | Q31: 152428.8 | R31: 167671.68 | S31: 182914.56 | T31: 198157.44 | U31: 213400.32 | V31: 228643.2 | W31: 243886.08 | X31: 258112.26 | Y31: 272338.44 | Z31: 286564.62 | AA31: 300790.8 | AB31: 315050.51 | AC31: 329310.22 | AD31: 343569.93 | AE31: 357829.64 | AF31: 372089.35 | AG31: 386349.06 | AH31: 400608.77 | AI31: 414868.48 | AJ31: 429128.19 | AK31: 441912.39 | AL31: 454696.59 | AM31: 467480.79 | AN31: 480264.99 | AO31: 492241.32 | AP31: 504217.65 | AQ31: 516193.98 | AR31: 528170.31 | AS31: 537512.67 | AT31: 546855.03 | AU31: 546855.03 | AV31: 546855.03 | AW31: 546855.03 | AX31: 546855.03 | AY31: 546855.03 | AZ31: 546855.03 | BA31: 546855.03 | BB31: 546855.03 | BC31: 546855.03 | BD31: 546855.03 | BE31: 546855.03 | BF31: 546855.03 | BG31: 546855.03 | BH31: 546855.03
E32: % Semanal | H32: 0.0279 | I32: 0.0279 | J32: 0.0279 | K32: 0.0279 | L32: 0.0279 | M32: 0.0279 | N32: 0.0279 | O32: 0.0279 | P32: 0.0279 | Q32: 0.0279 | R32: 0.0279 | S32: 0.0279 | T32: 0.0279 | U32: 0.0279 | V32: 0.0279 | W32: 0.0279 | X32: 0.026 | Y32: 0.026 | Z32: 0.026 | AA32: 0.026 | AB32: 0.0261 | AC32: 0.0261 | AD32: 0.0261 | AE32: 0.0261 | AF32: 0.0261 | AG32: 0.0261 | AH32: 0.0261 | AI32: 0.0261 | AJ32: 0.0261 | AK32: 0.0234 | AL32: 0.0234 | AM32: 0.0234 | AN32: 0.0234 | AO32: 0.0219 | AP32: 0.0219 | AQ32: 0.0219 | AR32: 0.0219 | AS32: 0.0171 | AT32: 0.0171
E33: % Acumulado | H33: 0.0279 | I33: 0.0557 | J33: 0.0836 | K33: 0.1115 | L33: 0.1394 | M33: 0.1672 | N33: 0.1951 | O33: 0.223 | P33: 0.2509 | Q33: 0.2787 | R33: 0.3066 | S33: 0.3345 | T33: 0.3624 | U33: 0.3902 | V33: 0.4181 | W33: 0.446 | X33: 0.472 | Y33: 0.498 | Z33: 0.524 | AA33: 0.55 | AB33: 0.5761 | AC33: 0.6022 | AD33: 0.6283 | AE33: 0.6543 | AF33: 0.6804 | AG33: 0.7065 | AH33: 0.7326 | AI33: 0.7586 | AJ33: 0.7847 | AK33: 0.8081 | AL33: 0.8315 | AM33: 0.8549 | AN33: 0.8782 | AO33: 0.9001 | AP33: 0.922 | AQ33: 0.9439 | AR33: 0.9658 | AS33: 0.9829 | AT33: 1 | AU33: 1 | AV33: 1 | AW33: 1 | AX33: 1 | AY33: 1 | AZ33: 1 | BA33: 1 | BB33: 1 | BC33: 1 | BD33: 1 | BE33: 1 | BF33: 1 | BG33: 1 | BH33: 1
A34: eap-1_5 | B34: Esc/carg/transp 3aCat DMT<=2000m | C34: m3 | D34: 304634.46 | E34: Dias Trabalhados | H34: 6 | I34: 6 | J34: 6 | K34: 6 | L34: 6 | M34: 6 | N34: 6 | O34: 6 | P34: 6 | Q34: 6 | R34: 6 | S34: 6 | T34: 6 | U34: 6 | V34: 6
E35: Nº De Equipes | H35: 3 | I35: 3 | J35: 3 | K35: 3 | L35: 3 | M35: 3 | N35: 3 | O35: 3 | P35: 3 | Q35: 3 | R35: 3 | S35: 3 | T35: 3 | U35: 3 | V35: 3
E36: Qtd. Planejada | H36: 20450.88 | I36: 20450.88 | J36: 20450.88 | K36: 20450.88 | L36: 20450.88 | M36: 20450.88 | N36: 20450.88 | O36: 20450.88 | P36: 20450.88 | Q36: 20450.88 | R36: 20450.88 | S36: 20450.88 | T36: 20450.88 | U36: 20450.88 | V36: 18322.14
E37: Qtd Plan. Acumulada | H37: 20450.88 | I37: 40901.76 | J37: 61352.64 | K37: 81803.52 | L37: 102254.4 | M37: 122705.28 | N37: 143156.16 | O37: 163607.04 | P37: 184057.92 | Q37: 204508.8 | R37: 224959.68 | S37: 245410.56 | T37: 265861.44 | U37: 286312.32 | V37: 304634.46 | W37: 304634.46 | X37: 304634.46 | Y37: 304634.46 | Z37: 304634.46 | AA37: 304634.46 | AB37: 304634.46 | AC37: 304634.46 | AD37: 304634.46 | AE37: 304634.46 | AF37: 304634.46 | AG37: 304634.46 | AH37: 304634.46 | AI37: 304634.46 | AJ37: 304634.46 | AK37: 304634.46 | AL37: 304634.46 | AM37: 304634.46 | AN37: 304634.46 | AO37: 304634.46 | AP37: 304634.46 | AQ37: 304634.46 | AR37: 304634.46 | AS37: 304634.46 | AT37: 304634.46 | AU37: 304634.46 | AV37: 304634.46 | AW37: 304634.46 | AX37: 304634.46 | AY37: 304634.46 | AZ37: 304634.46 | BA37: 304634.46 | BB37: 304634.46 | BC37: 304634.46 | BD37: 304634.46 | BE37: 304634.46 | BF37: 304634.46 | BG37: 304634.46 | BH37: 304634.46
E38: % Semanal | H38: 0.0671 | I38: 0.0671 | J38: 0.0671 | K38: 0.0671 | L38: 0.0671 | M38: 0.0671 | N38: 0.0671 | O38: 0.0671 | P38: 0.0671 | Q38: 0.0671 | R38: 0.0671 | S38: 0.0671 | T38: 0.0671 | U38: 0.0671 | V38: 0.0601
E39: % Acumulado | H39: 0.0671 | I39: 0.1343 | J39: 0.2014 | K39: 0.2685 | L39: 0.3357 | M39: 0.4028 | N39: 0.4699 | O39: 0.5371 | P39: 0.6042 | Q39: 0.6713 | R39: 0.7385 | S39: 0.8056 | T39: 0.8727 | U39: 0.9399 | V39: 1 | W39: 1 | X39: 1 | Y39: 1 | Z39: 1 | AA39: 1 | AB39: 1 | AC39: 1 | AD39: 1 | AE39: 1 | AF39: 1 | AG39: 1 | AH39: 1 | AI39: 1 | AJ39: 1 | AK39: 1 | AL39: 1 | AM39: 1 | AN39: 1 | AO39: 1 | AP39: 1 | AQ39: 1 | AR39: 1 | AS39: 1 | AT39: 1 | AU39: 1 | AV39: 1 | AW39: 1 | AX39: 1 | AY39: 1 | AZ39: 1 | BA39: 1 | BB39: 1 | BC39: 1 | BD39: 1 | BE39: 1 | BF39: 1 | BG39: 1 | BH39: 1
A40: eap-1_6 | B40: Esc/carg/transp 3aCat DMT<=3000m | C40: m3 | D40: 676519.04 | E40: Dias Trabalhados | H40: 6 | I40: 6 | J40: 6 | K40: 6 | L40: 6 | M40: 6 | N40: 6 | O40: 6 | P40: 6 | Q40: 6 | R40: 6 | S40: 6 | T40: 6 | U40: 6 | V40: 6 | W40: 6 | X40: 6 | Y40: 6 | Z40: 6 | AA40: 6 | AB40: 6 | AC40: 6 | AD40: 6 | AE40: 6 | AF40: 6 | AG40: 6 | AH40: 6 | AI40: 6 | AJ40: 6 | AK40: 6 | AL40: 6 | AM40: 6 | AN40: 6 | AO40: 6
E41: Nº De Equipes | H41: 3 | I41: 3 | J41: 3 | K41: 3 | L41: 3 | M41: 3 | N41: 3 | O41: 3 | P41: 3 | Q41: 3 | R41: 3 | S41: 3 | T41: 3 | U41: 3 | V41: 3 | W41: 3 | X41: 3 | Y41: 3 | Z41: 3 | AA41: 3 | AB41: 3 | AC41: 3 | AD41: 3 | AE41: 3 | AF41: 3 | AG41: 3 | AH41: 3 | AI41: 3 | AJ41: 3 | AK41: 3 | AL41: 3 | AM41: 3 | AN41: 3 | AO41: 3
E42: Qtd. Planejada | H42: 20471.04 | I42: 20471.04 | J42: 20471.04 | K42: 20471.04 | L42: 20471.04 | M42: 20471.04 | N42: 20471.04 | O42: 20471.04 | P42: 20471.04 | Q42: 20471.04 | R42: 20471.04 | S42: 20471.04 | T42: 20471.04 | U42: 20471.04 | V42: 20471.04 | W42: 20471.04 | X42: 19105.62 | Y42: 19105.62 | Z42: 19105.62 | AA42: 19105.62 | AB42: 19150.66 | AC42: 19150.66 | AD42: 19150.66 | AE42: 19150.66 | AF42: 19150.66 | AG42: 19150.66 | AH42: 19150.66 | AI42: 19150.66 | AJ42: 19150.66 | AK42: 17169.06 | AL42: 17169.06 | AM42: 17169.06 | AN42: 17169.06 | AO42: 16084.1
E43: Qtd Plan. Acumulada | H43: 20471.04 | I43: 40942.08 | J43: 61413.12 | K43: 81884.16 | L43: 102355.2 | M43: 122826.24 | N43: 143297.28 | O43: 163768.32 | P43: 184239.36 | Q43: 204710.4 | R43: 225181.44 | S43: 245652.48 | T43: 266123.52 | U43: 286594.56 | V43: 307065.6 | W43: 327536.64 | X43: 346642.26 | Y43: 365747.88 | Z43: 384853.5 | AA43: 403959.12 | AB43: 423109.78 | AC43: 442260.44 | AD43: 461411.1 | AE43: 480561.76 | AF43: 499712.42 | AG43: 518863.08 | AH43: 538013.74 | AI43: 557164.4 | AJ43: 576315.06 | AK43: 593484.12 | AL43: 610653.18 | AM43: 627822.24 | AN43: 644991.3 | AO43: 661075.4 | AP43: 661075.4 | AQ43: 661075.4 | AR43: 661075.4 | AS43: 661075.4 | AT43: 661075.4 | AU43: 661075.4 | AV43: 661075.4 | AW43: 661075.4 | AX43: 661075.4 | AY43: 661075.4 | AZ43: 661075.4 | BA43: 661075.4 | BB43: 661075.4 | BC43: 661075.4 | BD43: 661075.4 | BE43: 661075.4 | BF43: 661075.4 | BG43: 661075.4 | BH43: 661075.4
E44: % Semanal | H44: 0.031 | I44: 0.031 | J44: 0.031 | K44: 0.031 | L44: 0.031 | M44: 0.031 | N44: 0.031 | O44: 0.031 | P44: 0.031 | Q44: 0.031 | R44: 0.031 | S44: 0.031 | T44: 0.031 | U44: 0.031 | V44: 0.031 | W44: 0.031 | X44: 0.0289 | Y44: 0.0289 | Z44: 0.0289 | AA44: 0.0289 | AB44: 0.029 | AC44: 0.029 | AD44: 0.029 | AE44: 0.029 | AF44: 0.029 | AG44: 0.029 | AH44: 0.029 | AI44: 0.029 | AJ44: 0.029 | AK44: 0.026 | AL44: 0.026 | AM44: 0.026 | AN44: 0.026 | AO44: 0.0243
E45: % Acumulado | H45: 0.031 | I45: 0.0619 | J45: 0.0929 | K45: 0.1239 | L45: 0.1548 | M45: 0.1858 | N45: 0.2168 | O45: 0.2477 | P45: 0.2787 | Q45: 0.3097 | R45: 0.3406 | S45: 0.3716 | T45: 0.4026 | U45: 0.4335 | V45: 0.4645 | W45: 0.4955 | X45: 0.5244 | Y45: 0.5533 | Z45: 0.5822 | AA45: 0.6111 | AB45: 0.64 | AC45: 0.669 | AD45: 0.698 | AE45: 0.7269 | AF45: 0.7559 | AG45: 0.7849 | AH45: 0.8138 | AI45: 0.8428 | AJ45: 0.8718 | AK45: 0.8978 | AL45: 0.9237 | AM45: 0.9497 | AN45: 0.9757 | AO45: 1 | AP45: 1 | AQ45: 1 | AR45: 1 | AS45: 1 | AT45: 1 | AU45: 1 | AV45: 1 | AW45: 1 | AX45: 1 | AY45: 1 | AZ45: 1 | BA45: 1 | BB45: 1 | BC45: 1 | BD45: 1 | BE45: 1 | BF45: 1 | BG45: 1 | BH45: 1
A46: eap-1_7 | B46: Compactacao aterros 100% Proctor Normal | C46: m3 | D46: 1135635.3 | E46: Dias Trabalhados | S46: 6 | T46: 6 | U46: 6 | V46: 6 | W46: 6 | X46: 6 | Y46: 6 | Z46: 6 | AA46: 6 | AB46: 6 | AC46: 6 | AD46: 6 | AE46: 6 | AF46: 6 | AG46: 6 | AH46: 6 | AI46: 6 | AJ46: 6 | AK46: 6 | AL46: 6 | AM46: 6 | AN46: 6 | AO46: 6 | AP46: 6 | AQ46: 6 | AR46: 6 | AS46: 6 | AT46: 6 | AU46: 6 | AV46: 6 | AW46: 6 | AX46: 6 | AY46: 6 | AZ46: 6 | BA46: 6
E47: Nº De Equipes | S47: 4 | T47: 4 | U47: 4 | V47: 4 | W47: 4 | X47: 4 | Y47: 4 | Z47: 4 | AA47: 4 | AB47: 4 | AC47: 4 | AD47: 4 | AE47: 4 | AF47: 4 | AG47: 4 | AH47: 4 | AI47: 4 | AJ47: 4 | AK47: 4 | AL47: 4 | AM47: 4 | AN47: 4 | AO47: 4 | AP47: 4 | AQ47: 4 | AR47: 4 | AS47: 4 | AT47: 4 | AU47: 4 | AV47: 4 | AW47: 4 | AX47: 4 | AY47: 4 | AZ47: 4 | BA47: 4
E48: Qtd. Planejada | S48: 33217.92 | T48: 33217.92 | U48: 33217.92 | V48: 33217.92 | W48: 33217.92 | X48: 31002.28 | Y48: 31002.28 | Z48: 31002.28 | AA48: 31002.28 | AB48: 31075.36 | AC48: 31075.36 | AD48: 31075.36 | AE48: 31075.36 | AF48: 31075.36 | AG48: 31075.36 | AH48: 31075.36 | AI48: 31075.36 | AJ48: 31075.36 | AK48: 27859.87 | AL48: 27859.87 | AM48: 27859.87 | AN48: 27859.87 | AO48: 26099.32 | AP48: 26099.32 | AQ48: 26099.32 | AR48: 26099.32 | AS48: 20359.26 | AT48: 20359.26 | AU48: 20359.26 | AV48: 20359.26 | AW48: 29896.13 | AX48: 29896.13 | AY48: 29896.13 | AZ48: 29896.13 | BA48: 28932.81
E49: Qtd Plan. Acumulada | S49: 33217.92 | T49: 66435.84 | U49: 99653.76 | V49: 132871.68 | W49: 166089.6 | X49: 197091.88 | Y49: 228094.16 | Z49: 259096.44 | AA49: 290098.72 | AB49: 321174.08 | AC49: 352249.44 | AD49: 383324.8 | AE49: 414400.16 | AF49: 445475.52 | AG49: 476550.88 | AH49: 507626.24 | AI49: 538701.6 | AJ49: 569776.96 | AK49: 597636.83 | AL49: 625496.7 | AM49: 653356.57 | AN49: 681216.44 | AO49: 707315.76 | AP49: 733415.08 | AQ49: 759514.4 | AR49: 785613.72 | AS49: 805972.98 | AT49: 826332.24 | AU49: 846691.5 | AV49: 867050.76 | AW49: 896946.89 | AX49: 926843.02 | AY49: 956739.15 | AZ49: 986635.28 | BA49: 1015568.1 | BB49: 1015568.1 | BC49: 1015568.1 | BD49: 1015568.1 | BE49: 1015568.1 | BF49: 1015568.1 | BG49: 1015568.1 | BH49: 1015568.1
E50: % Semanal | S50: 0.0327 | T50: 0.0327 | U50: 0.0327 | V50: 0.0327 | W50: 0.0327 | X50: 0.0305 | Y50: 0.0305 | Z50: 0.0305 | AA50: 0.0305 | AB50: 0.0306 | AC50: 0.0306 | AD50: 0.0306 | AE50: 0.0306 | AF50: 0.0306 | AG50: 0.0306 | AH50: 0.0306 | AI50: 0.0306 | AJ50: 0.0306 | AK50: 0.0274 | AL50: 0.0274 | AM50: 0.0274 | AN50: 0.0274 | AO50: 0.0257 | AP50: 0.0257 | AQ50: 0.0257 | AR50: 0.0257 | AS50: 0.02 | AT50: 0.02 | AU50: 0.02 | AV50: 0.02 | AW50: 0.0294 | AX50: 0.0294 | AY50: 0.0294 | AZ50: 0.0294 | BA50: 0.0285
E51: % Acumulado | S51: 0.0327 | T51: 0.0654 | U51: 0.0981 | V51: 0.1308 | W51: 0.1635 | X51: 0.1941 | Y51: 0.2246 | Z51: 0.2551 | AA51: 0.2857 | AB51: 0.3163 | AC51: 0.3468 | AD51: 0.3774 | AE51: 0.408 | AF51: 0.4386 | AG51: 0.4692 | AH51: 0.4998 | AI51: 0.5304 | AJ51: 0.561 | AK51: 0.5885 | AL51: 0.6159 | AM51: 0.6433 | AN51: 0.6708 | AO51: 0.6965 | AP51: 0.7222 | AQ51: 0.7479 | AR51: 0.7736 | AS51: 0.7936 | AT51: 0.8137 | AU51: 0.8337 | AV51: 0.8538 | AW51: 0.8832 | AX51: 0.9126 | AY51: 0.9421 | AZ51: 0.9715 | BA51: 1 | BB51: 1 | BC51: 1 | BD51: 1 | BE51: 1 | BF51: 1 | BG51: 1 | BH51: 1
A52: eap-1_8 | B52: Compactacao aterros 100% Proctor Intermediario | C52: m3 | D52: 29411 | E52: Dias Trabalhados | BB52: 6 | BC52: 6 | BD52: 6
E53: Nº De Equipes | BB53: 1 | BC53: 1 | BD53: 1
E54: Qtd. Planejada | BB54: 5532.03 | BC54: 5532.03 | BD54: 5532.03
E55: Qtd Plan. Acumulada | BB55: 5532.03 | BC55: 11064.06 | BD55: 16596.09 | BE55: 16596.09 | BF55: 16596.09 | BG55: 16596.09 | BH55: 16596.09
E56: % Semanal | BB56: 0.3333 | BC56: 0.3333 | BD56: 0.3333
E57: % Acumulado | BB57: 0.3333 | BC57: 0.6667 | BD57: 1 | BE57: 1 | BF57: 1 | BG57: 1 | BH57: 1
A58: eap-1_9 | B58: Construcao corpo aterro material 3a categoria | C58: m3 | D58: 981153.5 | E58: Dias Trabalhados | AA58: 6 | AB58: 6 | AC58: 6 | AD58: 6 | AE58: 6 | AF58: 6 | AG58: 6 | AH58: 6 | AI58: 6 | AJ58: 6 | AK58: 6 | AL58: 6 | AM58: 6 | AN58: 6 | AO58: 6 | AP58: 6 | AQ58: 6 | AR58: 6 | AS58: 6 | AT58: 6 | AU58: 6 | AV58: 6 | AW58: 6 | AX58: 6 | AY58: 6 | AZ58: 6 | BA58: 6 | BB58: 6 | BC58: 6 | BD58: 6 | BE58: 6 | BF58: 6
E59: Nº De Equipes | AA59: 3 | AB59: 3 | AC59: 3 | AD59: 3 | AE59: 3 | AF59: 3 | AG59: 3 | AH59: 3 | AI59: 3 | AJ59: 3 | AK59: 3 | AL59: 3 | AM59: 3 | AN59: 3 | AO59: 3 | AP59: 3 | AQ59: 3 | AR59: 3 | AS59: 3 | AT59: 3 | AU59: 3 | AV59: 3 | AW59: 3 | AX59: 3 | AY59: 3 | AZ59: 3 | BA59: 3 | BB59: 3 | BC59: 3 | BD59: 3 | BE59: 3 | BF59: 3
E60: Qtd. Planejada | AA60: 28884.22 | AB60: 28952.3 | AC60: 28952.3 | AD60: 28952.3 | AE60: 28952.3 | AF60: 28952.3 | AG60: 28952.3 | AH60: 28952.3 | AI60: 28952.3 | AJ60: 28952.3 | AK60: 25956.49 | AL60: 25956.49 | AM60: 25956.49 | AN60: 25956.49 | AO60: 24316.22 | AP60: 24316.22 | AQ60: 24316.22 | AR60: 24316.22 | AS60: 18968.32 | AT60: 18968.32 | AU60: 18968.32 | AV60: 18968.32 | AW60: 27853.63 | AX60: 27853.63 | AY60: 27853.63 | AZ60: 27853.63 | BA60: 26956.13 | BB60: 26956.13 | BC60: 26956.13 | BD60: 26956.13 | BE60: 30948.48 | BF60: 30948.48
E61: Qtd Plan. Acumulada | AA61: 28884.22 | AB61: 57836.52 | AC61: 86788.82 | AD61: 115741.12 | AE61: 144693.42 | AF61: 173645.72 | AG61: 202598.02 | AH61: 231550.32 | AI61: 260502.62 | AJ61: 289454.92 | AK61: 315411.41 | AL61: 341367.9 | AM61: 367324.39 | AN61: 393280.88 | AO61: 417597.1 | AP61: 441913.32 | AQ61: 466229.54 | AR61: 490545.76 | AS61: 509514.08 | AT61: 528482.4 | AU61: 547450.72 | AV61: 566419.04 | AW61: 594272.67 | AX61: 622126.3 | AY61: 649979.93 | AZ61: 677833.56 | BA61: 704789.69 | BB61: 731745.82 | BC61: 758701.95 | BD61: 785658.08 | BE61: 816606.56 | BF61: 847555.04 | BG61: 847555.04 | BH61: 847555.04
E62: % Semanal | AA62: 0.0341 | AB62: 0.0342 | AC62: 0.0342 | AD62: 0.0342 | AE62: 0.0342 | AF62: 0.0342 | AG62: 0.0342 | AH62: 0.0342 | AI62: 0.0342 | AJ62: 0.0342 | AK62: 0.0306 | AL62: 0.0306 | AM62: 0.0306 | AN62: 0.0306 | AO62: 0.0287 | AP62: 0.0287 | AQ62: 0.0287 | AR62: 0.0287 | AS62: 0.0224 | AT62: 0.0224 | AU62: 0.0224 | AV62: 0.0224 | AW62: 0.0329 | AX62: 0.0329 | AY62: 0.0329 | AZ62: 0.0329 | BA62: 0.0318 | BB62: 0.0318 | BC62: 0.0318 | BD62: 0.0318 | BE62: 0.0365 | BF62: 0.0365
E63: % Acumulado | AA63: 0.0341 | AB63: 0.0682 | AC63: 0.1024 | AD63: 0.1366 | AE63: 0.1707 | AF63: 0.2049 | AG63: 0.239 | AH63: 0.2732 | AI63: 0.3074 | AJ63: 0.3415 | AK63: 0.3721 | AL63: 0.4028 | AM63: 0.4334 | AN63: 0.464 | AO63: 0.4927 | AP63: 0.5214 | AQ63: 0.5501 | AR63: 0.5788 | AS63: 0.6012 | AT63: 0.6235 | AU63: 0.6459 | AV63: 0.6683 | AW63: 0.7012 | AX63: 0.734 | AY63: 0.7669 | AZ63: 0.7998 | BA63: 0.8316 | BB63: 0.8634 | BC63: 0.8952 | BD63: 0.927 | BE63: 0.9635 | BF63: 1 | BG63: 1 | BH63: 1
A64: eap-1_10 | B64: Compactacao camada final aterro sobre rocha | C64: m3 | D64: 24721.17 | E64: Dias Trabalhados | BC64: 6 | BD64: 6 | BE64: 6 | BF64: 6 | BG64: 6 | BH64: 6
E65: Nº De Equipes | BC65: 1 | BD65: 1 | BE65: 1 | BF65: 1 | BG65: 1 | BH65: 1
E66: Qtd. Planejada | BC66: 4180.8 | BD66: 4180.8 | BE66: 4800 | BF66: 4800 | BG66: 4800 | BH66: 1959.57
E67: Qtd Plan. Acumulada | BC67: 4180.8 | BD67: 8361.6 | BE67: 13161.6 | BF67: 17961.6 | BG67: 22761.6 | BH67: 24721.17
E68: % Semanal | BC68: 0.1691 | BD68: 0.1691 | BE68: 0.1942 | BF68: 0.1942 | BG68: 0.1942 | BH68: 0.0793
E69: % Acumulado | BC69: 0.1691 | BD69: 0.3382 | BE69: 0.5324 | BF69: 0.7266 | BG69: 0.9207 | BH69: 1

Sheet CRONOGRAMA.RES
A1: CRONOGRAMA RESUMIDO — PRODUÇÃO MENSAL POR EAP
A2: Item ID | B2: Descrição | C2: Un. | D2: Total Qtd | E2: Jun/26 | F2: Jul/26 | G2: Ago/26 | H2: Set/26 | I2: Out/26 | J2: Nov/26 | K2: Dez/26 | L2: Jan/27 | M2: Fev/27 | N2: Mar/27 | O2: Abr/27 | P2: Mai/27 | Q2: Jun/27
A3: eap-1_0 | B3: Desmatamento e limpeza de area vegetada | C3: m2 | D3: 2400000 | E3: 354240 | F3: 283392 | G3: 354240 | H3: 283392 | I3: 264489.76 | J3: 331391.5 | K3: 265113.2 | L3: 178260.66
A4: eap-1_1 | B4: Esc/carg/transp 1aCat DMT<=2000m | C4: m3 | D4: 107463.11 | G4: 22259.52 | H4: 44519.04 | I4: 40684.55
A5: eap-1_2 | B5: Esc/carg/transp 1aCat DMT<=3000m | C5: m3 | D5: 336915.09 | G5: 11083.68 | H5: 44334.72 | I5: 41377.6 | J5: 51843.9 | K5: 41475.12 | L5: 37183.52 | M5: 34833.8 | N5: 37148.07
A6: eap-1_3 | B6: Esc/carg/transp 2aCat DMT<=2000m | C6: m3 | D6: 105311.33 | N6: 32301.27 | O6: 54260.91
A7: eap-1_4 | B7: Esc/carg/transp 2aCat DMT<=3000m | C7: m3 | D7: 585945.77 | E7: 45728.64 | F7: 60971.52 | G7: 76214.4 | H7: 60971.52 | I7: 56904.72 | J7: 71298.55 | K7: 57038.84 | L7: 51136.8 | M7: 47905.32 | N7: 18684.72
A8: eap-1_5 | B8: Esc/carg/transp 3aCat DMT<=2000m | C8: m3 | D8: 304634.46 | E8: 61352.64 | F8: 81803.52 | G8: 102254.4 | H8: 59223.9
A9: eap-1_6 | B9: Esc/carg/transp 3aCat DMT<=3000m | C9: m3 | D9: 676519.04 | E9: 61413.12 | F9: 81884.16 | G9: 102355.2 | H9: 81884.16 | I9: 76422.48 | J9: 95753.3 | K9: 76602.64 | L9: 68676.24 | M9: 16084.1
A10: eap-1_7 | B10: Compactacao aterros 100% Proctor Normal | C10: m3 | D10: 1135635.3 | G10: 33217.92 | H10: 132871.68 | I10: 124009.12 | J10: 155376.8 | K10: 124301.44 | L10: 111439.48 | M10: 104397.28 | N10: 111333.17 | O10: 118621.2
A11: eap-1_8 | B11: Compactacao aterros 100% Proctor Intermediario | C11: m3 | D11: 29411 | P11: 16596.09
A12: eap-1_9 | B12: Construcao corpo aterro material 3a categoria | C12: m3 | D12: 981153.5 | I12: 28884.22 | J12: 144761.5 | K12: 115809.2 | L12: 103825.96 | M12: 97264.88 | N12: 103726.91 | O12: 110517.02 | P12: 142765.35
A13: eap-1_10 | B13: Compactacao camada final aterro sobre rocha | C13: m3 | D13: 24721.17 | P13: 17961.6 | Q13: 6759.57

Sheet EQUIPE
A1: EQUIPE — COMPOSIÇÃO DE RECURSOS DIRETOS POR ATIVIDADE
A2: Item ID | B2: CPU ID | C2: Nome / Tipo | D2: Papel | E2: Qtd | F2: Custo Mensal (R$) | G2: Perm. (m) | H2: Nº Eq. | I2: Custo Total (R$)
A3: eap-1_0 — Desmatamento e limpeza de area vegetada
A4: eap-1_0 | B4: CPU-TERRA-ATI-003 | C4: Operador de Trator de Esteiras | D4: DIRETO | E4: 1 | F4: 9394 | G4: 7.82 | H4: 1 | I4: 73461.08
A5: eap-1_0 | B5: CPU-TERRA-ATI-003 | C5: Operador de Escavadeira | D5: DIRETO | E5: 1 | F5: 9394 | G5: 7.82 | H5: 1 | I5: 73461.08
A6: eap-1_0 | B6: CPU-TERRA-ATI-003 | C6: Operador de Motosserra | D6: DIRETO | E6: 1 | F6: 9394 | G6: 7.82 | H6: 1 | I6: 73461.08
A7: eap-1_0 | B7: CPU-TERRA-ATI-003 | C7: Ajudante | D7: DIRETO | E7: 1 | F7: 4279 | G7: 7.82 | H7: 1 | I7: 33461.78
A8: eap-1_0 | B8: CPU-TERRA-ATI-003 | C8: Encarregado de Frente | D8: DIRETO | E8: 1 | F8: 7499.8 | G8: 7.82 | H8: 1 | I8: 58648.44
A9: eap-1_0 | B9: CPU-TERRA-ATI-003 | C9: Apontador | D9: DIRETO | E9: 1 | F9: 6448.2 | G9: 7.82 | H9: 1 | I9: 50424.92
A10: eap-1_0 | B10: CPU-TERRA-ATI-003 | C10: Sinaleiro | D10: DIRETO | E10: 1 | F10: 4279 | G10: 7.82 | H10: 1 | I10: 33461.78
A11: eap-1_0 | B11: AGIS-TRAT-EST-20T | C11: Trator de Esteiras 20T [EQ] | D11: EQ | E11: 1 | F11: 52470 | G11: 7.82 | H11: 1 | I11: 410315.4
A12: eap-1_0 | B12: AGIS-TRAT-EST-20T | C12: Diesel — Trator de Esteiras 20T | D12: COMB | E12: 1 | F12: 33161.14 | G12: 7.82 | H12: 1 | I12: 259320.11
A13: eap-1_0 | B13: AGIS-ESCAV-22T | C13: Escavadeira Hidráulica sobre esteira 22T [EQ] | D13: EQ | E13: 1 | F13: 42416 | G13: 7.82 | H13: 1 | I13: 331693.12
A14: eap-1_0 | B14: AGIS-ESCAV-22T | C14: Diesel — Escavadeira Hidráulica sobre esteira 22T | D14: COMB | E14: 1 | F14: 28059.43 | G14: 7.82 | H14: 1 | I14: 219424.74
A15: eap-1_0 | B15: AGIS-MOTOSSERRA | C15: Motosserra a Gasolina [EQ] | D15: EQ | E15: 1 | F15: 3300 | G15: 7.82 | H15: 1 | I15: 25806
A16: eap-1_0 | B16: AGIS-MOTOSSERRA | C16: Diesel — Motosserra a Gasolina | D16: COMB | E16: 1 | F16: 1913.14 | G16: 7.82 | H16: 1 | I16: 14960.75
A17: Subtotal eap-1_0 | I17: 2097750.5
A18: eap-1_1 — Esc/carg/transp 1aCat DMT<=2000m
A19: eap-1_1 | B19: CPU-TERRA-ESCO-CARGA-1CAT-DMT2000 | C19: Operador de Escavadeira | D19: DIRETO | E19: 1 | F19: 9394 | G19: 2.3 | H19: 1 | I19: 21606.2
A20: eap-1_1 | B20: CPU-TERRA-ESCO-CARGA-1CAT-DMT2000 | C20: Ajudante | D20: DIRETO | E20: 1 | F20: 4279 | G20: 2.3 | H20: 1 | I20: 9841.7
A21: eap-1_1 | B21: CPU-TERRA-ESCO-CARGA-1CAT-DMT2000 | C21: Encarregado de Frente | D21: DIRETO | E21: 1 | F21: 7499.8 | G21: 2.3 | H21: 1 | I21: 17249.54
A22: eap-1_1 | B22: CPU-TERRA-ESCO-CARGA-1CAT-DMT2000 | C22: Motorista de Caminhão Basculante | D22: DIRETO | E22: 7 | F22: 58674 | G22: 2.3 | H22: 1 | I22: 134950.2
A23: eap-1_1 | B23: AGIS-E0015 | C23: Escavadeira Hidráulica sobre esteira 38T [EQ] | D23: EQ | E23: 1 | F23: 59048 | G23: 2.3 | H23: 1 | I23: 135810.4
A24: eap-1_1 | B24: AGIS-E0015 | C24: Diesel — Escavadeira Hidráulica sobre esteira 38T | D24: COMB | E24: 1 | F24: 33161.14 | G24: 2.3 | H24: 1 | I24: 76270.62
A25: eap-1_1 | B25: AGIS-E0002 | C25: Caminhão Basculante 14 m³ [EQ] | D25: EQ | E25: 7 | F25: 26945.6 | G25: 2.3 | H25: 1 | I25: 61974.88
A26: eap-1_1 | B26: AGIS-E0002 | C26: Diesel — Caminhão Basculante 14 m³ | D26: COMB | E26: 7 | F26: 3188.57 | G26: 2.3 | H26: 1 | I26: 7333.71
A27: Subtotal eap-1_1 | I27: 938899.81
A28: eap-1_2 — Esc/carg/transp 1aCat DMT<=3000m
A29: eap-1_2 | B29: CPU-TERRA-ESCO-CARGA-1CAT-DMT3000 | C29: Operador de Escavadeira | D29: DIRETO | E29: 1 | F29: 9394 | G29: 7.13 | H29: 1 | I29: 66979.22
A30: eap-1_2 | B30: CPU-TERRA-ESCO-CARGA-1CAT-DMT3000 | C30: Ajudante | D30: DIRETO | E30: 1 | F30: 4279 | G30: 7.13 | H30: 1 | I30: 30509.27
A31: eap-1_2 | B31: CPU-TERRA-ESCO-CARGA-1CAT-DMT3000 | C31: Encarregado de Frente | D31: DIRETO | E31: 1 | F31: 7499.8 | G31: 7.13 | H31: 1 | I31: 53473.57
A32: eap-1_2 | B32: CPU-TERRA-ESCO-CARGA-1CAT-DMT3000 | C32: Motorista de Caminhão Basculante | D32: DIRETO | E32: 8 | F32: 67056 | G32: 7.13 | H32: 1 | I32: 478109.28
A33: eap-1_2 | B33: AGIS-E0015 | C33: Escavadeira Hidráulica sobre esteira 38T [EQ] | D33: EQ | E33: 1 | F33: 59048 | G33: 7.13 | H33: 1 | I33: 421012.24
A34: eap-1_2 | B34: AGIS-E0015 | C34: Diesel — Escavadeira Hidráulica sobre esteira 38T | D34: COMB | E34: 1 | F34: 33161.14 | G34: 7.13 | H34: 1 | I34: 236438.93
A35: eap-1_2 | B35: AGIS-E0002 | C35: Caminhão Basculante 14 m³ [EQ] | D35: EQ | E35: 8 | F35: 26945.6 | G35: 7.13 | H35: 1 | I35: 192122.13
A36: eap-1_2 | B36: AGIS-E0002 | C36: Diesel — Caminhão Basculante 14 m³ | D36: COMB | E36: 8 | F36: 3188.57 | G36: 7.13 | H36: 1 | I36: 22734.5
A37: Subtotal eap-1_2 | I37: 2910596.3
A38: eap-1_3 — Esc/carg/transp 2aCat DMT<=2000m
A39: eap-1_3 | B39: CPU-TERRA-ESCO-CARGA-2CAT-DMT2000 | C39: Operador de Escavadeira | D39: DIRETO | E39: 1 | F39: 9394 | G39: 1.61 | H39: 1 | I39: 15124.34
A40: eap-1_3 | B40: CPU-TERRA-ESCO-CARGA-2CAT-DMT2000 | C40: Ajudante | D40: DIRETO | E40: 1 | F40: 4279 | G40: 1.61 | H40: 1 | I40: 6889.19
A41: eap-1_3 | B41: CPU-TERRA-ESCO-CARGA-2CAT-DMT2000 | C41: Encarregado de Frente | D41: DIRETO | E41: 1 | F41: 7499.8 | G41: 1.61 | H41: 1 | I41: 12074.68
A42: eap-1_3 | B42: CPU-TERRA-ESCO-CARGA-2CAT-DMT2000 | C42: Motorista de Caminhão Basculante | D42: DIRETO | E42: 6 | F42: 50292 | G42: 1.61 | H42: 1 | I42: 80970.12
A43: eap-1_3 | B43: AGIS-E0015 | C43: Escavadeira Hidráulica sobre esteira 38T [EQ] | D43: EQ | E43: 1 | F43: 59048 | G43: 1.61 | H43: 1 | I43: 95067.28
A44: eap-1_3 | B44: AGIS-E0015 | C44: Diesel — Escavadeira Hidráulica sobre esteira 38T | D44: COMB | E44: 1 | F44: 33161.14 | G44: 1.61 | H44: 1 | I44: 53389.44
A45: eap-1_3 | B45: AGIS-E0002 | C45: Caminhão Basculante 14 m³ [EQ] | D45: EQ | E45: 6 | F45: 26945.6 | G45: 1.61 | H45: 1 | I45: 43382.42
A46: eap-1_3 | B46: AGIS-E0002 | C46: Diesel — Caminhão Basculante 14 m³ | D46: COMB | E46: 6 | F46: 3188.57 | G46: 1.61 | H46: 1 | I46: 5133.6
A47: Subtotal eap-1_3 | I47: 1162236.9
A48: eap-1_4 — Esc/carg/transp 2aCat DMT<=3000m
A49: eap-1_4 | B49: CPU-TERRA-ESCO-CARGA-2CAT-DMT3000 | C49: Operador de Escavadeira | D49: DIRETO | E49: 1 | F49: 9394 | G49: 8.97 | H49: 1 | I49: 84264.18
A50: eap-1_4 | B50: CPU-TERRA-ESCO-CARGA-2CAT-DMT3000 | C50: Ajudante | D50: DIRETO | E50: 1 | F50: 4279 | G50: 8.97 | H50: 1 | I50: 38382.63
A51: eap-1_4 | B51: CPU-TERRA-ESCO-CARGA-2CAT-DMT3000 | C51: Encarregado de Frente | D51: DIRETO | E51: 1 | F51: 7499.8 | G51: 8.97 | H51: 1 | I51: 67273.21
A52: eap-1_4 | B52: CPU-TERRA-ESCO-CARGA-2CAT-DMT3000 | C52: Motorista de Caminhão Basculante | D52: DIRETO | E52: 7 | F52: 58674 | G52: 8.97 | H52: 1 | I52: 526305.78
A53: eap-1_4 | B53: AGIS-E0015 | C53: Escavadeira Hidráulica sobre esteira 38T [EQ] | D53: EQ | E53: 1 | F53: 59048 | G53: 8.97 | H53: 1 | I53: 529660.56
A54: eap-1_4 | B54: AGIS-E0015 | C54: Diesel — Escavadeira Hidráulica sobre esteira 38T | D54: COMB | E54: 1 | F54: 33161.14 | G54: 8.97 | H54: 1 | I54: 297455.43
A55: eap-1_4 | B55: AGIS-E0002 | C55: Caminhão Basculante 14 m³ [EQ] | D55: EQ | E55: 7 | F55: 26945.6 | G55: 8.97 | H55: 1 | I55: 241702.03
A56: eap-1_4 | B56: AGIS-E0002 | C56: Diesel — Caminhão Basculante 14 m³ | D56: COMB | E56: 7 | F56: 3188.57 | G56: 8.97 | H56: 1 | I56: 28601.47
A57: Subtotal eap-1_4 | I57: 6475315.7
A58: eap-1_5 — Esc/carg/transp 3aCat DMT<=2000m
A59: eap-1_5 | B59: CPU-TERRA-ESCO-CARGA-3CAT-DMT2000 | C59: Operador de Escavadeira | D59: DIRETO | E59: 1 | F59: 9394 | G59: 3.45 | H59: 1 | I59: 32409.3
A60: eap-1_5 | B60: CPU-TERRA-ESCO-CARGA-3CAT-DMT2000 | C60: Ajudante | D60: DIRETO | E60: 1 | F60: 4279 | G60: 3.45 | H60: 1 | I60: 14762.55
A61: eap-1_5 | B61: CPU-TERRA-ESCO-CARGA-3CAT-DMT2000 | C61: Motorista de Caminhão Basculante | D61: DIRETO | E61: 6 | F61: 50292 | G61: 3.45 | H61: 1 | I61: 173507.4
A62: eap-1_5 | B62: AGIS-E0016 | C62: Escavadeira Hidráulica sobre esteira 48T [EQ] | D62: EQ | E62: 1 | F62: 82401 | G62: 3.45 | H62: 1 | I62: 284283.45
A63: eap-1_5 | B63: AGIS-E0016 | C63: Diesel — Escavadeira Hidráulica sobre esteira 48T | D63: COMB | E63: 1 | F63: 38262.86 | G63: 3.45 | H63: 1 | I63: 132006.87
A64: eap-1_5 | B64: AGIS-E0004 | C64: Caminhão Basculante 14 m³ - Rochas [EQ] | D64: EQ | E64: 6 | F64: 40744 | G64: 3.45 | H64: 1 | I64: 140566.8
A65: eap-1_5 | B65: AGIS-E0004 | C65: Diesel — Caminhão Basculante 14 m³ - Rochas | D65: COMB | E65: 6 | F65: 3826.29 | G65: 3.45 | H65: 1 | I65: 13200.7
A66: Subtotal eap-1_5 | I66: 4406341.9
A67: eap-1_6 — Esc/carg/transp 3aCat DMT<=3000m
A68: eap-1_6 | B68: CPU-TERRA-ESCO-CARGA-3CAT-DMT3000 | C68: Operador de Escavadeira | D68: DIRETO | E68: 1 | F68: 9394 | G68: 7.82 | H68: 1 | I68: 73461.08
A69: eap-1_6 | B69: CPU-TERRA-ESCO-CARGA-3CAT-DMT3000 | C69: Ajudante | D69: DIRETO | E69: 1 | F69: 4279 | G69: 7.82 | H69: 1 | I69: 33461.78
A70: eap-1_6 | B70: CPU-TERRA-ESCO-CARGA-3CAT-DMT3000 | C70: Motorista de Caminhão Basculante | D70: DIRETO | E70: 8 | F70: 67056 | G70: 7.82 | H70: 1 | I70: 524377.92
A71: eap-1_6 | B71: AGIS-E0016 | C71: Escavadeira Hidráulica sobre esteira 48T [EQ] | D71: EQ | E71: 1 | F71: 82401 | G71: 7.82 | H71: 1 | I71: 644375.82
A72: eap-1_6 | B72: AGIS-E0016 | C72: Diesel — Escavadeira Hidráulica sobre esteira 48T | D72: COMB | E72: 1 | F72: 38262.86 | G72: 7.82 | H72: 1 | I72: 299215.57
A73: eap-1_6 | B73: AGIS-E0004 | C73: Caminhão Basculante 14 m³ - Rochas [EQ] | D73: EQ | E73: 8 | F73: 40744 | G73: 7.82 | H73: 1 | I73: 318618.08
A74: eap-1_6 | B74: AGIS-E0004 | C74: Diesel — Caminhão Basculante 14 m³ - Rochas | D74: COMB | E74: 8 | F74: 3826.29 | G74: 7.82 | H74: 1 | I74: 29921.59
A75: Subtotal eap-1_6 | I75: 9987716.2
A76: eap-1_7 — Compactacao aterros 100% Proctor Normal
A77: eap-1_7 | B77: CPU-TERRA-COMPAC-PN | C77: Operador de Rolo Compactador | D77: DIRETO | E77: 2 | F77: 16764 | G77: 8.05 | H77: 1 | I77: 134950.2
A78: eap-1_7 | B78: CPU-TERRA-COMPAC-PN | C78: Operador de Trator de Pneus | D78: DIRETO | E78: 1 | F78: 9394 | G78: 8.05 | H78: 1 | I78: 75621.7
A79: eap-1_7 | B79: CPU-TERRA-COMPAC-PN | C79: Operador de Motoniveladora | D79: DIRETO | E79: 1 | F79: 9394 | G79: 8.05 | H79: 1 | I79: 75621.7
A80: eap-1_7 | B80: CPU-TERRA-COMPAC-PN | C80: Motorista de Caminhão Pipa | D80: DIRETO | E80: 1 | F80: 8382 | G80: 8.05 | H80: 1 | I80: 67475.1
A81: eap-1_7 | B81: CPU-TERRA-COMPAC-PN | C81: Ajudante | D81: DIRETO | E81: 2 | F81: 8558 | G81: 8.05 | H81: 1 | I81: 68891.9
A82: eap-1_7 | B82: CPU-TERRA-COMPAC-PN | C82: Gredista | D82: DIRETO | E82: 1 | F82: 6448.2 | G82: 8.05 | H82: 1 | I82: 51908.01
A83: eap-1_7 | B83: CPU-TERRA-COMPAC-PN | C83: Encarregado de Frente | D83: DIRETO | E83: 1 | F83: 7499.8 | G83: 8.05 | H83: 1 | I83: 60373.39
A84: eap-1_7 | B84: AGIS-ROLO-PC-10T | C84: Rolo Compactador Pé de Carneiro 10T [EQ] | D84: EQ | E84: 2 | F84: 24200 | G84: 8.05 | H84: 1 | I84: 194810
A85: eap-1_7 | B85: AGIS-ROLO-PC-10T | C85: Diesel — Rolo Compactador Pé de Carneiro 10T | D85: COMB | E85: 2 | F85: 20406.86 | G85: 8.05 | H85: 1 | I85: 164275.22
A86: eap-1_7 | B86: AGIS-TRATOR-PNEU-GRADE | C86: Trator de Pneus com Grade [EQ] | D86: EQ | E86: 1 | F86: 33660 | G86: 8.05 | H86: 1 | I86: 270963
A87: eap-1_7 | B87: AGIS-TRATOR-PNEU-GRADE | C87: Diesel — Trator de Pneus com Grade | D87: COMB | E87: 1 | F87: 22957.71 | G87: 8.05 | H87: 1 | I87: 184809.57
A88: eap-1_7 | B88: AGIS-MOTON-140K | C88: Motoniveladora 140K [EQ] | D88: EQ | E88: 1 | F88: 56020.8 | G88: 8.05 | H88: 1 | I88: 450967.44
... A91: eap-1_7 | B91: AGIS-CAM-PIPA-18K | C91: Diesel — Caminhão Pipa 18.000 L | D91: COMB | E91: 1 | F91: 8928 | G91: 8.05 | H91: 1 | I91: 71870.4
A92: Subtotal eap-1_7 | I92: 10490751
A93: eap-1_8 — Compactacao aterros 100% Proctor Intermediario
A94: eap-1_8 | B94: CPU-TERRA-COMPAC-PI | C94: Operador de Rolo Compactador | D94: DIRETO | E94: 2 | F94: 16764 | G94: 0.69 | H94: 1 | I94: 11567.16
A95: eap-1_8 | B95: CPU-TERRA-COMPAC-PI | C95: Operador de Trator de Pneus | D95: DIRETO | E95: 1 | F95: 9394 | G95: 0.69 | H95: 1 | I95: 6481.86
A96: eap-1_8 | B96: CPU-TERRA-COMPAC-PI | C96: Operador de Motoniveladora | D96: DIRETO | E96: 1 | F96: 9394 | G96: 0.69 | H96: 1 | I96: 6481.86
A97: eap-1_8 | B97: CPU-TERRA-COMPAC-PI | C97: Motorista de Caminhão Pipa | D97: DIRETO | E97: 1 | F97: 8382 | G97: 0.69 | H97: 1 | I97: 5783.58
A98: eap-1_8 | B98: CPU-TERRA-COMPAC-PI | C98: Ajudante | D98: DIRETO | E98: 2 | F98: 8558 | G98: 0.69 | H98: 1 | I98: 5905.02
A99: eap-1_8 | B99: CPU-TERRA-COMPAC-PI | C99: Gredista | D99: DIRETO | E99: 1 | F99: 6448.2 | G99: 0.69 | H99: 1 | I99: 4449.26
A100: eap-1_8 | B100: CPU-TERRA-COMPAC-PI | C100: Encarregado de Frente | D100: DIRETO | E100: 1 | F100: 7499.8 | G100: 0.69 | H100: 1 | I100: 5174.86
A101: eap-1_8 | B101: AGIS-ROLO-PC-10T | C101: Rolo Compactador Pé de Carneiro 10T [EQ] | D101: EQ | E101: 2 | F101: 24200 | G101: 0.69 | H101: 1 | I101: 16698
A102: eap-1_8 | B102: AGIS-ROLO-PC-10T | C102: Diesel — Rolo Compactador Pé de Carneiro 10T | D102: COMB | E102: 2 | F102: 20406.86 | G102: 0.69 | H102: 1 | I102: 14080.73
...

Sheet EQUILIBRIO
A1: PONTO DE EQUILÍBRIO — CUSTO FIXO vs PREÇO DE VENDA (CPU)
A2: Item ID | B2: CPU ID | C2: Custo Fixo Equipe (R$) | D2: Preço Venda CPU (R$) | E2: Delta (R$) | F2: Status
A3: eap-1_0 | B3: CPU-TERRA-ATI-003 | C3: 2097749.9 | D3: 2477673.2 | E3: 379923.24 | F3: OK
A4: eap-1_1 | B4: CPU-TERRA-ESCO-CARGA-1CAT-DMT2000 | C4: 871125.3 | D4: 992406.46 | E4: 121281.16 | F4: OK
A5: eap-1_2 | B5: CPU-TERRA-ESCO-CARGA-1CAT-DMT3000 | C5: 2978388.1 | D5: 3441418.8 | E5: 463030.71 | F5: OK
A6: eap-1_3 | B6: CPU-TERRA-ESCO-CARGA-2CAT-DMT2000 | C6: 1097045.4 | D6: 1280092 | E6: 183046.61 | F6: OK
A7: eap-1_4 | B7: CPU-TERRA-ESCO-CARGA-2CAT-DMT3000 | C7: 6540503.7 | D7: 7597204.5 | E7: 1056700.8 | F7: OK
A8: eap-1_5 | B8: CPU-TERRA-ESCO-CARGA-3CAT-DMT2000 | C8: 4673919.8 | D8: 5452981.8 | E8: 779061.92 | F8: OK
A9: eap-1_6 | B9: CPU-TERRA-ESCO-CARGA-3CAT-DMT3000 | C9: 13038269 | D9: 14870247 | E9: 1831978.2 | F9: OK
A10: eap-1_7 | B10: CPU-TERRA-COMPAC-PN | C10: 10522970 | D10: 12156798 | E10: 1633827.8 | F10: OK
A11: eap-1_8 | B11: CPU-TERRA-COMPAC-PI | C11: 225479.85 | D11: 411657.26 | E11: 186177.41 | F11: OK
A12: eap-1_9 | B12: CPU-TERRA-CORPO-ATERRO-3CAT | C12: 5760051.5 | D12: 6741771.1 | E12: 981719.59 | F12: OK
A13: eap-1_10 | B13: CPU-TERRA-COMPAC-FINAL-ROCHA | C13: 394885.9 | D13: 415123.69 | E13: 20237.79 | F13: OK

Sheet CALENDARIO.OP
A1: CALENDARIO OPERACIONAL
A3: Semana ISO | B3: Dias úteis base | C3: Dias úteis efetivos | D3: Fator calendário | E3: Fator clima | F3: Fator total | G3: Eventos aplicados
A4: 2026-W23 | B4: 6 | C4: 6 | D4: 1 | E4: 1 | F4: 1
A5: 2026-W24 | B5: 6 | C5: 6 | D5: 1 | E5: 1 | F5: 1
A6: 2026-W25 | B6: 6 | C6: 6 | D6: 1 | E6: 1 | F6: 1
A7: 2026-W26 | B7: 6 | C7: 6 | D7: 1 | E7: 1 | F7: 1
A8: 2026-W27 | B8: 6 | C8: 6 | D8: 1 | E8: 1 | F8: 1
A9: 2026-W28 | B9: 6 | C9: 6 | D9: 1 | E9: 1 | F9: 1
A10: 2026-W29 | B10: 6 | C10: 6 | D10: 1 | E10: 1 | F10: 1
A11: 2026-W30 | B11: 6 | C11: 6 | D11: 1 | E11: 1 | F11: 1
A12: 2026-W31 | B12: 6 | C12: 6 | D12: 1 | E12: 1 | F12: 1
A13: 2026-W32 | B13: 6 | C13: 6 | D13: 1 | E13: 1 | F13: 1
A14: 2026-W33 | B14: 6 | C14: 6 | D14: 1 | E14: 1 | F14: 1
A15: 2026-W34 | B15: 6 | C15: 6 | D15: 1 | E15: 1 | F15: 1
... A59: 2027-W25 | B59: 6 | C59: 6 | D59: 1 | E59: 1 | F59: 1

Sheet RESULTADO
A1: RESULTADO FINANCEIRO — MENDESLOBO CONSTRUTORA
A3: PROJETO
A4: Nome | B4: AGIS - Ferrovia Nova Transnordestina (Supressao e Terraplanagem)
A5: Tipo de obra | B5: terraplenagem
A6: Localização | B6: Ceara, Brasil
A7: Período | B7: 2026-06-01 -> 2027-06-27
A8: Regime | B8: 6 dias/sem · 8 h/dia
A10: RECEITA CONTRATUAL (COM BDI)
A11: Preço de venda s/ BDI | B11: =PLANEJAMENTO!$M$15
A12: Preço de venda c/ BDI | B12: 85639774
A14: CUSTOS
A15: Custo direto (catálogo s/BDI) | B15: =PLANEJAMENTO!$M$15
A16: ADM | B16: ='INDIRETOS.DET'!$H$26
A17: TOP | B17: ='INDIRETOS.DET'!$H$32
A18: LAB | B18: ='INDIRETOS.DET'!$H$36
A19: QSMS | B19: ='INDIRETOS.DET'!$H$43
A20: MOB | B20: ='INDIRETOS.DET'!$H$46
A21: Custo indireto (subtotal) | B21: ='INDIRETOS.DET'!$H$48
A22: CUSTO TOTAL | B22: =B15+B21
A24: RESULTADO
A25: Resultado bruto (R$) | B25: =B12-B22
A26: Margem bruta (%) | B26: =IF(B12>0, B25/B12, 0)
A28: STATUS: VERMELHO
A30: COMPOSIÇÃO DE CUSTO
A31: Total Direto (catálogo s/BDI) | B31: =PLANEJAMENTO!$M$15
A32: Total Direto (c/BDI) | B32: 85639774
A33: RAZÃO CI / CD (%) | B33: 45.44
A34: CI / PVT (%) | B34: 24.85
A36: CAPITAL DE GIRO
A37: Exposição máxima | B37: 8083316.4
A38: Parcela mensal (meses 2 a n) | B38: 6587674
A39: Resíduo (mês n+1) | B39: 6587686
A40: Duração da execução (meses) | B40: 13
A41: ALAVANCAS DE REAJUSTE
A42: Preço de venda total | B42: 85639774 | C42: Depende de MO/EQ/MAT/DIESEL + BDI indireto
A43: Base catálogo s/BDI | B43: 46843791 | C43: Knob de partida para precificação
A44: Markup efetivo | B44: 0.25702828 | C44: Resultado consolidado, não a fórmula de composição
A45: Custo direto de equipes | B45: 48544218 | C45: Sensível a permanência, produtividade e nº de frentes
A46: Custo fixo mensal de equipes | B46: 3844188.3 | C46: Multiplica diretamente pela permanência
A47: Permanência média (meses) | B47: 5.1436364 | C47: Reduzir prazo reduz custo fixo e mobilização
A48: Pico de equipes | B48: 1 | C48: Se subir, pressiona custo fixo e mobilização
A49: Praticabilidade média | B49: 0.9083434 | C49: Baixa praticabilidade aumenta permanência

Sheet ANALISE.FC_CAIXA
A1: FLUXO DE CAIXA — ACOMPANHAMENTO MENSAL
A2: Mês | B2: Despesa (R$) | C2: Receita (R$) | D2: Rec. Acumulada (R$) | E2: Saldo do Mês (R$) | F2: Saldo Atual (R$) | G2: Exposição Acum. (R$)
A3: Jun/26 | B3: 8083316.4 | C3: 0 | D3: 0 | E3: -8083316.4 | F3: -8083316.4 | G3: 8083316.4
A4: Jul/26 | B4: 4807790.6 | C4: 6587674 | D4: 6587674 | E4: 1779883.4 | F4: -6303433 | G4: 6303433
A5: Ago/26 | B5: 6278658.5 | C5: 6587674 | D5: 13175348 | E5: 309015.49 | F5: -5994417.5 | G5: 5994417.5
A6: Set/26 | B6: 6401356 | C6: 6587674 | D6: 19763022 | E6: 186317.95 | F6: -5808099.6 | G6: 5808099.6
A7: Out/26 | B7: 5395086.1 | C7: 6587674 | D7: 26350696 | E7: 1192587.9 | F7: -4615511.7 | G7: 4615511.7
A8: Nov/26 | B8: 6704830.9 | C8: 6587674 | D8: 32938370 | E8: -117156.86 | F8: -4732668.6 | G8: 4732668.6
A9: Dez/26 | B9: 5602786.8 | C9: 6587674 | D9: 39526044 | E9: 984887.17 | F9: -3747781.4 | G9: 3747781.4
A10: Jan/27 | B10: 5094563.1 | C10: 6587674 | D10: 46113718 | E10: 1493110.9 | F10: -2254670.5 | G10: 2254670.5
A11: Fev/27 | B11: 3822326.3 | C11: 6587674 | D11: 52701392 | E11: 2765347.7 | F11: 510677.2 | G11: -510677.2
A12: Mar/27 | B12: 3661772.2 | C12: 6587674 | D12: 59289066 | E12: 2925901.8 | F12: 3436579 | G12: -3436579
A13: Abr/27 | B13: 3474542 | C13: 6587674 | D13: 65876740 | E13: 3113132 | F13: 6549711 | G13: -6549711
A14: Mai/27 | B14: 2490520 | C14: 6587674 | D14: 72464414 | E14: 4097154 | F14: 10646865 | G14: -10646865
... A16: Jul/27 | B16: 0 | C16: 6587686 | D16: 85639774 | E16: 6587686 | F16: 22530027 | G16: -22530027
A18: TOTAL | B18: 63109747 | C18: 85639774 | D18: 85639774 | E18: 22530027 | F18: 22530027
A21: MÉTRICAS DO FLUXO DE CAIXA
A22: Duração da execução (meses) | C22: 13
A23: Parcela mensal (meses 2 a n) | C23: 6587674
A24: Resíduo (mês n+1) | C24: 6587686
A25: Exposição máxima | C25: 8083316.4
A26: Mês da exposição máxima | C26: Jun/26
A27: Saldo final do projeto | C27: 22530027
A29: Mês 1: receita = 0. Meses 2..n: ⌊M/n⌋ cada. Mês n+1: resíduo M − ⌊M/n⌋×(n−1). Saldo Atual = Rec. Acumulada − Desp. Acumulada. Exposição Acum. = −Saldo Atual (positivo = empresa precisa de capital de giro).

Sheet HIST.EQUIPAMENTOS
A1: HISTOGRAMA DE EQUIPAMENTOS — DEMANDA SEMANAL (UN.)
A2: Equip. ID | B2: Descrição | C2: Un. | D2: 01/Jun | E2: 08/Jun | F2: 15/Jun | G2: 22/Jun | H2: 29/Jun | I2: 06/Jul | J2: 13/Jul | K2: 20/Jul | L2: 27/Jul | M2: 03/Ago | N2: 10/Ago | O2: 17/Ago | P2: 24/Ago | Q2: 31/Ago | R2: 07/Set | S2: 14/Set | T2: 21/Set | U2: 28/Set | V2: 05/Out | W2: 12/Out | X2: 19/Out | Y2: 26/Out | Z2: 02/Nov | AA2: 09/Nov | AB2: 16/Nov | AC2: 23/Nov | AD2: 30/Nov | AE2: 07/Dez | AF2: 14/Dez | AG2: 21/Dez | AH2: 28/Dez | AI2: 04/Jan | AJ2: 11/Jan | AK2: 18/Jan | AL2: 25/Jan | AM2: 01/Fev | AN2: 08/Fev | AO2: 15/Fev | AP2: 22/Fev | AQ2: 01/Mar | AR2: 08/Mar | AS2: 15/Mar | AT2: 22/Mar | AU2: 29/Mar | AV2: 05/Abr | AW2: 12/Abr | AX2: 19/Abr | AY2: 26/Abr | AZ2: 03/Mai | BA2: 10/Mai | BB2: 17/Mai | BC2: 24/Mai | BD2: 31/Mai | BE2: 07/Jun | BF2: 14/Jun
A3: AGIS-CAM-PIPA-18K | B3: Caminhão Pipa 18.000 L | C3: un | Q3: 4 | R3: 4 | S3: 4 | T3: 4 | U3: 4 | V3: 4 | W3: 4 | X3: 4 | Y3: 4 | Z3: 4 | AA3: 4 | AB3: 4 | AC3: 4 | AD3: 4 | AE3: 4 | AF3: 4 | AG3: 4 | AH3: 4 | AI3: 4 | AJ3: 4 | AK3: 4 | AL3: 4 | AM3: 4 | AN3: 4 | AO3: 4 | AP3: 4 | AQ3: 4 | AR3: 4 | AS3: 4 | AT3: 4 | AU3: 4 | AV3: 4 | AW3: 4 | AX3: 4 | AY3: 4 | AZ3: 1 | BA3: 2 | BB3: 2 | BC3: 1 | BD3: 1 | BE3: 1 | BF3: 1
A4: AGIS-E0002 | B4: Caminhão Basculante 14 m³ | C4: un | F4: 14 | G4: 14 | H4: 14 | I4: 14 | J4: 14 | K4: 14 | L4: 14 | M4: 14 | N4: 14 | O4: 14 | P4: 21 | Q4: 29 | R4: 29 | S4: 29 | T4: 29 | U4: 29 | V4: 29 | W4: 29 | X4: 29 | Y4: 29 | Z4: 22 | AA4: 22 | AB4: 22 | AC4: 22 | AD4: 22 | AE4: 22 | AF4: 22 | AG4: 22 | AH4: 22 | AI4: 22 | AJ4: 22 | AK4: 22 | AL4: 22 | AM4: 22 | AN4: 22 | AO4: 22 | AP4: 22 | AQ4: 22 | AR4: 22 | AS4: 20 | AT4: 20 | AU4: 20 | AV4: 12 | AW4: 12 | AX4: 12 | AY4: 12
A5: AGIS-E0004 | B5: Caminhão Basculante 14 m³ - Rochas | C5: un | F5: 42 | G5: 42 | H5: 42 | I5: 42 | J5: 42 | K5: 42 | L5: 42 | M5: 42 | N5: 42 | O5: 42 | P5: 42 | Q5: 42 | R5: 42 | S5: 42 | T5: 42 | U5: 24 | V5: 24 | W5: 24 | X5: 24 | Y5: 24 | Z5: 24 | AA5: 24 | AB5: 24 | AC5: 24 | AD5: 24 | AE5: 24 | AF5: 24 | AG5: 24 | AH5: 24 | AI5: 24 | AJ5: 24 | AK5: 24 | AL5: 24 | AM5: 24
A6: AGIS-E0015 | B6: Escavadeira Hidráulica sobre esteira 38T | C6: un | F6: 2 | G6: 2 | H6: 2 | I6: 2 | J6: 2 | K6: 2 | L6: 2 | M6: 2 | N6: 2 | O6: 2 | P6: 3 | Q6: 4 | R6: 4 | S6: 4 | T6: 4 | U6: 4 | V6: 4 | W6: 4 | X6: 4 | Y6: 4 | Z6: 3 | AA6: 3 | AB6: 3 | AC6: 3 | AD6: 3 | AE6: 3 | AF6: 3 | AG6: 3 | AH6: 3 | AI6: 3 | AJ6: 3 | AK6: 3 | AL6: 3 | AM6: 3 | AN6: 3 | AO6: 3 | AP6: 3 | AQ6: 3 | AR6: 3 | AS6: 3 | AT6: 3 | AU6: 3 | AV6: 2 | AW6: 2 | AX6: 2 | AY6: 2
A7: AGIS-E0016 | B7: Escavadeira Hidráulica sobre esteira 48T | C7: un | F7: 6 | G7: 6 | H7: 6 | I7: 6 | J7: 6 | K7: 6 | L7: 6 | M7: 6 | N7: 6 | O7: 6 | P7: 6 | Q7: 6 | R7: 6 | S7: 6 | T7: 6 | U7: 3 | V7: 3 | W7: 3 | X7: 3 | Y7: 3 | Z7: 3 | AA7: 3 | AB7: 3 | AC7: 3 | AD7: 3 | AE7: 3 | AF7: 3 | AG7: 3 | AH7: 3 | AI7: 3 | AJ7: 3 | AK7: 3 | AL7: 3 | AM7: 3
A8: AGIS-ESCAV-22T | B8: Escavadeira Hidráulica sobre esteira 22T | C8: un | D8: 2 | E8: 2 | F8: 2 | G8: 2 | H8: 2 | I8: 2 | J8: 2 | K8: 2 | L8: 2 | M8: 2 | N8: 2 | O8: 2 | P8: 2 | Q8: 2 | R8: 2 | S8: 2 | T8: 2 | U8: 2 | V8: 2 | W8: 2 | X8: 2 | Y8: 2 | Z8: 2 | AA8: 2 | AB8: 2 | AC8: 2 | AD8: 2 | AE8: 2 | AF8: 2 | AG8: 2 | AH8: 2 | AI8: 2 | AJ8: 2 | AK8: 2
A9: AGIS-MOTON-140K | B9: Motoniveladora 140K | C9: un | Q9: 4 | R9: 4 | S9: 4 | T9: 4 | U9: 4 | V9: 4 | W9: 4 | X9: 4 | Y9: 4 | Z9: 4 | AA9: 4 | AB9: 4 | AC9: 4 | AD9: 4 | AE9: 4 | AF9: 4 | AG9: 4 | AH9: 4 | AI9: 4 | AJ9: 4 | AK9: 4 | AL9: 4 | AM9: 4 | AN9: 4 | AO9: 4 | AP9: 4 | AQ9: 4 | AR9: 4 | AS9: 4 | AT9: 4 | AU9: 4 | AV9: 4 | AW9: 4 | AX9: 4 | AY9: 4 | AZ9: 1 | BA9: 1 | BB9: 1
A10: AGIS-MOTOSSERRA | B10: Motosserra a Gasolina | C10: un | D10: 2 | E10: 2 | F10: 2 | G10: 2 | H10: 2 | I10: 2 | J10: 2 | K10: 2 | L10: 2 | M10: 2 | N10: 2 | O10: 2 | P10: 2 | Q10: 2 | R10: 2 | S10: 2 | T10: 2 | U10: 2 | V10: 2 | W10: 2 | X10: 2 | Y10: 2 | Z10: 2 | AA10: 2 | AB10: 2 | AC10: 2 | AD10: 2 | AE10: 2 | AF10: 2 | AG10: 2 | AH10: 2 | AI10: 2 | AJ10: 2 | AK10: 2
A11: AGIS-ROLO-LISO | B11: Rolo Compactador Liso | C11: un | BA11: 2 | BB11: 2 | BC11: 2 | BD11: 2 | BE11: 2 | BF11: 2
A12: AGIS-ROLO-PC-10T | B12: Rolo Compactador Pé de Carneiro 10T | C12: un | Q12: 8 | R12: 8 | S12: 8 | T12: 8 | U12: 8 | V12: 8 | W12: 8 | X12: 8 | Y12: 14 | Z12: 14 | AA12: 14 | AB12: 14 | AC12: 14 | AD12: 14 | AE12: 14 | AF12: 14 | AG12: 14 | AH12: 14 | AI12: 14 | AJ12: 14 | AK12: 14 | AL12: 14 | AM12: 14 | AN12: 14 | AO12: 14 | AP12: 14 | AQ12: 14 | AR12: 14 | AS12: 14 | AT12: 14 | AU12: 14 | AV12: 14 | AW12: 14 | AX12: 14 | AY12: 14 | AZ12: 8 | BA12: 9 | BB12: 9 | BC12: 7 | BD12: 7 | BE12: 1 | BF12: 1
A13: AGIS-TRAT-EST-20T | B13: Trator de Esteiras 20T | C13: un | D13: 2 | E13: 2 | F13: 2 | G13: 2 | H13: 2 | I13: 2 | J13: 2 | K13: 2 | L13: 2 | M13: 2 | N13: 2 | O13: 2 | P13: 2 | Q13: 2 | R13: 2 | S13: 2 | T13: 2 | U13: 2 | V13: 2 | W13: 2 | X13: 2 | Y13: 2 | Z13: 2 | AA13: 2 | AB13: 2 | AC13: 2 | AD13: 2 | AE13: 2 | AF13: 2 | AG13: 2 | AH13: 2 | AI13: 2 | AJ13: 2 | AK13: 2 | BA13: 1 | BB13: 1 | BC13: 1 | BD13: 1 | BE13: 1 | BF13: 1
A14: AGIS-TRAT-EST-40T | B14: Trator de Esteiras 40T | C14: un | Y14: 3 | Z14: 3 | AA14: 3 | AB14: 3 | AC14: 3 | AD14: 3 | AE14: 3 | AF14: 3 | AG14: 3 | AH14: 3 | AI14: 3 | AJ14: 3 | AK14: 3 | AL14: 3 | AM14: 3 | AN14: 3 | AO14: 3 | AP14: 3 | AQ14: 3 | AR14: 3 | AS14: 3 | AT14: 3 | AU14: 3 | AV14: 3 | AW14: 3 | AX14: 3 | AY14: 3 | AZ14: 3 | BA14: 3 | BB14: 3 | BC14: 3 | BD14: 3
A15: AGIS-TRATOR-PNEU-GRADE | B15: Trator de Pneus com Grade | C15: un | Q15: 4 | R15: 4 | S15: 4 | T15: 4 | U15: 4 | V15: 4 | W15: 4 | X15: 4 | Y15: 4 | Z15: 4 | AA15: 4 | AB15: 4 | AC15: 4 | AD15: 4 | AE15: 4 | AF15: 4 | AG15: 4 | AH15: 4 | AI15: 4 | AJ15: 4 | AK15: 4 | AL15: 4 | AM15: 4 | AN15: 4 | AO15: 4 | AP15: 4 | AQ15: 4 | AR15: 4 | AS15: 4 | AT15: 4 | AU15: 4 | AV15: 4 | AW15: 4 | AX15: 4 | AY15: 4 | AZ15: 1 | BA15: 1 | BB15: 1
A17: TOTAL SEMANAL | D17: 6 | E17: 6 | F17: 70 | G17: 70 | H17: 70 | I17: 70 | J17: 70 | K17: 70 | L17: 70 | M17: 70 | N17: 70 | O17: 70 | P17: 78 | Q17: 107 | R17: 107 | S17: 107 | T17: 107 | U17: 86 | V17: 86 | W17: 86 | X17: 86 | Y17: 95 | Z17: 87 | AA17: 87 | AB17: 87 | AC17: 87 | AD17: 87 | AE17: 87 | AF17: 87 | AG17: 87 | AH17: 87 | AI17: 87 | AJ17: 87 | AK17: 87 | AL17: 81 | AM17: 81 | AN17: 54 | AO17: 54 | AP17: 54 | AQ17: 54 | AR17: 54 | AS17: 52 | AT17: 52 | AU17: 52 | AV17: 43 | AW17: 43 | AX17: 43 | AY17: 43 | AZ17: 14 | BA17: 19 | BB17: 19 | BC17: 14 | BD17: 14 | BE17: 5 | BF17: 5

Sheet HIST.MAO_OBRA
A1: HISTOGRAMA DE MÃO DE OBRA — DEMANDA SEMANAL (PESSOAS)
A2: Função ID | B2: Descrição | C2: Un. | D2: 01/Jun | E2: 08/Jun | F2: 15/Jun | G2: 22/Jun | H2: 29/Jun | I2: 06/Jul | J2: 13/Jul | K2: 20/Jul | L2: 27/Jul | M2: 03/Ago | N2: 10/Ago | O2: 17/Ago | P2: 24/Ago | Q2: 31/Ago | R2: 07/Set | S2: 14/Set | T2: 21/Set | U2: 28/Set | V2: 05/Out | W2: 12/Out | X2: 19/Out | Y2: 26/Out | Z2: 02/Nov | AA2: 09/Nov | AB2: 16/Nov | AC2: 23/Nov | AD2: 30/Nov | AE2: 07/Dez | AF2: 14/Dez | AG2: 21/Dez | AH2: 28/Dez | AI2: 04/Jan | AJ2: 11/Jan | AK2: 18/Jan | AL2: 25/Jan | AM2: 01/Fev | AN2: 08/Fev | AO2: 15/Fev | AP2: 22/Fev | AQ2: 01/Mar | AR2: 08/Mar | AS2: 15/Mar | AT2: 22/Mar | AU2: 29/Mar | AV2: 05/Abr | AW2: 12/Abr | AX2: 19/Abr | AY2: 26/Abr | AZ2: 03/Mai | BA2: 10/Mai | BB2: 17/Mai | BC2: 24/Mai | BD2: 31/Mai | BE2: 07/Jun | BF2: 14/Jun
A3: AGIS-FN-AJUD | B3: Ajudante | C3: pax | D3: 2 | E3: 2 | F3: 10 | G3: 10 | H3: 10 | I3: 10 | J3: 10 | K3: 10 | L3: 10 | M3: 10 | N3: 10 | O3: 10 | P3: 11 | Q3: 20 | R3: 20 | S3: 20 | T3: 20 | U3: 17 | V3: 17 | W3: 17 | X3: 17 | Y3: 23 | Z3: 22 | AA3: 22 | AB3: 22 | AC3: 22 | AD3: 22 | AE3: 22 | AF3: 22 | AG3: 22 | AH3: 22 | AI3: 22 | AJ3: 22 | AK3: 22 | AL3: 20 | AM3: 20 | AN3: 17 | AO3: 17 | AP3: 17 | AQ3: 17 | AR3: 17 | AS3: 17 | AT3: 17 | AU3: 17 | AV3: 16 | AW3: 16 | AX3: 16 | AY3: 16 | AZ3: 8 | BA3: 10 | BB3: 10 | BC3: 8 | BD3: 8 | BE3: 2 | BF3: 2
A4: AGIS-FN-APONTADOR | B4: Apontador | C4: pax | D4: 2 | E4: 2 | F4: 2 | G4: 2 | H4: 2 | I4: 2 | J4: 2 | K4: 2 | L4: 2 | M4: 2 | N4: 2 | O4: 2 | P4: 2 | Q4: 2 | R4: 2 | S4: 2 | T4: 2 | U4: 2 | V4: 2 | W4: 2 | X4: 2 | Y4: 2 | Z4: 2 | AA4: 2 | AB4: 2 | AC4: 2 | AD4: 2 | AE4: 2 | AF4: 2 | AG4: 2 | AH4: 2 | AI4: 2 | AJ4: 2 | AK4: 2
A5: AGIS-FN-ENCAR | B5: Encarregado de Frente | C5: pax | D5: 2 | E5: 2 | F5: 4 | G5: 4 | H5: 4 | I5: 4 | J5: 4 | K5: 4 | L5: 4 | M5: 4 | N5: 4 | O5: 4 | P5: 5 | Q5: 10 | R5: 10 | S5: 10 | T5: 10 | U5: 10 | V5: 10 | W5: 10 | X5: 10 | Y5: 13 | Z5: 12 | AA5: 12 | AB5: 12 | AC5: 12 | AD5: 12 | AE5: 12 | AF5: 12 | AG5: 12 | AH5: 12 | AI5: 12 | AJ5: 12 | AK5: 12 | AL5: 10 | AM5: 10 | AN5: 10 | AO5: 10 | AP5: 10 | AQ5: 10 | AR5: 10 | AS5: 10 | AT5: 10 | AU5: 10 | AV5: 9 | AW5: 9 | AX5: 9 | AY5: 9 | AZ5: 4 | BA5: 4 | BB5: 4 | BC5: 3 | BD5: 3
A6: AGIS-FN-GREDISTA | B6: Gredista | C6: pax | Q6: 4 | R6: 4 | S6: 4 | T6: 4 | U6: 4 | V6: 4 | W6: 4 | X6: 4 | Y6: 7 | Z6: 7 | AA6: 7 | AB6: 7 | AC6: 7 | AD6: 7 | AE6: 7 | AF6: 7 | AG6: 7 | AH6: 7 | AI6: 7 | AJ6: 7 | AK6: 7 | AL6: 7 | AM6: 7 | AN6: 7 | AO6: 7 | AP6: 7 | AQ6: 7 | AR6: 7 | AS6: 7 | AT6: 7 | AU6: 7 | AV6: 7 | AW6: 7 | AX6: 7 | AY6: 7 | AZ6: 4 | BA6: 4 | BB6: 4 | BC6: 3 | BD6: 3
A7: AGIS-FN-MOTOR-BASC | B7: Motorista de Caminhão Basculante | C7: pax | F7: 56 | G7: 56 | H7: 56 | I7: 56 | J7: 56 | K7: 56 | L7: 56 | M7: 56 | N7: 56 | O7: 56 | P7: 63 | Q7: 71 | R7: 71 | S7: 71 | T7: 71 | U7: 53 | V7: 53 | W7: 53 | X7: 53 | Y7: 53 | Z7: 46 | AA7: 46 | AB7: 46 | AC7: 46 | AD7: 46 | AE7: 46 | AF7: 46 | AG7: 46 | AH7: 46 | AI7: 46 | AJ7: 46 | AK7: 46 | AL7: 46 | AM7: 46 | AN7: 22 | AO7: 22 | AP7: 22 | AQ7: 22 | AR7: 22 | AS7: 20 | AT7: 20 | AU7: 20 | AV7: 12 | AW7: 12 | AX7: 12 | AY7: 12
A8: AGIS-FN-MOTOR-PIPA | B8: Motorista de Caminhão Pipa | C8: pax | Q8: 4 | R8: 4 | S8: 4 | T8: 4 | U8: 4 | V8: 4 | W8: 4 | X8: 4 | Y8: 4 | Z8: 4 | AA8: 4 | AB8: 4 | AC8: 4 | AD8: 4 | AE8: 4 | AF8: 4 | AG8: 4 | AH8: 4 | AI8: 4 | AJ8: 4 | AK8: 4 | AL8: 4 | AM8: 4 | AN8: 4 | AO8: 4 | AP8: 4 | AQ8: 4 | AR8: 4 | AS8: 4 | AT8: 4 | AU8: 4 | AV8: 4 | AW8: 4 | AX8: 4 | AY8: 4 | AZ8: 1 | BA8: 2 | BB8: 2 | BC8: 1 | BD8: 1 | BE8: 1 | BF8: 1
A9: AGIS-FN-OPER-ESCAV | B9: Operador de Escavadeira | C9: pax | D9: 2 | E9: 2 | F9: 10 | G9: 10 | H9: 10 | I9: 10 | J9: 10 | K9: 10 | L9: 10 | M9: 10 | N9: 10 | O9: 10 | P9: 11 | Q9: 12 | R9: 12 | S9: 12 | T9: 12 | U9: 9 | V9: 9 | W9: 9 | X9: 9 | Y9: 9 | Z9: 8 | AA9: 8 | AB9: 8 | AC9: 8 | AD9: 8 | AE9: 8 | AF9: 8 | AG9: 8 | AH9: 8 | AI9: 8 | AJ9: 8 | AK9: 8 | AL9: 6 | AM9: 6 | AN9: 3 | AO9: 3 | AP9: 3 | AQ9: 3 | AR9: 3 | AS9: 3 | AT9: 3 | AU9: 3 | AV9: 2 | AW9: 2 | AX9: 2 | AY9: 2
A10: AGIS-FN-OPER-MOTON | B10: Operador de Motoniveladora | C10: pax | Q10: 4 | R10: 4 | S10: 4 | T10: 4 | U10: 4 | V10: 4 | W10: 4 | X10: 4 | Y10: 4 | Z10: 4 | AA10: 4 | AB10: 4 | AC10: 4 | AD10: 4 | AE10: 4 | AF10: 4 | AG10: 4 | AH10: 4 | AI10: 4 | AJ10: 4 | AK10: 4 | AL10: 4 | AM10: 4 | AN10: 4 | AO10: 4 | AP10: 4 | AQ10: 4 | AR10: 4 | AS10: 4 | AT10: 4 | AU10: 4 | AV10: 4 | AW10: 4 | AX10: 4 | AY10: 4 | AZ10: 1 | BA10: 1 | BB10: 1
A11: AGIS-FN-OPER-MOTOSSERRA | B11: Operador de Motosserra | C11: pax | D11: 2 | E11: 2 | F11: 2 | G11: 2 | H11: 2 | I11: 2 | J11: 2 | K11: 2 | L11: 2 | M11: 2 | N11: 2 | O11: 2 | P11: 2 | Q11: 2 | R11: 2 | S11: 2 | T11: 2 | U11: 2 | V11: 2 | W11: 2 | X11: 2 | Y11: 2 | Z11: 2 | AA11: 2 | AB11: 2 | AC11: 2 | AD11: 2 | AE11: 2 | AF11: 2 | AG11: 2 | AH11: 2 | AI11: 2 | AJ11: 2 | AK11: 2
A12: AGIS-FN-OPER-ROLO | B12: Operador de Rolo Compactador | C12: pax | Q12: 8 | R12: 8 | S12: 8 | T12: 8 | U12: 8 | V12: 8 | W12: 8 | X12: 8 | Y12: 14 | Z12: 14 | AA12: 14 | AB12: 14 | AC12: 14 | AD12: 14 | AE12: 14 | AF12: 14 | AG12: 14 | AH12: 14 | AI12: 14 | AJ12: 14 | AK12: 14 | AL12: 14 | AM12: 14 | AN12: 14 | AO12: 14 | AP12: 14 | AQ12: 14 | AR12: 14 | AS12: 14 | AT12: 14 | AU12: 14 | AV12: 14 | AW12: 14 | AX12: 14 | AY12: 14 | AZ12: 8 | BA12: 11 | BB12: 11 | BC12: 9 | BD12: 9 | BE12: 3 | BF12: 3
A13: AGIS-FN-OPER-TRAT-EST | B13: Operador de Trator de Esteiras | C13: pax | D13: 2 | E13: 2 | F13: 2 | G13: 2 | H13: 2 | I13: 2 | J13: 2 | K13: 2 | L13: 2 | M13: 2 | N13: 2 | O13: 2 | P13: 2 | Q13: 2 | R13: 2 | S13: 2 | T13: 2 | U13: 2 | V13: 2 | W13: 2 | X13: 2 | Y13: 5 | Z13: 5 | AA13: 5 | AB13: 5 | AC13: 5 | AD13: 5 | AE13: 5 | AF13: 5 | AG13: 5 | AH13: 5 | AI13: 5 | AJ13: 5 | AK13: 5 | AL13: 3 | AM13: 3 | AN13: 3 | AO13: 3 | AP13: 3 | AQ13: 3 | AR13: 3 | AS13: 3 | AT13: 3 | AU13: 3 | AV13: 3 | AW13: 3 | AX13: 3 | AY13: 3 | AZ13: 3 | BA13: 4 | BB13: 4 | BC13: 4 | BD13: 4 | BE13: 1 | BF13: 1
A14: AGIS-FN-OPER-TRAT-PNEU | B14: Operador de Trator de Pneus | C14: pax | Q14: 4 | R14: 4 | S14: 4 | T14: 4 | U14: 4 | V14: 4 | W14: 4 | X14: 4 | Y14: 4 | Z14: 4 | AA14: 4 | AB14: 4 | AC14: 4 | AD14: 4 | AE14: 4 | AF14: 4 | AG14: 4 | AH14: 4 | AI14: 4 | AJ14: 4 | AK14: 4 | AL14: 4 | AM14: 4 | AN14: 4 | AO14: 4 | AP14: 4 | AQ14: 4 | AR14: 4 | AS14: 4 | AT14: 4 | AU14: 4 | AV14: 4 | AW14: 4 | AX14: 4 | AY14: 4 | AZ14: 1 | BA14: 1 | BB14: 1
A15: AGIS-FN-SINALEIRO | B15: Sinaleiro | C15: pax | D15: 2 | E15: 2 | F15: 2 | G15: 2 | H15: 2 | I15: 2 | J15: 2 | K15: 2 | L15: 2 | M15: 2 | N15: 2 | O15: 2 | P15: 2 | Q15: 2 | R15: 2 | S15: 2 | T15: 2 | U15: 2 | V15: 2 | W15: 2 | X15: 2 | Y15: 2 | Z15: 2 | AA15: 2 | AB15: 2 | AC15: 2 | AD15: 2 | AE15: 2 | AF15: 2 | AG15: 2 | AH15: 2 | AI15: 2 | AJ15: 2 | AK15: 2
A17: TOTAL SEMANAL | D17: 14 | E17: 14 | F17: 88 | G17: 88 | H17: 88 | I17: 88 | J17: 88 | K17: 88 | L17: 88 | M17: 88 | N17: 88 | O17: 88 | P17: 98 | Q17: 145 | R17: 145 | S17: 145 | T17: 145 | U17: 121 | V17: 121 | W17: 121 | X17: 121 | Y17: 142 | Z17: 132 | AA17: 132 | AB17: 132 | AC17: 132 | AD17: 132 | AE17: 132 | AF17: 132 | AG17: 132 | AH17: 132 | AI17: 132 | AJ17: 132 | AK17: 132 | AL17: 118 | AM17: 118 | AN17: 88 | AO17: 88 | AP17: 88 | AQ17: 88 | AR17: 88 | AS17: 86 | AT17: 86 | AU17: 86 | AV17: 75 | AW17: 75 | AX17: 75 | AY17: 75 | AZ17: 30 | BA17: 37 | BB17: 37 | BC17: 28 | BD17: 28 | BE17: 7 | BF17: 7

Sheet GRAFICOS
A1: Histograma de Equipamentos | D1: Histograma de Mao de Obra | G1: Cronograma (Gantt)
A2: Categoria | B2: Valor | D2: Categoria | E2: Valor | G2: Tarefa | H2: Inicio | I2: Duracao (dias)
A3: 01/Jun | B3: 6 | D3: 01/Jun | E3: 14 | G3: eap-1_0 | H3: 0 | I3: 238
A4: 08/Jun | B4: 6 | D4: 08/Jun | E4: 14 | G4: eap-1_1 | H4: 84 | I4: 70
A5: 15/Jun | B5: 70 | D5: 15/Jun | E5: 88 | G5: eap-1_2 | H5: 91 | I5: 217
A6: 22/Jun | B6: 70 | D6: 22/Jun | E6: 88 | G6: eap-1_3 | H6: 287 | I6: 49
A7: 29/Jun | B7: 70 | D7: 29/Jun | E7: 88 | G7: eap-1_4 | H7: 14 | I7: 273
A8: 06/Jul | B8: 70 | D8: 06/Jul | E8: 88 | G8: eap-1_5 | H8: 14 | I8: 105
A9: 13/Jul | B9: 70 | D9: 13/Jul | E9: 88 | G9: eap-1_6 | H9: 14 | I9: 238
A10: 20/Jul | B10: 70 | D10: 20/Jul | E10: 88 | G10: eap-1_7 | H10: 91 | I10: 245
A11: 27/Jul | B11: 70 | D11: 27/Jul | E11: 88 | G11: eap-1_8 | H11: 336 | I11: 21
A12: 03/Ago | B12: 70 | D12: 03/Ago | E12: 88 | G12: eap-1_9 | H12: 147 | I12: 224
A13: 10/Ago | B13: 70 | D13: 10/Ago | E13: 88 | G13: eap-1_10 | H13: 343 | I13: 42
A14: 17/Ago | B14: 70 | D14: 17/Ago | E14: 88
A15: 24/Ago | B15: 78 | D15: 24/Ago | E15: 98
A16: 31/Ago | B16: 107 | D16: 31/Ago | E16: 145
A17: 07/Set | B17: 107 | D17: 07/Set | E17: 145
A18: 14/Set | B18: 107 | D18: 14/Set | E18: 145
A19: 21/Set | B19: 107 | D19: 21/Set | E19: 145
A20: Fluxo mensal | B20: 86 | D20: 28/Set | E20: 121
A21: Mes | B21: Receita | C21: Despesa | D21: Saldo | E21: Exposicao
A22: Jun/26 | B22: 0 | C22: 8083316.4 | D22: -8083316.4 | E22: 8083316.4
A23: Jul/26 | B23: 6587674 | C23: 4807790.6 | D23: 1779883.4 | E23: 6303433
A24: Ago/26 | B24: 6587674 | C24: 6278658.5 | D24: 309015.49 | E24: 5994417.5
A25: Set/26 | B25: 6587674 | C25: 6401356 | D25: 186317.95 | E25: 5808099.6
A26: Out/26 | B26: 6587674 | C26: 5395086.1 | D26: 1192587.9 | E26: 4615511.7
A27: Nov/26 | B27: 6587674 | C27: 6704830.9 | D27: -117156.86 | E27: 4732668.6
A28: Dez/26 | B28: 6587674 | C28: 5602786.8 | D28: 984887.17 | E28: 3747781.4
A29: Jan/27 | B29: 6587674 | C29: 5094563.1 | D29: 1493110.9 | E29: 2254670.5
A30: Fev/27 | B30: 6587674 | C30: 3822326.3 | D30: 2765347.7 | E30: -510677.2
A31: Mar/27 | B31: 6587674 | C31: 3661772.2 | D31: 2925901.8 | E31: -3436579
A32: Abr/27 | B32: 6587674 | C32: 3474542 | D32: 3113132 | E32: -6549711
A33: Mai/27 | B33: 6587674 | C33: 2490520 | D33: 4097154 | E33: -10646865
... A35: Jul/27 | B35: 6587686 | C35: 0 | D35: 6587686 | E35: -22530027
A36: 18/Jan | B36: 87 | D36: 18/Jan | E36: 132
A37: 25/Jan | B37: 81 | D37: 25/Jan | E37: 118
A38: 01/Fev | B38: 81 | D38: 01/Fev | E38: 118
A39: 08/Fev | B39: 54 | D39: 08/Fev | E39: 88
A40: 15/Fev | B40: 54 | D40: 15/Fev | E40: 88
A41: 22/Fev | B41: 54 | D41: 22/Fev | E41: 88
A42: 01/Mar | B42: 54 | D42: 01/Mar | E42: 88
A43: 08/Mar | B43: 54 | D43: 08/Mar | E43: 88
A44: 15/Mar | B44: 52 | D44: 15/Mar | E44: 86
A45: 22/Mar | B45: 52 | D45: 22/Mar | E45: 86
A46: 29/Mar | B46: 52 | D46: 29/Mar | E46: 86
A47: 05/Abr | B47: 43 | D47: 05/Abr | E47: 75
... A57: 14/Jun | B57: 5 | D57: 14/Jun | E57: 7
